Workbook

Sheet Резюме
B2: БИЗНЕС-ПЛАН ИНВЕСТИЦИОННОГО ПРОЕКТА
B3: Освоение центральной части вольфрамового месторождения Сарикуль (1-я очередь)
B4: (Освоение вольфрамового месторождения Сарикул)
B6: 1. ОБЩИЕ СВЕДЕНИЯ
B7: Суть проекта | C7: Освоение центральной части вольфрамового месторождения Сарикуль (1-я очередь). Переработка 600 тыс. т руды в год; выпуск основной продукции - Вольфрамовый концентрат 57 8% WO3 4 200 t/год при проектной мощности; реализация - внутренний рынок.
B8: Заемщик | C8: АО «Узбекский комбинат технологических металлов» (АО «Ўзбекистон ТМК», UzTMK)
B9: Местоположение | C9: месторождение Сарикул
B10: Продукция | C10: Вольфрамовый концентрат 57,8% WO3
B11: Производственная мощность | C11: Переработка 600 тыс. т руды в год; выпуск основной продукции - 4 200 t/год
B12: Рынок сбыта | C12: внутренний рынок (поставка концентрата на переработку), цены в USD
B13: Сроки | C13: начало строительства - 01.09.2026; начало производства - 01.09.2027; выход на проектную мощность - 2030 г.
B14: Стадия проработки | C14: Предварительное ТЭО
B16: 2. ПАРАМЕТРЫ КРЕДИТА
B17: Сумма кредита, USD | C17: =ИНФОРМАЦИЯ!$C$26 -> 42783896
B18: Процентная ставка | C18: =ИНФОРМАЦИЯ!$C$27 -> 0.07
B19: Срок кредита | C19: 84 месяца (7 лет): льготный (инвестиционный) период - 12 месяцев (2027 г.), погашение - 72 месяца (2028-2033 гг.)
B20: Порядок погашения | C20: основной долг - ежемесячно равными долями; проценты - ежемесячно на остаток задолженности
B21: Проценты льготного периода | C21: =TEXT(LOANS!$C$106,"#,##0") & " USD - уплачиваются за счёт собственных средств заемщика (включены в стоимость проекта)" -> 3,036,468 USD - уплачиваются за счёт собственных средств заемщика (включены в стоимость проекта)
B22: Целевое назначение | C22: 30% авансовый платёж по EPC-контракту (E - проектирование, P - поставка оборудования, C - строительство)
B24: 3. СТОИМОСТЬ ПРОЕКТА И ИСТОЧНИКИ ФИНАНСИРОВАНИЯ
B25: Статья | C25: USD | D25: Доля
B26: Фиксированные активы | C26: =ProjCost!E5 -> 1.4161333e+08 | D26: =IFERROR(C26/ProjCost!$E$22,0) -> 0.8259959
B27: Рабочий капитал | C27: =ProjCost!E11 -> 25294194 | D27: =IFERROR(C27/ProjCost!$E$22,0) -> 0.14753484
B28: Проценты льготного периода и расходы подготовительного периода | C28: =ProjCost!E17 -> 4110198.3 | D28: =IFERROR(C28/ProjCost!$E$22,0) -> 0.02397378
B29: Резерв | C29: =ProjCost!E20 -> 427838.96 | D29: =IFERROR(C29/ProjCost!$E$22,0) -> 0.0024954799
B30: ВСЕГО СТОИМОСТЬ ПРОЕКТА | C30: =ProjCost!E22 -> 1.7144556e+08 | D30: =IFERROR(C30/ProjCost!$E$22,0) -> 1
B31: Собственные средства заемщика | C31: =FinPlan!$E$10 -> 1.2866167e+08 | D31: =IFERROR(C31/ProjCost!$E$22,0) -> 0.75045201
B32: Кредит банка | C32: =FinPlan!$E$14 -> 42783896 | D32: =IFERROR(C32/ProjCost!$E$22,0) -> 0.24954799
B34: 4. ОСНОВНЫЕ ФИНАНСОВЫЕ ПОКАЗАТЕЛИ ПО ГОДАМ
B35: ПОКАЗАТЕЛИ | C35: Ед. изм. | D35: 1 год (льготный / инвест.) | E35: 2 год | F35: 3 год | G35: 4 год | H35: 5 год | I35: 6 год | J35: 7 год
D36: 2027 | E36: 2028 | F36: 2029 | G36: 2030 | H36: 2031 | I36: 2032 | J36: 2033
B37: Выручка (без НДС) | C37: USD | D37: =ProfLoss!D10 -> 23861585 | E37: =ProfLoss!E10 -> 85083568 | F37: =ProfLoss!F10 -> 94036971 | G37: =ProfLoss!G10 -> 1.2209613e+08 | H37: =ProfLoss!H10 -> 1.19963e+08 | I37: =ProfLoss!I10 -> 1.2252059e+08 | J37: =ProfLoss!J10 -> 1.2521653e+08
B38: EBITDA | C38: USD | D38: =ProfLoss!D27 -> 11035331 | E38: =ProfLoss!E27 -> 53030081 | F38: =ProfLoss!F27 -> 56029869 | G38: =ProfLoss!G27 -> 63019565 | H38: =ProfLoss!H27 -> 52039956 | I38: =ProfLoss!I27 -> 53069157 | J38: =ProfLoss!J27 -> 54159268
B39: Чистая прибыль | C39: USD | D39: =ProfLoss!D22 -> 3541570.5 | E39: =ProfLoss!E22 -> 19438643 | F39: =ProfLoss!F22 -> 21292482 | G39: =ProfLoss!G22 -> 24368803 | H39: =ProfLoss!H22 -> 15587710 | I39: =ProfLoss!I22 -> 16481056 | J39: =ProfLoss!J22 -> 17415037
B40: Операционный поток наличности (A) | C40: USD | D40: =CashFlow!D18 -> -16752461 | E40: =CashFlow!E18 -> 52390242 | F40: =CashFlow!F18 -> 42237651 | G40: =CashFlow!G18 -> 40056298 | H40: =CashFlow!H18 -> 33451740 | I40: =CashFlow!I18 -> 33632223 | J40: =CashFlow!J18 -> 34187695
B41: Обслуживание долга (проценты + основной долг) | C41: USD | D41: =LOANS!$C$107 -> 3036468.2 | E41: =LOANS!$D$107 -> 9942271 | F41: =LOANS!$E$107 -> 9427989.5 | G41: =LOANS!$F$107 -> 8921911.4 | H41: =LOANS!$G$107 -> 8415833.4 | I41: =LOANS!$H$107 -> 7912412.9 | J41: =LOANS!$I$107 -> 7403677.3
B42: Чистый поток наличности | C42: USD | D42: =CashFlow!D26 -> 10043303 | E42: =CashFlow!E26 -> 41036542 | F42: =CashFlow!F26 -> 31398233 | G42: =CashFlow!G26 -> 29722958 | H42: =CashFlow!H26 -> 23624478 | I42: =CashFlow!I26 -> 24308382 | J42: =CashFlow!J26 -> 25372589
B43: Кумулятивный поток наличности | C43: USD | D43: =CashFlow!D27 -> 10043303 | E43: =CashFlow!E27 -> 51079845 | F43: =CashFlow!F27 -> 82478078 | G43: =CashFlow!G27 -> 1.1220104e+08 | H43: =CashFlow!H27 -> 1.3582551e+08 | I43: =CashFlow!I27 -> 1.601339e+08 | J43: =CashFlow!J27 -> 1.8550648e+08
B44: DSCR (с учётом поддерживающих капвложений) | C44: x | D44: =CashFlow!D30 -> - | E44: =CashFlow!E30 -> 5.1274818 | F44: =CashFlow!F30 -> 4.3303212 | G44: =CashFlow!G30 -> 4.3314563 | H44: =CashFlow!H30 -> 3.8071466 | I44: =CashFlow!I30 -> 4.0721832 | J44: =CashFlow!J30 -> 4.4270252
B45: Задолженность по кредиту на конец года | C45: USD | D45: =LOANS!$C$108 -> 42783896 | E45: =LOANS!$D$108 -> 35653247 | F45: =LOANS!$E$108 -> 28522598 | G45: =LOANS!$F$108 -> 21391948 | H45: =LOANS!$G$108 -> 14261299 | I45: =LOANS!$H$108 -> 7130649.4 | J45: =LOANS!$I$108 -> 0
B47: 5. ПОКАЗАТЕЛИ ЭФФЕКТИВНОСТИ И УСТОЙЧИВОСТИ
B48: NPV проекта за 7 лет, USD | C48: =NPV_IRR!D18 -> 4579191.2
B49: IRR проекта за 7 лет | C49: =NPV_IRR!D19 -> 0.1259814
B50: Индекс доходности (PI) | C50: =NPV_IRR!D20 -> 1.0322036
B51: Простой срок окупаемости, лет | C51: =NPV_IRR!D21 -> 4.8712739
B52: Дисконтированный срок окупаемости, лет | C52: =NPV_IRR!D22 -> 6.7030576
B53: Минимальный / средний DSCR (2-7 годы) | C53: =TEXT(CashFlow!D31,"0.00") & "x / " & TEXT(CashFlow!D32,"0.00") & "x" -> 3.81x / 4.35x
B54: Точка безубыточности (2030 г.), % от выручки | C54: =BreakPoint!C10 -> 0.37256274
B56: 6. ВЫПОЛНЕНИЕ УСЛОВИЙ ФИНАНСИРОВАНИЯ
B57: Положительный чистый поток наличности в каждом из 1-7 годов | C57: =IF(MIN(CashFlow!D26:J26)>0,"Да","Нет") -> Да
B58: Чистая прибыль в каждом из 1-7 годов | C58: =IF(MIN(ProfLoss!D22:J22)>0,"Да","Нет") -> Да
B59: Погашение кредита в течение 6 лет после льготного периода | C59: =IF(ABS(LOANS!$I$108)<1,"Да","Нет") -> Да
B60: Проценты льготного периода покрыты собственными средствами | C60: =IF(ProjCost!E18>0,"Да","Нет") -> Да
B61: Дисконтированный срок окупаемости - в пределах срока кредита (7 лет) | C61: =IF(AND(ISNUMBER(NPV_IRR!D22),NPV_IRR!D22<=7),"Да","Нет") -> Да
B63: 7. ОСНОВНЫЕ ДОПУЩЕНИЯ
B64: - Производственные, затратные, налоговые и инвестиционные показатели приняты по ТЭО проекта; цены реализации - на консервативном уровне.
B65: - Сумма кредита определена по 30% авансу по EPC-контрактам (распределение 78 млн USD между тремя проектами - лист «ИНФОРМАЦИЯ»).
B66: - Кредит: 7% годовых, 84 месяца, льготный период 12 месяцев, погашение основного долга ежемесячно равными долями; база начисления процентов - 360 дней.
B67: - Все затраты сверх суммы кредита финансируются за счёт собственных средств заемщика.
B68: - Кредит выдаётся единовременно 01.01.2027; проценты 2027 г. капитализируются в стоимость основных средств.
B69: - Резерв на непредвиденные расходы - 1% суммы кредита.
B71: 8. ОСНОВНЫЕ РИСКИ И МЕРЫ ПО ИХ СНИЖЕНИЮ
B72: Ценовой риск | C72: ="Точка безубыточности при проектной мощности - " & TEXT(BreakPoint!C10,"0%") & " выручки; цены реализации в плане приняты консервативно. Меры: долгосрочные контракты на реализацию, мониторинг рыночных цен." -> Точка безубыточности при проектной мощности - 37% выручки; цены реализации в плане приняты консервативно. Меры: долгосрочные контракты на реализацию, мониторинг рыночных цен.
B73: Валютный риск | C73: ="Доля экспорта в выручке: " & TEXT(SalePlan!G8/SalePlan!G14,"0%") & "; цены продукции установлены в USD; кредит - в USD (естественное хеджирование валютной позиции)." -> Доля экспорта в выручке: 0%; цены продукции установлены в USD; кредит - в USD (естественное хеджирование валютной позиции).
B74: Риск освоения мощностей | C74: ="Освоение мощности: 1-й год - " & TEXT(ProdPlan!D11,"0%") & ", 2-й год - " & TEXT(ProdPlan!E11,"0%") & ", 3-й год - " & TEXT(ProdPlan!F11,"0%") & "; льготный период 12 мес. и запас DSCR (мин. " & TEXT(CashFlow!D31,"0.00") & "x) покрывают период выхода на мощность." -> Освоение мощности: 1-й год - 16%, 2-й год - 56%, 3-й год - 60%; льготный период 12 мес. и запас DSCR (мин. 3.81x) покрывают период выхода на мощность.
B75: Строительный риск | C75: ="Капитальные затраты приняты в фиксированных ценах (EPC-контракт: проектирование, поставка, строительство); превышение сметы финансируется за счёт собственных средств заемщика." -> Капитальные затраты приняты в фиксированных ценах (EPC-контракт: проектирование, поставка, строительство); превышение сметы финансируется за счёт собственных средств заемщика.
B76: Налоговый риск | C76: ="Проект является плательщиком специального рентного налога (25%) и НДПИ; налоговая нагрузка учтена в Приложении 9." -> Проект является плательщиком специального рентного налога (25%) и НДПИ; налоговая нагрузка учтена в Приложении 9.

Sheet ИНФОРМАЦИЯ
B2: ДАННЫЕ ПО ПРОЕКТУ
B4: ЗАЕМЩИК | C4: АО «Узбекский комбинат технологических металлов» (АО «Ўзбекистон ТМК», UzTMK)
B5: ИНН | C5: - (заполняется заемщиком)
B6: ДЕЯТЕЛЬНОСТЬ | C6: Добыча и переработка редких и тугоплавких металлов (вольфрам, молибден)
B7: НАИМЕНОВАНИЕ ПРОЕКТА | C7: Освоение центральной части вольфрамового месторождения Сарикуль (1-я очередь) (Освоение вольфрамового месторождения Сарикул)
B8: МЕСТО РЕАЛИЗАЦИИ | C8: месторождение Сарикул
B9: ПРОИЗВОДСТВЕННАЯ МОЩНОСТЬ | C9: Переработка 600 тыс. т руды в год
B10: ОСНОВНАЯ ПРОДУКЦИЯ | C10: Вольфрамовый концентрат 57,8% WO3
B11: СТАДИЯ ПРОРАБОТКИ | C11: Предварительное ТЭО (Pre-FS)
B12: НАЧАЛО СТРОИТЕЛЬСТВА | C12: 01.09.2026
B13: НАЧАЛО ПРОИЗВОДСТВА | C13: 01.09.2027
B14: СРОК РЕАЛИЗАЦИИ (по данным заемщика) | C14: декабрь 2027 г.
B16: УЧАСТНИКИ ПРОЕКТА
B17: Заемщик (инициатор проекта) | C17: АО «Узбекский комбинат технологических металлов» (АО «Ўзбекистон ТМК», UzTMK)
B18: Доля заемщика в проекте | C18: 100%
B19: Кредитор №1 | C19: Банк-кредитор (наименование уточняется)
B20: Генеральный подрядчик | C20: EPC-подрядчик (по EPC-контракту)
B22: ВАЛЮТА ПРОЕКТА | C22: Доллар США (экв.)
B23: 1 USD = (сум, средний курс 1-го года) | C23: 12218.063
B25: УСЛОВИЯ КРЕДИТА
B26: Сумма кредита, USD | C26: =O40 -> 42783896
B27: Процентная ставка, % годовых | C27: 0.07
B28: Срок кредита, месяцев | C28: 84
B29: Льготный период по основному долгу, месяцев | C29: 12
B30: Инвестиционный период, месяцев | C30: 12
B31: Дата выдачи кредита | C31: 46388
B32: База начисления процентов, дней в году (по форме банка) | C32: 360
B33: Погашение основного долга | C33: ежемесячно равными долями (72 платежа), с 31.01.2028 по 31.12.2033
B34: Уплата процентов | C34: ежемесячно; в льготный период (2027 г.) - за счёт собственных средств заемщика (включены в стоимость проекта)
B35: Целевое назначение | C35: 30% авансовый платёж по EPC-контракту (данные заемщика)
B36: Резерв (непредвиденные расходы) - % от суммы кредита (по форме банка) | C36: 0.01
B38: РАСПРЕДЕЛЕНИЕ КРЕДИТА 78 МЛН USD МЕЖДУ ПРОЕКТАМИ (по 30% авансу EPC-контрактов, файл заемщика от 14.10.2026)
B39: Проект | C39: Мощность | D39: Стоимость проекта, млн USD | E39: EPC: E (Engineering), млрд сум | F39: EPC: P (Procurement), млрд сум | G39: EPC: C (Construction), млрд сум | H39: EPC итого, млрд сум | I39: Курс EPC (тыс. сум/USD) | J39: EPC итого, экв. млн USD | K39: 30% аванс, млрд сум | L39: Курс аванса (тыс. сум/USD) | M39: 30% аванс, млн USD | N39: Доля в кредите | O39: Кредит, USD
B40: Освоение центральной части вольфрамового месторождения Сарикуль (1-я очередь) | C40: Переработка 600 тыс. т руды в год | D40: 158 | E40: 116.0323 | F40: 532.896 | G40: 1041.5674 | H40: =E40+F40+G40 -> 1690.4957 | I40: 12.2 | J40: =H40/I40 -> 138.56522 | K40: =H40*30% -> 507.1487 | L40: 11.838 | M40: =K40/L40 -> 42.840742 | N40: =M40/$M$43 -> 0.54851149 | O40: =N40*$O$44 -> 42783896
B41: Строительство нового гидрометаллургического завода по переработке вольфрамового концентрата (1-я очередь) | C41: Переработка 5 000 т вольфрамового концентрата в год | D41: 80 | E41: 25.272 | F41: 293.4 | G41: 353.99904 | H41: =E41+F41+G41 -> 672.67104 | I41: 12 | J41: =H41/I41 -> 56.05592 | K41: =H41*30% -> 201.80131 | L41: 11.838 | M41: =K41/L41 -> 17.046909 | N41: =M41/$M$43 -> 0.21826012 | O41: =N41*$O$44 -> 17024290
B42: Строительство нового гидрометаллургического завода по переработке промышленного продукта - молибденового огарка | C42: Переработка 5 000 т молибденового огарка (концентрата) в год | D42: 65 | E42: 25.35648 | F42: 251.13528 | G42: 442.311 | H42: =E42+F42+G42 -> 718.80276 | I42: 12 | J42: =H42/I42 -> 59.90023 | K42: =H42*30% -> 215.64083 | L42: 11.838 | M42: =K42/L42 -> 18.215985 | N42: =M42/$M$43 -> 0.23322838 | O42: =N42*$O$44 -> 18191814
B43: ИТОГО | D43: =SUM(D40:D42) -> 303 | E43: =SUM(E40:E42) -> 166.66078 | F43: =SUM(F40:F42) -> 1077.4313 | G43: =SUM(G40:G42) -> 1837.8774 | H43: =SUM(H40:H42) -> 3081.9695 | J43: =SUM(J40:J42) -> 254.52137 | K43: =SUM(K40:K42) -> 924.59084 | M43: =SUM(M40:M42) -> 78.103636 | N43: =SUM(N40:N42) -> 1 | O43: =SUM(O40:O42) -> 78000000
N44: Лимит кредита, USD | O44: 78000000
B46: Распределение кредита - пропорционально 30% авансу по EPC-контрактам, с приведением к лимиту 78,0 млн USD.

Sheet ProjCost
B2: ПЕРВОНАЧАЛЬНАЯ СТОИМОСТЬ ПРОЕКТА (в экв. долл. США) | F2: Приложение 1
B3: Инвестиционный период: с начала строительства по 31.12.2027 (1-й год кредита, льготный период).
B4: Наименование затрат | C4: МЕСТНАЯ ВАЛЮТА | D4: ТВЕРДАЯ ВАЛЮТА | E4: ВСЕГО | F4: СТРУКТУРА (%)
B5: ВСЕГО ФИКСИРОВАННЫЕ АКТИВЫ | C5: =SUM(C6:C10) -> 0 | D5: =SUM(D6:D10) -> 1.4161333e+08 | E5: =SUM(E6:E10) -> 1.4161333e+08 | F5: =IFERROR(E5/$E$22,0) -> 0.8259959
B6: Здания, сооружения и передаточные устройства | C6: =0 -> 0 | D6: 28000000 | E6: =C6+D6 -> 28000000 | F6: =IFERROR(E6/$E$22,0) -> 0.16331714
B7: Машины и оборудование | C7: =0 -> 0 | D7: 82470476 | E7: =C7+D7 -> 82470476 | F7: =IFERROR(E7/$E$22,0) -> 0.48103009
B8: Горно-капитальные работы и геологоразведка | C8: =0 -> 0 | D8: 22142857 | E8: =C8+D8 -> 22142857 | F8: =IFERROR(E8/$E$22,0) -> 0.12915386
B9: Транспортные средства | C9: =0 -> 0 | D9: 5000000 | E9: =C9+D9 -> 5000000 | F9: =IFERROR(E9/$E$22,0) -> 0.029163776
B10: Прочие основные средства | C10: =0 -> 0 | D10: 4000000 | E10: =C10+D10 -> 4000000 | F10: =IFERROR(E10/$E$22,0) -> 0.023331021
B11: РАБОЧИЙ КАПИТАЛ (на 31.12.2027), ВКЛЮЧАЯ: | C11: =SUM(C12:C16) -> 17580621 | D11: =SUM(D12:D16) -> 7713573.4 | E11: =SUM(E12:E16) -> 25294194 | F11: =IFERROR(E11/$E$22,0) -> 0.14753484
B12: Запасы сырья, материалов и готовой продукции | C12: 1521163.9 | D12: 0 | E12: =C12+D12 -> 1521163.9 | F12: =IFERROR(E12/$E$22,0) -> 0.0088725766
B13: Дебиторская задолженность покупателей | C13: 0 | D13: 7713573.4 | E13: =C13+D13 -> 7713573.4 | F13: =IFERROR(E13/$E$22,0) -> 0.044991385
B14: НДС к возмещению (в т.ч. по капитальным вложениям) | C14: 16825503 | D14: 0 | E14: =C14+D14 -> 16825503 | F14: =IFERROR(E14/$E$22,0) -> 0.098139038
B15: Кредиторская задолженность поставщикам (уменьшает потребность) | C15: -397060 | D15: 0 | E15: =C15+D15 -> -397060 | F15: =IFERROR(E15/$E$22,0) -> -0.0023159538
B16: Задолженность по оплате труда и налогам с ФОТ (уменьшает потребность) | C16: -368986 | D16: 0 | E16: =C16+D16 -> -368986 | F16: =IFERROR(E16/$E$22,0) -> -0.002152205
B17: ПРОЧИЕ ФИНАНСОВЫЕ ИЗДЕРЖКИ, ВКЛЮЧАЯ: | C17: =SUM(C18:C19) -> 1073730.1 | D17: =SUM(D18:D19) -> 3036468.2 | E17: =SUM(E18:E19) -> 4110198.3 | F17: =IFERROR(E17/$E$22,0) -> 0.02397378
B18: Проценты по кредиту за льготный период (2027 г.) - за счёт собственных средств | C18: 0 | D18: =LOANS!$C$106 -> 3036468.2 | E18: =C18+D18 -> 3036468.2 | F18: =IFERROR(E18/$E$22,0) -> 0.017710976
B19: Расходы подготовительного периода 2026 г. (административные и пусковые расходы) | C19: 1073730.1 | D19: 0 | E19: =C19+D19 -> 1073730.1 | F19: =IFERROR(E19/$E$22,0) -> 0.0062628049
B20: НЕПРЕДВИДЕННЫЕ РАСХОДЫ/РЕЗЕРВ (1% от суммы кредита) | C20: 0 | D20: =ИНФОРМАЦИЯ!$C$26*ИНФОРМАЦИЯ!$C$36 -> 427838.96 | E20: =C20+D20 -> 427838.96 | F20: =IFERROR(E20/$E$22,0) -> 0.0024954799
B22: ВСЕГО ПЕРВОНАЧАЛЬНАЯ СТОИМОСТЬ ПРОЕКТА | C22: =C5+C11+C17+C20 -> 18654351 | D22: =D5+D11+D17+D20 -> 1.5279121e+08 | E22: =E5+E11+E17+E20 -> 1.7144556e+08 | F22: =IFERROR(E22/$E$22,0) -> 1

Sheet FinPlan
B2: ФИНАНСОВЫЙ ПЛАН (в экв. долл. США) | G2: Приложение 2
B4: ПОКАЗАТЕЛИ | C4: МЕСТНАЯ ВАЛЮТА | D4: ТВЁРДАЯ ВАЛЮТА | E4: ВСЕГО | F4: СТРУКТУРА (%) | G4: ДОЛЯ В ФИНАНСИРОВАНИИ
B5: СОБСТВЕННЫЙ КАПИТАЛ
B6: АО «Узбекский комбинат технологических металлов» (АО «Ўзбекистон ТМК», UzTMK)
B7: Фиксированные активы | C7: ='Share of costs'!C6 -> 0 | D7: ='Share of costs'!D6 -> 98829437 | E7: =C7+D7 -> 98829437 | F7: =IFERROR(E7/$E$10,0) -> 0.76813427
B8: Рабочий капитал | C8: ='Share of costs'!C12 -> 17580621 | D8: ='Share of costs'!D12 -> 7713573.4 | E8: =C8+D8 -> 25294194 | F8: =IFERROR(E8/$E$10,0) -> 0.19659464
B9: Денежные средства (финансовые издержки льготного периода, расходы подготовительного периода, резерв) | C9: ='Share of costs'!C13+'Share of costs'!C16 -> 1073730.1 | D9: ='Share of costs'!D13+'Share of costs'!D16 -> 3464307.2 | E9: =C9+D9 -> 4538037.3 | F9: =IFERROR(E9/$E$10,0) -> 0.03527109
B10: ВСЕГО | C10: =SUM(C7:C9) -> 18654351 | D10: =SUM(D7:D9) -> 1.1000732e+08 | E10: =SUM(E7:E9) -> 1.2866167e+08 | F10: =IFERROR(E10/$E$10,0) -> 1 | G10: =IFERROR(E10/$E$15,0) -> 0.75045201
B11: КРЕДИТЫ
B12: Банк (кредит 7% годовых, 84 мес., льготный период 12 мес.) | C12: =C13 -> 0 | D12: =D13 -> 42783896 | E12: =C12+D12 -> 42783896 | F12: =IFERROR(E12/$E$14,0) -> 1
B13: Фиксированные активы (30% аванс по EPC-контракту) | C13: ='Share of costs'!E6 -> 0 | D13: ='Share of costs'!F6 -> 42783896 | E13: =C13+D13 -> 42783896 | F13: =IFERROR(E13/$E$14,0) -> 1
B14: ВСЕГО | C14: =C12 -> 0 | D14: =D12 -> 42783896 | E14: =E12 -> 42783896 | F14: =IFERROR(E14/$E$14,0) -> 1 | G14: =IFERROR(E14/$E$15,0) -> 0.24954799
B15: ВСЕГО ФИНАНСИРОВАНИЯ | C15: =C14+C10 -> 18654351 | D15: =D14+D10 -> 1.5279121e+08 | E15: =E14+E10 -> 1.7144556e+08 | G15: =IFERROR(E15/$E$15,0) -> 1

Sheet Share of costs
B2: ПЕРВОНАЧАЛЬНАЯ СТОИМОСТЬ ПРОЕКТА ПО ИСТОЧНИКАМ ФИНАНСИРОВАНИЯ (в экв. долл. США) | H2: Приложение 3
B4: Наименование затрат | C4: Собственные средства заемщика | E4: Кредит банка | G4: Всего
C5: в местной валюте | D5: в твердой валюте | E5: в местной валюте | F5: в твердой валюте | G5: в местной валюте | H5: в твердой валюте
B6: ВСЕГО ФИКСИРОВАННЫЕ АКТИВЫ | C6: =SUM(C7:C11) -> 0 | D6: =SUM(D7:D11) -> 98829437 | E6: =SUM(E7:E11) -> 0 | F6: =SUM(F7:F11) -> 42783896 | G6: =SUM(G7:G11) -> 0 | H6: =SUM(H7:H11) -> 1.4161333e+08
B7: Здания, сооружения и передаточные устройства | C7: =ProjCost!$C$6 -> 0 | D7: =ProjCost!$D$6-F7 -> 12848992 | E7: 0 | F7: =ИНФОРМАЦИЯ!$C$26*(1-ИНФОРМАЦИЯ!$F$40/ИНФОРМАЦИЯ!$H$40)*ProjCost!$E$6/(ProjCost!$E$6+ProjCost!$E$8+ProjCost!$E$10) -> 15151008 | G7: =C7+E7 -> 0 | H7: =D7+F7 -> 28000000
B8: Машины и оборудование | C8: =ProjCost!$C$7 -> 0 | D8: =ProjCost!$D$7-F8 -> 69754616 | E8: 0 | F8: =ИНФОРМАЦИЯ!$C$26*ИНФОРМАЦИЯ!$F$40/ИНФОРМАЦИЯ!$H$40*ProjCost!$E$7/(ProjCost!$E$7+ProjCost!$E$9) -> 12715860 | G8: =C8+E8 -> 0 | H8: =D8+F8 -> 82470476
B9: Горно-капитальные работы и геологоразведка | C9: =ProjCost!$C$8 -> 0 | D9: =ProjCost!$D$8-F9 -> 10161193 | E9: 0 | F9: =ИНФОРМАЦИЯ!$C$26*(1-ИНФОРМАЦИЯ!$F$40/ИНФОРМАЦИЯ!$H$40)*ProjCost!$E$8/(ProjCost!$E$6+ProjCost!$E$8+ProjCost!$E$10) -> 11981664 | G9: =C9+E9 -> 0 | H9: =D9+F9 -> 22142857
B10: Транспортные средства | C10: =ProjCost!$C$9 -> 0 | D10: =ProjCost!$D$9-F10 -> 4229065.9 | E10: 0 | F10: =ИНФОРМАЦИЯ!$C$26*ИНФОРМАЦИЯ!$F$40/ИНФОРМАЦИЯ!$H$40*ProjCost!$E$9/(ProjCost!$E$7+ProjCost!$E$9) -> 770934.08 | G10: =C10+E10 -> 0 | H10: =D10+F10 -> 5000000
B11: Прочие основные средства | C11: =ProjCost!$C$10 -> 0 | D11: =ProjCost!$D$10-F11 -> 1835570.3 | E11: 0 | F11: =ИНФОРМАЦИЯ!$C$26*(1-ИНФОРМАЦИЯ!$F$40/ИНФОРМАЦИЯ!$H$40)*ProjCost!$E$10/(ProjCost!$E$6+ProjCost!$E$8+ProjCost!$E$10) -> 2164429.7 | G11: =C11+E11 -> 0 | H11: =D11+F11 -> 4000000
B12: РАБОЧИЙ КАПИТАЛ | C12: =ProjCost!$C$11 -> 17580621 | D12: =ProjCost!$D$11 -> 7713573.4 | E12: 0 | F12: 0 | G12: =C12+E12 -> 17580621 | H12: =D12+F12 -> 7713573.4
B13: ПРОЧИЕ ФИНАНСОВЫЕ ИЗДЕРЖКИ | C13: =ProjCost!$C$17 -> 1073730.1 | D13: =ProjCost!$D$17 -> 3036468.2 | E13: 0 | F13: 0 | G13: =C13+E13 -> 1073730.1 | H13: =D13+F13 -> 3036468.2
B14: в т.ч. проценты по кредиту за льготный период | C14: =ProjCost!$C$18 -> 0 | D14: =ProjCost!$D$18 -> 3036468.2 | E14: 0 | F14: 0 | G14: =C14+E14 -> 0 | H14: =D14+F14 -> 3036468.2
B15: в т.ч. расходы подготовительного периода 2026 г. | C15: =ProjCost!$C$19 -> 1073730.1 | D15: =ProjCost!$D$19 -> 0 | E15: 0 | F15: 0 | G15: =C15+E15 -> 1073730.1 | H15: =D15+F15 -> 0
B16: НЕПРЕДВИДЕННЫЕ РАСХОДЫ/РЕЗЕРВ | C16: =ProjCost!$C$20 -> 0 | D16: =ProjCost!$D$20 -> 427838.96 | E16: 0 | F16: 0 | G16: =C16+E16 -> 0 | H16: =D16+F16 -> 427838.96
B18: ВСЕГО ПЕРВОНАЧАЛЬНАЯ СТОИМОСТЬ ПРОЕКТА | C18: =C6+C12+C13+C16 -> 18654351 | D18: =D6+D12+D13+D16 -> 1.1000732e+08 | E18: =E6+E12+E13+E16 -> 0 | F18: =F6+F12+F13+F16 -> 42783896 | G18: =G6+G12+G13+G16 -> 18654351 | H18: =H6+H12+H13+H16 -> 1.5279121e+08
B19: Итого по источнику | C19: =C18+D18 -> 1.2866167e+08 | E19: =E18+F18 -> 42783896 | G19: =G18+H18 -> 1.7144556e+08
B21: Кредит банка направляется на 30% авансовый платёж по EPC-контракту; распределение по группам активов - пропорционально составу EPC-контракта: P (поставка оборудования) - машины и оборудование, E+C (проектирование и строительство) - здания, сооружения и прочие объекты.

Sheet Depreciate
B2: АМОРТИЗАЦИЯ (в долл. США) | N2: Приложение 4
B3: Линейный метод. Проценты льготного периода капитализированы в стоимость основных средств (МСФО IAS 23).
B5: ОБЪЕКТЫ АМОРТИЗАЦИИ | C5: Группа основных средств | D5: Первоначальная стоимость | E5: Срок, лет | F5: Норма, % | G5: 1 год | H5: 2 год | I5: 3 год | J5: 4 год | K5: 5 год | L5: 6 год | M5: 7 год
G6: 2027 | H6: 2028 | I6: 2029 | J6: 2030 | K6: 2031 | L6: 2032 | M6: 2033
B7: Хвостохранилище | C7: Здания, сооружения и передаточные устройства | D7: 10000000 | E7: 9 | F7: =1/E7 -> 0.11111111 | G7: 370370.37 | H7: 1111111.1 | I7: 1111111.1 | J7: 1111111.1 | K7: 1111111.1 | L7: 1111111.1 | M7: 1111111.1
B8: Здания | C8: Здания, сооружения и передаточные устройства | D8: 8000000 | E8: 9 | F8: =1/E8 -> 0.11111111 | G8: 296296.3 | H8: 888888.89 | I8: 888888.89 | J8: 888888.89 | K8: 888888.89 | L8: 888888.89 | M8: 888888.89
B9: Тоннель и автодороги | C9: Здания, сооружения и передаточные устройства | D9: 5000000 | E9: 9 | F9: =1/E9 -> 0.11111111 | G9: 185185.19 | H9: 555555.56 | I9: 555555.56 | J9: 555555.56 | K9: 555555.56 | L9: 555555.56 | M9: 555555.56
B10: Обогатительная фабрика | C10: Машины и оборудование | D10: 82000000 | E10: 9 | F10: =1/E10 -> 0.11111111 | G10: 3037037 | H10: 9111111.1 | I10: 9111111.1 | J10: 9111111.1 | K10: 9111111.1 | L10: 9111111.1 | M10: 9111111.1
B11: Электро- и водоснабжение | C11: Здания, сооружения и передаточные устройства | D11: 5000000 | E11: 9 | F11: =1/E11 -> 0.11111111 | G11: 185185.19 | H11: 555555.56 | I11: 555555.56 | J11: 555555.56 | K11: 555555.56 | L11: 555555.56 | M11: 555555.56
B12: Карьер (открытые горные работы) | C12: Горно-капитальные работы и геологоразведка | D12: 5000000 | E12: 9 | F12: =1/E12 -> 0.11111111 | G12: 185185.19 | H12: 555555.56 | I12: 555555.56 | J12: 555555.56 | K12: 555555.56 | L12: 555555.56 | M12: 555555.56
B13: Подземный рудник | C13: Горно-капитальные работы и геологоразведка | D13: 10000000 | E13: 9 | F13: =1/E13 -> 0.11111111 | G13: 370370.37 | H13: 1111111.1 | I13: 1111111.1 | J13: 1111111.1 | K13: 1111111.1 | L13: 1111111.1 | M13: 1111111.1
B14: Транспортные средства | C14: Транспортные средства | D14: 5000000 | E14: 9 | F14: =1/E14 -> 0.11111111 | G14: 185185.19 | H14: 555555.56 | I14: 555555.56 | J14: 555555.56 | K14: 555555.56 | L14: 555555.56 | M14: 555555.56
B15: Прочие объекты | C15: Прочие основные средства | D15: 4000000 | E15: 9 | F15: =1/E15 -> 0.11111111 | G15: 148148.15 | H15: 444444.44 | I15: 444444.44 | J15: 444444.44 | K15: 444444.44 | L15: 444444.44 | M15: 444444.44
B16: Геологоразведочные и прочие исследования (выполненные) | C16: Горно-капитальные работы и геологоразведка | D16: 7142857.1 | E16: 9 | F16: =1/E16 -> 0.11111111 | G16: 264550.26 | H16: 793650.79 | I16: 793650.79 | J16: 793650.79 | K16: 793650.79 | L16: 793650.79 | M16: 793650.79
B17: Поддерживающие капвложения (% от первоначальной стоимости ОС) | C17: Машины и оборудование | D17: 8939047.6 | E17: 10 | F17: =1/E17 -> 0.1 | G17: 9801.5873 | H17: 188190.48 | I17: 329333.33 | J17: 470476.19 | K17: 611619.05 | L17: 752761.9 | M17: 893904.76
B18: Капитализированные проценты по кредиту за льготный период (2027 г.) | C18: Затраты по займам (МСФО IAS 23) | D18: =LOANS!$C$106 -> 3036468.2 | E18: 20 | F18: =1/E18 -> 0.05 | G18: 50607.803 | H18: =D18/E18 -> 151823.41 | I18: =D18/E18 -> 151823.41 | J18: =D18/E18 -> 151823.41 | K18: =D18/E18 -> 151823.41 | L18: =D18/E18 -> 151823.41 | M18: =D18/E18 -> 151823.41
B19: ВСЕГО | C19: Х | D19: =SUM(D7:D18) -> 1.5311837e+08 | G19: =SUM(G7:G18) -> 5287922.6 | H19: =SUM(H7:H18) -> 16022554 | I19: =SUM(I7:I18) -> 16163696 | J19: =SUM(J7:J18) -> 16304839 | K19: =SUM(K7:K18) -> 16445982 | L19: =SUM(L7:L18) -> 16587125 | M19: =SUM(M7:M18) -> 16728268
B20: в т.ч. в себестоимости продукции | G20: =G19-G21 -> 5287922.6 | H20: =H19-H21 -> 16022554 | I20: =I19-I21 -> 16163696 | J20: =J19-J21 -> 16304839 | K20: =K19-K21 -> 16445982 | L20: =L19-L21 -> 16587125 | M20: =M19-M21 -> 16728268
B21: в т.ч. в административных расходах | G21: 0 | H21: 0 | I21: 0 | J21: 0 | K21: 0 | L21: 0 | M21: 0
B23: Накопленная амортизация | G23: =SUM($G$19:G19) -> 5287922.6 | H23: =SUM($G$19:H19) -> 21310476 | I23: =SUM($G$19:I19) -> 37474173 | J23: =SUM($G$19:J19) -> 53779012 | K23: =SUM($G$19:K19) -> 70224994 | L23: =SUM($G$19:L19) -> 86812119 | M23: =SUM($G$19:M19) -> 1.0354039e+08
B24: Остаточная стоимость основных средств (на конец года) | G24: 1.3936188e+08 | H24: 1.2475075e+08 | I24: 1.0999849e+08 | J24: 95105075 | K24: 80070522 | L24: 64894825 | M24: 49577986

Sheet ProdPlan
B2: ПРОИЗВОДСТВЕННЫЙ ПЛАН | K2: Приложение 5
B4: Н А И М Е Н О В А Н И Е | C4: Ед. изм. | D4: Мощность в год | E4: Рынок сбыта | F4: Цена за единицу, USD (2030 г.) | G4: Выручка при полной мощности: экспорт | H4: Выручка при полной мощности: внутр. рынок
B5: Вольфрамовый концентрат 57,8% WO3 | C5: t | D5: 4200 | E5: внутренний рынок | F5: 38116 | G5: 0 | H5: =D5*F5 -> 160087200
B6: Всего | G6: =SUM(G5:G5) -> 0 | H6: =SUM(H5:H5) -> 160087200
B8: ПОКАЗАТЕЛИ | C8: Ед. изм. | D8: 1 год (льготный / инвест.) | E8: 2 год | F8: 3 год | G8: 4 год | H8: 5 год | I8: 6 год | J8: 7 год
D9: 2027 | E9: 2028 | F9: 2029 | G9: 2030 | H9: 2031 | I9: 2032 | J9: 2033
B10: ОСВОЕНИЕ МОЩНОСТЕЙ
B11: Вольфрамовый концентрат 57,8% WO3 | C11: % | D11: 0.15786295 | E11: 0.55511995 | F11: 0.600342 | G11: 0.76268516 | H11: 0.73323971 | I11: 0.73275148 | J11: 0.73275148
B12: КОЛИЧЕСТВО ПРОИЗВОДСТВА
B13: Вольфрамовый концентрат 57,8% WO3 | C13: t | D13: =$D$5*D11 -> 663.02439 | E13: =$D$5*E11 -> 2331.5038 | F13: =$D$5*F11 -> 2521.4364 | G13: =$D$5*G11 -> 3203.2777 | H13: =$D$5*H11 -> 3079.6068 | I13: =$D$5*I11 -> 3077.5562 | J13: =$D$5*J11 -> 3077.5562
B14: КОЛИЧЕСТВО ДЛЯ РЕАЛИЗАЦИИ
B15: Вольфрамовый концентрат 57,8% WO3 - экспорт | C15: t | D15: 0 | E15: 0 | F15: 0 | G15: 0 | H15: 0 | I15: 0 | J15: 0
B16: Вольфрамовый концентрат 57,8% WO3 - внутренний рынок | C16: t | D16: 663.02439 | E16: 2331.5038 | F16: 2521.4364 | G16: 3203.2777 | H16: 3079.6068 | I16: 3077.5562 | J16: 3077.5562
B17: КОЛИЧЕСТВО ЗАПАСА ГОТОВОЙ ПРОДУКЦИИ НА КОНЕЦ ГОДА
B18: Вольфрамовый концентрат 57,8% WO3 | C18: t | D18: =0+D13-D15-D16 -> 0 | E18: =D18+E13-E15-E16 -> 0 | F18: =E18+F13-F15-F16 -> 0 | G18: =F18+G13-G15-G16 -> 0 | H18: =G18+H13-H15-H16 -> 0 | I18: =H18+I13-I15-I16 -> 0 | J18: =I18+J13-J15-J16 -> 0
B19: ЦЕНА РЕАЛИЗАЦИИ
B20: Вольфрамовый концентрат 57,8% WO3 | C20: USD/t | D20: 35989 | E20: 36493 | F20: 37295 | G20: 38116 | H20: 38954 | I20: 39811 | J20: 40687

Sheet SalePlan
B2: ПЛАН ПРОДАЖ (в экв. долл. США, без НДС) | K2: Приложение 6
B4: ПОКАЗАТЕЛИ | C4: Ед. изм. | D4: 1 год (льготный / инвест.) | E4: 2 год | F4: 3 год | G4: 4 год | H4: 5 год | I4: 6 год | J4: 7 год
D5: 2027 | E5: 2028 | F5: 2029 | G5: 2030 | H5: 2031 | I5: 2032 | J5: 2033
B6: ЭКСПОРТ
B7: Вольфрамовый концентрат 57,8% WO3 | C7: USD | D7: =ProdPlan!D15*ProdPlan!D20 -> 0 | E7: =ProdPlan!E15*ProdPlan!E20 -> 0 | F7: =ProdPlan!F15*ProdPlan!F20 -> 0 | G7: =ProdPlan!G15*ProdPlan!G20 -> 0 | H7: =ProdPlan!H15*ProdPlan!H20 -> 0 | I7: =ProdPlan!I15*ProdPlan!I20 -> 0 | J7: =ProdPlan!J15*ProdPlan!J20 -> 0
B8: Всего | C8: USD | D8: =SUM(D7:D7) -> 0 | E8: =SUM(E7:E7) -> 0 | F8: =SUM(F7:F7) -> 0 | G8: =SUM(G7:G7) -> 0 | H8: =SUM(H7:H7) -> 0 | I8: =SUM(I7:I7) -> 0 | J8: =SUM(J7:J7) -> 0
B10: ВНУТРЕННИЕ ПРОДАЖИ
B11: Вольфрамовый концентрат 57,8% WO3 | C11: USD | D11: =ProdPlan!D16*ProdPlan!D20 -> 23861585 | E11: =ProdPlan!E16*ProdPlan!E20 -> 85083568 | F11: =ProdPlan!F16*ProdPlan!F20 -> 94036971 | G11: =ProdPlan!G16*ProdPlan!G20 -> 1.2209613e+08 | H11: =ProdPlan!H16*ProdPlan!H20 -> 1.19963e+08 | I11: =ProdPlan!I16*ProdPlan!I20 -> 1.2252059e+08 | J11: =ProdPlan!J16*ProdPlan!J20 -> 1.2521653e+08
B12: Всего | C12: USD | D12: =SUM(D11:D11) -> 23861585 | E12: =SUM(E11:E11) -> 85083568 | F12: =SUM(F11:F11) -> 94036971 | G12: =SUM(G11:G11) -> 1.2209613e+08 | H12: =SUM(H11:H11) -> 1.19963e+08 | I12: =SUM(I11:I11) -> 1.2252059e+08 | J12: =SUM(J11:J11) -> 1.2521653e+08
B14: ВСЕГО ПРОДАЖ | C14: USD | D14: =D8+D12 -> 23861585 | E14: =E8+E12 -> 85083568 | F14: =F8+F12 -> 94036971 | G14: =G8+G12 -> 1.2209613e+08 | H14: =H8+H12 -> 1.19963e+08 | I14: =I8+I12 -> 1.2252059e+08 | J14: =J8+J12 -> 1.2521653e+08
B15: Доля экспорта в выручке | C15: % | D15: =IFERROR(D8/D14,0) -> 0 | E15: =IFERROR(E8/E14,0) -> 0 | F15: =IFERROR(F8/F14,0) -> 0 | G15: =IFERROR(G8/G14,0) -> 0 | H15: =IFERROR(H8/H14,0) -> 0 | I15: =IFERROR(I8/I14,0) -> 0 | J15: =IFERROR(J8/J14,0) -> 0

Sheet RawMat
B2: СТОИМОСТЬ СЫРЬЯ И МАТЕРИАЛОВ ПРИ ПРОЕКТНОЙ МОЩНОСТИ (в экв. долл. США, 2030 г.) | G2: Приложение 7
B3: Базовый год - 2030 г. (освоение мощности 76%); цены - в номинальном выражении ТЭО; без НДС.
B5: НАИМЕНОВАНИЕ | C5: Ед. изм. | D5: Цена за единицу, USD | E5: Годовая потребность | F5: Годовая стоимость, USD | G5: ДОЛЯ (%) | H5: Примечание
B6: СЫРЬЁ, МАТЕРИАЛЫ И ПЕРЕМЕННЫЕ ЗАТРАТЫ С ЦЕНОЙ В ТВЁРДОЙ ВАЛЮТЕ (USD)
B7: Добыча (USD 31/т руды, без ФОТ) | C7: t | D7: =IFERROR(F7/E7,0) -> 28.389042 | E7: 600000 | F7: 17033425 | G7: =IFERROR(F7/$F$16,0) -> 0.54006132 | H7: Прочие производственные расходы
B8: Переработка (USD 25/т руды, без ФОТ) | C8: t | D8: =IFERROR(F8/E8,0) -> 23.189764 | E8: 600000 | F8: 13913858 | G8: =IFERROR(F8/$F$16,0) -> 0.44115242 | H8: Прочие производственные расходы
B9: Транспортировка концентрата | C9: t | D9: =IFERROR(F9/E9,0) -> 166.87098 | E9: 3203.2777 | F9: 534534.07 | G9: =IFERROR(F9/$F$16,0) -> 0.016947923 | H9: Прочие производственные расходы
B10: ВСЕГО В ТВЁРДОЙ ВАЛЮТЕ | F10: =SUM(F7:F9) -> 31481818 | G10: =IFERROR(F10/$F$16,0) -> 0.99816167
B12: СЫРЬЁ, МАТЕРИАЛЫ И ПЕРЕМЕННЫЕ ЗАТРАТЫ С ЦЕНОЙ В НАЦИОНАЛЬНОЙ ВАЛЮТЕ (UZS)
B13: Налог за пользование водой | C13: m3 | D13: =IFERROR(F13/E13,0) -> 0.096634468 | E13: 600000 | F13: 57980.681 | G13: =IFERROR(F13/$F$16,0) -> 0.0018383339 | H13: Прочие производственные расходы
B14: ВСЕГО В НАЦИОНАЛЬНОЙ ВАЛЮТЕ | F14: =SUM(F13:F13) -> 57980.681 | G14: =IFERROR(F14/$F$16,0) -> 0.0018383339
B16: ИТОГО СЫРЬЁ, МАТЕРИАЛЫ И ПРОЧИЕ ПЕРЕМЕННЫЕ ЗАТРАТЫ | F16: =F10+F14 -> 31539799 | G16: =IFERROR(F16/$F$16,0) -> 1
B18: ПРОЧИЕ ПРОИЗВОДСТВЕННЫЕ РАСХОДЫ (постоянные)
B19: Статьи затрат | F19: Годовая стоимость, USD | H19: Состав затрат
B20: Ремонт и техническое обслуживание | F20: 0
B21: Прочие производственные расходы (охрана труда, накладные и др.) | F21: 467556.21 | H21: Питание персонала
B22: Налог за пользование недрами (НДПИ) | F22: 3296595.5
B23: Итого: | F23: =SUM(F20:F22) -> 3764151.8

Sheet Labour
B2: ЭНЕРГОРЕСУРСЫ И ОПЛАТА ТРУДА ПРИ ПРОЕКТНОЙ МОЩНОСТИ (в экв. долл. США, 2030 г.) | G2: Приложение 8
B5: СТАТЬИ ЗАТРАТ | C5: Ед. изм. | D5: Годовая потребность | E5: Цена за единицу, USD | F5: Годовая стоимость, USD
B6: Электроэнергия - постоянная часть | F6: 0
B7: Природный газ / топливо - постоянная часть | F7: 0
B8: Вода - постоянная часть | F8: 0
B9: ВСЕГО ЭНЕРГОРЕСУРСЫ | F9: =SUM(F6:F8) -> 0
B11: РАСЧЕТ ЗАРАБОТНОЙ ПЛАТЫ
B12: ПОКАЗАТЕЛИ | C12: Количество, чел. | D12: Среднемесячная з/плата на 1 чел., сум (в ценах 2026 г.) | E12: Среднемесячная з/плата на 1 чел., USD | F12: Годовой фонд з/платы, USD | G12: Отчисления (соц. налог), USD
B13: ПРОИЗВОДСТВЕННЫЙ ПЕРСОНАЛ
B14: Горный отдел - иностранные специалисты | C14: 10 | D14: - | E14: =IFERROR(F14/C14/12,0) -> 5144.687 | F14: 617362.45 | G14: 74083.493
B15: Горный отдел - местный персонал | C15: 31 | D15: - | E15: =IFERROR(F15/C15/12,0) -> 2529.3983 | F15: 940936.18 | G15: 112912.34
B16: Геологический отдел - иностранные специалисты | C16: 8 | D16: - | E16: =IFERROR(F16/C16/12,0) -> 6092.3926 | F16: 584869.68 | G16: 70184.362
B17: Геологический отдел - местный персонал | C17: 32 | D17: - | E17: =IFERROR(F17/C17/12,0) -> 1071.8098 | F17: 411574.96 | G17: 49388.996
B18: Обогатительный отдел (фабрика) - иностранные специалисты | C18: 9 | D18: - | E18: =IFERROR(F18/C18/12,0) -> 4888.957 | F18: 528007.35 | G18: 63360.883
B19: Обогатительный отдел (фабрика) - местный персонал | C19: 47 | D19: - | E19: =IFERROR(F19/C19/12,0) -> 1212.2373 | F19: 683701.83 | G19: 82044.22
B20: Служба технического обслуживания и ремонта - иностранные специалисты | C20: 9 | D20: - | E20: =IFERROR(F20/C20/12,0) -> 4588.0981 | F20: 495514.59 | G20: 59461.751
B21: Служба технического обслуживания и ремонта - местный персонал | C21: 33 | D21: - | E21: =IFERROR(F21/C21/12,0) -> 1517.9699 | F21: 601116.07 | G21: 72133.928
B22: Пробирно-аналитическая лаборатория - иностранные специалисты | C22: 3 | D22: - | E22: =IFERROR(F22/C22/12,0) -> 6994.9692 | F22: 251818.89 | G22: 30218.267
B23: Пробирно-аналитическая лаборатория - местный персонал | C23: 19 | D23: - | E23: =IFERROR(F23/C23/12,0) -> 1466.6871 | F23: 334404.66 | G23: 40128.559
B24: Отдел охраны труда, промбезопасности и экологии - иностранные специалисты | C24: 3 | D24: - | E24: =IFERROR(F24/C24/12,0) -> 6994.9692 | F24: 251818.89 | G24: 30218.267
B25: Отдел охраны труда, промбезопасности и экологии - местный персонал | C25: 17 | D25: - | E25: =IFERROR(F25/C25/12,0) -> 1327.3186 | F25: 270773 | G25: 32492.76
B26: Административный отдел - обслуживание площадки - местный персонал | C26: 56 | D26: - | E26: =IFERROR(F26/C26/12,0) -> 741.40227 | F26: 498222.32 | G26: 59786.679
B27: ВСЕГО | C27: =SUM(C14:C26) -> 277 | F27: =SUM(F14:F26) -> 6470120.9 | G27: =SUM(G14:G26) -> 776414.51
B28: ИТОГО (фонд оплаты труда + социальный налог) | F28: =F27+G27 -> 7246535.4
B30: АДМИНИСТРАЦИЯ
B31: Руководство - местный персонал | C31: 7 | D31: - | E31: =IFERROR(F31/C31/12,0) -> 4529.5723 | F31: 380484.07 | G31: 45658.088
B32: Руководство - иностранные специалисты | C32: 2 | D32: - | E32: =IFERROR(F32/C32/12,0) -> 9477.0551 | F32: 227449.32 | G32: 27293.919
B33: Административный отдел - офис - местный персонал | C33: 20 | D33: - | E33: =IFERROR(F33/C33/12,0) -> 792.57514 | F33: 190218.03 | G33: 22826.164
B34: Отдел кадров - местный персонал | C34: 6 | D34: - | E34: =IFERROR(F34/C34/12,0) -> 2388.0675 | F34: 171940.86 | G34: 20632.903
B35: Отдел закупок - местный персонал | C35: 15 | D35: - | E35: =IFERROR(F35/C35/12,0) -> 1624.638 | F35: 292434.84 | G35: 35092.181
B36: Отдел закупок - иностранные специалисты | C36: 1 | D36: - | E36: =IFERROR(F36/C36/12,0) -> 7446.2576 | F36: 89355.091 | G36: 10722.611
B37: Финансовый отдел - местный персонал | C37: 4 | D37: - | E37: =IFERROR(F37/C37/12,0) -> 3384.6625 | F37: 162463.8 | G37: 19495.656
B38: Юридический отдел - местный персонал | C38: 2 | D38: - | E38: =IFERROR(F38/C38/12,0) -> 3384.6625 | F38: 81231.901 | G38: 9747.8281
B39: Отдел по связям с местным сообществом - местный персонал | C39: 2 | D39: - | E39: =IFERROR(F39/C39/12,0) -> 3102.6073 | F39: 74462.576 | G39: 8935.5091
B40: ВСЕГО | C40: =SUM(C31:C39) -> 59 | F40: =SUM(F31:F39) -> 1670040.5 | G40: =SUM(G31:G39) -> 200404.86
B41: ИТОГО (фонд оплаты труда + социальный налог) | F41: =F40+G40 -> 1870445.4
B43: ОБЩАЯ СУММА | C43: =C27+C40 -> 336 | F43: =F28+F41 -> 9116980.7
B44: Заработная плата установлена в сумах (в ценах 2026 г.) и пересчитана в USD с учётом индексации и курса.

Sheet Taxes
B2: НАЛОГИ И СБОРЫ (в экв. долл. США) | K2: Приложение 9
B4: ПОКАЗАТЕЛИ | C4: Ставка | D4: 1 год (льготный / инвест.) | E4: 2 год | F4: 3 год | G4: 4 год | H4: 5 год | I4: 6 год | J4: 7 год
D5: 2027 | E5: 2028 | F5: 2029 | G5: 2030 | H5: 2031 | I5: 2032 | J5: 2033
B6: Налоги и сборы, включаемые в расходы | D6: =SUM(D7:D11) -> 2530637.3 | E6: =SUM(E7:E11) -> 4646251.3 | F6: =SUM(F7:F11) -> 4967501.3 | G6: =SUM(G7:G11) -> 17195569 | H6: =SUM(H7:H11) -> 24664671 | I6: =SUM(I7:I11) -> 25251269 | J6: =SUM(J7:J11) -> 25884855 | K6: =SUM(K7:K11) -> 0
B7: Налог на имущество | C7: 0.75% | D7: =CostSold!D34 -> 68379.63 | E7: =CostSold!E34 -> 357777.78 | F7: =CostSold!F34 -> 311111.11 | G7: =CostSold!G34 -> 264444.44 | H7: =CostSold!H34 -> 217777.78 | I7: =CostSold!I34 -> 171111.11 | J7: =CostSold!J34 -> 124444.44
B8: Земельный налог | D8: =CostSold!D35 -> 1056000 | E8: =CostSold!E35 -> 1056000 | F8: =CostSold!F35 -> 1161600 | G8: =CostSold!G35 -> 1277760 | H8: =CostSold!H35 -> 1405536 | I8: =CostSold!I35 -> 1546089.6 | J8: =CostSold!J35 -> 1700698.6
B9: Специальный рентный налог | C9: 25% | D9: =CostSold!D36 -> 0 | E9: =CostSold!E36 -> 0 | F9: =CostSold!F36 -> 0 | G9: =CostSold!G36 -> 11379950 | H9: =CostSold!H36 -> 18804047 | I9: =CostSold!I36 -> 19205740 | J9: =CostSold!J36 -> 19636147
B10: Налог за пользование недрами (НДПИ) - в себестоимости | D10: =CostSold!D19 -> 644262.79 | E10: =CostSold!E19 -> 2297256.3 | F10: =CostSold!F19 -> 2538998.2 | G10: =CostSold!G19 -> 3296595.5 | H10: =CostSold!H19 -> 3239001.1 | I10: =CostSold!I19 -> 3308056 | J10: =CostSold!J19 -> 3380846.3
B11: Социальный налог (производственный и административный персонал) | C11: 12% | D11: 761994.9 | E11: 935217.17 | F11: 955791.94 | G11: 976819.37 | H11: 998309.39 | I11: 1020272.2 | J11: 1042718.2
B13: Прочие налоги | D13: =D14+D15 -> 2205838.3 | E13: =E14+E15 -> 23056840 | F13: =F14+F15 -> 25123650 | G13: =G14+G15 -> 31964119 | H13: =H14+H15 -> 29808987 | I13: =I14+I15 -> 30545023 | J13: =J14+J15 -> 31321698 | K13: =K14+K15 -> 0
B14: Налог на прибыль (Приложение 13) | D14: =ProfLoss!D21 -> 2205838.3 | E14: =ProfLoss!E21 -> 14757263 | F14: =ProfLoss!F21 -> 16276351 | G14: =ProfLoss!G21 -> 20554661 | H14: =ProfLoss!H21 -> 18721079 | I14: =ProfLoss!I21 -> 19219212 | J14: =ProfLoss!J21 -> 19742935
B15: НДС к уплате в бюджет (при превышении входящего НДС - к возмещению, см. ниже) | C15: 12% | D15: =MAX(0,D22) -> 0 | E15: =MAX(0,E22) -> 8299577 | F15: =MAX(0,F22) -> 8847299.1 | G15: =MAX(0,G22) -> 11409458 | H15: =MAX(0,H22) -> 11087908 | I15: =MAX(0,I22) -> 11325811 | J15: =MAX(0,J22) -> 11578763
B16: ВСЕГО НАЛОГОВ И ОТЧИСЛЕНИЙ | D16: =D6+D13 -> 4736475.6 | E16: =E6+E13 -> 27703092 | F16: =F6+F13 -> 30091151 | G16: =G6+G13 -> 49159688 | H16: =H6+H13 -> 54473658 | I16: =I6+I13 -> 55796292 | J16: =J6+J13 -> 57206552
B18: Расчет НДС
B19: НДС исходящий (реализация на внутреннем рынке; экспорт - 0%) | D19: 2863390.2 | E19: 10210028 | F19: 11284437 | G19: 14651536 | H19: 14395560 | I19: 14702471 | J19: 15025984
B20: НДС входящий - по операционным затратам | D20: 463843.01 | E20: 1741079.8 | F20: 2267766 | G20: 3072706.1 | H20: 3138280.9 | I20: 3207288.7 | J20: 3277849.1
B21: НДС входящий - по капитальным вложениям (1-й год вкл. 2026 г.) | D21: 16993600 | E21: 169371.43 | F21: 169371.43 | G21: 169371.43 | H21: 169371.43 | I21: 169371.43 | J21: 169371.43
B22: НДС к уплате (+) / к возмещению из бюджета (-) | D22: =D19-D20-D21 -> -14594053 | E22: =E19-E20-E21 -> 8299577 | F22: =F19-F20-F21 -> 8847299.1 | G22: =G19-G20-G21 -> 11409458 | H22: =H19-H20-H21 -> 11087908 | I22: =I19-I20-I21 -> 11325811 | J22: =J19-J20-J21 -> 11578763
B24: Расчет налога на прибыль
B25: Прибыль (убыток) до налогообложения (Приложение 13) | D25: =ProfLoss!D20 -> 5747408.8 | E25: =ProfLoss!E20 -> 34195906 | F25: =ProfLoss!F20 -> 37568832 | G25: =ProfLoss!G20 -> 44923464 | H25: =ProfLoss!H20 -> 34308789 | I25: =ProfLoss!I20 -> 35700268 | J25: =ProfLoss!J20 -> 37157972
B26: Налоговые корректировки (вменённый доход по реализации со скидкой и др.) | D26: 23663768 | E26: 64185850 | F26: 70940171 | G26: 92107608 | H26: 90498405 | I26: 92427814 | J26: 94461593
B27: Налогооблагаемая прибыль | D27: =D25+D26 -> 29411177 | E27: =E25+E26 -> 98381756 | F27: =F25+F26 -> 1.08509e+08 | G27: =G25+G26 -> 1.3703107e+08 | H27: =H25+H26 -> 1.2480719e+08 | I27: =I25+I26 -> 1.2812808e+08 | J27: =J25+J26 -> 1.3161957e+08
B28: Ставка налога на прибыль | C28: % | D28: 0.075 | E28: 0.15 | F28: 0.15 | G28: 0.15 | H28: 0.15 | I28: 0.15 | J28: 0.15
B29: Налог на прибыль | D29: =D27*D28 -> 2205838.3 | E29: =E27*E28 -> 14757263 | F29: =F27*F28 -> 16276351 | G29: =G27*G28 -> 20554661 | H29: =H27*H28 -> 18721079 | I29: =I27*I28 -> 19219212 | J29: =J27*J28 -> 19742935

Sheet CostTotal
B2: СТОИМОСТЬ ПРОДУКЦИИ ПРИ ПРОЕКТНОЙ МОЩНОСТИ (в экв. долл. США, 2030 г.) | H2: Приложение 10
B3: Разделение на постоянные и переменные затраты.
B5: Статьи издержек | C5: Всего стоимость | D5: Доля постоянных затрат (%) | E5: Доля переменных затрат (%) | F5: Фиксированная стоимость | G5: Переменная стоимость
B6: Сырьё, материалы и прочие переменные затраты по статьям ТЭО | C6: =C7+C8 -> 31539799 | D6: =IFERROR(F6/C6,0) -> 0 | E6: =IFERROR(G6/C6,0) -> 1 | F6: =F7+F8 -> 0 | G6: =G7+G8 -> 31539799
B7: с ценой в твёрдой валюте (USD) | C7: =F7+G7 -> 31481818 | D7: =IFERROR(F7/C7,0) -> 0 | E7: =IFERROR(G7/C7,0) -> 1 | F7: 0 | G7: 31481818
B8: с ценой в национальной валюте | C8: =F8+G8 -> 57980.681 | D8: =IFERROR(F8/C8,0) -> 0 | E8: =IFERROR(G8/C8,0) -> 1 | F8: 0 | G8: 57980.681
B9: Энергоресурсы (электроэнергия, газ, вода) | C9: =F9+G9 -> 0 | D9: =IFERROR(F9/C9,0) -> 0 | E9: =IFERROR(G9/C9,0) -> 0 | F9: 0 | G9: =0 -> 0
B10: Зарплата производственного персонала (с соц. налогом) | C10: =F10+G10 -> 7246535.4 | D10: =IFERROR(F10/C10,0) -> 1 | E10: =IFERROR(G10/C10,0) -> 0 | F10: 7246535.4 | G10: 0
B11: Зарплата административного персонала (с соц. налогом) | C11: =F11+G11 -> 1870445.4 | D11: =IFERROR(F11/C11,0) -> 1 | E11: =IFERROR(G11/C11,0) -> 0 | F11: 1870445.4 | G11: 0
B12: Ремонт и техническое обслуживание (постоянная часть) | C12: =F12+G12 -> 0 | D12: =IFERROR(F12/C12,0) -> 0 | E12: =IFERROR(G12/C12,0) -> 0 | F12: 0 | G12: 0
B13: Прочие производственные расходы (постоянная часть) | C13: =F13+G13 -> 467556.21 | D13: =IFERROR(F13/C13,0) -> 1 | E13: =IFERROR(G13/C13,0) -> 0 | F13: 467556.21 | G13: 0
B14: Налог за пользование недрами (НДПИ) | C14: =F14+G14 -> 3296595.5 | D14: =IFERROR(F14/C14,0) -> 0 | E14: =IFERROR(G14/C14,0) -> 1 | F14: 0 | G14: 3296595.5
B15: Административные расходы (без персонала и амортизации) | C15: =F15+G15 -> 0 | D15: =IFERROR(F15/C15,0) -> 0 | E15: =IFERROR(G15/C15,0) -> 0 | F15: 0 | G15: 0
B16: Коммерческие расходы | C16: =F16+G16 -> 0 | D16: =IFERROR(F16/C16,0) -> 0 | E16: =IFERROR(G16/C16,0) -> 0 | F16: 0 | G16: 0
B17: Налог на имущество и земельный налог | C17: =F17+G17 -> 1542204.4 | D17: =IFERROR(F17/C17,0) -> 1 | E17: =IFERROR(G17/C17,0) -> 0 | F17: 1542204.4 | G17: 0
B18: Специальный рентный налог | C18: =F18+G18 -> 11379950 | D18: =IFERROR(F18/C18,0) -> 0 | E18: =IFERROR(G18/C18,0) -> 1 | F18: 0 | G18: 11379950
B19: Резерв на непредвиденные операционные расходы | C19: =F19+G19 -> 2250361.9 | D19: =IFERROR(F19/C19,0) -> 0 | E19: =IFERROR(G19/C19,0) -> 1 | F19: 0 | G19: 2250361.9
B20: Прочие операционные расходы / (доходы) | C20: =F20+G20 -> 0 | D20: =IFERROR(F20/C20,0) -> 0 | E20: =IFERROR(G20/C20,0) -> 0 | F20: 0 | G20: 0
B21: Амортизация (Приложение 4) | C21: =F21+G21 -> 16304839 | D21: =IFERROR(F21/C21,0) -> 1 | E21: =IFERROR(G21/C21,0) -> 0 | F21: =Depreciate!J19 -> 16304839 | G21: 0
B22: ИТОГО | C22: =SUM(C6:C21)-C6 -> 75898286 | D22: =IFERROR(F22/C22,0) -> 0.36142556 | E22: =IFERROR(G22/C22,0) -> 0.63857444 | F22: =SUM(F6:F21)-F6 -> 27431581 | G22: =SUM(G6:G21)-G6 -> 48466706
B23: в т.ч. в местной валюте | C23: =C22-C24 -> 32393405
B24: в т.ч. в твёрдой валюте (производственные затраты в USD) | C24: 43504881
B26: Выручка (2030 г.) | C26: =SalePlan!G14 -> 1.2209613e+08
B27: Затраты на 1 USD выручки | C27: =IFERROR(C22/C26,0) -> 0.62162728
B28: Полная себестоимость единицы основной продукции, USD/t | C28: =IFERROR(C22/ProdPlan!G13,0) -> 23693.946

Sheet CostSold
B2: ГОДОВАЯ СТОИМОСТЬ ПРОДАННОЙ ПРОДУКЦИИ (в экв. долл. США) | K2: Приложение 11
B4: ПОКАЗАТЕЛИ | C4: Ед. изм. | D4: 1 год (льготный / инвест.) | E4: 2 год | F4: 3 год | G4: 4 год | H4: 5 год | I4: 6 год | J4: 7 год
D5: 2027 | E5: 2028 | F5: 2029 | G5: 2030 | H5: 2031 | I5: 2032 | J5: 2033
B6: Освоение мощностей (основная продукция) | C6: % | D6: =ProdPlan!D11 -> 0.15786295 | E6: =ProdPlan!E11 -> 0.55511995 | F6: =ProdPlan!F11 -> 0.600342 | G6: =ProdPlan!G11 -> 0.76268516 | H6: =ProdPlan!H11 -> 0.73323971 | I6: =ProdPlan!I11 -> 0.73275148 | J6: =ProdPlan!J11 -> 0.73275148
B8: ПРОИЗВОДСТВЕННАЯ СЕБЕСТОИМОСТЬ ПО ЭЛЕМЕНТАМ
B9: Сырьё | C9: USD | D9: 0 | E9: 0 | F9: 0 | G9: 0 | H9: 0 | I9: 0 | J9: 0
B10: Вспомогательные материалы | C10: USD | D10: 0 | E10: 0 | F10: 0 | G10: 0 | H10: 0 | I10: 0 | J10: 0
B11: Электроэнергия | C11: USD | D11: 0 | E11: 0 | F11: 0 | G11: 0 | H11: 0 | I11: 0 | J11: 0
B12: Природный газ / топливо | C12: USD | D12: 0 | E12: 0 | F12: 0 | G12: 0 | H12: 0 | I12: 0 | J12: 0
B13: Вода | C13: USD | D13: 0 | E13: 0 | F13: 0 | G13: 0 | H13: 0 | I13: 0 | J13: 0
B14: Заработная плата | C14: USD | D14: 4921963 | E14: 6194562 | F14: 6330842.4 | G14: 6470120.9 | H14: 6612463.5 | I14: 6757937.7 | J14: 6906612.4
B15: Социальный налог | C15: USD | D15: 590635.56 | E15: 743347.44 | F15: 759701.08 | G15: 776414.51 | H15: 793495.63 | I15: 810952.53 | J15: 828793.49
B16: Амортизация (Приложение 4) | C16: USD | D16: =Depreciate!$G$20 -> 5287922.6 | E16: =Depreciate!$H$20 -> 16022554 | F16: =Depreciate!$I$20 -> 16163696 | G16: =Depreciate!$J$20 -> 16304839 | H16: =Depreciate!$K$20 -> 16445982 | I16: =Depreciate!$L$20 -> 16587125 | J16: =Depreciate!$M$20 -> 16728268
B17: Ремонт и техобслуживание | C17: USD | D17: 0 | E17: 0 | F17: 0 | G17: 0 | H17: 0 | I17: 0 | J17: 0
B18: Прочие производственные расходы (без НДПИ) | C18: USD | D18: 4831698 | E18: 18136248 | F18: 23622563 | G18: 32007355 | H18: 32690426 | I18: 33409258 | J18: 34144261
B19: Налог за пользование недрами (НДПИ) | C19: USD | D19: 644262.79 | E19: 2297256.3 | F19: 2538998.2 | G19: 3296595.5 | H19: 3239001.1 | I19: 3308056 | J19: 3380846.3
B20: Себестоимость произведенной продукции | C20: USD | D20: =SUM(D9:D19) -> 16276482 | E20: =SUM(E9:E19) -> 43393967 | F20: =SUM(F9:F19) -> 49415801 | G20: =SUM(G9:G19) -> 58855325 | H20: =SUM(H9:H19) -> 59781368 | I20: =SUM(I9:I19) -> 60873329 | J20: =SUM(J9:J19) -> 61988781
B21: Изменение остатков готовой продукции (- прирост запаса) | C21: USD | D21: -4959831.2 | E21: -1025.6981 | F21: -324589.05 | G21: -516881.18 | H21: -42449.905 | I21: -52772.575 | J21: -54095.411
B22: Себестоимость реализованной продукции | C22: USD | D22: =D20+D21 -> 11316651 | E22: =E20+E21 -> 43392942 | F22: =F20+F21 -> 49091212 | G22: =G20+G21 -> 58338444 | H22: =H20+H21 -> 59738918 | I22: =I20+I21 -> 60820556 | J22: =J20+J21 -> 61934686
B23: в т.ч. затраты в твёрдой валюте (USD) | C23: USD | D23: 11316651 | E23: 43392942 | F23: 49091212 | G23: 58338444 | H23: 59738918 | I23: 60820556 | J23: 61934686
B24: в т.ч. затраты в национальной валюте | C24: USD | D24: =D22-D23 -> -4.0978193e-08 | E24: =E22-E23 -> 0 | F24: =F22-F23 -> 0 | G24: =G22-G23 -> 0 | H24: =H22-H23 -> 0 | I24: =I22-I23 -> 0 | J24: =J22-J23 -> 0
B26: РАСХОДЫ ПЕРИОДА
B27: Зарплата административного персонала (с соц. налогом) | C27: USD | D27: 1599353.8 | E27: 1790784.1 | F27: 1830181.4 | G27: 1870445.4 | H27: 1911595.2 | I27: 1953650.2 | J27: 1996630.5
B28: Амортизация административных активов | C28: USD | D28: =Depreciate!$G$21 -> 0 | E28: =Depreciate!$H$21 -> 0 | F28: =Depreciate!$I$21 -> 0 | G28: =Depreciate!$J$21 -> 0 | H28: =Depreciate!$K$21 -> 0 | I28: =Depreciate!$L$21 -> 0 | J28: =Depreciate!$M$21 -> 0
B29: Прочие административные расходы (аренда, налог за воду, прочие) | C29: USD | D29: 0 | E29: 0 | F29: 0 | G29: 0 | H29: 0 | I29: 0 | J29: 0
B30: Коммерческие расходы (расходы по реализации) | C30: USD | D30: 0 | E30: 0 | F30: 0 | G30: 0 | H30: 0 | I30: 0 | J30: 0
B31: Итого расходы периода | C31: USD | D31: =SUM(D27:D30) -> 1599353.8 | E31: =SUM(E27:E30) -> 1790784.1 | F31: =SUM(F27:F30) -> 1830181.4 | G31: =SUM(G27:G30) -> 1870445.4 | H31: =SUM(H27:H30) -> 1911595.2 | I31: =SUM(I27:I30) -> 1953650.2 | J31: =SUM(J27:J30) -> 1996630.5
B33: НАЛОГИ И ПРОЧИЕ ОПЕРАЦИОННЫЕ РАСХОДЫ
B34: Налог на имущество | C34: USD | D34: 68379.63 | E34: 357777.78 | F34: 311111.11 | G34: 264444.44 | H34: 217777.78 | I34: 171111.11 | J34: 124444.44
B35: Земельный налог | C35: USD | D35: 1056000 | E35: 1056000 | F35: 1161600 | G35: 1277760 | H35: 1405536 | I35: 1546089.6 | J35: 1700698.6
B36: Специальный рентный налог | C36: USD | D36: 0 | E36: 0 | F36: 0 | G36: 11379950 | H36: 18804047 | I36: 19205740 | J36: 19636147
B37: Резерв на непредвиденные операционные расходы | C37: USD | D37: 635124.7 | E37: 1478537.2 | F37: 1776694.6 | G37: 2250361.9 | H37: 2291154.9 | I37: 2341412.6 | J37: 2392923.7
B38: Прочие операционные расходы / (доходы) | C38: USD | D38: 3438667.3 | E38: 0 | F38: 0 | G38: 0 | H38: 0 | I38: 0 | J38: 0
B39: Итого налоги и прочие операционные расходы | C39: USD | D39: =SUM(D34:D38) -> 5198171.6 | E39: =SUM(E34:E38) -> 2892315 | F39: =SUM(F34:F38) -> 3249405.7 | G39: =SUM(G34:G38) -> 15172516 | H39: =SUM(H34:H38) -> 22718516 | I39: =SUM(I34:I38) -> 23264353 | J39: =SUM(J34:J38) -> 23854214
B41: ФИНАНСОВЫЕ ИЗДЕРЖКИ
B42: Проценты за кредит (1-й год - капитализированы, оплачены за счёт собственных средств) | C42: USD | D42: =0 -> 0 | E42: =LOANS!$D$106 -> 2811621.7 | F42: =LOANS!$E$106 -> 2297340.1 | G42: =LOANS!$F$106 -> 1791262 | H42: =LOANS!$G$106 -> 1285184 | I42: =LOANS!$H$106 -> 781763.46 | J42: =LOANS!$I$106 -> 273027.94
B44: ПОЛНАЯ СТОИМОСТЬ ПРОДАННОЙ ПРОДУКЦИИ | C44: USD | D44: =D22+D31+D39+D42 -> 18114176 | E44: =E22+E31+E39+E42 -> 50887662 | F44: =F22+F31+F39+F42 -> 56468139 | G44: =G22+G31+G39+G42 -> 77172667 | H44: =H22+H31+H39+H42 -> 85654213 | I44: =I22+I31+I39+I42 -> 86820323 | J44: =J22+J31+J39+J42 -> 88058558
B45: Полная себестоимость единицы основной продукции | C45: USD/t | D45: =IFERROR(D44/(ProdPlan!D15+ProdPlan!D16),0) -> 27320.527 | E45: =IFERROR(E44/(ProdPlan!E15+ProdPlan!E16),0) -> 21826.112 | F45: =IFERROR(F44/(ProdPlan!F15+ProdPlan!F16),0) -> 22395.226 | G45: =IFERROR(G44/(ProdPlan!G15+ProdPlan!G16),0) -> 24091.782 | H45: =IFERROR(H44/(ProdPlan!H15+ProdPlan!H16),0) -> 27813.36 | I45: =IFERROR(I44/(ProdPlan!I15+ProdPlan!I16),0) -> 28210.8 | J45: =IFERROR(J44/(ProdPlan!J15+ProdPlan!J16),0) -> 28613.144

Sheet LOANS
B2: СХЕМА ВЫПЛАТЫ КРЕДИТА (в долл. США) | H2: Приложение 12
B5: Срок кредита | C5: =ИНФОРМАЦИЯ!$C$28 -> 84 | D5: месяцев
B6: Льготный период | C6: =ИНФОРМАЦИЯ!$C$29 -> 12 | D6: месяцев
B7: Инвестиционный период | C7: =ИНФОРМАЦИЯ!$C$30 -> 12 | D7: месяцев
B8: Процентная ставка | C8: =ИНФОРМАЦИЯ!$C$27 -> 0.07 | D8: годовых
B9: Сумма кредита | C9: =ИНФОРМАЦИЯ!$C$26 -> 42783896 | D9: USD
B10: Дата выдачи | C10: =ИНФОРМАЦИЯ!$C$31 -> 46388
B11: База начисления процентов | C11: =ИНФОРМАЦИЯ!$C$32 -> 360 | D11: дней
B12: Количество платежей по основному долгу | C12: =C5-C6 -> 72 | D12: платежей
B13: Ежемесячный платёж по основному долгу | C13: =C9/C12 -> 594220.78 | D13: USD
A15: № | B15: Дата платежа | C15: Остаток на начало | D15: Погашение основного долга | E15: Проценты | F15: Всего выплат | G15: Остаток на конец | H15: Год | I15: № года
A16: 1 | B16: =EOMONTH($C$10,0) -> 46418 | C16: =$C$9 -> 42783896 | D16: =IF(A16>$C$6,MIN(C16,$C$13),0) -> 0 | E16: =C16*$C$8*DAY(B16)/$C$11 -> 257891.82 | F16: =D16+E16 -> 257891.82 | G16: =C16-D16 -> 42783896 | H16: =YEAR(B16) -> 2027 | I16: =H16-2026 -> 1
A17: 2 | B17: =EOMONTH($C$10,1) -> 46446 | C17: =G16 -> 42783896 | D17: =IF(A17>$C$6,MIN(C17,$C$13),0) -> 0 | E17: =C17*$C$8*DAY(B17)/$C$11 -> 232934.55 | F17: =D17+E17 -> 232934.55 | G17: =C17-D17 -> 42783896 | H17: =YEAR(B17) -> 2027 | I17: =H17-2026 -> 1
A18: 3 | B18: =EOMONTH($C$10,2) -> 46477 | C18: =G17 -> 42783896 | D18: =IF(A18>$C$6,MIN(C18,$C$13),0) -> 0 | E18: =C18*$C$8*DAY(B18)/$C$11 -> 257891.82 | F18: =D18+E18 -> 257891.82 | G18: =C18-D18 -> 42783896 | H18: =YEAR(B18) -> 2027 | I18: =H18-2026 -> 1
A19: 4 | B19: =EOMONTH($C$10,3) -> 46507 | C19: =G18 -> 42783896 | D19: =IF(A19>$C$6,MIN(C19,$C$13),0) -> 0 | E19: =C19*$C$8*DAY(B19)/$C$11 -> 249572.73 | F19: =D19+E19 -> 249572.73 | G19: =C19-D19 -> 42783896 | H19: =YEAR(B19) -> 2027 | I19: =H19-2026 -> 1
A20: 5 | B20: =EOMONTH($C$10,4) -> 46538 | C20: =G19 -> 42783896 | D20: =IF(A20>$C$6,MIN(C20,$C$13),0) -> 0 | E20: =C20*$C$8*DAY(B20)/$C$11 -> 257891.82 | F20: =D20+E20 -> 257891.82 | G20: =C20-D20 -> 42783896 | H20: =YEAR(B20) -> 2027 | I20: =H20-2026 -> 1
A21: 6 | B21: =EOMONTH($C$10,5) -> 46568 | C21: =G20 -> 42783896 | D21: =IF(A21>$C$6,MIN(C21,$C$13),0) -> 0 | E21: =C21*$C$8*DAY(B21)/$C$11 -> 249572.73 | F21: =D21+E21 -> 249572.73 | G21: =C21-D21 -> 42783896 | H21: =YEAR(B21) -> 2027 | I21: =H21-2026 -> 1
A22: 7 | B22: =EOMONTH($C$10,6) -> 46599 | C22: =G21 -> 42783896 | D22: =IF(A22>$C$6,MIN(C22,$C$13),0) -> 0 | E22: =C22*$C$8*DAY(B22)/$C$11 -> 257891.82 | F22: =D22+E22 -> 257891.82 | G22: =C22-D22 -> 42783896 | H22: =YEAR(B22) -> 2027 | I22: =H22-2026 -> 1
A23: 8 | B23: =EOMONTH($C$10,7) -> 46630 | C23: =G22 -> 42783896 | D23: =IF(A23>$C$6,MIN(C23,$C$13),0) -> 0 | E23: =C23*$C$8*DAY(B23)/$C$11 -> 257891.82 | F23: =D23+E23 -> 257891.82 | G23: =C23-D23 -> 42783896 | H23: =YEAR(B23) -> 2027 | I23: =H23-2026 -> 1
A24: 9 | B24: =EOMONTH($C$10,8) -> 46660 | C24: =G23 -> 42783896 | D24: =IF(A24>$C$6,MIN(C24,$C$13),0) -> 0 | E24: =C24*$C$8*DAY(B24)/$C$11 -> 249572.73 | F24: =D24+E24 -> 249572.73 | G24: =C24-D24 -> 42783896 | H24: =YEAR(B24) -> 2027 | I24: =H24-2026 -> 1
A25: 10 | B25: =EOMONTH($C$10,9) -> 46691 | C25: =G24 -> 42783896 | D25: =IF(A25>$C$6,MIN(C25,$C$13),0) -> 0 | E25: =C25*$C$8*DAY(B25)/$C$11 -> 257891.82 | F25: =D25+E25 -> 257891.82 | G25: =C25-D25 -> 42783896 | H25: =YEAR(B25) -> 2027 | I25: =H25-2026 -> 1
A26: 11 | B26: =EOMONTH($C$10,10) -> 46721 | C26: =G25 -> 42783896 | D26: =IF(A26>$C$6,MIN(C26,$C$13),0) -> 0 | E26: =C26*$C$8*DAY(B26)/$C$11 -> 249572.73 | F26: =D26+E26 -> 249572.73 | G26: =C26-D26 -> 42783896 | H26: =YEAR(B26) -> 2027 | I26: =H26-2026 -> 1
A27: 12 | B27: =EOMONTH($C$10,11) -> 46752 | C27: =G26 -> 42783896 | D27: =IF(A27>$C$6,MIN(C27,$C$13),0) -> 0 | E27: =C27*$C$8*DAY(B27)/$C$11 -> 257891.82 | F27: =D27+E27 -> 257891.82 | G27: =C27-D27 -> 42783896 | H27: =YEAR(B27) -> 2027 | I27: =H27-2026 -> 1
A28: 13 | B28: =EOMONTH($C$10,12) -> 46783 | C28: =G27 -> 42783896 | D28: =IF(A28>$C$6,MIN(C28,$C$13),0) -> 594220.78 | E28: =C28*$C$8*DAY(B28)/$C$11 -> 257891.82 | F28: =D28+E28 -> 852112.6 | G28: =C28-D28 -> 42189676 | H28: =YEAR(B28) -> 2028 | I28: =H28-2026 -> 2
A29: 14 | B29: =EOMONTH($C$10,13) -> 46812 | C29: =G28 -> 42189676 | D29: =IF(A29>$C$6,MIN(C29,$C$13),0) -> 594220.78 | E29: =C29*$C$8*DAY(B29)/$C$11 -> 237902.89 | F29: =D29+E29 -> 832123.68 | G29: =C29-D29 -> 41595455 | H29: =YEAR(B29) -> 2028 | I29: =H29-2026 -> 2
A30: 15 | B30: =EOMONTH($C$10,14) -> 46843 | C30: =G29 -> 41595455 | D30: =IF(A30>$C$6,MIN(C30,$C$13),0) -> 594220.78 | E30: =C30*$C$8*DAY(B30)/$C$11 -> 250728.16 | F30: =D30+E30 -> 844948.94 | G30: =C30-D30 -> 41001234 | H30: =YEAR(B30) -> 2028 | I30: =H30-2026 -> 2
A31: 16 | B31: =EOMONTH($C$10,15) -> 46873 | C31: =G30 -> 41001234 | D31: =IF(A31>$C$6,MIN(C31,$C$13),0) -> 594220.78 | E31: =C31*$C$8*DAY(B31)/$C$11 -> 239173.86 | F31: =D31+E31 -> 833394.65 | G31: =C31-D31 -> 40407013 | H31: =YEAR(B31) -> 2028 | I31: =H31-2026 -> 2
A32: 17 | B32: =EOMONTH($C$10,16) -> 46904 | C32: =G31 -> 40407013 | D32: =IF(A32>$C$6,MIN(C32,$C$13),0) -> 594220.78 | E32: =C32*$C$8*DAY(B32)/$C$11 -> 243564.5 | F32: =D32+E32 -> 837785.28 | G32: =C32-D32 -> 39812792 | H32: =YEAR(B32) -> 2028 | I32: =H32-2026 -> 2
A33: 18 | B33: =EOMONTH($C$10,17) -> 46934 | C33: =G32 -> 39812792 | D33: =IF(A33>$C$6,MIN(C33,$C$13),0) -> 594220.78 | E33: =C33*$C$8*DAY(B33)/$C$11 -> 232241.29 | F33: =D33+E33 -> 826462.07 | G33: =C33-D33 -> 39218572 | H33: =YEAR(B33) -> 2028 | I33: =H33-2026 -> 2
A34: 19 | B34: =EOMONTH($C$10,18) -> 46965 | C34: =G33 -> 39218572 | D34: =IF(A34>$C$6,MIN(C34,$C$13),0) -> 594220.78 | E34: =C34*$C$8*DAY(B34)/$C$11 -> 236400.83 | F34: =D34+E34 -> 830621.62 | G34: =C34-D34 -> 38624351 | H34: =YEAR(B34) -> 2028 | I34: =H34-2026 -> 2
A35: 20 | B35: =EOMONTH($C$10,19) -> 46996 | C35: =G34 -> 38624351 | D35: =IF(A35>$C$6,MIN(C35,$C$13),0) -> 594220.78 | E35: =C35*$C$8*DAY(B35)/$C$11 -> 232819 | F35: =D35+E35 -> 827039.79 | G35: =C35-D35 -> 38030130 | H35: =YEAR(B35) -> 2028 | I35: =H35-2026 -> 2
A36: 21 | B36: =EOMONTH($C$10,20) -> 47026 | C36: =G35 -> 38030130 | D36: =IF(A36>$C$6,MIN(C36,$C$13),0) -> 594220.78 | E36: =C36*$C$8*DAY(B36)/$C$11 -> 221842.43 | F36: =D36+E36 -> 816063.21 | G36: =C36-D36 -> 37435909 | H36: =YEAR(B36) -> 2028 | I36: =H36-2026 -> 2
A37: 22 | B37: =EOMONTH($C$10,21) -> 47057 | C37: =G36 -> 37435909 | D37: =IF(A37>$C$6,MIN(C37,$C$13),0) -> 594220.78 | E37: =C37*$C$8*DAY(B37)/$C$11 -> 225655.34 | F37: =D37+E37 -> 819876.12 | G37: =C37-D37 -> 36841689 | H37: =YEAR(B37) -> 2028 | I37: =H37-2026 -> 2
A38: 23 | B38: =EOMONTH($C$10,22) -> 47087 | C38: =G37 -> 36841689 | D38: =IF(A38>$C$6,MIN(C38,$C$13),0) -> 594220.78 | E38: =C38*$C$8*DAY(B38)/$C$11 -> 214909.85 | F38: =D38+E38 -> 809130.63 | G38: =C38-D38 -> 36247468 | H38: =YEAR(B38) -> 2028 | I38: =H38-2026 -> 2
A39: 24 | B39: =EOMONTH($C$10,23) -> 47118 | C39: =G38 -> 36247468 | D39: =IF(A39>$C$6,MIN(C39,$C$13),0) -> 594220.78 | E39: =C39*$C$8*DAY(B39)/$C$11 -> 218491.68 | F39: =D39+E39 -> 812712.46 | G39: =C39-D39 -> 35653247 | H39: =YEAR(B39) -> 2028 | I39: =H39-2026 -> 2
A40: 25 | B40: =EOMONTH($C$10,24) -> 47149 | C40: =G39 -> 35653247 | D40: =IF(A40>$C$6,MIN(C40,$C$13),0) -> 594220.78 | E40: =C40*$C$8*DAY(B40)/$C$11 -> 214909.85 | F40: =D40+E40 -> 809130.63 | G40: =C40-D40 -> 35059026 | H40: =YEAR(B40) -> 2029 | I40: =H40-2026 -> 3
A41: 26 | B41: =EOMONTH($C$10,25) -> 47177 | C41: =G40 -> 35059026 | D41: =IF(A41>$C$6,MIN(C41,$C$13),0) -> 594220.78 | E41: =C41*$C$8*DAY(B41)/$C$11 -> 190876.92 | F41: =D41+E41 -> 785097.7 | G41: =C41-D41 -> 34464805 | H41: =YEAR(B41) -> 2029 | I41: =H41-2026 -> 3
A42: 27 | B42: =EOMONTH($C$10,26) -> 47208 | C42: =G41 -> 34464805 | D42: =IF(A42>$C$6,MIN(C42,$C$13),0) -> 594220.78 | E42: =C42*$C$8*DAY(B42)/$C$11 -> 207746.19 | F42: =D42+E42 -> 801966.97 | G42: =C42-D42 -> 33870585 | H42: =YEAR(B42) -> 2029 | I42: =H42-2026 -> 3
A43: 28 | B43: =EOMONTH($C$10,27) -> 47238 | C43: =G42 -> 33870585 | D43: =IF(A43>$C$6,MIN(C43,$C$13),0) -> 594220.78 | E43: =C43*$C$8*DAY(B43)/$C$11 -> 197578.41 | F43: =D43+E43 -> 791799.19 | G43: =C43-D43 -> 33276364 | H43: =YEAR(B43) -> 2029 | I43: =H43-2026 -> 3
A44: 29 | B44: =EOMONTH($C$10,28) -> 47269 | C44: =G43 -> 33276364 | D44: =IF(A44>$C$6,MIN(C44,$C$13),0) -> 594220.78 | E44: =C44*$C$8*DAY(B44)/$C$11 -> 200582.53 | F44: =D44+E44 -> 794803.31 | G44: =C44-D44 -> 32682143 | H44: =YEAR(B44) -> 2029 | I44: =H44-2026 -> 3
A45: 30 | B45: =EOMONTH($C$10,29) -> 47299 | C45: =G44 -> 32682143 | D45: =IF(A45>$C$6,MIN(C45,$C$13),0) -> 594220.78 | E45: =C45*$C$8*DAY(B45)/$C$11 -> 190645.83 | F45: =D45+E45 -> 784866.62 | G45: =C45-D45 -> 32087922 | H45: =YEAR(B45) -> 2029 | I45: =H45-2026 -> 3
A46: 31 | B46: =EOMONTH($C$10,30) -> 47330 | C46: =G45 -> 32087922 | D46: =IF(A46>$C$6,MIN(C46,$C$13),0) -> 594220.78 | E46: =C46*$C$8*DAY(B46)/$C$11 -> 193418.86 | F46: =D46+E46 -> 787639.65 | G46: =C46-D46 -> 31493701 | H46: =YEAR(B46) -> 2029 | I46: =H46-2026 -> 3
A47: 32 | B47: =EOMONTH($C$10,31) -> 47361 | C47: =G46 -> 31493701 | D47: =IF(A47>$C$6,MIN(C47,$C$13),0) -> 594220.78 | E47: =C47*$C$8*DAY(B47)/$C$11 -> 189837.03 | F47: =D47+E47 -> 784057.82 | G47: =C47-D47 -> 30899481 | H47: =YEAR(B47) -> 2029 | I47: =H47-2026 -> 3
A48: 33 | B48: =EOMONTH($C$10,32) -> 47391 | C48: =G47 -> 30899481 | D48: =IF(A48>$C$6,MIN(C48,$C$13),0) -> 594220.78 | E48: =C48*$C$8*DAY(B48)/$C$11 -> 180246.97 | F48: =D48+E48 -> 774467.75 | G48: =C48-D48 -> 30305260 | H48: =YEAR(B48) -> 2029 | I48: =H48-2026 -> 3
A49: 34 | B49: =EOMONTH($C$10,33) -> 47422 | C49: =G48 -> 30305260 | D49: =IF(A49>$C$6,MIN(C49,$C$13),0) -> 594220.78 | E49: =C49*$C$8*DAY(B49)/$C$11 -> 182673.37 | F49: =D49+E49 -> 776894.15 | G49: =C49-D49 -> 29711039 | H49: =YEAR(B49) -> 2029 | I49: =H49-2026 -> 3
A50: 35 | B50: =EOMONTH($C$10,34) -> 47452 | C50: =G49 -> 29711039 | D50: =IF(A50>$C$6,MIN(C50,$C$13),0) -> 594220.78 | E50: =C50*$C$8*DAY(B50)/$C$11 -> 173314.39 | F50: =D50+E50 -> 767535.18 | G50: =C50-D50 -> 29116818 | H50: =YEAR(B50) -> 2029 | I50: =H50-2026 -> 3
A51: 36 | B51: =EOMONTH($C$10,35) -> 47483 | C51: =G50 -> 29116818 | D51: =IF(A51>$C$6,MIN(C51,$C$13),0) -> 594220.78 | E51: =C51*$C$8*DAY(B51)/$C$11 -> 175509.71 | F51: =D51+E51 -> 769730.49 | G51: =C51-D51 -> 28522598 | H51: =YEAR(B51) -> 2029 | I51: =H51-2026 -> 3
A52: 37 | B52: =EOMONTH($C$10,36) -> 47514 | C52: =G51 -> 28522598 | D52: =IF(A52>$C$6,MIN(C52,$C$13),0) -> 594220.78 | E52: =C52*$C$8*DAY(B52)/$C$11 -> 171927.88 | F52: =D52+E52 -> 766148.66 | G52: =C52-D52 -> 27928377 | H52: =YEAR(B52) -> 2030 | I52: =H52-2026 -> 4
A53: 38 | B53: =EOMONTH($C$10,37) -> 47542 | C53: =G52 -> 27928377 | D53: =IF(A53>$C$6,MIN(C53,$C$13),0) -> 594220.78 | E53: =C53*$C$8*DAY(B53)/$C$11 -> 152054.5 | F53: =D53+E53 -> 746275.28 | G53: =C53-D53 -> 27334156 | H53: =YEAR(B53) -> 2030 | I53: =H53-2026 -> 4
A54: 39 | B54: =EOMONTH($C$10,38) -> 47573 | C54: =G53 -> 27334156 | D54: =IF(A54>$C$6,MIN(C54,$C$13),0) -> 594220.78 | E54: =C54*$C$8*DAY(B54)/$C$11 -> 164764.22 | F54: =D54+E54 -> 758985 | G54: =C54-D54 -> 26739935 | H54: =YEAR(B54) -> 2030 | I54: =H54-2026 -> 4
A55: 40 | B55: =EOMONTH($C$10,39) -> 47603 | C55: =G54 -> 26739935 | D55: =IF(A55>$C$6,MIN(C55,$C$13),0) -> 594220.78 | E55: =C55*$C$8*DAY(B55)/$C$11 -> 155982.96 | F55: =D55+E55 -> 750203.74 | G55: =C55-D55 -> 26145714 | H55: =YEAR(B55) -> 2030 | I55: =H55-2026 -> 4
A56: 41 | B56: =EOMONTH($C$10,40) -> 47634 | C56: =G55 -> 26145714 | D56: =IF(A56>$C$6,MIN(C56,$C$13),0) -> 594220.78 | E56: =C56*$C$8*DAY(B56)/$C$11 -> 157600.56 | F56: =D56+E56 -> 751821.34 | G56: =C56-D56 -> 25551494 | H56: =YEAR(B56) -> 2030 | I56: =H56-2026 -> 4
A57: 42 | B57: =EOMONTH($C$10,41) -> 47664 | C57: =G56 -> 25551494 | D57: =IF(A57>$C$6,MIN(C57,$C$13),0) -> 594220.78 | E57: =C57*$C$8*DAY(B57)/$C$11 -> 149050.38 | F57: =D57+E57 -> 743271.16 | G57: =C57-D57 -> 24957273 | H57: =YEAR(B57) -> 2030 | I57: =H57-2026 -> 4
A58: 43 | B58: =EOMONTH($C$10,42) -> 47695 | C58: =G57 -> 24957273 | D58: =IF(A58>$C$6,MIN(C58,$C$13),0) -> 594220.78 | E58: =C58*$C$8*DAY(B58)/$C$11 -> 150436.89 | F58: =D58+E58 -> 744657.68 | G58: =C58-D58 -> 24363052 | H58: =YEAR(B58) -> 2030 | I58: =H58-2026 -> 4
A59: 44 | B59: =EOMONTH($C$10,43) -> 47726 | C59: =G58 -> 24363052 | D59: =IF(A59>$C$6,MIN(C59,$C$13),0) -> 594220.78 | E59: =C59*$C$8*DAY(B59)/$C$11 -> 146855.06 | F59: =D59+E59 -> 741075.85 | G59: =C59-D59 -> 23768831 | H59: =YEAR(B59) -> 2030 | I59: =H59-2026 -> 4
A60: 45 | B60: =EOMONTH($C$10,44) -> 47756 | C60: =G59 -> 23768831 | D60: =IF(A60>$C$6,MIN(C60,$C$13),0) -> 594220.78 | E60: =C60*$C$8*DAY(B60)/$C$11 -> 138651.52 | F60: =D60+E60 -> 732872.3 | G60: =C60-D60 -> 23174611 | H60: =YEAR(B60) -> 2030 | I60: =H60-2026 -> 4
A61: 46 | B61: =EOMONTH($C$10,45) -> 47787 | C61: =G60 -> 23174611 | D61: =IF(A61>$C$6,MIN(C61,$C$13),0) -> 594220.78 | E61: =C61*$C$8*DAY(B61)/$C$11 -> 139691.4 | F61: =D61+E61 -> 733912.18 | G61: =C61-D61 -> 22580390 | H61: =YEAR(B61) -> 2030 | I61: =H61-2026 -> 4
A62: 47 | B62: =EOMONTH($C$10,46) -> 47817 | C62: =G61 -> 22580390 | D62: =IF(A62>$C$6,MIN(C62,$C$13),0) -> 594220.78 | E62: =C62*$C$8*DAY(B62)/$C$11 -> 131718.94 | F62: =D62+E62 -> 725939.72 | G62: =C62-D62 -> 21986169 | H62: =YEAR(B62) -> 2030 | I62: =H62-2026 -> 4
A63: 48 | B63: =EOMONTH($C$10,47) -> 47848 | C63: =G62 -> 21986169 | D63: =IF(A63>$C$6,MIN(C63,$C$13),0) -> 594220.78 | E63: =C63*$C$8*DAY(B63)/$C$11 -> 132527.74 | F63: =D63+E63 -> 726748.52 | G63: =C63-D63 -> 21391948 | H63: =YEAR(B63) -> 2030 | I63: =H63-2026 -> 4
A64: 49 | B64: =EOMONTH($C$10,48) -> 47879 | C64: =G63 -> 21391948 | D64: =IF(A64>$C$6,MIN(C64,$C$13),0) -> 594220.78 | E64: =C64*$C$8*DAY(B64)/$C$11 -> 128945.91 | F64: =D64+E64 -> 723166.69 | G64: =C64-D64 -> 20797727 | H64: =YEAR(B64) -> 2031 | I64: =H64-2026 -> 5
A65: 50 | B65: =EOMONTH($C$10,49) -> 47907 | C65: =G64 -> 20797727 | D65: =IF(A65>$C$6,MIN(C65,$C$13),0) -> 594220.78 | E65: =C65*$C$8*DAY(B65)/$C$11 -> 113232.07 | F65: =D65+E65 -> 707452.85 | G65: =C65-D65 -> 20203507 | H65: =YEAR(B65) -> 2031 | I65: =H65-2026 -> 5
A66: 51 | B66: =EOMONTH($C$10,50) -> 47938 | C66: =G65 -> 20203507 | D66: =IF(A66>$C$6,MIN(C66,$C$13),0) -> 594220.78 | E66: =C66*$C$8*DAY(B66)/$C$11 -> 121782.25 | F66: =D66+E66 -> 716003.03 | G66: =C66-D66 -> 19609286 | H66: =YEAR(B66) -> 2031 | I66: =H66-2026 -> 5
A67: 52 | B67: =EOMONTH($C$10,51) -> 47968 | C67: =G66 -> 19609286 | D67: =IF(A67>$C$6,MIN(C67,$C$13),0) -> 594220.78 | E67: =C67*$C$8*DAY(B67)/$C$11 -> 114387.5 | F67: =D67+E67 -> 708608.28 | G67: =C67-D67 -> 19015065 | H67: =YEAR(B67) -> 2031 | I67: =H67-2026 -> 5
A68: 53 | B68: =EOMONTH($C$10,52) -> 47999 | C68: =G67 -> 19015065 | D68: =IF(A68>$C$6,MIN(C68,$C$13),0) -> 594220.78 | E68: =C68*$C$8*DAY(B68)/$C$11 -> 114618.59 | F68: =D68+E68 -> 708839.37 | G68: =C68-D68 -> 18420844 | H68: =YEAR(B68) -> 2031 | I68: =H68-2026 -> 5
A69: 54 | B69: =EOMONTH($C$10,53) -> 48029 | C69: =G68 -> 18420844 | D69: =IF(A69>$C$6,MIN(C69,$C$13),0) -> 594220.78 | E69: =C69*$C$8*DAY(B69)/$C$11 -> 107454.92 | F69: =D69+E69 -> 701675.71 | G69: =C69-D69 -> 17826623 | H69: =YEAR(B69) -> 2031 | I69: =H69-2026 -> 5
A70: 55 | B70: =EOMONTH($C$10,54) -> 48060 | C70: =G69 -> 17826623 | D70: =IF(A70>$C$6,MIN(C70,$C$13),0) -> 594220.78 | E70: =C70*$C$8*DAY(B70)/$C$11 -> 107454.92 | F70: =D70+E70 -> 701675.71 | G70: =C70-D70 -> 17232403 | H70: =YEAR(B70) -> 2031 | I70: =H70-2026 -> 5
A71: 56 | B71: =EOMONTH($C$10,55) -> 48091 | C71: =G70 -> 17232403 | D71: =IF(A71>$C$6,MIN(C71,$C$13),0) -> 594220.78 | E71: =C71*$C$8*DAY(B71)/$C$11 -> 103873.09 | F71: =D71+E71 -> 698093.88 | G71: =C71-D71 -> 16638182 | H71: =YEAR(B71) -> 2031 | I71: =H71-2026 -> 5
A72: 57 | B72: =EOMONTH($C$10,56) -> 48121 | C72: =G71 -> 16638182 | D72: =IF(A72>$C$6,MIN(C72,$C$13),0) -> 594220.78 | E72: =C72*$C$8*DAY(B72)/$C$11 -> 97056.061 | F72: =D72+E72 -> 691276.84 | G72: =C72-D72 -> 16043961 | H72: =YEAR(B72) -> 2031 | I72: =H72-2026 -> 5
A73: 58 | B73: =EOMONTH($C$10,57) -> 48152 | C73: =G72 -> 16043961 | D73: =IF(A73>$C$6,MIN(C73,$C$13),0) -> 594220.78 | E73: =C73*$C$8*DAY(B73)/$C$11 -> 96709.432 | F73: =D73+E73 -> 690930.21 | G73: =C73-D73 -> 15449740 | H73: =YEAR(B73) -> 2031 | I73: =H73-2026 -> 5
A74: 59 | B74: =EOMONTH($C$10,58) -> 48182 | C74: =G73 -> 15449740 | D74: =IF(A74>$C$6,MIN(C74,$C$13),0) -> 594220.78 | E74: =C74*$C$8*DAY(B74)/$C$11 -> 90123.485 | F74: =D74+E74 -> 684344.27 | G74: =C74-D74 -> 14855520 | H74: =YEAR(B74) -> 2031 | I74: =H74-2026 -> 5
A75: 60 | B75: =EOMONTH($C$10,59) -> 48213 | C75: =G74 -> 14855520 | D75: =IF(A75>$C$6,MIN(C75,$C$13),0) -> 594220.78 | E75: =C75*$C$8*DAY(B75)/$C$11 -> 89545.771 | F75: =D75+E75 -> 683766.55 | G75: =C75-D75 -> 14261299 | H75: =YEAR(B75) -> 2031 | I75: =H75-2026 -> 5
A76: 61 | B76: =EOMONTH($C$10,60) -> 48244 | C76: =G75 -> 14261299 | D76: =IF(A76>$C$6,MIN(C76,$C$13),0) -> 594220.78 | E76: =C76*$C$8*DAY(B76)/$C$11 -> 85963.94 | F76: =D76+E76 -> 680184.72 | G76: =C76-D76 -> 13667078 | H76: =YEAR(B76) -> 2032 | I76: =H76-2026 -> 6
A77: 62 | B77: =EOMONTH($C$10,61) -> 48273 | C77: =G76 -> 13667078 | D77: =IF(A77>$C$6,MIN(C77,$C$13),0) -> 594220.78 | E77: =C77*$C$8*DAY(B77)/$C$11 -> 77067.134 | F77: =D77+E77 -> 671287.92 | G77: =C77-D77 -> 13072857 | H77: =YEAR(B77) -> 2032 | I77: =H77-2026 -> 6
A78: 63 | B78: =EOMONTH($C$10,62) -> 48304 | C78: =G77 -> 13072857 | D78: =IF(A78>$C$6,MIN(C78,$C$13),0) -> 594220.78 | E78: =C78*$C$8*DAY(B78)/$C$11 -> 78800.278 | F78: =D78+E78 -> 673021.06 | G78: =C78-D78 -> 12478636 | H78: =YEAR(B78) -> 2032 | I78: =H78-2026 -> 6
A79: 64 | B79: =EOMONTH($C$10,63) -> 48334 | C79: =G78 -> 12478636 | D79: =IF(A79>$C$6,MIN(C79,$C$13),0) -> 594220.78 | E79: =C79*$C$8*DAY(B79)/$C$11 -> 72792.046 | F79: =D79+E79 -> 667012.83 | G79: =C79-D79 -> 11884416 | H79: =YEAR(B79) -> 2032 | I79: =H79-2026 -> 6
A80: 65 | B80: =EOMONTH($C$10,64) -> 48365 | C80: =G79 -> 11884416 | D80: =IF(A80>$C$6,MIN(C80,$C$13),0) -> 594220.78 | E80: =C80*$C$8*DAY(B80)/$C$11 -> 71636.617 | F80: =D80+E80 -> 665857.4 | G80: =C80-D80 -> 11290195 | H80: =YEAR(B80) -> 2032 | I80: =H80-2026 -> 6
A81: 66 | B81: =EOMONTH($C$10,65) -> 48395 | C81: =G80 -> 11290195 | D81: =IF(A81>$C$6,MIN(C81,$C$13),0) -> 594220.78 | E81: =C81*$C$8*DAY(B81)/$C$11 -> 65859.47 | F81: =D81+E81 -> 660080.25 | G81: =C81-D81 -> 10695974 | H81: =YEAR(B81) -> 2032 | I81: =H81-2026 -> 6
A82: 67 | B82: =EOMONTH($C$10,66) -> 48426 | C82: =G81 -> 10695974 | D82: =IF(A82>$C$6,MIN(C82,$C$13),0) -> 594220.78 | E82: =C82*$C$8*DAY(B82)/$C$11 -> 64472.955 | F82: =D82+E82 -> 658693.74 | G82: =C82-D82 -> 10101753 | H82: =YEAR(B82) -> 2032 | I82: =H82-2026 -> 6
A83: 68 | B83: =EOMONTH($C$10,67) -> 48457 | C83: =G82 -> 10101753 | D83: =IF(A83>$C$6,MIN(C83,$C$13),0) -> 594220.78 | E83: =C83*$C$8*DAY(B83)/$C$11 -> 60891.124 | F83: =D83+E83 -> 655111.91 | G83: =C83-D83 -> 9507532.5 | H83: =YEAR(B83) -> 2032 | I83: =H83-2026 -> 6
A84: 69 | B84: =EOMONTH($C$10,68) -> 48487 | C84: =G83 -> 9507532.5 | D84: =IF(A84>$C$6,MIN(C84,$C$13),0) -> 594220.78 | E84: =C84*$C$8*DAY(B84)/$C$11 -> 55460.606 | F84: =D84+E84 -> 649681.39 | G84: =C84-D84 -> 8913311.7 | H84: =YEAR(B84) -> 2032 | I84: =H84-2026 -> 6
A85: 70 | B85: =EOMONTH($C$10,69) -> 48518 | C85: =G84 -> 8913311.7 | D85: =IF(A85>$C$6,MIN(C85,$C$13),0) -> 594220.78 | E85: =C85*$C$8*DAY(B85)/$C$11 -> 53727.462 | F85: =D85+E85 -> 647948.24 | G85: =C85-D85 -> 8319091 | H85: =YEAR(B85) -> 2032 | I85: =H85-2026 -> 6
A86: 71 | B86: =EOMONTH($C$10,70) -> 48548 | C86: =G85 -> 8319091 | D86: =IF(A86>$C$6,MIN(C86,$C$13),0) -> 594220.78 | E86: =C86*$C$8*DAY(B86)/$C$11 -> 48528.031 | F86: =D86+E86 -> 642748.81 | G86: =C86-D86 -> 7724870.2 | H86: =YEAR(B86) -> 2032 | I86: =H86-2026 -> 6
A87: 72 | B87: =EOMONTH($C$10,71) -> 48579 | C87: =G86 -> 7724870.2 | D87: =IF(A87>$C$6,MIN(C87,$C$13),0) -> 594220.78 | E87: =C87*$C$8*DAY(B87)/$C$11 -> 46563.801 | F87: =D87+E87 -> 640784.58 | G87: =C87-D87 -> 7130649.4 | H87: =YEAR(B87) -> 2032 | I87: =H87-2026 -> 6
A88: 73 | B88: =EOMONTH($C$10,72) -> 48610 | C88: =G87 -> 7130649.4 | D88: =IF(A88>$C$6,MIN(C88,$C$13),0) -> 594220.78 | E88: =C88*$C$8*DAY(B88)/$C$11 -> 42981.97 | F88: =D88+E88 -> 637202.75 | G88: =C88-D88 -> 6536428.6 | H88: =YEAR(B88) -> 2033 | I88: =H88-2026 -> 7
A89: 74 | B89: =EOMONTH($C$10,73) -> 48638 | C89: =G88 -> 6536428.6 | D89: =IF(A89>$C$6,MIN(C89,$C$13),0) -> 594220.78 | E89: =C89*$C$8*DAY(B89)/$C$11 -> 35587.222 | F89: =D89+E89 -> 629808 | G89: =C89-D89 -> 5942207.8 | H89: =YEAR(B89) -> 2033 | I89: =H89-2026 -> 7
A90: 75 | B90: =EOMONTH($C$10,74) -> 48669 | C90: =G89 -> 5942207.8 | D90: =IF(A90>$C$6,MIN(C90,$C$13),0) -> 594220.78 | E90: =C90*$C$8*DAY(B90)/$C$11 -> 35818.308 | F90: =D90+E90 -> 630039.09 | G90: =C90-D90 -> 5347987 | H90: =YEAR(B90) -> 2033 | I90: =H90-2026 -> 7
A91: 76 | B91: =EOMONTH($C$10,75) -> 48699 | C91: =G90 -> 5347987 | D91: =IF(A91>$C$6,MIN(C91,$C$13),0) -> 594220.78 | E91: =C91*$C$8*DAY(B91)/$C$11 -> 31196.591 | F91: =D91+E91 -> 625417.37 | G91: =C91-D91 -> 4753766.3 | H91: =YEAR(B91) -> 2033 | I91: =H91-2026 -> 7
A92: 77 | B92: =EOMONTH($C$10,76) -> 48730 | C92: =G91 -> 4753766.3 | D92: =IF(A92>$C$6,MIN(C92,$C$13),0) -> 594220.78 | E92: =C92*$C$8*DAY(B92)/$C$11 -> 28654.647 | F92: =D92+E92 -> 622875.43 | G92: =C92-D92 -> 4159545.5 | H92: =YEAR(B92) -> 2033 | I92: =H92-2026 -> 7
A93: 78 | B93: =EOMONTH($C$10,77) -> 48760 | C93: =G92 -> 4159545.5 | D93: =IF(A93>$C$6,MIN(C93,$C$13),0) -> 594220.78 | E93: =C93*$C$8*DAY(B93)/$C$11 -> 24264.015 | F93: =D93+E93 -> 618484.8 | G93: =C93-D93 -> 3565324.7 | H93: =YEAR(B93) -> 2033 | I93: =H93-2026 -> 7
A94: 79 | B94: =EOMONTH($C$10,78) -> 48791 | C94: =G93 -> 3565324.7 | D94: =IF(A94>$C$6,MIN(C94,$C$13),0) -> 594220.78 | E94: =C94*$C$8*DAY(B94)/$C$11 -> 21490.985 | F94: =D94+E94 -> 615711.77 | G94: =C94-D94 -> 2971103.9 | H94: =YEAR(B94) -> 2033 | I94: =H94-2026 -> 7
A95: 80 | B95: =EOMONTH($C$10,79) -> 48822 | C95: =G94 -> 2971103.9 | D95: =IF(A95>$C$6,MIN(C95,$C$13),0) -> 594220.78 | E95: =C95*$C$8*DAY(B95)/$C$11 -> 17909.154 | F95: =D95+E95 -> 612129.94 | G95: =C95-D95 -> 2376883.1 | H95: =YEAR(B95) -> 2033 | I95: =H95-2026 -> 7
A96: 81 | B96: =EOMONTH($C$10,80) -> 48852 | C96: =G95 -> 2376883.1 | D96: =IF(A96>$C$6,MIN(C96,$C$13),0) -> 594220.78 | E96: =C96*$C$8*DAY(B96)/$C$11 -> 13865.152 | F96: =D96+E96 -> 608085.93 | G96: =C96-D96 -> 1782662.3 | H96: =YEAR(B96) -> 2033 | I96: =H96-2026 -> 7
A97: 82 | B97: =EOMONTH($C$10,81) -> 48883 | C97: =G96 -> 1782662.3 | D97: =IF(A97>$C$6,MIN(C97,$C$13),0) -> 594220.78 | E97: =C97*$C$8*DAY(B97)/$C$11 -> 10745.492 | F97: =D97+E97 -> 604966.27 | G97: =C97-D97 -> 1188441.6 | H97: =YEAR(B97) -> 2033 | I97: =H97-2026 -> 7
A98: 83 | B98: =EOMONTH($C$10,82) -> 48913 | C98: =G97 -> 1188441.6 | D98: =IF(A98>$C$6,MIN(C98,$C$13),0) -> 594220.78 | E98: =C98*$C$8*DAY(B98)/$C$11 -> 6932.5758 | F98: =D98+E98 -> 601153.36 | G98: =C98-D98 -> 594220.78 | H98: =YEAR(B98) -> 2033 | I98: =H98-2026 -> 7
A99: 84 | B99: =EOMONTH($C$10,83) -> 48944 | C99: =G98 -> 594220.78 | D99: =IF(A99>$C$6,MIN(C99,$C$13),0) -> 594220.78 | E99: =C99*$C$8*DAY(B99)/$C$11 -> 3581.8308 | F99: =D99+E99 -> 597802.61 | G99: =C99-D99 -> 0 | H99: =YEAR(B99) -> 2033 | I99: =H99-2026 -> 7
B100: ИТОГО | D100: =SUM(D16:D99) -> 42783896 | E100: =SUM(E16:E99) -> 12276667 | F100: =SUM(F16:F99) -> 55060564
B102: ГОДОВАЯ СВОДКА ПО КРЕДИТУ
B103: ПОКАЗАТЕЛИ | C103: 1 год (2027) | D103: 2 год (2028) | E103: 3 год (2029) | F103: 4 год (2030) | G103: 5 год (2031) | H103: 6 год (2032) | I103: 7 год (2033)
B104: Выдача кредита | C104: =$C$9 -> 42783896 | D104: 0 | E104: 0 | F104: 0 | G104: 0 | H104: 0 | I104: 0
B105: Погашение основного долга | C105: =SUMIF($I$16:$I$99,1,$D$16:$D$99) -> 0 | D105: =SUMIF($I$16:$I$99,2,$D$16:$D$99) -> 7130649.4 | E105: =SUMIF($I$16:$I$99,3,$D$16:$D$99) -> 7130649.4 | F105: =SUMIF($I$16:$I$99,4,$D$16:$D$99) -> 7130649.4 | G105: =SUMIF($I$16:$I$99,5,$D$16:$D$99) -> 7130649.4 | H105: =SUMIF($I$16:$I$99,6,$D$16:$D$99) -> 7130649.4 | I105: =SUMIF($I$16:$I$99,7,$D$16:$D$99) -> 7130649.4
...

Sheet ProfLoss
B2: ПРЕДПОЛАГАЕМЫЕ СЧЕТА ПРИБЫЛЕЙ И УБЫТКОВ (в экв. долл. США) | K2: Приложение 13
B4: ПОКАЗАТЕЛИ | C4: Ед. изм. | D4: 1 год (льготный / инвест.) | E4: 2 год | F4: 3 год | G4: 4 год | H4: 5 год | I4: 6 год | J4: 7 год
D5: 2027 | E5: 2028 | F5: 2029 | G5: 2030 | H5: 2031 | I5: 2032 | J5: 2033
B6: Выручка от реализации продукции (с НДС) | C6: USD | D6: =D7+D8 -> 26724975 | E6: =E7+E8 -> 95293597 | F6: =F7+F8 -> 1.0532141e+08 | G6: =G7+G8 -> 1.3674767e+08 | H6: =H7+H8 -> 1.3435856e+08 | I6: =I7+I8 -> 1.3722306e+08 | J6: =J7+J8 -> 1.4024251e+08
B7: экспорт (в твёрдой валюте) | C7: USD | D7: =SalePlan!D8 -> 0 | E7: =SalePlan!E8 -> 0 | F7: =SalePlan!F8 -> 0 | G7: =SalePlan!G8 -> 0 | H7: =SalePlan!H8 -> 0 | I7: =SalePlan!I8 -> 0 | J7: =SalePlan!J8 -> 0
B8: внутренний рынок (с НДС) | C8: USD | D8: =SalePlan!D12+Taxes!D19 -> 26724975 | E8: =SalePlan!E12+Taxes!E19 -> 95293597 | F8: =SalePlan!F12+Taxes!F19 -> 1.0532141e+08 | G8: =SalePlan!G12+Taxes!G19 -> 1.3674767e+08 | H8: =SalePlan!H12+Taxes!H19 -> 1.3435856e+08 | I8: =SalePlan!I12+Taxes!I19 -> 1.3722306e+08 | J8: =SalePlan!J12+Taxes!J19 -> 1.4024251e+08
B9: НДС, начисленный с реализации | C9: USD | D9: =Taxes!D19 -> 2863390.2 | E9: =Taxes!E19 -> 10210028 | F9: =Taxes!F19 -> 11284437 | G9: =Taxes!G19 -> 14651536 | H9: =Taxes!H19 -> 14395560 | I9: =Taxes!I19 -> 14702471 | J9: =Taxes!J19 -> 15025984
B10: Чистая выручка от реализации продукции | C10: USD | D10: =D6-D9 -> 23861585 | E10: =E6-E9 -> 85083568 | F10: =F6-F9 -> 94036971 | G10: =G6-G9 -> 1.2209613e+08 | H10: =H6-H9 -> 1.19963e+08 | I10: =I6-I9 -> 1.2252059e+08 | J10: =J6-J9 -> 1.2521653e+08
B11: Себестоимость реализованной продукции | C11: USD | D11: =CostSold!D22 -> 11316651 | E11: =CostSold!E22 -> 43392942 | F11: =CostSold!F22 -> 49091212 | G11: =CostSold!G22 -> 58338444 | H11: =CostSold!H22 -> 59738918 | I11: =CostSold!I22 -> 60820556 | J11: =CostSold!J22 -> 61934686
B12: в твёрдой валюте | C12: USD | D12: =CostSold!D23 -> 11316651 | E12: =CostSold!E23 -> 43392942 | F12: =CostSold!F23 -> 49091212 | G12: =CostSold!G23 -> 58338444 | H12: =CostSold!H23 -> 59738918 | I12: =CostSold!I23 -> 60820556 | J12: =CostSold!J23 -> 61934686
B13: в местной валюте | C13: USD | D13: =CostSold!D24 -> -4.0978193e-08 | E13: =CostSold!E24 -> 0 | F13: =CostSold!F24 -> 0 | G13: =CostSold!G24 -> 0 | H13: =CostSold!H24 -> 0 | I13: =CostSold!I24 -> 0 | J13: =CostSold!J24 -> 0
B14: Валовая прибыль (убыток) | C14: USD | D14: =D10-D11 -> 12544934 | E14: =E10-E11 -> 41690627 | F14: =F10-F11 -> 44945759 | G14: =G10-G11 -> 63757687 | H14: =H10-H11 -> 60224084 | I14: =I10-I11 -> 61700035 | J14: =J10-J11 -> 63281844
B15: Расходы периода (административные и коммерческие) | C15: USD | D15: =CostSold!D31 -> 1599353.8 | E15: =CostSold!E31 -> 1790784.1 | F15: =CostSold!F31 -> 1830181.4 | G15: =CostSold!G31 -> 1870445.4 | H15: =CostSold!H31 -> 1911595.2 | I15: =CostSold!I31 -> 1953650.2 | J15: =CostSold!J31 -> 1996630.5
B16: Налоги и прочие операционные расходы | C16: USD | D16: =CostSold!D39 -> 5198171.6 | E16: =CostSold!E39 -> 2892315 | F16: =CostSold!F39 -> 3249405.7 | G16: =CostSold!G39 -> 15172516 | H16: =CostSold!H39 -> 22718516 | I16: =CostSold!I39 -> 23264353 | J16: =CostSold!J39 -> 23854214
B17: Прибыль (убыток) от основной деятельности (EBIT) | C17: USD | D17: =D14-D15-D16 -> 5747408.8 | E17: =E14-E15-E16 -> 37007528 | F17: =F14-F15-F16 -> 39866172 | G17: =G14-G15-G16 -> 46714726 | H17: =H14-H15-H16 -> 35593973 | I17: =I14-I15-I16 -> 36482032 | J17: =J14-J15-J16 -> 37431000
B18: Финансовые расходы | C18: USD | D18: =D19 -> 0 | E18: =E19 -> 2811621.7 | F18: =F19 -> 2297340.1 | G18: =G19 -> 1791262 | H18: =H19 -> 1285184 | I18: =I19 -> 781763.46 | J18: =J19 -> 273027.94
B19: Проценты за кредит | C19: USD | D19: =CostSold!D42 -> 0 | E19: =CostSold!E42 -> 2811621.7 | F19: =CostSold!F42 -> 2297340.1 | G19: =CostSold!G42 -> 1791262 | H19: =CostSold!H42 -> 1285184 | I19: =CostSold!I42 -> 781763.46 | J19: =CostSold!J42 -> 273027.94
B20: Прибыль (убыток) до налогообложения | C20: USD | D20: =D17-D18 -> 5747408.8 | E20: =E17-E18 -> 34195906 | F20: =F17-F18 -> 37568832 | G20: =G17-G18 -> 44923464 | H20: =H17-H18 -> 34308789 | I20: =I17-I18 -> 35700268 | J20: =J17-J18 -> 37157972
B21: Налог на прибыль (Приложение 9) | C21: USD | D21: =Taxes!D29 -> 2205838.3 | E21: =Taxes!E29 -> 14757263 | F21: =Taxes!F29 -> 16276351 | G21: =Taxes!G29 -> 20554661 | H21: =Taxes!H29 -> 18721079 | I21: =Taxes!I29 -> 19219212 | J21: =Taxes!J29 -> 19742935
B22: Чистая прибыль (убыток) | C22: USD | D22: =D20-D21 -> 3541570.5 | E22: =E20-E21 -> 19438643 | F22: =F20-F21 -> 21292482 | G22: =G20-G21 -> 24368803 | H22: =H20-H21 -> 15587710 | I22: =I20-I21 -> 16481056 | J22: =J20-J21 -> 17415037
B24: Коэффициенты рентабельности и покрытия
B25: Валовая рентабельность | C25: % | D25: =IFERROR(D14/D10,0) -> 0.52573768 | E25: =IFERROR(E14/E10,0) -> 0.48999622 | F25: =IFERROR(F14/F10,0) -> 0.47795839 | G25: =IFERROR(G14/G10,0) -> 0.52219253 | H25: =IFERROR(H14/H10,0) -> 0.50202215 | I25: =IFERROR(I14/I10,0) -> 0.50358911 | J25: =IFERROR(J14/J10,0) -> 0.50537932
B26: Чистая рентабельность | C26: % | D26: =IFERROR(D22/D10,0) -> 0.14842143 | E26: =IFERROR(E22/E10,0) -> 0.2284653 | F26: =IFERROR(F22/F10,0) -> 0.22642671 | G26: =IFERROR(G22/G10,0) -> 0.19958702 | H26: =IFERROR(H22/H10,0) -> 0.12993765 | I26: =IFERROR(I22/I10,0) -> 0.13451662 | J26: =IFERROR(J22/J10,0) -> 0.13907938
B27: EBITDA | C27: USD | D27: =D17+Depreciate!$G$19 -> 11035331 | E27: =E17+Depreciate!$H$19 -> 53030081 | F27: =F17+Depreciate!$I$19 -> 56029869 | G27: =G17+Depreciate!$J$19 -> 63019565 | H27: =H17+Depreciate!$K$19 -> 52039956 | I27: =I17+Depreciate!$L$19 -> 53069157 | J27: =J17+Depreciate!$M$19 -> 54159268
B28: Маржа EBITDA | C28: % | D28: =IFERROR(D27/D10,0) -> 0.46247269 | E28: =IFERROR(E27/E10,0) -> 0.62327053 | F28: =IFERROR(F27/F10,0) -> 0.59582809 | G28: =IFERROR(G27/G10,0) -> 0.51614711 | H28: =IFERROR(H27/H10,0) -> 0.43380004 | I28: =IFERROR(I27/I10,0) -> 0.4331448 | J28: =IFERROR(J27/J10,0) -> 0.43252491
B29: EBIT / Проценты за кредит | C29: x | D29: =IF(D19>0,D17/D19,"-") -> - | E29: =IF(E19>0,E17/E19,"-") -> 13.162343 | F29: =IF(F19>0,F17/F19,"-") -> 17.353187 | G29: =IF(G19>0,G17/G19,"-") -> 26.079225 | H29: =IF(H19>0,H17/H19,"-") -> 27.695624 | I29: =IF(I19>0,I17/I19,"-") -> 46.66633 | J29: =IF(J19>0,J17/J19,"-") -> 137.09586
B30: Задолженность по кредиту на конец года | C30: USD | D30: =LOANS!$C$108 -> 42783896 | E30: =LOANS!$D$108 -> 35653247 | F30: =LOANS!$E$108 -> 28522598 | G30: =LOANS!$F$108 -> 21391948 | H30: =LOANS!$G$108 -> 14261299 | I30: =LOANS!$H$108 -> 7130649.4 | J30: =LOANS!$I$108 -> 0
B31: Долг / EBITDA | C31: x | D31: =IFERROR(D30/D27,0) -> 3.8769924 | E31: =IFERROR(E30/E27,0) -> 0.67232118 | F31: =IFERROR(F30/F27,0) -> 0.50906058 | G31: =IFERROR(G30/G27,0) -> 0.33944931 | H31: =IFERROR(H30/H27,0) -> 0.27404518 | I31: =IFERROR(I30/I27,0) -> 0.13436523 | J31: =IFERROR(J30/J27,0) -> 0
B33: 1-й год: проценты за кредит льготного периода оплачиваются за счёт собственных средств и капитализируются в стоимость основных средств (МСФО IAS 23, Приложения 1 и 4); в отчёт о прибылях и убытках не включаются.

Sheet WorkCap
B2: ПРЕДПОЛОЖЕНИЯ ПО РАБОЧЕМУ КАПИТАЛУ (в экв. долл. США) | K2: Приложение 14
B4: Показатели | C4: Дни покрытия
B5: Период поступления от продаж (дебиторская задолженность) | C5: 30
B6: Запасы сырья и материалов на складе | C6: 0
B7: Незавершенная продукция | C7: 5
B8: Запасы готовой продукции (минимальный запас) | C8: 15
B9: Период оплаты поставщикам (кредиторская задолженность) | C9: 8
B10: Задолженность по заработной плате | C10: 15
B11: Возмещение НДС (операционный) | C11: 90
B12: Возмещение НДС по капитальным вложениям | C12: 540
B14: ПОКАЗАТЕЛИ (на конец года) | C14: Начало | D14: 1 год | E14: 2 год | F14: 3 год | G14: 4 год | H14: 5 год | I14: 6 год | J14: 7 год
C15: 01.01.2026 | D15: 2027 | E15: 2028 | F15: 2029 | G15: 2030 | H15: 2031 | I15: 2032 | J15: 2033
B16: Дебиторская задолженность | C16: 0 | D16: 7713573.4 | E16: 6993170 | F16: 7729066.1 | G16: 10035298 | H16: 9859972.8 | I16: 10070186 | J16: 10291770
B17: Запасы (сырьё, материалы, НЗП, готовая продукция) | C17: 0 | D17: 1521163.9 | E17: 1522189.6 | F17: 1846778.7 | G17: 2363659.8 | H17: 2406109.7 | I17: 2458882.3 | J17: 2512977.7
B18: НДС к возмещению | C18: 0 | D18: 16825503 | E18: 3359810.7 | F18: 0 | G18: 0 | H18: 0 | I18: 0 | J18: 0
B19: Итого текущих активов | C19: 0 | D19: =SUM(D16:D18) -> 26060240 | E19: =SUM(E16:E18) -> 11875170 | F19: =SUM(F16:F18) -> 9575844.8 | G19: =SUM(G16:G18) -> 12398958 | H19: =SUM(H16:H18) -> 12266083 | I19: =SUM(I16:I18) -> 12529068 | J19: =SUM(J16:J18) -> 12804747
B20: Кредиторская задолженность | C20: 0 | D20: 397060 | E20: 397506.81 | F20: 517754.8 | G20: 701531.07 | H20: 716502.48 | I20: 732257.7 | J20: 748367.37
B21: Задолженность по оплате труда и налогам с ФОТ | C21: 0 | D21: 368986 | E21: 384335.82 | F21: 392791.21 | G21: 401432.62 | H21: 410264.13 | I21: 419289.94 | J21: 428514.32
B22: Итого текущих обязательств | C22: 0 | D22: =D20+D21 -> 766046.01 | E22: =E20+E21 -> 781842.63 | F22: =F20+F21 -> 910546.01 | G22: =G20+G21 -> 1102963.7 | H22: =H20+H21 -> 1126766.6 | I22: =I20+I21 -> 1151547.6 | J22: =J20+J21 -> 1176881.7
B23: Чистый рабочий капитал | C23: 0 | D23: =D19-D22 -> 25294194 | E23: =E19-E22 -> 11093328 | F23: =F19-F22 -> 8665298.8 | G23: =G19-G22 -> 11295995 | H23: =H19-H22 -> 11139316 | I23: =I19-I22 -> 11377520 | J23: =J19-J22 -> 11627866
B25: Изменения в рабочем капитале (- рост / + снижение) | D25: =-(D23-C23) -> -25294194 | E25: =-(E23-D23) -> 14200866 | F25: =-(F23-E23) -> 2428028.9 | G25: =-(G23-F23) -> -2630695.8 | H25: =-(H23-G23) -> 156678.7 | I25: =-(I23-H23) -> -238204.32 | J25: =-(J23-I23) -> -250345.41
B26: Прочие изменения операционных статей (налоги к уплате и пр.) | D26: 785970.41 | E26: -83442.081 | F26: 56104.048 | G26: 222089 | H26: -23814.766 | I26: 20483.496 | J26: 21706.756
B27: Изменение рабочего капитала для потока наличности (Приложение 15) | D27: =D25+D26 -> -24508224 | E27: =E25+E26 -> 14117424 | F27: =F25+F26 -> 2484133 | G27: =G25+G26 -> -2408606.8 | H27: =H25+H26 -> 132863.94 | I27: =I25+I26 -> -217720.82 | J27: =J25+J26 -> -228638.66
B29: 1-й год: изменение рассчитано от начала строительства (01.01.2026), т.е. включает 2026 г.

Sheet CashFlow
B2: ПОТОКИ НАЛИЧНОСТИ (в экв. долл. США) | K2: Приложение 15
B3: 1-й год (2027) - инвестиционный и льготный период; включает также освоение капвложений и расходы подготовительного периода 2026 г.
B4: ПОКАЗАТЕЛИ | C4: Ед. изм. | D4: 1 год (льготный / инвест.) | E4: 2 год | F4: 3 год | G4: 4 год | H4: 5 год | I4: 6 год | J4: 7 год
D5: 2027 | E5: 2028 | F5: 2029 | G5: 2030 | H5: 2031 | I5: 2032 | J5: 2033
B6: Выручка от реализации продукции (с НДС) | C6: USD | D6: =ProfLoss!D6 -> 26724975 | E6: =ProfLoss!E6 -> 95293597 | F6: =ProfLoss!F6 -> 1.0532141e+08 | G6: =ProfLoss!G6 -> 1.3674767e+08 | H6: =ProfLoss!H6 -> 1.3435856e+08 | I6: =ProfLoss!I6 -> 1.3722306e+08 | J6: =ProfLoss!J6 -> 1.4024251e+08
B7: НДС, начисленный с реализации | C7: USD | D7: =-ProfLoss!D9 -> -2863390.2 | E7: =-ProfLoss!E9 -> -10210028 | F7: =-ProfLoss!F9 -> -11284437 | G7: =-ProfLoss!G9 -> -14651536 | H7: =-ProfLoss!H9 -> -14395560 | I7: =-ProfLoss!I9 -> -14702471 | J7: =-ProfLoss!J9 -> -15025984
B8: Чистая выручка от реализации продукции | C8: USD | D8: =D6+D7 -> 23861585 | E8: =E6+E7 -> 85083568 | F8: =F6+F7 -> 94036971 | G8: =G6+G7 -> 1.2209613e+08 | H8: =H6+H7 -> 1.19963e+08 | I8: =I6+I7 -> 1.2252059e+08 | J8: =J6+J7 -> 1.2521653e+08
B9: Изменения в рабочем капитале (Приложение 14) | C9: USD | D9: =WorkCap!D27 -> -24508224 | E9: =WorkCap!E27 -> 14117424 | F9: =WorkCap!F27 -> 2484133 | G9: =WorkCap!G27 -> -2408606.8 | H9: =WorkCap!H27 -> 132863.94 | I9: =WorkCap!I27 -> -217720.82 | J9: =WorkCap!J27 -> -228638.66
B10: Наличность от продаж | C10: USD | D10: =D8+D9 -> -646638.7 | E10: =E8+E9 -> 99200993 | F10: =F8+F9 -> 96521104 | G10: =G8+G9 -> 1.1968752e+08 | H10: =H8+H9 -> 1.2009587e+08 | I10: =I8+I9 -> 1.2230287e+08 | J10: =J8+J9 -> 1.2498789e+08
B11: Себестоимость реализованной продукции | C11: USD | D11: =-ProfLoss!D11 -> -11316651 | E11: =-ProfLoss!E11 -> -43392942 | F11: =-ProfLoss!F11 -> -49091212 | G11: =-ProfLoss!G11 -> -58338444 | H11: =-ProfLoss!H11 -> -59738918 | I11: =-ProfLoss!I11 -> -60820556 | J11: =-ProfLoss!J11 -> -61934686
B12: Валовые поступления наличности | C12: USD | D12: =D10+D11 -> -11963289 | E12: =E10+E11 -> 55808051 | F12: =F10+F11 -> 47429892 | G12: =G10+G11 -> 61349081 | H12: =H10+H11 -> 60356948 | I12: =I10+I11 -> 61482314 | J12: =J10+J11 -> 63053206
B13: Расходы периода | C13: USD | D13: =-ProfLoss!D15 -> -1599353.8 | E13: =-ProfLoss!E15 -> -1790784.1 | F13: =-ProfLoss!F15 -> -1830181.4 | G13: =-ProfLoss!G15 -> -1870445.4 | H13: =-ProfLoss!H15 -> -1911595.2 | I13: =-ProfLoss!I15 -> -1953650.2 | J13: =-ProfLoss!J15 -> -1996630.5
B14: Налоги и прочие операционные расходы | C14: USD | D14: =-ProfLoss!D16 -> -5198171.6 | E14: =-ProfLoss!E16 -> -2892315 | F14: =-ProfLoss!F16 -> -3249405.7 | G14: =-ProfLoss!G16 -> -15172516 | H14: =-ProfLoss!H16 -> -22718516 | I14: =-ProfLoss!I16 -> -23264353 | J14: =-ProfLoss!J16 -> -23854214
B15: Расходы подготовительного периода 2026 г. | C15: USD | D15: =-ProjCost!$E$19 -> -1073730.1 | E15: =0 -> 0 | F15: =0 -> 0 | G15: =0 -> 0 | H15: =0 -> 0 | I15: =0 -> 0 | J15: =0 -> 0
B16: Налог на прибыль | C16: USD | D16: =-ProfLoss!D21 -> -2205838.3 | E16: =-ProfLoss!E21 -> -14757263 | F16: =-ProfLoss!F21 -> -16276351 | G16: =-ProfLoss!G21 -> -20554661 | H16: =-ProfLoss!H21 -> -18721079 | I16: =-ProfLoss!I21 -> -19219212 | J16: =-ProfLoss!J21 -> -19742935
B17: Амортизация (неденежная статья, прибавляется) | C17: USD | D17: =Depreciate!$G$19 -> 5287922.6 | E17: =Depreciate!$H$19 -> 16022554 | F17: =Depreciate!$I$19 -> 16163696 | G17: =Depreciate!$J$19 -> 16304839 | H17: =Depreciate!$K$19 -> 16445982 | I17: =Depreciate!$L$19 -> 16587125 | J17: =Depreciate!$M$19 -> 16728268
B18: Операционный поток наличности (A) | C18: USD | D18: =SUM(D12:D17) -> -16752461 | E18: =SUM(E12:E17) -> 52390242 | F18: =SUM(F12:F17) -> 42237651 | G18: =SUM(G12:G17) -> 40056298 | H18: =SUM(H12:H17) -> 33451740 | I18: =SUM(I12:I17) -> 33632223 | J18: =SUM(J12:J17) -> 34187695
B19: Собственный капитал (взнос заемщика) | C19: USD | D19: =FinPlan!$E$10 -> 1.2866167e+08 | E19: =0 -> 0 | F19: =0 -> 0 | G19: =0 -> 0 | H19: =0 -> 0 | I19: =0 -> 0 | J19: =0 -> 0
B20: Привлеченный кредит банка | C20: USD | D20: =LOANS!$C$104 -> 42783896 | E20: =LOANS!$D$104 -> 0 | F20: =LOANS!$E$104 -> 0 | G20: =LOANS!$F$104 -> 0 | H20: =LOANS!$G$104 -> 0 | I20: =LOANS!$H$104 -> 0 | J20: =LOANS!$I$104 -> 0
B21: Инвестиции (капитальные вложения; 1-й год вкл. 2026 г.) | C21: USD | D21: -1.4161333e+08 | E21: -1411428.6 | F21: -1411428.6 | G21: -1411428.6 | H21: -1411428.6 | I21: -1411428.6 | J21: -1411428.6
B22: Проценты за кредит (B) | C22: USD | D22: =-ProfLoss!D19 -> 0 | E22: =-ProfLoss!E19 -> -2811621.7 | F22: =-ProfLoss!F19 -> -2297340.1 | G22: =-ProfLoss!G19 -> -1791262 | H22: =-ProfLoss!H19 -> -1285184 | I22: =-ProfLoss!I19 -> -781763.46 | J22: =-ProfLoss!J19 -> -273027.94
B23: Прочие финансовые издержки в инвестиционный период (проценты льготного периода) | C23: USD | D23: =-LOANS!$C$106 -> -3036468.2 | E23: =0 -> 0 | F23: =0 -> 0 | G23: =0 -> 0 | H23: =0 -> 0 | I23: =0 -> 0 | J23: =0 -> 0
B24: Чистые поступления наличности | C24: USD | D24: =D18+D19+D20+D21+D22+D23 -> 10043303 | E24: =E18+E19+E20+E21+E22+E23 -> 48167192 | F24: =F18+F19+F20+F21+F22+F23 -> 38528883 | G24: =G18+G19+G20+G21+G22+G23 -> 36853607 | H24: =H18+H19+H20+H21+H22+H23 -> 30755128 | I24: =I18+I19+I20+I21+I22+I23 -> 31439031 | J24: =J18+J19+J20+J21+J22+J23 -> 32503238
B25: Выплата основного долга (C) | C25: USD | D25: =-LOANS!$C$105 -> 0 | E25: =-LOANS!$D$105 -> -7130649.4 | F25: =-LOANS!$E$105 -> -7130649.4 | G25: =-LOANS!$F$105 -> -7130649.4 | H25: =-LOANS!$G$105 -> -7130649.4 | I25: =-LOANS!$H$105 -> -7130649.4 | J25: =-LOANS!$I$105 -> -7130649.4
B26: Чистый поток наличности | C26: USD | D26: =D24+D25 -> 10043303 | E26: =E24+E25 -> 41036542 | F26: =F24+F25 -> 31398233 | G26: =G24+G25 -> 29722958 | H26: =H24+H25 -> 23624478 | I26: =I24+I25 -> 24308382 | J26: =J24+J25 -> 25372589
B27: Кумулятивный поток наличности | C27: USD | D27: =D26 -> 10043303 | E27: =D27+E26 -> 51079845 | F27: =E27+F26 -> 82478078 | G27: =F27+G26 -> 1.1220104e+08 | H27: =G27+H26 -> 1.3582551e+08 | I27: =H27+I26 -> 1.601339e+08 | J27: =I27+J26 -> 1.8550648e+08
B29: Коэффициент обслуживания долга, DSCR [(A)/(B+C)] | C29: x | D29: ="-" -> - | E29: =IFERROR(E18/-(E22+E25),0) -> 5.2694442 | F29: =IFERROR(F18/-(F22+F25),0) -> 4.4800274 | G29: =IFERROR(G18/-(G22+G25),0) -> 4.4896543 | H29: =IFERROR(H18/-(H22+H25),0) -> 3.9748577 | I29: =IFERROR(I18/-(I22+I25),0) -> 4.2505648 | J29: =IFERROR(J18/-(J22+J25),0) -> 4.617664
B30: DSCR с учётом поддерживающих капвложений [(A - инвестиции)/(B+C)] | C30: x | D30: ="-" -> - | E30: =IFERROR((E18+E21)/-(E22+E25),0) -> 5.1274818 | F30: =IFERROR((F18+F21)/-(F22+F25),0) -> 4.3303212 | G30: =IFERROR((G18+G21)/-(G22+G25),0) -> 4.3314563 | H30: =IFERROR((H18+H21)/-(H22+H25),0) -> 3.8071466 | I30: =IFERROR((I18+I21)/-(I22+I25),0) -> 4.0721832 | J30: =IFERROR((J18+J21)/-(J22+J25),0) -> 4.4270252
B31: Минимальный DSCR (2-7 годы) | D31: =MIN(E30:J30) -> 3.8071466
B32: Средний DSCR (2-7 годы) | D32: =AVERAGE(E30:J30) -> 4.349269
B34: Проценты льготного периода (1-й год) уплачиваются за счёт собственных средств заемщика (включены в стоимость проекта, Приложение 1). Налог на прибыль - в размере начисленного (без учёта отсрочки уплаты).

Sheet BreakPoint
B2: ТОЧКА БЕЗУБЫТОЧНОСТИ (в экв. долл. США, 2030 г.) | D2: Приложение 16
B4: Общие продажи при проектной мощности | C4: =CostTotal!C26 -> 1.2209613e+08
B5: в местной валюте | C5: =SalePlan!G12 -> 1.2209613e+08
B6: в твердой валюте | C6: =SalePlan!G8 -> 0
B7: Фиксированная стоимость | C7: =CostTotal!F22 -> 27431581
B8: Переменная стоимость | C8: =CostTotal!G22 -> 48466706
B9: Маржинальный доход | C9: =C4-C8 -> 73629426
B10: Точка безубыточности (доля от выручки при проектной мощности) | C10: =IFERROR(C7/C9,0) -> 0.37256274
B11: Точка безубыточности, USD выручки | C11: =C10*C4 -> 45488469
B12: Точка безубыточности в натуральном выражении (основная продукция) | C12: =C10*ProdPlan!G13 -> 1193.4219 | D12: t
B13: Запас финансовой прочности | C13: =1-C10 -> 0.62743726

Sheet NPV_IRR
B2: РАСЧЁТ NPV, IRR И СРОКА ОКУПАЕМОСТИ ПРОЕКТА (в экв. долл. США)
B3: Денежный поток проекта (до финансирования) = операционный поток (A) - инвестиции; горизонт - срок кредита (7 лет), без остаточной стоимости.
B4: ПОКАЗАТЕЛИ | C4: Ед. изм. | D4: 1 год (льготный / инвест.) | E4: 2 год | F4: 3 год | G4: 4 год | H4: 5 год | I4: 6 год | J4: 7 год
D5: 2027 | E5: 2028 | F5: 2029 | G5: 2030 | H5: 2031 | I5: 2032 | J5: 2033
B6: Период (лет) | D6: 1 | E6: 2 | F6: 3 | G6: 4 | H6: 5 | I6: 6 | J6: 7
B7: Операционный поток наличности (A) | C7: USD | D7: =CashFlow!D18 -> -16752461 | E7: =CashFlow!E18 -> 52390242 | F7: =CashFlow!F18 -> 42237651 | G7: =CashFlow!G18 -> 40056298 | H7: =CashFlow!H18 -> 33451740 | I7: =CashFlow!I18 -> 33632223 | J7: =CashFlow!J18 -> 34187695
B8: Инвестиции | C8: USD | D8: =CashFlow!D21 -> -1.4161333e+08 | E8: =CashFlow!E21 -> -1411428.6 | F8: =CashFlow!F21 -> -1411428.6 | G8: =CashFlow!G21 -> -1411428.6 | H8: =CashFlow!H21 -> -1411428.6 | I8: =CashFlow!I21 -> -1411428.6 | J8: =CashFlow!J21 -> -1411428.6
B9: Поток наличности проекта (FCFF) | C9: USD | D9: =D7+D8 -> -1.5836579e+08 | E9: =E7+E8 -> 50978814 | F9: =F7+F8 -> 40826223 | G9: =G7+G8 -> 38644869 | H9: =H7+H8 -> 32040312 | I9: =I7+I8 -> 32220795 | J9: =J7+J8 -> 32776266
B10: Ставка дисконта (WACC) | C10: % | D10: 0.11372393 | E10: 0.11372393 | F10: 0.11372393 | G10: 0.11372393 | H10: 0.11372393 | I10: 0.11372393 | J10: 0.11372393
B11: Коэффициент дисконтирования | D11: =1/(1+D10)^D6 -> 0.89788858 | E11: =1/(1+E10)^E6 -> 0.80620391 | F11: =1/(1+F10)^F6 -> 0.72388129 | G11: =1/(1+G10)^G6 -> 0.64996475 | H11: =1/(1+H10)^H6 -> 0.58359593 | I11: =1/(1+I10)^I6 -> 0.52400412 | J11: =1/(1+J10)^J6 -> 0.47049732
B12: Дисконтированный поток | C12: USD | D12: =D9*D11 -> -1.4219484e+08 | E12: =E9*E11 -> 41099319 | F12: =F9*F11 -> 29553339 | G12: =G9*G11 -> 25117803 | H12: =H9*H11 -> 18698595 | I12: =I9*I11 -> 16883829 | J12: =J9*J11 -> 15421145
B13: Накопленный поток | C13: USD | D13: =D9 -> -1.5836579e+08 | E13: =D13+E9 -> -1.0738698e+08 | F13: =E13+F9 -> -66560758 | G13: =F13+G9 -> -27915889 | H13: =G13+H9 -> 4124423 | I13: =H13+I9 -> 36345218 | J13: =I13+J9 -> 69121484
B14: Накопленный дисконтированный поток (NPV нарастающим итогом) | C14: USD | D14: =D12 -> -1.4219484e+08 | E14: =D14+E12 -> -1.0109552e+08 | F14: =E14+F12 -> -71542181 | G14: =F14+G12 -> -46424379 | H14: =G14+H12 -> -27725783 | I14: =H14+I12 -> -10841954 | J14: =I14+J12 -> 4579191.2
B15: вспом.: окупаемость | D15: ="" | E15: =IF(AND(D13<0,E13>=0),D6-D13/E9,"") | F15: =IF(AND(E13<0,F13>=0),E6-E13/F9,"") | G15: =IF(AND(F13<0,G13>=0),F6-F13/G9,"") | H15: =IF(AND(G13<0,H13>=0),G6-G13/H9,"") -> 4.8712739 | I15: =IF(AND(H13<0,I13>=0),H6-H13/I9,"") | J15: =IF(AND(I13<0,J13>=0),I6-I13/J9,"")
B16: вспом.: дисконтированная окупаемость | D16: ="" | E16: =IF(AND(D14<0,E14>=0),D6-D14/E12,"") | F16: =IF(AND(E14<0,F14>=0),E6-E14/F12,"") | G16: =IF(AND(F14<0,G14>=0),F6-F14/G12,"") | H16: =IF(AND(G14<0,H14>=0),G6-G14/H12,"") | I16: =IF(AND(H14<0,I14>=0),H6-H14/I12,"") | J16: =IF(AND(I14<0,J14>=0),I6-I14/J12,"") -> 6.7030576
B18: NPV (чистая приведённая стоимость), USD | D18: =SUM(D12:J12) -> 4579191.2
B19: IRR (внутренняя норма доходности) | D19: =IFERROR(IRR(D9:J9),"-") -> 0.1259814
B20: Индекс доходности (PI) | D20: =IFERROR(SUM(E12:J12)/-D12,0) -> 1.0322036
B21: Простой срок окупаемости, лет (от начала 1-го года) | D21: =IF(COUNT(E15:J15)>0,SUM(E15:J15),"> 7") -> 4.8712739
B22: Дисконтированный срок окупаемости, лет | D22: =IF(COUNT(E16:J16)>0,SUM(E16:J16),"> 7") -> 6.7030576
