Workbook

Sheet Резюме
B2: БИЗНЕС-ПЛАН ИНВЕСТИЦИОННОГО ПРОЕКТА
B3: Строительство нового гидрометаллургического завода по переработке промышленного продукта - молибденового огарка
B4: (Цех по производству триоксида молибдена)
B6: 1. ОБЩИЕ СВЕДЕНИЯ
B7: Суть проекта | C7: Строительство нового гидрометаллургического завода по переработке промышленного продукта - молибденового огарка. Переработка 5 000 т молибденового огарка (концентрата) в год; выпуск основной продукции - Триоксид молибдена MoO3 1 983.1 t/год при проектной мощности; реализация - экспорт.
B8: Заемщик | C8: АО «Узбекский комбинат технологических металлов» (АО «Ўзбекистон ТМК», UzTMK)
B9: Местоположение | C9: Ташкентская область, Ахангаранский район - новая площадка, 10,4 га
B10: Продукция | C10: Триоксид молибдена MoO3, Медный шлак (25% Cu) (попутная), Кальциевая селитра (попутная)
B11: Производственная мощность | C11: Переработка 5 000 т молибденового огарка (концентрата) в год; выпуск основной продукции - 1 983 t/год
B12: Рынок сбыта | C12: экспорт (100% выручки в USD)
B13: Сроки | C13: начало строительства - 01.10.2026; начало производства - 01.10.2027; выход на проектную мощность - 2030 г.
B14: Стадия проработки | C14: ТЭО
B16: 2. ПАРАМЕТРЫ КРЕДИТА
B17: Сумма кредита, USD | C17: =ИНФОРМАЦИЯ!$C$26 -> 18191814
B18: Процентная ставка | C18: =ИНФОРМАЦИЯ!$C$27 -> 0.07
B19: Срок кредита | C19: 84 месяца (7 лет): льготный (инвестиционный) период - 12 месяцев (2027 г.), погашение - 72 месяца (2028-2033 гг.)
B20: Порядок погашения | C20: основной долг - ежемесячно равными долями; проценты - ежемесячно на остаток задолженности
B21: Проценты льготного периода | C21: =TEXT(LOANS!$C$106,"#,##0") & " USD - уплачиваются за счёт собственных средств заемщика (включены в стоимость проекта)" -> 1,291,113 USD - уплачиваются за счёт собственных средств заемщика (включены в стоимость проекта)
B22: Целевое назначение | C22: 30% авансовый платёж по EPC-контракту (E - проектирование, P - поставка оборудования, C - строительство)
B24: 3. СТОИМОСТЬ ПРОЕКТА И ИСТОЧНИКИ ФИНАНСИРОВАНИЯ
B25: Статья | C25: USD | D25: Доля
B26: Фиксированные активы | C26: =ProjCost!E5 -> 54094706 | D26: =IFERROR(C26/ProjCost!$E$20,0) -> 0.78232047
B27: Рабочий капитал | C27: =ProjCost!E9 -> 12384487 | D27: =IFERROR(C27/ProjCost!$E$20,0) -> 0.1791051
B28: Проценты льготного периода и расходы подготовительного периода | C28: =ProjCost!E15 -> 2485367.5 | D28: =IFERROR(C28/ProjCost!$E$20,0) -> 0.035943516
B29: Резерв | C29: =ProjCost!E18 -> 181918.14 | D29: =IFERROR(C29/ProjCost!$E$20,0) -> 0.0026309097
B30: ВСЕГО СТОИМОСТЬ ПРОЕКТА | C30: =ProjCost!E20 -> 69146479 | D30: =IFERROR(C30/ProjCost!$E$20,0) -> 1
B31: Собственные средства заемщика | C31: =FinPlan!$E$10 -> 50954665 | D31: =IFERROR(C31/ProjCost!$E$20,0) -> 0.73690903
B32: Кредит банка | C32: =FinPlan!$E$14 -> 18191814 | D32: =IFERROR(C32/ProjCost!$E$20,0) -> 0.26309097
B34: 4. ОСНОВНЫЕ ФИНАНСОВЫЕ ПОКАЗАТЕЛИ ПО ГОДАМ
B35: ПОКАЗАТЕЛИ | C35: Ед. изм. | D35: 1 год (льготный / инвест.) | E35: 2 год | F35: 3 год | G35: 4 год | H35: 5 год | I35: 6 год | J35: 7 год
D36: 2027 | E36: 2028 | F36: 2029 | G36: 2030 | H36: 2031 | I36: 2032 | J36: 2033
B37: Выручка (без НДС) | C37: USD | D37: =ProfLoss!D10 -> 9058233.4 | E37: =ProfLoss!E10 -> 36777950 | F37: =ProfLoss!F10 -> 48825712 | G37: =ProfLoss!G10 -> 58917295 | H37: =ProfLoss!H10 -> 60592704 | I37: =ProfLoss!I10 -> 61925327 | J37: =ProfLoss!J10 -> 63287696
B38: EBITDA | C38: USD | D38: =ProfLoss!D27 -> 731448.94 | E38: =ProfLoss!E27 -> 11251688 | F38: =ProfLoss!F27 -> 16832637 | G38: =ProfLoss!G27 -> 21369559 | H38: =ProfLoss!H27 -> 21930327 | I38: =ProfLoss!I27 -> 22433613 | J38: =ProfLoss!J27 -> 22948165
B39: Чистая прибыль | C39: USD | D39: =ProfLoss!D22 -> 54544.337 | E39: =ProfLoss!E22 -> 6229315.9 | F39: =ProfLoss!F22 -> 11113129 | G39: =ProfLoss!G22 -> 15106555 | H39: =ProfLoss!H22 -> 15720250 | I39: =ProfLoss!I22 -> 16284124 | J39: =ProfLoss!J22 -> 16859496
B40: Операционный поток наличности (A) | C40: USD | D40: =CashFlow!D18 -> -12856918 | E40: =CashFlow!E18 -> 16865940 | F40: =CashFlow!F18 -> 13020261 | G40: =CashFlow!G18 -> 17181750 | H40: =CashFlow!H18 -> 18926304 | I40: =CashFlow!I18 -> 19356302 | J40: =CashFlow!J18 -> 19764802
B41: Обслуживание долга (проценты + основной долг) | C41: USD | D41: =LOANS!$C$107 -> 1291113.5 | E41: =LOANS!$D$107 -> 4227477.2 | F41: =LOANS!$E$107 -> 4008803.4 | G41: =LOANS!$F$107 -> 3793617.9 | H41: =LOANS!$G$107 -> 3578432.3 | I41: =LOANS!$H$107 -> 3364376.7 | J41: =LOANS!$I$107 -> 3148061.1
B42: Чистый поток наличности | C42: USD | D42: =CashFlow!D26 -> 903741.6 | E42: =CashFlow!E26 -> 12098865 | F42: =CashFlow!F26 -> 8471859.2 | G42: =CashFlow!G26 -> 12848534 | H42: =CashFlow!H26 -> 14808274 | I42: =CashFlow!I26 -> 15452327 | J42: =CashFlow!J26 -> 16077143
B43: Кумулятивный поток наличности | C43: USD | D43: =CashFlow!D27 -> 903741.6 | E43: =CashFlow!E27 -> 13002606 | F43: =CashFlow!F27 -> 21474465 | G43: =CashFlow!G27 -> 34323000 | H43: =CashFlow!H27 -> 49131273 | I43: =CashFlow!I27 -> 64583601 | J43: =CashFlow!J27 -> 80660744
B44: DSCR (с учётом поддерживающих капвложений) | C44: x | D44: =CashFlow!D30 -> - | E44: =CashFlow!E30 -> 3.8619586 | F44: =CashFlow!F30 -> 3.1133137 | G44: =CashFlow!G30 -> 4.3868816 | H44: =CashFlow!H30 -> 5.1382015 | I44: =CashFlow!I30 -> 5.5929243 | J44: =CashFlow!J30 -> 6.1069984
B45: Задолженность по кредиту на конец года | C45: USD | D45: =LOANS!$C$108 -> 18191814 | E45: =LOANS!$D$108 -> 15159845 | F45: =LOANS!$E$108 -> 12127876 | G45: =LOANS!$F$108 -> 9095907 | H45: =LOANS!$G$108 -> 6063938 | I45: =LOANS!$H$108 -> 3031969 | J45: =LOANS!$I$108 -> 0
B47: 5. ПОКАЗАТЕЛИ ЭФФЕКТИВНОСТИ И УСТОЙЧИВОСТИ
B48: NPV проекта за 7 лет, USD | C48: =NPV_IRR!D18 -> 2921942.4
B49: IRR проекта за 7 лет | C49: =NPV_IRR!D19 -> 0.12759398
B50: Индекс доходности (PI) | C50: =NPV_IRR!D20 -> 1.0485178
B51: Простой срок окупаемости, лет | C51: =NPV_IRR!D21 -> 5.1655848
B52: Дисконтированный срок окупаемости, лет | C52: =NPV_IRR!D22 -> 6.68104
B53: Минимальный / средний DSCR (2-7 годы) | C53: =TEXT(CashFlow!D31,"0.00") & "x / " & TEXT(CashFlow!D32,"0.00") & "x" -> 3.11x / 4.70x
B54: Точка безубыточности (2030 г.), % от выручки | C54: =BreakPoint!C10 -> 0.35014908
B56: 6. ВЫПОЛНЕНИЕ УСЛОВИЙ ФИНАНСИРОВАНИЯ
B57: Положительный чистый поток наличности в каждом из 1-7 годов | C57: =IF(MIN(CashFlow!D26:J26)>0,"Да","Нет") -> Да
B58: Чистая прибыль в каждом из 1-7 годов | C58: =IF(MIN(ProfLoss!D22:J22)>0,"Да","Нет") -> Да
B59: Погашение кредита в течение 6 лет после льготного периода | C59: =IF(ABS(LOANS!$I$108)<1,"Да","Нет") -> Да
B60: Проценты льготного периода покрыты собственными средствами | C60: =IF(ProjCost!E16>0,"Да","Нет") -> Да
B61: Дисконтированный срок окупаемости - в пределах срока кредита (7 лет) | C61: =IF(AND(ISNUMBER(NPV_IRR!D22),NPV_IRR!D22<=7),"Да","Нет") -> Да
B63: 7. ОСНОВНЫЕ ДОПУЩЕНИЯ
B64: - Производственные, затратные, налоговые и инвестиционные показатели приняты по ТЭО проекта; цены реализации - на консервативном уровне.
B65: - Сумма кредита определена по 30% авансу по EPC-контрактам (распределение 78 млн USD между тремя проектами - лист «ИНФОРМАЦИЯ»).
B66: - Кредит: 7% годовых, 84 месяца, льготный период 12 месяцев, погашение основного долга ежемесячно равными долями; база начисления процентов - 360 дней.
B67: - Все затраты сверх суммы кредита финансируются за счёт собственных средств заемщика.
B68: - Кредит выдаётся единовременно 01.01.2027; проценты 2027 г. капитализируются в стоимость основных средств.
B69: - Резерв на непредвиденные расходы - 1% суммы кредита.
B71: 8. ОСНОВНЫЕ РИСКИ И МЕРЫ ПО ИХ СНИЖЕНИЮ
B72: Ценовой риск | C72: ="Точка безубыточности при проектной мощности - " & TEXT(BreakPoint!C10,"0%") & " выручки; цены реализации в плане приняты консервативно. Меры: долгосрочные контракты на реализацию, мониторинг рыночных цен." -> Точка безубыточности при проектной мощности - 35% выручки; цены реализации в плане приняты консервативно. Меры: долгосрочные контракты на реализацию, мониторинг рыночных цен.
B73: Валютный риск | C73: ="Доля экспорта в выручке: " & TEXT(SalePlan!G10/SalePlan!G18,"0%") & "; цены продукции установлены в USD; кредит - в USD (естественное хеджирование валютной позиции)." -> Доля экспорта в выручке: 100%; цены продукции установлены в USD; кредит - в USD (естественное хеджирование валютной позиции).
B74: Риск освоения мощностей | C74: ="Освоение мощности: 1-й год - " & TEXT(ProdPlan!D13,"0%") & ", 2-й год - " & TEXT(ProdPlan!E13,"0%") & ", 3-й год - " & TEXT(ProdPlan!F13,"0%") & "; льготный период 12 мес. и запас DSCR (мин. " & TEXT(CashFlow!D31,"0.00") & "x) покрывают период выхода на мощность." -> Освоение мощности: 1-й год - 15%, 2-й год - 65%, 3-й год - 85%; льготный период 12 мес. и запас DSCR (мин. 3.11x) покрывают период выхода на мощность.
B75: Строительный риск | C75: ="Капитальные затраты приняты в фиксированных ценах (EPC-контракт: проектирование, поставка, строительство); превышение сметы финансируется за счёт собственных средств заемщика." -> Капитальные затраты приняты в фиксированных ценах (EPC-контракт: проектирование, поставка, строительство); превышение сметы финансируется за счёт собственных средств заемщика.
B76: Сырьевой риск | C76: ="Основное сырьё - Молибденовый огарок: " & TEXT(RawMat!F20/CostTotal!C22,"0%") & " затрат при проектной мощности (с учётом прочих материалов). Меры: долгосрочные договоры поставки." -> Основное сырьё - Молибденовый огарок: 67% затрат при проектной мощности (с учётом прочих материалов). Меры: долгосрочные договоры поставки.

Sheet ИНФОРМАЦИЯ
B2: ДАННЫЕ ПО ПРОЕКТУ
B4: ЗАЕМЩИК | C4: АО «Узбекский комбинат технологических металлов» (АО «Ўзбекистон ТМК», UzTMK)
B5: ИНН | C5: - (заполняется заемщиком)
B6: ДЕЯТЕЛЬНОСТЬ | C6: Добыча и переработка редких и тугоплавких металлов (вольфрам, молибден)
B7: НАИМЕНОВАНИЕ ПРОЕКТА | C7: Строительство нового гидрометаллургического завода по переработке промышленного продукта - молибденового огарка (Цех по производству триоксида молибдена)
B8: МЕСТО РЕАЛИЗАЦИИ | C8: Ташкентская область, Ахангаранский район - новая площадка, 10,4 га
B9: ПРОИЗВОДСТВЕННАЯ МОЩНОСТЬ | C9: Переработка 5 000 т молибденового огарка (концентрата) в год
B10: ОСНОВНАЯ ПРОДУКЦИЯ | C10: Триоксид молибдена MoO3, Медный шлак (25% Cu), Кальциевая селитра
B11: СТАДИЯ ПРОРАБОТКИ | C11: ТЭО (технико-экономическое обоснование)
B12: НАЧАЛО СТРОИТЕЛЬСТВА | C12: 01.10.2026
B13: НАЧАЛО ПРОИЗВОДСТВА | C13: 01.10.2027
B14: СРОК РЕАЛИЗАЦИИ (по данным заемщика) | C14: декабрь 2027 г.
B16: УЧАСТНИКИ ПРОЕКТА
B17: Заемщик (инициатор проекта) | C17: АО «Узбекский комбинат технологических металлов» (АО «Ўзбекистон ТМК», UzTMK)
B18: Доля заемщика в проекте | C18: 100%
B19: Кредитор №1 | C19: Банк-кредитор (наименование уточняется)
B20: Генеральный подрядчик | C20: EPC-подрядчик (по EPC-контракту)
B22: ВАЛЮТА ПРОЕКТА | C22: Доллар США (экв.)
B23: 1 USD = (сум, средний курс 1-го года) | C23: 12218.063
B25: УСЛОВИЯ КРЕДИТА
B26: Сумма кредита, USD | C26: =O42 -> 18191814
B27: Процентная ставка, % годовых | C27: 0.07
B28: Срок кредита, месяцев | C28: 84
B29: Льготный период по основному долгу, месяцев | C29: 12
B30: Инвестиционный период, месяцев | C30: 12
B31: Дата выдачи кредита | C31: 46388
B32: База начисления процентов, дней в году (по форме банка) | C32: 360
B33: Погашение основного долга | C33: ежемесячно равными долями (72 платежа), с 31.01.2028 по 31.12.2033
B34: Уплата процентов | C34: ежемесячно; в льготный период (2027 г.) - за счёт собственных средств заемщика (включены в стоимость проекта)
B35: Целевое назначение | C35: 30% авансовый платёж по EPC-контракту (данные заемщика)
B36: Резерв (непредвиденные расходы) - % от суммы кредита (по форме банка) | C36: 0.01
B38: РАСПРЕДЕЛЕНИЕ КРЕДИТА 78 МЛН USD МЕЖДУ ПРОЕКТАМИ (по 30% авансу EPC-контрактов, файл заемщика от 14.10.2026)
B39: Проект | C39: Мощность | D39: Стоимость проекта, млн USD | E39: EPC: E (Engineering), млрд сум | F39: EPC: P (Procurement), млрд сум | G39: EPC: C (Construction), млрд сум | H39: EPC итого, млрд сум | I39: Курс EPC (тыс. сум/USD) | J39: EPC итого, экв. млн USD | K39: 30% аванс, млрд сум | L39: Курс аванса (тыс. сум/USD) | M39: 30% аванс, млн USD | N39: Доля в кредите | O39: Кредит, USD
B40: Освоение центральной части вольфрамового месторождения Сарикуль (1-я очередь) | C40: Переработка 600 тыс. т руды в год | D40: 158 | E40: 116.0323 | F40: 532.896 | G40: 1041.5674 | H40: =E40+F40+G40 -> 1690.4957 | I40: 12.2 | J40: =H40/I40 -> 138.56522 | K40: =H40*30% -> 507.1487 | L40: 11.838 | M40: =K40/L40 -> 42.840742 | N40: =M40/$M$43 -> 0.54851149 | O40: =N40*$O$44 -> 42783896
B41: Строительство нового гидрометаллургического завода по переработке вольфрамового концентрата (1-я очередь) | C41: Переработка 5 000 т вольфрамового концентрата в год | D41: 80 | E41: 25.272 | F41: 293.4 | G41: 353.99904 | H41: =E41+F41+G41 -> 672.67104 | I41: 12 | J41: =H41/I41 -> 56.05592 | K41: =H41*30% -> 201.80131 | L41: 11.838 | M41: =K41/L41 -> 17.046909 | N41: =M41/$M$43 -> 0.21826012 | O41: =N41*$O$44 -> 17024290
B42: Строительство нового гидрометаллургического завода по переработке промышленного продукта - молибденового огарка | C42: Переработка 5 000 т молибденового огарка (концентрата) в год | D42: 65 | E42: 25.35648 | F42: 251.13528 | G42: 442.311 | H42: =E42+F42+G42 -> 718.80276 | I42: 12 | J42: =H42/I42 -> 59.90023 | K42: =H42*30% -> 215.64083 | L42: 11.838 | M42: =K42/L42 -> 18.215985 | N42: =M42/$M$43 -> 0.23322838 | O42: =N42*$O$44 -> 18191814
B43: ИТОГО | D43: =SUM(D40:D42) -> 303 | E43: =SUM(E40:E42) -> 166.66078 | F43: =SUM(F40:F42) -> 1077.4313 | G43: =SUM(G40:G42) -> 1837.8774 | H43: =SUM(H40:H42) -> 3081.9695 | J43: =SUM(J40:J42) -> 254.52137 | K43: =SUM(K40:K42) -> 924.59084 | M43: =SUM(M40:M42) -> 78.103636 | N43: =SUM(N40:N42) -> 1 | O43: =SUM(O40:O42) -> 78000000
N44: Лимит кредита, USD | O44: 78000000
B46: Распределение кредита - пропорционально 30% авансу по EPC-контрактам, с приведением к лимиту 78,0 млн USD.

Sheet ProjCost
B2: ПЕРВОНАЧАЛЬНАЯ СТОИМОСТЬ ПРОЕКТА (в экв. долл. США) | F2: Приложение 1
B3: Инвестиционный период: с начала строительства по 31.12.2027 (1-й год кредита, льготный период).
B4: Наименование затрат | C4: МЕСТНАЯ ВАЛЮТА | D4: ТВЕРДАЯ ВАЛЮТА | E4: ВСЕГО | F4: СТРУКТУРА (%)
B5: ВСЕГО ФИКСИРОВАННЫЕ АКТИВЫ | C5: =SUM(C6:C8) -> 0 | D5: =SUM(D6:D8) -> 54094706 | E5: =SUM(E6:E8) -> 54094706 | F5: =IFERROR(E5/$E$20,0) -> 0.78232047
B6: Здания, сооружения и передаточные устройства | C6: =0 -> 0 | D6: 35274145 | E6: =C6+D6 -> 35274145 | F6: =IFERROR(E6/$E$20,0) -> 0.51013654
B7: Машины и оборудование | C7: =0 -> 0 | D7: 16465650 | E7: =C7+D7 -> 16465650 | F7: =IFERROR(E7/$E$20,0) -> 0.2381271
B8: Мебель, оргтехника и офисное оборудование | C8: =0 -> 0 | D8: 2354910.1 | E8: =C8+D8 -> 2354910.1 | F8: =IFERROR(E8/$E$20,0) -> 0.034056833
B9: РАБОЧИЙ КАПИТАЛ (на 31.12.2027), ВКЛЮЧАЯ: | C9: =SUM(C10:C14) -> 8872986.9 | D9: =SUM(D10:D14) -> 3511500.4 | E9: =SUM(E10:E14) -> 12384487 | F9: =IFERROR(E9/$E$20,0) -> 0.1791051
B10: Запасы сырья, материалов и готовой продукции | C10: 1919043.6 | D10: 0 | E10: =C10+D10 -> 1919043.6 | F10: =IFERROR(E10/$E$20,0) -> 0.027753309
B11: Дебиторская задолженность покупателей | C11: 0 | D11: 3511500.4 | E11: =C11+D11 -> 3511500.4 | F11: =IFERROR(E11/$E$20,0) -> 0.050783503
B12: НДС к возмещению (в т.ч. по капитальным вложениям) | C12: 7100743.1 | D12: 0 | E12: =C12+D12 -> 7100743.1 | F12: =IFERROR(E12/$E$20,0) -> 0.10269132
B13: Кредиторская задолженность поставщикам (уменьшает потребность) | C13: 0 | D13: 0 | E13: =C13+D13 -> 0 | F13: =IFERROR(E13/$E$20,0) -> 0
B14: Задолженность по оплате труда и налогам с ФОТ (уменьшает потребность) | C14: -146799.77 | D14: 0 | E14: =C14+D14 -> -146799.77 | F14: =IFERROR(E14/$E$20,0) -> -0.002123026
B15: ПРОЧИЕ ФИНАНСОВЫЕ ИЗДЕРЖКИ, ВКЛЮЧАЯ: | C15: =SUM(C16:C17) -> 1194254.1 | D15: =SUM(D16:D17) -> 1291113.5 | E15: =SUM(E16:E17) -> 2485367.5 | F15: =IFERROR(E15/$E$20,0) -> 0.035943516
B16: Проценты по кредиту за льготный период (2027 г.) - за счёт собственных средств | C16: 0 | D16: =LOANS!$C$106 -> 1291113.5 | E16: =C16+D16 -> 1291113.5 | F16: =IFERROR(E16/$E$20,0) -> 0.018672151
B17: Расходы подготовительного периода 2026 г. (административные и пусковые расходы) | C17: 1194254.1 | D17: 0 | E17: =C17+D17 -> 1194254.1 | F17: =IFERROR(E17/$E$20,0) -> 0.017271365
B18: НЕПРЕДВИДЕННЫЕ РАСХОДЫ/РЕЗЕРВ (1% от суммы кредита) | C18: 0 | D18: =ИНФОРМАЦИЯ!$C$26*ИНФОРМАЦИЯ!$C$36 -> 181918.14 | E18: =C18+D18 -> 181918.14 | F18: =IFERROR(E18/$E$20,0) -> 0.0026309097
B20: ВСЕГО ПЕРВОНАЧАЛЬНАЯ СТОИМОСТЬ ПРОЕКТА | C20: =C5+C9+C15+C18 -> 10067241 | D20: =D5+D9+D15+D18 -> 59079238 | E20: =E5+E9+E15+E18 -> 69146479 | F20: =IFERROR(E20/$E$20,0) -> 1

Sheet FinPlan
B2: ФИНАНСОВЫЙ ПЛАН (в экв. долл. США) | G2: Приложение 2
B4: ПОКАЗАТЕЛИ | C4: МЕСТНАЯ ВАЛЮТА | D4: ТВЁРДАЯ ВАЛЮТА | E4: ВСЕГО | F4: СТРУКТУРА (%) | G4: ДОЛЯ В ФИНАНСИРОВАНИИ
B5: СОБСТВЕННЫЙ КАПИТАЛ
B6: АО «Узбекский комбинат технологических металлов» (АО «Ўзбекистон ТМК», UzTMK)
B7: Фиксированные активы | C7: ='Share of costs'!C6 -> 0 | D7: ='Share of costs'!D6 -> 35902892 | E7: =C7+D7 -> 35902892 | F7: =IFERROR(E7/$E$10,0) -> 0.70460461
B8: Рабочий капитал | C8: ='Share of costs'!C10 -> 8872986.9 | D8: ='Share of costs'!D10 -> 3511500.4 | E8: =C8+D8 -> 12384487 | F8: =IFERROR(E8/$E$10,0) -> 0.24304914
B9: Денежные средства (финансовые издержки льготного периода, расходы подготовительного периода, резерв) | C9: ='Share of costs'!C11+'Share of costs'!C14 -> 1194254.1 | D9: ='Share of costs'!D11+'Share of costs'!D14 -> 1473031.6 | E9: =C9+D9 -> 2667285.7 | F9: =IFERROR(E9/$E$10,0) -> 0.052346251
B10: ВСЕГО | C10: =SUM(C7:C9) -> 10067241 | D10: =SUM(D7:D9) -> 40887424 | E10: =SUM(E7:E9) -> 50954665 | F10: =IFERROR(E10/$E$10,0) -> 1 | G10: =IFERROR(E10/$E$15,0) -> 0.73690903
B11: КРЕДИТЫ
B12: Банк (кредит 7% годовых, 84 мес., льготный период 12 мес.) | C12: =C13 -> 0 | D12: =D13 -> 18191814 | E12: =C12+D12 -> 18191814 | F12: =IFERROR(E12/$E$14,0) -> 1
B13: Фиксированные активы (30% аванс по EPC-контракту) | C13: ='Share of costs'!E6 -> 0 | D13: ='Share of costs'!F6 -> 18191814 | E13: =C13+D13 -> 18191814 | F13: =IFERROR(E13/$E$14,0) -> 1
B14: ВСЕГО | C14: =C12 -> 0 | D14: =D12 -> 18191814 | E14: =E12 -> 18191814 | F14: =IFERROR(E14/$E$14,0) -> 1 | G14: =IFERROR(E14/$E$15,0) -> 0.26309097
B15: ВСЕГО ФИНАНСИРОВАНИЯ | C15: =C14+C10 -> 10067241 | D15: =D14+D10 -> 59079238 | E15: =E14+E10 -> 69146479 | G15: =IFERROR(E15/$E$15,0) -> 1

Sheet Share of costs
B2: ПЕРВОНАЧАЛЬНАЯ СТОИМОСТЬ ПРОЕКТА ПО ИСТОЧНИКАМ ФИНАНСИРОВАНИЯ (в экв. долл. США) | H2: Приложение 3
B4: Наименование затрат | C4: Собственные средства заемщика | E4: Кредит банка | G4: Всего
C5: в местной валюте | D5: в твердой валюте | E5: в местной валюте | F5: в твердой валюте | G5: в местной валюте | H5: в твердой валюте
B6: ВСЕГО ФИКСИРОВАННЫЕ АКТИВЫ | C6: =SUM(C7:C9) -> 0 | D6: =SUM(D7:D9) -> 35902892 | E6: =SUM(E7:E9) -> 0 | F6: =SUM(F7:F9) -> 18191814 | G6: =SUM(G7:G9) -> 0 | H6: =SUM(H7:H9) -> 54094706
B7: Здания, сооружения и передаточные устройства | C7: =ProjCost!$C$6 -> 0 | D7: =ProjCost!$D$6-F7 -> 23438187 | E7: 0 | F7: =ИНФОРМАЦИЯ!$C$26*(1-ИНФОРМАЦИЯ!$F$42/ИНФОРМАЦИЯ!$H$42)*ProjCost!$E$6/(ProjCost!$E$6) -> 11835959 | G7: =C7+E7 -> 0 | H7: =D7+F7 -> 35274145
B8: Машины и оборудование | C8: =ProjCost!$C$7 -> 0 | D8: =ProjCost!$D$7-F8 -> 10905067 | E8: 0 | F8: =ИНФОРМАЦИЯ!$C$26*ИНФОРМАЦИЯ!$F$42/ИНФОРМАЦИЯ!$H$42*ProjCost!$E$7/(ProjCost!$E$7+ProjCost!$E$8) -> 5560583.1 | G8: =C8+E8 -> 0 | H8: =D8+F8 -> 16465650
B9: Мебель, оргтехника и офисное оборудование | C9: =ProjCost!$C$8 -> 0 | D9: =ProjCost!$D$8-F9 -> 1559637.9 | E9: 0 | F9: =ИНФОРМАЦИЯ!$C$26*ИНФОРМАЦИЯ!$F$42/ИНФОРМАЦИЯ!$H$42*ProjCost!$E$8/(ProjCost!$E$7+ProjCost!$E$8) -> 795272.16 | G9: =C9+E9 -> 0 | H9: =D9+F9 -> 2354910.1
B10: РАБОЧИЙ КАПИТАЛ | C10: =ProjCost!$C$9 -> 8872986.9 | D10: =ProjCost!$D$9 -> 3511500.4 | E10: 0 | F10: 0 | G10: =C10+E10 -> 8872986.9 | H10: =D10+F10 -> 3511500.4
B11: ПРОЧИЕ ФИНАНСОВЫЕ ИЗДЕРЖКИ | C11: =ProjCost!$C$15 -> 1194254.1 | D11: =ProjCost!$D$15 -> 1291113.5 | E11: 0 | F11: 0 | G11: =C11+E11 -> 1194254.1 | H11: =D11+F11 -> 1291113.5
B12: в т.ч. проценты по кредиту за льготный период | C12: =ProjCost!$C$16 -> 0 | D12: =ProjCost!$D$16 -> 1291113.5 | E12: 0 | F12: 0 | G12: =C12+E12 -> 0 | H12: =D12+F12 -> 1291113.5
B13: в т.ч. расходы подготовительного периода 2026 г. | C13: =ProjCost!$C$17 -> 1194254.1 | D13: =ProjCost!$D$17 -> 0 | E13: 0 | F13: 0 | G13: =C13+E13 -> 1194254.1 | H13: =D13+F13 -> 0
B14: НЕПРЕДВИДЕННЫЕ РАСХОДЫ/РЕЗЕРВ | C14: =ProjCost!$C$18 -> 0 | D14: =ProjCost!$D$18 -> 181918.14 | E14: 0 | F14: 0 | G14: =C14+E14 -> 0 | H14: =D14+F14 -> 181918.14
B16: ВСЕГО ПЕРВОНАЧАЛЬНАЯ СТОИМОСТЬ ПРОЕКТА | C16: =C6+C10+C11+C14 -> 10067241 | D16: =D6+D10+D11+D14 -> 40887424 | E16: =E6+E10+E11+E14 -> 0 | F16: =F6+F10+F11+F14 -> 18191814 | G16: =G6+G10+G11+G14 -> 10067241 | H16: =H6+H10+H11+H14 -> 59079238
B17: Итого по источнику | C17: =C16+D16 -> 50954665 | E17: =E16+F16 -> 18191814 | G17: =G16+H16 -> 69146479
B19: Кредит банка направляется на 30% авансовый платёж по EPC-контракту; распределение по группам активов - пропорционально составу EPC-контракта: P (поставка оборудования) - машины и оборудование, E+C (проектирование и строительство) - здания, сооружения и прочие объекты.

Sheet Depreciate
B2: АМОРТИЗАЦИЯ (в долл. США) | N2: Приложение 4
B3: Линейный метод. Проценты льготного периода капитализированы в стоимость основных средств (МСФО IAS 23).
B5: ОБЪЕКТЫ АМОРТИЗАЦИИ | C5: Группа основных средств | D5: Первоначальная стоимость | E5: Срок, лет | F5: Норма, % | G5: 1 год | H5: 2 год | I5: 3 год | J5: 4 год | K5: 5 год | L5: 6 год | M5: 7 год
G6: 2027 | H6: 2028 | I6: 2029 | J6: 2030 | K6: 2031 | L6: 2032 | M6: 2033
B7: Проектирование: ТЭО/ЗВОС и PFS | C7: Здания, сооружения и передаточные устройства | D7: 477455.36 | E7: 50 | F7: =1/E7 -> 0.02 | G7: 2387.2768 | H7: 9549.1071 | I7: 9549.1071 | J7: 9549.1071 | K7: 9549.1071 | L7: 9549.1071 | M7: 9549.1071
B8: Строительство - цеха | C8: Здания, сооружения и передаточные устройства | D8: 7979203.1 | E8: 50 | F8: =1/E8 -> 0.02 | G8: 39896.015 | H8: 159584.06 | I8: 159584.06 | J8: 159584.06 | K8: 159584.06 | L8: 159584.06 | M8: 159584.06
B9: Строительство - АБК и соцобъекты | C9: Здания, сооружения и передаточные устройства | D9: 8453466.9 | E9: 50 | F9: =1/E9 -> 0.02 | G9: 42267.335 | H9: 169069.34 | I9: 169069.34 | J9: 169069.34 | K9: 169069.34 | L9: 169069.34 | M9: 169069.34
B10: Прочие затраты на строительство | C10: Здания, сооружения и передаточные устройства | D10: 8236950 | E10: 50 | F10: =1/E10 -> 0.02 | G10: 41184.75 | H10: 164739 | I10: 164739 | J10: 164739 | K10: 164739 | L10: 164739 | M10: 164739
B11: Инфраструктура (вода, газ, эл.) | C11: Здания, сооружения и передаточные устройства | D11: 3710280 | E11: 50 | F11: =1/E11 -> 0.02 | G11: 18551.4 | H11: 74205.6 | I11: 74205.6 | J11: 74205.6 | K11: 74205.6 | L11: 74205.6 | M11: 74205.6
B12: Строительство ж.д. | C12: Здания, сооружения и передаточные устройства | D12: 1473000 | E12: 50 | F12: =1/E12 -> 0.02 | G12: 7365 | H12: 29460 | I12: 29460 | J12: 29460 | K12: 29460 | L12: 29460 | M12: 29460
B13: Технол. оборудование с монтажом | C13: Машины и оборудование | D13: 16330751 | E13: 10 | F13: =1/E13 -> 0.1 | G13: 408268.77 | H13: 1633075.1 | I13: 1633075.1 | J13: 1633075.1 | K13: 1633075.1 | L13: 1633075.1 | M13: 1633075.1
B14: Оборудование АБК и соцобъектов | C14: Мебель, оргтехника и офисное оборудование | D14: 2354910.1 | E14: 10 | F14: =1/E14 -> 0.1 | G14: 58872.752 | H14: 235491.01 | I14: 235491.01 | J14: 235491.01 | K14: 235491.01 | L14: 235491.01 | M14: 235491.01
B15: Непредвиденные расходы | C15: Здания, сооружения и передаточные устройства | D15: 4943790 | E15: 50 | F15: =1/E15 -> 0.02 | G15: 24718.95 | H15: 98875.8 | I15: 98875.8 | J15: 98875.8 | K15: 98875.8 | L15: 98875.8 | M15: 98875.8
B16: Поддерживающие капвложения (% от первоначальной стоимости ОС) | C16: Машины и оборудование | D16: 3372487.9 | E16: 10 | F16: =1/E16 -> 0.1 | G16: 2248.3253 | H16: 67449.758 | I16: 121409.56 | J16: 175369.37 | K16: 229329.18 | L16: 283288.98 | M16: 337248.79
B17: Капитализированные проценты по кредиту за льготный период (2027 г.) | C17: Затраты по займам (МСФО IAS 23) | D17: =LOANS!$C$106 -> 1291113.5 | E17: 15 | F17: =1/E17 -> 0.066666667 | G17: 21518.558 | H17: =D17/E17 -> 86074.231 | I17: =D17/E17 -> 86074.231 | J17: =D17/E17 -> 86074.231 | K17: =D17/E17 -> 86074.231 | L17: =D17/E17 -> 86074.231 | M17: =D17/E17 -> 86074.231
B18: ВСЕГО | C18: Х | D18: =SUM(D7:D17) -> 58623407 | G18: =SUM(G7:G17) -> 667279.13 | H18: =SUM(H7:H17) -> 2727573 | I18: =SUM(I7:I17) -> 2781532.8 | J18: =SUM(J7:J17) -> 2835492.6 | K18: =SUM(K7:K17) -> 2889452.4 | L18: =SUM(L7:L17) -> 2943412.2 | M18: =SUM(M7:M17) -> 2997372
B19: в т.ч. в себестоимости продукции | G19: =G18-G20 -> 566139.04 | H19: =H18-H20 -> 2323012.6 | I19: =I18-I20 -> 2376972.4 | J19: =J18-J20 -> 2430932.2 | K19: =K18-K20 -> 2484892 | L19: =L18-L20 -> 2538851.8 | M19: =M18-M20 -> 2592811.7
B20: в т.ч. в административных расходах | G20: 101140.09 | H20: 404560.35 | I20: 404560.35 | J20: 404560.35 | K20: 404560.35 | L20: 404560.35 | M20: 404560.35
B22: Накопленная амортизация | G22: =SUM($G$18:G18) -> 667279.13 | H22: =SUM($G$18:H18) -> 3394852.1 | I22: =SUM($G$18:I18) -> 6176384.9 | J22: =SUM($G$18:J18) -> 9011877.4 | K22: =SUM($G$18:K18) -> 11901330 | L22: =SUM($G$18:L18) -> 14844742 | M22: =SUM($G$18:M18) -> 17842114
B23: Остаточная стоимость основных средств (на конец года) | G23: 54718540 | H23: 52530565 | I23: 50288630 | J23: 47992736 | K23: 45642881 | L23: 43239067 | M23: 40781293

Sheet ProdPlan
B2: ПРОИЗВОДСТВЕННЫЙ ПЛАН | K2: Приложение 5
B4: Н А И М Е Н О В А Н И Е | C4: Ед. изм. | D4: Мощность в год | E4: Рынок сбыта | F4: Цена за единицу, USD (2030 г.) | G4: Выручка при полной мощности: экспорт | H4: Выручка при полной мощности: внутр. рынок
B5: Триоксид молибдена MoO3 | C5: t | D5: 1983.07 | E5: экспорт | F5: 29897 | G5: =D5*F5 -> 59287844 | H5: 0
B6: Медный шлак (25% Cu) | C6: t | D6: 609.57 | E6: внутренний рынок | F6: 0 | G6: 0 | H6: =D6*F6 -> 0
B7: Кальциевая селитра | C7: t | D7: 3000 | E7: внутренний рынок | F7: 0 | G7: 0 | H7: =D7*F7 -> 0
B8: Всего | G8: =SUM(G5:G7) -> 59287844 | H8: =SUM(H5:H7) -> 0
B10: ПОКАЗАТЕЛИ | C10: Ед. изм. | D10: 1 год (льготный / инвест.) | E10: 2 год | F10: 3 год | G10: 4 год | H10: 5 год | I10: 6 год | J10: 7 год
D11: 2027 | E11: 2028 | F11: 2029 | G11: 2030 | H11: 2031 | I11: 2032 | J11: 2033
B12: ОСВОЕНИЕ МОЩНОСТЕЙ
B13: Триоксид молибдена MoO3 | C13: % | D13: 0.15 | E13: 0.65 | F13: 0.85 | G13: 1 | H13: 1 | I13: 1 | J13: 1
B14: Медный шлак (25% Cu) | C14: % | D14: 0.15 | E14: 0.65 | F14: 0.85 | G14: 1 | H14: 1 | I14: 1 | J14: 1
B15: Кальциевая селитра | C15: % | D15: 0.15 | E15: 0.65 | F15: 0.85 | G15: 1 | H15: 1 | I15: 1 | J15: 1
B16: КОЛИЧЕСТВО ПРОИЗВОДСТВА
B17: Триоксид молибдена MoO3 | C17: t | D17: =$D$5*D13 -> 297.4605 | E17: =$D$5*E13 -> 1288.9955 | F17: =$D$5*F13 -> 1685.6095 | G17: =$D$5*G13 -> 1983.07 | H17: =$D$5*H13 -> 1983.07 | I17: =$D$5*I13 -> 1983.07 | J17: =$D$5*J13 -> 1983.07
B18: Медный шлак (25% Cu) | C18: t | D18: =$D$6*D14 -> 91.4355 | E18: =$D$6*E14 -> 396.2205 | F18: =$D$6*F14 -> 518.1345 | G18: =$D$6*G14 -> 609.57 | H18: =$D$6*H14 -> 609.57 | I18: =$D$6*I14 -> 609.57 | J18: =$D$6*J14 -> 609.57
B19: Кальциевая селитра | C19: t | D19: =$D$7*D15 -> 450 | E19: =$D$7*E15 -> 1950 | F19: =$D$7*F15 -> 2550 | G19: =$D$7*G15 -> 3000 | H19: =$D$7*H15 -> 3000 | I19: =$D$7*I15 -> 3000 | J19: =$D$7*J15 -> 3000
B20: КОЛИЧЕСТВО ДЛЯ РЕАЛИЗАЦИИ
B21: Триоксид молибдена MoO3 - экспорт | C21: t | D21: 247.88375 | E21: 1284.8641 | F21: 1669.0839 | G21: 1970.6758 | H21: 1983.07 | I21: 1983.07 | J21: 1983.07
B22: Триоксид молибдена MoO3 - внутренний рынок | C22: t | D22: 0 | E22: 0 | F22: 0 | G22: 0 | H22: 0 | I22: 0 | J22: 0
B23: Медный шлак (25% Cu) - экспорт | C23: t | D23: 0 | E23: 0 | F23: 0 | G23: 0 | H23: 0 | I23: 0 | J23: 0
B24: Медный шлак (25% Cu) - внутренний рынок | C24: t | D24: 76.19625 | E24: 394.95056 | F24: 513.05475 | G24: 605.76019 | H24: 609.57 | I24: 609.57 | J24: 609.57
B25: Кальциевая селитра - экспорт | C25: t | D25: 0 | E25: 0 | F25: 0 | G25: 0 | H25: 0 | I25: 0 | J25: 0
B26: Кальциевая селитра - внутренний рынок | C26: t | D26: 375 | E26: 1943.75 | F26: 2525 | G26: 2981.25 | H26: 3000 | I26: 3000 | J26: 3000
B27: КОЛИЧЕСТВО ЗАПАСА ГОТОВОЙ ПРОДУКЦИИ НА КОНЕЦ ГОДА
B28: Триоксид молибдена MoO3 | C28: t | D28: =0+D17-D21-D22 -> 49.57675 | E28: =D28+E17-E21-E22 -> 53.708146 | F28: =E28+F17-F21-F22 -> 70.233729 | G28: =F28+G17-G21-G22 -> 82.627917 | H28: =G28+H17-H21-H22 -> 82.627917 | I28: =H28+I17-I21-I22 -> 82.627917 | J28: =I28+J17-J21-J22 -> 82.627917
B29: Медный шлак (25% Cu) | C29: t | D29: =0+D18-D23-D24 -> 15.23925 | E29: =D29+E18-E23-E24 -> 16.509188 | F29: =E29+F18-F23-F24 -> 21.588938 | G29: =F29+G18-G23-G24 -> 25.39875 | H29: =G29+H18-H23-H24 -> 25.39875 | I29: =H29+I18-I23-I24 -> 25.39875 | J29: =I29+J18-J23-J24 -> 25.39875
B30: Кальциевая селитра | C30: t | D30: =0+D19-D25-D26 -> 75 | E30: =D30+E19-E25-E26 -> 81.25 | F30: =E30+F19-F25-F26 -> 106.25 | G30: =F30+G19-G25-G26 -> 125 | H30: =G30+H19-H25-H26 -> 125 | I30: =H30+I19-I25-I26 -> 125 | J30: =I30+J19-J25-J26 -> 125
B31: ЦЕНА РЕАЛИЗАЦИИ
B32: Триоксид молибдена MoO3 | C32: USD/t | D32: 36542.264 | E32: 28624 | F32: 29253 | G32: 29897 | H32: 30555 | I32: 31227 | J32: 31914
B33: Медный шлак (25% Cu) | C33: USD/t | D33: 0 | E33: 0 | F33: 0 | G33: 0 | H33: 0 | I33: 0 | J33: 0
B34: Кальциевая селитра | C34: USD/t | D34: 0 | E34: 0 | F34: 0 | G34: 0 | H34: 0 | I34: 0 | J34: 0
B36: Попутная продукция (медный шлак, кальциевая селитра) в базовом сценарии ТЭО выручки не формирует - отражена в натуральном выражении (консервативный подход).

Sheet SalePlan
B2: ПЛАН ПРОДАЖ (в экв. долл. США, без НДС) | K2: Приложение 6
B4: ПОКАЗАТЕЛИ | C4: Ед. изм. | D4: 1 год (льготный / инвест.) | E4: 2 год | F4: 3 год | G4: 4 год | H4: 5 год | I4: 6 год | J4: 7 год
D5: 2027 | E5: 2028 | F5: 2029 | G5: 2030 | H5: 2031 | I5: 2032 | J5: 2033
B6: ЭКСПОРТ
B7: Триоксид молибдена MoO3 | C7: USD | D7: =ProdPlan!D21*ProdPlan!D32 -> 9058233.4 | E7: =ProdPlan!E21*ProdPlan!E32 -> 36777950 | F7: =ProdPlan!F21*ProdPlan!F32 -> 48825712 | G7: =ProdPlan!G21*ProdPlan!G32 -> 58917295 | H7: =ProdPlan!H21*ProdPlan!H32 -> 60592704 | I7: =ProdPlan!I21*ProdPlan!I32 -> 61925327 | J7: =ProdPlan!J21*ProdPlan!J32 -> 63287696
B8: Медный шлак (25% Cu) | C8: USD | D8: =ProdPlan!D23*ProdPlan!D33 -> 0 | E8: =ProdPlan!E23*ProdPlan!E33 -> 0 | F8: =ProdPlan!F23*ProdPlan!F33 -> 0 | G8: =ProdPlan!G23*ProdPlan!G33 -> 0 | H8: =ProdPlan!H23*ProdPlan!H33 -> 0 | I8: =ProdPlan!I23*ProdPlan!I33 -> 0 | J8: =ProdPlan!J23*ProdPlan!J33 -> 0
B9: Кальциевая селитра | C9: USD | D9: =ProdPlan!D25*ProdPlan!D34 -> 0 | E9: =ProdPlan!E25*ProdPlan!E34 -> 0 | F9: =ProdPlan!F25*ProdPlan!F34 -> 0 | G9: =ProdPlan!G25*ProdPlan!G34 -> 0 | H9: =ProdPlan!H25*ProdPlan!H34 -> 0 | I9: =ProdPlan!I25*ProdPlan!I34 -> 0 | J9: =ProdPlan!J25*ProdPlan!J34 -> 0
B10: Всего | C10: USD | D10: =SUM(D7:D9) -> 9058233.4 | E10: =SUM(E7:E9) -> 36777950 | F10: =SUM(F7:F9) -> 48825712 | G10: =SUM(G7:G9) -> 58917295 | H10: =SUM(H7:H9) -> 60592704 | I10: =SUM(I7:I9) -> 61925327 | J10: =SUM(J7:J9) -> 63287696
B12: ВНУТРЕННИЕ ПРОДАЖИ
B13: Триоксид молибдена MoO3 | C13: USD | D13: =ProdPlan!D22*ProdPlan!D32 -> 0 | E13: =ProdPlan!E22*ProdPlan!E32 -> 0 | F13: =ProdPlan!F22*ProdPlan!F32 -> 0 | G13: =ProdPlan!G22*ProdPlan!G32 -> 0 | H13: =ProdPlan!H22*ProdPlan!H32 -> 0 | I13: =ProdPlan!I22*ProdPlan!I32 -> 0 | J13: =ProdPlan!J22*ProdPlan!J32 -> 0
B14: Медный шлак (25% Cu) | C14: USD | D14: =ProdPlan!D24*ProdPlan!D33 -> 0 | E14: =ProdPlan!E24*ProdPlan!E33 -> 0 | F14: =ProdPlan!F24*ProdPlan!F33 -> 0 | G14: =ProdPlan!G24*ProdPlan!G33 -> 0 | H14: =ProdPlan!H24*ProdPlan!H33 -> 0 | I14: =ProdPlan!I24*ProdPlan!I33 -> 0 | J14: =ProdPlan!J24*ProdPlan!J33 -> 0
B15: Кальциевая селитра | C15: USD | D15: =ProdPlan!D26*ProdPlan!D34 -> 0 | E15: =ProdPlan!E26*ProdPlan!E34 -> 0 | F15: =ProdPlan!F26*ProdPlan!F34 -> 0 | G15: =ProdPlan!G26*ProdPlan!G34 -> 0 | H15: =ProdPlan!H26*ProdPlan!H34 -> 0 | I15: =ProdPlan!I26*ProdPlan!I34 -> 0 | J15: =ProdPlan!J26*ProdPlan!J34 -> 0
B16: Всего | C16: USD | D16: =SUM(D13:D15) -> 0 | E16: =SUM(E13:E15) -> 0 | F16: =SUM(F13:F15) -> 0 | G16: =SUM(G13:G15) -> 0 | H16: =SUM(H13:H15) -> 0 | I16: =SUM(I13:I15) -> 0 | J16: =SUM(J13:J15) -> 0
B18: ВСЕГО ПРОДАЖ | C18: USD | D18: =D10+D16 -> 9058233.4 | E18: =E10+E16 -> 36777950 | F18: =F10+F16 -> 48825712 | G18: =G10+G16 -> 58917295 | H18: =H10+H16 -> 60592704 | I18: =I10+I16 -> 61925327 | J18: =J10+J16 -> 63287696
B19: Доля экспорта в выручке | C19: % | D19: =IFERROR(D10/D18,0) -> 1 | E19: =IFERROR(E10/E18,0) -> 1 | F19: =IFERROR(F10/F18,0) -> 1 | G19: =IFERROR(G10/G18,0) -> 1 | H19: =IFERROR(H10/H18,0) -> 1 | I19: =IFERROR(I10/I18,0) -> 1 | J19: =IFERROR(J10/J18,0) -> 1

Sheet RawMat
B2: СТОИМОСТЬ СЫРЬЯ И МАТЕРИАЛОВ ПРИ ПРОЕКТНОЙ МОЩНОСТИ (в экв. долл. США, 2030 г.) | G2: Приложение 7
B3: Базовый год - 2030 г. (освоение мощности 100%); цены - в номинальном выражении ТЭО; без НДС.
B5: НАИМЕНОВАНИЕ | C5: Ед. изм. | D5: Цена за единицу, USD | E5: Годовая потребность | F5: Годовая стоимость, USD | G5: ДОЛЯ (%) | H5: Примечание
B6: СЫРЬЁ, МАТЕРИАЛЫ И ПЕРЕМЕННЫЕ ЗАТРАТЫ С ЦЕНОЙ В ТВЁРДОЙ ВАЛЮТЕ (USD)
B7: Ингибитор | C7: t | D7: =IFERROR(F7/E7,0) -> 11086.394 | E7: 50 | F7: 554319.68 | G7: =IFERROR(F7/$F$20,0) -> 0.020277742 | H7: Вспомогательные материалы
B8: Фильтроткань | C8: m2 | D8: =IFERROR(F8/E8,0) -> 12.383081 | E8: 2000 | F8: 24766.162 | G8: =IFERROR(F8/$F$20,0) -> 0.00090597874 | H8: Вспомогательные материалы
B9: ВСЕГО В ТВЁРДОЙ ВАЛЮТЕ | F9: =SUM(F7:F8) -> 579085.84 | G9: =IFERROR(F9/$F$20,0) -> 0.021183721
B11: СЫРЬЁ, МАТЕРИАЛЫ И ПЕРЕМЕННЫЕ ЗАТРАТЫ С ЦЕНОЙ В НАЦИОНАЛЬНОЙ ВАЛЮТЕ (UZS)
B12: Молибденовый огарок | C12: t | D12: =IFERROR(F12/E12,0) -> 4937.0381 | E12: 5000 | F12: 24685190 | G12: =IFERROR(F12/$F$20,0) -> 0.90301669 | H12: Сырьё
B13: Аммиачная вода | C13: t | D13: =IFERROR(F13/E13,0) -> 341.7778 | E13: 1119.94 | F13: 382770.63 | G13: =IFERROR(F13/$F$20,0) -> 0.014002253 | H13: Вспомогательные материалы
B14: Азотная кислота | C14: t | D14: =IFERROR(F14/E14,0) -> 348.43471 | E14: 3334.62 | F14: 1161897.4 | G14: =IFERROR(F14/$F$20,0) -> 0.042503732 | H14: Вспомогательные материалы
B15: Гидроксид натрия | C15: t | D15: =IFERROR(F15/E15,0) -> 1080.5373 | E15: 162.56 | F15: 175652.15 | G15: =IFERROR(F15/$F$20,0) -> 0.0064255863 | H15: Вспомогательные материалы
B16: Оксид кальция | C16: t | D16: =IFERROR(F16/E16,0) -> 88.308413 | E16: 2000 | F16: 176616.83 | G16: =IFERROR(F16/$F$20,0) -> 0.0064608756 | H16: Вспомогательные материалы
B17: Сульфид аммония | C17: t | D17: =IFERROR(F17/E17,0) -> 872.94594 | E17: 200.64 | F17: 175147.87 | G17: =IFERROR(F17/$F$20,0) -> 0.0064071393 | H17: Вспомогательные материалы
B18: ВСЕГО В НАЦИОНАЛЬНОЙ ВАЛЮТЕ | F18: =SUM(F12:F17) -> 26757275 | G18: =IFERROR(F18/$F$20,0) -> 0.97881628
B20: ИТОГО СЫРЬЁ, МАТЕРИАЛЫ И ПРОЧИЕ ПЕРЕМЕННЫЕ ЗАТРАТЫ | F20: =F9+F18 -> 27336361 | G20: =IFERROR(F20/$F$20,0) -> 1
B22: ПРОЧИЕ ПРОИЗВОДСТВЕННЫЕ РАСХОДЫ (постоянные)
B23: Статьи затрат | F23: Годовая стоимость, USD | H23: Состав затрат
B24: Ремонт и техническое обслуживание | F24: 1018194 | H24: Ремонт и содержание зданий; Ремонт и обслуживание оборудования
B25: Прочие производственные расходы (охрана труда, накладные и др.) | F25: 94026.769 | H25: Охрана труда; Стоки (канализация); Кек возвратный, вода из скважин, прочее
B26: Налог за пользование недрами (НДПИ) | F26: 0
B27: Итого: | F27: =SUM(F24:F26) -> 1112220.8

Sheet Labour
B2: ЭНЕРГОРЕСУРСЫ И ОПЛАТА ТРУДА ПРИ ПРОЕКТНОЙ МОЩНОСТИ (в экв. долл. США, 2030 г.) | G2: Приложение 8
B5: СТАТЬИ ЗАТРАТ | C5: Ед. изм. | D5: Годовая потребность | E5: Цена за единицу, USD | F5: Годовая стоимость, USD
B6: Электроэнергия - переменная часть | C6: kWh | D6: 7619042.4 | E6: =IFERROR(F6/D6,0) -> 0.10284668 | F6: 783593.24
B7: Природный газ - переменная часть | C7: m3 | D7: 2959722.4 | E7: =IFERROR(F7/D7,0) -> 0.17256152 | F7: 510734.2
B8: Электроэнергия - постоянная часть | F8: 324288.72
B9: Природный газ / топливо - постоянная часть | F9: 0
B10: Вода - постоянная часть | F10: 0
B11: ВСЕГО ЭНЕРГОРЕСУРСЫ | F11: =SUM(F6:F10) -> 1618616.2
B13: РАСЧЕТ ЗАРАБОТНОЙ ПЛАТЫ
B14: ПОКАЗАТЕЛИ | C14: Количество, чел. | D14: Среднемесячная з/плата на 1 чел., сум (в ценах 2026 г.) | E14: Среднемесячная з/плата на 1 чел., USD | F14: Годовой фонд з/платы, USD | G14: Отчисления (соц. налог), USD
B15: ПРОИЗВОДСТВЕННЫЙ ПЕРСОНАЛ
B16: Начальник цеха | C16: 1 | D16: 17835000 | E16: =IFERROR(F16/C16/12,0) -> 1646.1634 | F16: 19753.96 | G16: 2370.4752
B17: Операторы промывки и выщелачивания | C17: 40 | D17: 15457000 | E17: =IFERROR(F17/C17/12,0) -> 1426.6749 | F17: 684803.95 | G17: 82176.475
B18: Начальник цеха | C18: 1 | D18: 17835000 | E18: =IFERROR(F18/C18/12,0) -> 1646.1634 | F18: 19753.96 | G18: 2370.4752
B19: Операторы очистки и осаждения | C19: 8 | D19: 15457000 | E19: =IFERROR(F19/C19/12,0) -> 1426.6749 | F19: 136960.79 | G19: 16435.295
B20: Начальник цеха | C20: 1 | D20: 17835000 | E20: =IFERROR(F20/C20/12,0) -> 1646.1634 | F20: 19753.96 | G20: 2370.4752
B21: Операторы фильтр-прессов и прокалки | C21: 12 | D21: 15457000 | E21: =IFERROR(F21/C21/12,0) -> 1426.6749 | F21: 205441.19 | G21: 24652.942
B22: Бригадир очистки сточных вод | C22: 1 | D22: 9512000 | E22: =IFERROR(F22/C22/12,0) -> 877.95379 | F22: 10535.445 | G22: 1264.2535
B23: Рабочие очистки сточных вод | C23: 8 | D23: 11592750 | E23: =IFERROR(F23/C23/12,0) -> 1070.0062 | F23: 102720.59 | G23: 12326.471
B24: Операторы котельной | C24: 8 | D24: 11592750 | E24: =IFERROR(F24/C24/12,0) -> 1070.0062 | F24: 102720.59 | G24: 12326.471
B25: Персонал РУ и обслуживания систем | C25: 12 | D25: 11592750 | E25: =IFERROR(F25/C25/12,0) -> 1070.0062 | F25: 154080.89 | G25: 18489.707
B26: Водители | C26: 10 | D26: 7134000 | E26: =IFERROR(F26/C26/12,0) -> 658.46534 | F26: 79015.841 | G26: 9481.9009
B27: Автовесовая и охрана КПП | C27: 8 | D27: 8917500 | E27: =IFERROR(F27/C27/12,0) -> 823.08168 | F27: 79015.841 | G27: 9481.9009
B28: ВСЕГО | C28: =SUM(C16:C27) -> 110 | F28: =SUM(F16:F27) -> 1614557 | G28: =SUM(G16:G27) -> 193746.84
B29: ИТОГО (фонд оплаты труда + социальный налог) | F29: =F28+G28 -> 1808303.9
B31: АДМИНИСТРАЦИЯ
B32: Генеральный директор | C32: 1 | D32: 35670000 | E32: =IFERROR(F32/C32/12,0) -> 3292.3267 | F32: 39507.92 | G32: 4740.9505
B33: Заместитель ген. директора | C33: 1 | D33: 23780000 | E33: =IFERROR(F33/C33/12,0) -> 2194.8845 | F33: 26338.614 | G33: 3160.6336
B34: Офисные служащие | C34: 3 | D34: 8323000 | E34: =IFERROR(F34/C34/12,0) -> 768.20956 | F34: 27655.544 | G34: 3318.6653
B35: Руководитель фин.-эконом. отдела | C35: 1 | D35: 14268000 | E35: =IFERROR(F35/C35/12,0) -> 1316.9307 | F35: 15803.168 | G35: 1896.3802
B36: Бухгалтер | C36: 1 | D36: 11890000 | E36: =IFERROR(F36/C36/12,0) -> 1097.4422 | F36: 13169.307 | G36: 1580.3168
B37: Кассир | C37: 1 | D37: 8323000 | E37: =IFERROR(F37/C37/12,0) -> 768.20956 | F37: 9218.5148 | G37: 1106.2218
B38: Руководитель отдела снабжения и сбыта | C38: 1 | D38: 14268000 | E38: =IFERROR(F38/C38/12,0) -> 1316.9307 | F38: 15803.168 | G38: 1896.3802
B39: Специалист по закупкам | C39: 1 | D39: 9512000 | E39: =IFERROR(F39/C39/12,0) -> 877.95379 | F39: 10535.445 | G39: 1264.2535
B40: Менеджер по продажам | C40: 1 | D40: 9512000 | E40: =IFERROR(F40/C40/12,0) -> 877.95379 | F40: 10535.445 | G40: 1264.2535
B41: Руководитель отдела кадров | C41: 1 | D41: 14268000 | E41: =IFERROR(F41/C41/12,0) -> 1316.9307 | F41: 15803.168 | G41: 1896.3802
B42: Специалист по кадрам | C42: 1 | D42: 9512000 | E42: =IFERROR(F42/C42/12,0) -> 877.95379 | F42: 10535.445 | G42: 1264.2535
B43: Специалист по обучению | C43: 1 | D43: 9512000 | E43: =IFERROR(F43/C43/12,0) -> 877.95379 | F43: 10535.445 | G43: 1264.2535
... B49: Прочий обслуживающий персонал | C49: 3 | D49: 7134000 | E49: =IFERROR(F49/C49/12,0) -> 658.46534 | F49: 23704.752 | G49: 2844.5703
B50: ВСЕГО | C50: =SUM(C32:C49) -> 28 | F50: =SUM(F32:F49) -> 351620.49 | G50: =SUM(G32:G49) -> 42194.459
B51: ИТОГО (фонд оплаты труда + социальный налог) | F51: =F50+G50 -> 393814.95
B53: ОБЩАЯ СУММА | C53: =C28+C50 -> 138 | F53: =F29+F51 -> 2202118.8
B54: Заработная плата установлена в сумах (в ценах 2026 г.) и пересчитана в USD с учётом индексации и курса.

Sheet Taxes
B2: НАЛОГИ И СБОРЫ (в экв. долл. США) | K2: Приложение 9
B4: ПОКАЗАТЕЛИ | C4: Ставка | D4: 1 год (льготный / инвест.) | E4: 2 год | F4: 3 год | G4: 4 год | H4: 5 год | I4: 6 год | J4: 7 год
D5: 2027 | E5: 2028 | F5: 2029 | G5: 2030 | H5: 2031 | I5: 2032 | J5: 2033
B6: Налоги и сборы, включаемые в расходы | D6: =SUM(D7:D11) -> 354260.87 | E6: =SUM(E7:E11) -> 741803.03 | F6: =SUM(F7:F11) -> 736166.57 | G6: =SUM(G7:G11) -> 730661.19 | H6: =SUM(H7:H11) -> 725269.65 | I6: =SUM(I7:I11) -> 719992.32 | J6: =SUM(J7:J11) -> 714831.68 | K6: =SUM(K7:K11) -> 0
B7: Налог на имущество | C7: 1.50% | D7: =CostSold!D34 -> 131837.12 | E7: =CostSold!E34 -> 515884.38 | F7: =CostSold!F34 -> 505302.13 | G7: =CostSold!G34 -> 494719.89 | H7: =CostSold!H34 -> 484137.65 | I7: =CostSold!I34 -> 473555.4 | J7: =CostSold!J34 -> 462973.16
B8: Земельный налог | D8: =CostSold!D35 -> 0 | E8: =CostSold!E35 -> 0 | F8: =CostSold!F35 -> 0 | G8: =CostSold!G35 -> 0 | H8: =CostSold!H35 -> 0 | I8: =CostSold!I35 -> 0 | J8: =CostSold!J35 -> 0
B9: Специальный рентный налог | D9: =CostSold!D36 -> 0 | E9: =CostSold!E36 -> 0 | F9: =CostSold!F36 -> 0 | G9: =CostSold!G36 -> 0 | H9: =CostSold!H36 -> 0 | I9: =CostSold!I36 -> 0 | J9: =CostSold!J36 -> 0
B10: Налог за пользование недрами (НДПИ) - в себестоимости | D10: =CostSold!D19 -> 0 | E10: =CostSold!E19 -> 0 | F10: =CostSold!F19 -> 0 | G10: =CostSold!G19 -> 0 | H10: =CostSold!H19 -> 0 | I10: =CostSold!I19 -> 0 | J10: =CostSold!J19 -> 0
B11: Социальный налог (производственный и административный персонал) | C11: 12% | D11: 222423.75 | E11: 225918.65 | F11: 230864.44 | G11: 235941.3 | H11: 241132.01 | I11: 246436.91 | J11: 251858.53
B13: Прочие налоги | D13: =D14+D15 -> 9625.4712 | E13: =E14+E15 -> 1099291 | F13: =F14+F15 -> 1961140.5 | G13: =G14+G15 -> 2665862.7 | H13: =H14+H15 -> 2774161.7 | I13: =I14+I15 -> 2873669 | J13: =J14+J15 -> 2975205.2 | K13: =K14+K15 -> 0
B14: Налог на прибыль (Приложение 13) | D14: =ProfLoss!D21 -> 9625.4712 | E14: =ProfLoss!E21 -> 1099291 | F14: =ProfLoss!F21 -> 1961140.5 | G14: =ProfLoss!G21 -> 2665862.7 | H14: =ProfLoss!H21 -> 2774161.7 | I14: =ProfLoss!I21 -> 2873669 | J14: =ProfLoss!J21 -> 2975205.2
B15: НДС к уплате в бюджет (при превышении входящего НДС - к возмещению, см. ниже) | C15: 12% | D15: =MAX(0,D22) -> 0 | E15: =MAX(0,E22) -> 0 | F15: =MAX(0,F22) -> 0 | G15: =MAX(0,G22) -> 0 | H15: =MAX(0,H22) -> 0 | I15: =MAX(0,I22) -> 0 | J15: =MAX(0,J22) -> 0
B16: ВСЕГО НАЛОГОВ И ОТЧИСЛЕНИЙ | D16: =D6+D13 -> 363886.34 | E16: =E6+E13 -> 1841094.1 | F16: =F6+F13 -> 2697307.1 | G16: =G6+G13 -> 3396523.9 | H16: =H6+H13 -> 3499431.4 | I16: =I6+I13 -> 3593661.3 | J16: =J6+J13 -> 3690036.8
B18: Расчет НДС
B19: НДС исходящий (реализация на внутреннем рынке; экспорт - 0%) | D19: 0 | E19: 0 | F19: 0 | G19: 0 | H19: 0 | I19: 0 | J19: 0
B20: НДС входящий - по операционным затратам | D20: 867145.92 | E20: 2710683.4 | F20: 3505443.9 | G20: 4146349.5 | H20: 4237863.2 | I20: 4331096.1 | J20: 4426380.3
B21: НДС входящий - по капитальным вложениям (1-й год вкл. 2026 г.) | D21: 6491364.7 | E21: 64751.767 | F21: 64751.767 | G21: 64751.767 | H21: 64751.767 | I21: 64751.767 | J21: 64751.767
B22: НДС к уплате (+) / к возмещению из бюджета (-) | D22: =D19-D20-D21 -> -7358510.6 | E22: =E19-E20-E21 -> -2775435.1 | F22: =F19-F20-F21 -> -3570195.6 | G22: =G19-G20-G21 -> -4211101.3 | H22: =H19-H20-H21 -> -4302614.9 | I22: =I19-I20-I21 -> -4395847.9 | J22: =J19-J20-J21 -> -4491132
B24: Расчет налога на прибыль
B25: Прибыль (убыток) до налогообложения (Приложение 13) | D25: =ProfLoss!D20 -> 64169.808 | E25: =ProfLoss!E20 -> 7328607 | F25: =ProfLoss!F20 -> 13074270 | G25: =ProfLoss!G20 -> 17772418 | H25: =ProfLoss!H20 -> 18494412 | I25: =ProfLoss!I20 -> 19157793 | J25: =ProfLoss!J20 -> 19834701
B26: Налоговые корректировки | D26: -1.2805685e-09 | E26: 0 | F26: 0 | G26: 0 | H26: 0 | I26: 7.4505806e-09 | J26: 0
B27: Налогооблагаемая прибыль | D27: =D25+D26 -> 64169.808 | E27: =E25+E26 -> 7328607 | F27: =F25+F26 -> 13074270 | G27: =G25+G26 -> 17772418 | H27: =H25+H26 -> 18494412 | I27: =I25+I26 -> 19157793 | J27: =J25+J26 -> 19834701
B28: Ставка налога на прибыль | C28: % | D28: 0.15 | E28: 0.15 | F28: 0.15 | G28: 0.15 | H28: 0.15 | I28: 0.15 | J28: 0.15
B29: Налог на прибыль | D29: =D27*D28 -> 9625.4712 | E29: =E27*E28 -> 1099291 | F29: =F27*F28 -> 1961140.5 | G29: =G27*G28 -> 2665862.7 | H29: =H27*H28 -> 2774161.7 | I29: =I27*I28 -> 2873669 | J29: =J27*J28 -> 2975205.2

Sheet CostTotal
B2: СТОИМОСТЬ ПРОДУКЦИИ ПРИ ПРОЕКТНОЙ МОЩНОСТИ (в экв. долл. США, 2030 г.) | H2: Приложение 10
B3: Разделение на постоянные и переменные затраты.
B5: Статьи издержек | C5: Всего стоимость | D5: Доля постоянных затрат (%) | E5: Доля переменных затрат (%) | F5: Фиксированная стоимость | G5: Переменная стоимость
B6: Сырьё, материалы и прочие переменные затраты по статьям ТЭО | C6: =C7+C8 -> 27336361 | D6: =IFERROR(F6/C6,0) -> 0 | E6: =IFERROR(G6/C6,0) -> 1 | F6: =F7+F8 -> 0 | G6: =G7+G8 -> 27336361
B7: с ценой в твёрдой валюте (USD) | C7: =F7+G7 -> 579085.84 | D7: =IFERROR(F7/C7,0) -> 0 | E7: =IFERROR(G7/C7,0) -> 1 | F7: 0 | G7: 579085.84
B8: с ценой в национальной валюте | C8: =F8+G8 -> 26757275 | D8: =IFERROR(F8/C8,0) -> 0 | E8: =IFERROR(G8/C8,0) -> 1 | F8: 0 | G8: 26757275
B9: Энергоресурсы (электроэнергия, газ, вода) | C9: =F9+G9 -> 1618616.2 | D9: =IFERROR(F9/C9,0) -> 0.20034937 | E9: =IFERROR(G9/C9,0) -> 0.79965063 | F9: 324288.72 | G9: 1294327.4
B10: Зарплата производственного персонала (с соц. налогом) | C10: =F10+G10 -> 1808303.9 | D10: =IFERROR(F10/C10,0) -> 1 | E10: =IFERROR(G10/C10,0) -> 0 | F10: 1808303.9 | G10: 0
B11: Зарплата административного персонала (с соц. налогом) | C11: =F11+G11 -> 393814.95 | D11: =IFERROR(F11/C11,0) -> 1 | E11: =IFERROR(G11/C11,0) -> 0 | F11: 393814.95 | G11: 0
B12: Ремонт и техническое обслуживание (постоянная часть) | C12: =F12+G12 -> 1018194 | D12: =IFERROR(F12/C12,0) -> 1 | E12: =IFERROR(G12/C12,0) -> 0 | F12: 1018194 | G12: 0
B13: Прочие производственные расходы (постоянная часть) | C13: =F13+G13 -> 94026.769 | D13: =IFERROR(F13/C13,0) -> 1 | E13: =IFERROR(G13/C13,0) -> 0 | F13: 94026.769 | G13: 0
B14: Налог за пользование недрами (НДПИ) | C14: =F14+G14 -> 0 | D14: =IFERROR(F14/C14,0) -> 0 | E14: =IFERROR(G14/C14,0) -> 0 | F14: 0 | G14: 0
B15: Административные расходы (без персонала и амортизации) | C15: =F15+G15 -> 4104621.3 | D15: =IFERROR(F15/C15,0) -> 0.68936962 | E15: =IFERROR(G15/C15,0) -> 0.31063038 | F15: 2829601.3 | G15: 1275020.1
B16: Коммерческие расходы | C16: =F16+G16 -> 294586.47 | D16: =IFERROR(F16/C16,0) -> 0 | E16: =IFERROR(G16/C16,0) -> 1 | F16: 0 | G16: 294586.47
B17: Налог на имущество и земельный налог | C17: =F17+G17 -> 494719.89 | D17: =IFERROR(F17/C17,0) -> 1 | E17: =IFERROR(G17/C17,0) -> 0 | F17: 494719.89 | G17: 0
B18: Специальный рентный налог | C18: =F18+G18 -> 0 | D18: =IFERROR(F18/C18,0) -> 0 | E18: =IFERROR(G18/C18,0) -> 0 | F18: 0 | G18: 0
B19: Резерв на непредвиденные операционные расходы | C19: =F19+G19 -> 733370.49 | D19: =IFERROR(F19/C19,0) -> 0 | E19: =IFERROR(G19/C19,0) -> 1 | F19: 0 | G19: 733370.49
B20: Прочие операционные расходы / (доходы) | C20: =F20+G20 -> 0 | D20: =IFERROR(F20/C20,0) -> 0 | E20: =IFERROR(G20/C20,0) -> 0 | F20: 0 | G20: 0
B21: Амортизация (Приложение 4) | C21: =F21+G21 -> 2835492.6 | D21: =IFERROR(F21/C21,0) -> 1 | E21: =IFERROR(G21/C21,0) -> 0 | F21: =Depreciate!J18 -> 2835492.6 | G21: 0
B22: ИТОГО | C22: =SUM(C6:C21)-C6 -> 40732108 | D22: =IFERROR(F22/C22,0) -> 0.24055819 | E22: =IFERROR(G22/C22,0) -> 0.75944181 | F22: =SUM(F6:F21)-F6 -> 9798442.1 | G22: =SUM(G6:G21)-G6 -> 30933666
B23: в т.ч. в местной валюте | C23: =C22-C24 -> 39146524
B24: в т.ч. в твёрдой валюте (производственные затраты в USD) | C24: 1585583.8
B26: Выручка (2030 г.) | C26: =SalePlan!G18 -> 58917295
B27: Затраты на 1 USD выручки | C27: =IFERROR(C22/C26,0) -> 0.69134382
B28: Полная себестоимость единицы основной продукции, USD/t | C28: =IFERROR(C22/ProdPlan!G17,0) -> 20539.924

Sheet CostSold
B2: ГОДОВАЯ СТОИМОСТЬ ПРОДАННОЙ ПРОДУКЦИИ (в экв. долл. США) | K2: Приложение 11
B4: ПОКАЗАТЕЛИ | C4: Ед. изм. | D4: 1 год (льготный / инвест.) | E4: 2 год | F4: 3 год | G4: 4 год | H4: 5 год | I4: 6 год | J4: 7 год
D5: 2027 | E5: 2028 | F5: 2029 | G5: 2030 | H5: 2031 | I5: 2032 | J5: 2033
B6: Освоение мощностей (основная продукция) | C6: % | D6: =ProdPlan!D13 -> 0.15 | E6: =ProdPlan!E13 -> 0.65 | F6: =ProdPlan!F13 -> 0.85 | G6: =ProdPlan!G13 -> 1 | H6: =ProdPlan!H13 -> 1 | I6: =ProdPlan!I13 -> 1 | J6: =ProdPlan!J13 -> 1
B8: ПРОИЗВОДСТВЕННАЯ СЕБЕСТОИМОСТЬ ПО ЭЛЕМЕНТАМ
B9: Сырьё | C9: USD | D9: 3497193.1 | E9: 15362010 | F9: 20530736 | G9: 24685190 | H9: 25228265 | I9: 25783286 | J9: 26350519
B10: Вспомогательные материалы | C10: USD | D10: 375595.88 | E10: 1649868.2 | F10: 2204985.4 | G10: 2651170.7 | H10: 2709496.4 | I10: 2769105.4 | J10: 2830025.7
B11: Электроэнергия | C11: USD | D11: 187583.89 | E11: 798120.72 | F11: 969024.43 | G11: 1107882 | H11: 1132255.4 | I11: 1157165 | J11: 1182622.6
B12: Природный газ / топливо | C12: USD | D12: 72356.588 | E12: 317838.5 | F12: 424778.94 | G12: 510734.2 | H12: 521970.36 | I12: 533453.7 | J12: 545189.69
B13: Вода | C13: USD | D13: 0 | E13: 0 | F13: 0 | G13: 0 | H13: 0 | I13: 0 | J13: 0
B14: Заработная плата | C14: USD | D14: 1522055.8 | E14: 1545971.6 | F14: 1579815.8 | G14: 1614557 | H14: 1650077.3 | I14: 1686379 | J14: 1723479.3
B15: Социальный налог | C15: USD | D15: 182646.7 | E15: 185516.59 | F15: 189577.9 | G15: 193746.84 | H15: 198009.27 | I15: 202365.48 | J15: 206817.52
B16: Амортизация (Приложение 4) | C16: USD | D16: =Depreciate!$G$19 -> 566139.04 | E16: =Depreciate!$H$19 -> 2323012.6 | F16: =Depreciate!$I$19 -> 2376972.4 | G16: =Depreciate!$J$19 -> 2430932.2 | H16: =Depreciate!$K$19 -> 2484892 | I16: =Depreciate!$L$19 -> 2538851.8 | J16: =Depreciate!$M$19 -> 2592811.7
B17: Ремонт и техобслуживание | C17: USD | D17: 144249.29 | E17: 633639.3 | F17: 846834.56 | G17: 1018194 | H17: 1040594.3 | I17: 1063487.4 | J17: 1086884.1
B18: Прочие производственные расходы (без НДПИ) | C18: USD | D18: 13320.933 | E18: 58514.443 | F18: 78202.303 | G18: 94026.769 | H18: 96095.358 | I18: 98209.456 | J18: 100370.06
B19: Налог за пользование недрами (НДПИ) | C19: USD | D19: 0 | E19: 0 | F19: 0 | G19: 0 | H19: 0 | I19: 0 | J19: 0
B20: Себестоимость произведенной продукции | C20: USD | D20: =SUM(D9:D19) -> 6561141.3 | E20: =SUM(E9:E19) -> 22874492 | F20: =SUM(F9:F19) -> 29200927 | G20: =SUM(G9:G19) -> 34306434 | H20: =SUM(H9:H19) -> 35061655 | I20: =SUM(I9:I19) -> 35832304 | J20: =SUM(J9:J19) -> 36618719
B21: Изменение остатков готовой продукции (- прирост запаса) | C21: USD | D21: -2578055.9 | E21: -126098.79 | F21: -433201.8 | G21: -348879.66 | H21: -48431.841 | I21: -49497.342 | J21: -50586.283
B22: Себестоимость реализованной продукции | C22: USD | D22: =D20+D21 -> 3983085.3 | E22: =E20+E21 -> 22748393 | F22: =F20+F21 -> 28767726 | G22: =G20+G21 -> 33957554 | H22: =H20+H21 -> 35013223 | I22: =I20+I21 -> 35782806 | J22: =J20+J21 -> 36568133
B23: в т.ч. затраты в твёрдой валюте (USD) | C23: USD | D23: 154815.25 | E23: 1123057.2 | F23: 1434045.7 | G23: 1689151.4 | H23: 1717864.5 | I23: 1731824.2 | J23: 1746035.3
B24: в т.ч. затраты в национальной валюте | C24: USD | D24: =D22-D23 -> 3828270.1 | E24: =E22-E23 -> 21625336 | F24: =F22-F23 -> 27333680 | G24: =G22-G23 -> 32268403 | H24: =H22-H23 -> 33295359 | I24: =I22-I23 -> 34050982 | J24: =J22-J23 -> 34822098
B26: РАСХОДЫ ПЕРИОДА
B27: Зарплата административного персонала (с соц. налогом) | C27: USD | D27: 371252.51 | E27: 377085.92 | F27: 385341.05 | G27: 393814.95 | H27: 402478.88 | I27: 411333.42 | J27: 420382.75
B28: Амортизация административных активов | C28: USD | D28: =Depreciate!$G$20 -> 101140.09 | E28: =Depreciate!$H$20 -> 404560.35 | F28: =Depreciate!$I$20 -> 404560.35 | G28: =Depreciate!$J$20 -> 404560.35 | H28: =Depreciate!$K$20 -> 404560.35 | I28: =Depreciate!$L$20 -> 404560.35 | J28: =Depreciate!$M$20 -> 404560.35
B29: Прочие административные расходы (аренда, налог за воду, прочие) | C29: USD | D29: 2890625.1 | E29: 3531149.3 | F29: 3841648.3 | G29: 4104621.3 | H29: 4194923 | I29: 4287211.3 | J29: 4381530
B30: Коммерческие расходы (расходы по реализации) | C30: USD | D30: 45291.167 | E30: 183889.75 | F30: 244128.56 | G30: 294586.47 | H30: 302963.52 | I30: 309626.63 | J30: 316438.48
B31: Итого расходы периода | C31: USD | D31: =SUM(D27:D30) -> 3408308.9 | E31: =SUM(E27:E30) -> 4496685.3 | F31: =SUM(F27:F30) -> 4875678.2 | G31: =SUM(G27:G30) -> 5197583.1 | H31: =SUM(H27:H30) -> 5304925.8 | I31: =SUM(I27:I30) -> 5412731.7 | J31: =SUM(J27:J30) -> 5522911.5
B33: НАЛОГИ И ПРОЧИЕ ОПЕРАЦИОННЫЕ РАСХОДЫ
B34: Налог на имущество | C34: USD | D34: 131837.12 | E34: 515884.38 | F34: 505302.13 | G34: 494719.89 | H34: 484137.65 | I34: 473555.4 | J34: 462973.16
B35: Земельный налог | C35: USD | D35: 0 | E35: 0 | F35: 0 | G35: 0 | H35: 0 | I35: 0 | J35: 0
B36: Специальный рентный налог | C36: USD | D36: 0 | E36: 0 | F36: 0 | G36: 0 | H36: 0 | I36: 0 | J36: 0
B37: Резерв на непредвиденные операционные расходы | C37: USD | D37: 186043.42 | E37: 492872.09 | F37: 625901.46 | G37: 733370.49 | H37: 749542.57 | I37: 766032.46 | J37: 782885.18
B38: Прочие операционные расходы / (доходы) | C38: USD | D38: 1284788.8 | E38: 0 | F38: 0 | G38: 0 | H38: 0 | I38: 0 | J38: 0
B39: Итого налоги и прочие операционные расходы | C39: USD | D39: =SUM(D34:D38) -> 1602669.4 | E39: =SUM(E34:E38) -> 1008756.5 | F39: =SUM(F34:F38) -> 1131203.6 | G39: =SUM(G34:G38) -> 1228090.4 | H39: =SUM(H34:H38) -> 1233680.2 | I39: =SUM(I34:I38) -> 1239587.9 | J39: =SUM(J34:J38) -> 1245858.3
B41: ФИНАНСОВЫЕ ИЗДЕРЖКИ
B42: Проценты за кредит (1-й год - капитализированы, оплачены за счёт собственных средств) | C42: USD | D42: =0 -> 0 | E42: =LOANS!$D$106 -> 1195508.2 | F42: =LOANS!$E$106 -> 976834.44 | G42: =LOANS!$F$106 -> 761648.86 | H42: =LOANS!$G$106 -> 546463.28 | I42: =LOANS!$H$106 -> 332407.67 | J42: =LOANS!$I$106 -> 116092.13
B44: ПОЛНАЯ СТОИМОСТЬ ПРОДАННОЙ ПРОДУКЦИИ | C44: USD | D44: =D22+D31+D39+D42 -> 8994063.6 | E44: =E22+E31+E39+E42 -> 29449343 | F44: =F22+F31+F39+F42 -> 35751442 | G44: =G22+G31+G39+G42 -> 41144877 | H44: =H22+H31+H39+H42 -> 42098292 | I44: =I22+I31+I39+I42 -> 42767533 | J44: =J22+J31+J39+J42 -> 43452995
B45: Полная себестоимость единицы основной продукции | C45: USD/t | D45: =IFERROR(D44/(ProdPlan!D21+ProdPlan!D22),0) -> 36283.393 | E45: =IFERROR(E44/(ProdPlan!E21+ProdPlan!E22),0) -> 22920.201 | F45: =IFERROR(F44/(ProdPlan!F21+ProdPlan!F22),0) -> 21419.799 | G45: =IFERROR(G44/(ProdPlan!G21+ProdPlan!G22),0) -> 20878.562 | H45: =IFERROR(H44/(ProdPlan!H21+ProdPlan!H22),0) -> 21228.848 | I45: =IFERROR(I44/(ProdPlan!I21+ProdPlan!I22),0) -> 21566.326 | J45: =IFERROR(J44/(ProdPlan!J21+ProdPlan!J22),0) -> 21911.982

Sheet LOANS
B2: СХЕМА ВЫПЛАТЫ КРЕДИТА (в долл. США) | H2: Приложение 12
B5: Срок кредита | C5: =ИНФОРМАЦИЯ!$C$28 -> 84 | D5: месяцев
B6: Льготный период | C6: =ИНФОРМАЦИЯ!$C$29 -> 12 | D6: месяцев
B7: Инвестиционный период | C7: =ИНФОРМАЦИЯ!$C$30 -> 12 | D7: месяцев
B8: Процентная ставка | C8: =ИНФОРМАЦИЯ!$C$27 -> 0.07 | D8: годовых
B9: Сумма кредита | C9: =ИНФОРМАЦИЯ!$C$26 -> 18191814 | D9: USD
B10: Дата выдачи | C10: =ИНФОРМАЦИЯ!$C$31 -> 46388
B11: База начисления процентов | C11: =ИНФОРМАЦИЯ!$C$32 -> 360 | D11: дней
B12: Количество платежей по основному долгу | C12: =C5-C6 -> 72 | D12: платежей
B13: Ежемесячный платёж по основному долгу | C13: =C9/C12 -> 252664.08 | D13: USD
A15: № | B15: Дата платежа | C15: Остаток на начало | D15: Погашение основного долга | E15: Проценты | F15: Всего выплат | G15: Остаток на конец | H15: Год | I15: № года
A16: 1 | B16: =EOMONTH($C$10,0) -> 46418 | C16: =$C$9 -> 18191814 | D16: =IF(A16>$C$6,MIN(C16,$C$13),0) -> 0 | E16: =C16*$C$8*DAY(B16)/$C$11 -> 109656.21 | F16: =D16+E16 -> 109656.21 | G16: =C16-D16 -> 18191814 | H16: =YEAR(B16) -> 2027 | I16: =H16-2026 -> 1
A17: 2 | B17: =EOMONTH($C$10,1) -> 46446 | C17: =G16 -> 18191814 | D17: =IF(A17>$C$6,MIN(C17,$C$13),0) -> 0 | E17: =C17*$C$8*DAY(B17)/$C$11 -> 99044.32 | F17: =D17+E17 -> 99044.32 | G17: =C17-D17 -> 18191814 | H17: =YEAR(B17) -> 2027 | I17: =H17-2026 -> 1
A18: 3 | B18: =EOMONTH($C$10,2) -> 46477 | C18: =G17 -> 18191814 | D18: =IF(A18>$C$6,MIN(C18,$C$13),0) -> 0 | E18: =C18*$C$8*DAY(B18)/$C$11 -> 109656.21 | F18: =D18+E18 -> 109656.21 | G18: =C18-D18 -> 18191814 | H18: =YEAR(B18) -> 2027 | I18: =H18-2026 -> 1
A19: 4 | B19: =EOMONTH($C$10,3) -> 46507 | C19: =G18 -> 18191814 | D19: =IF(A19>$C$6,MIN(C19,$C$13),0) -> 0 | E19: =C19*$C$8*DAY(B19)/$C$11 -> 106118.91 | F19: =D19+E19 -> 106118.91 | G19: =C19-D19 -> 18191814 | H19: =YEAR(B19) -> 2027 | I19: =H19-2026 -> 1
A20: 5 | B20: =EOMONTH($C$10,4) -> 46538 | C20: =G19 -> 18191814 | D20: =IF(A20>$C$6,MIN(C20,$C$13),0) -> 0 | E20: =C20*$C$8*DAY(B20)/$C$11 -> 109656.21 | F20: =D20+E20 -> 109656.21 | G20: =C20-D20 -> 18191814 | H20: =YEAR(B20) -> 2027 | I20: =H20-2026 -> 1
A21: 6 | B21: =EOMONTH($C$10,5) -> 46568 | C21: =G20 -> 18191814 | D21: =IF(A21>$C$6,MIN(C21,$C$13),0) -> 0 | E21: =C21*$C$8*DAY(B21)/$C$11 -> 106118.91 | F21: =D21+E21 -> 106118.91 | G21: =C21-D21 -> 18191814 | H21: =YEAR(B21) -> 2027 | I21: =H21-2026 -> 1
A22: 7 | B22: =EOMONTH($C$10,6) -> 46599 | C22: =G21 -> 18191814 | D22: =IF(A22>$C$6,MIN(C22,$C$13),0) -> 0 | E22: =C22*$C$8*DAY(B22)/$C$11 -> 109656.21 | F22: =D22+E22 -> 109656.21 | G22: =C22-D22 -> 18191814 | H22: =YEAR(B22) -> 2027 | I22: =H22-2026 -> 1
A23: 8 | B23: =EOMONTH($C$10,7) -> 46630 | C23: =G22 -> 18191814 | D23: =IF(A23>$C$6,MIN(C23,$C$13),0) -> 0 | E23: =C23*$C$8*DAY(B23)/$C$11 -> 109656.21 | F23: =D23+E23 -> 109656.21 | G23: =C23-D23 -> 18191814 | H23: =YEAR(B23) -> 2027 | I23: =H23-2026 -> 1
A24: 9 | B24: =EOMONTH($C$10,8) -> 46660 | C24: =G23 -> 18191814 | D24: =IF(A24>$C$6,MIN(C24,$C$13),0) -> 0 | E24: =C24*$C$8*DAY(B24)/$C$11 -> 106118.91 | F24: =D24+E24 -> 106118.91 | G24: =C24-D24 -> 18191814 | H24: =YEAR(B24) -> 2027 | I24: =H24-2026 -> 1
A25: 10 | B25: =EOMONTH($C$10,9) -> 46691 | C25: =G24 -> 18191814 | D25: =IF(A25>$C$6,MIN(C25,$C$13),0) -> 0 | E25: =C25*$C$8*DAY(B25)/$C$11 -> 109656.21 | F25: =D25+E25 -> 109656.21 | G25: =C25-D25 -> 18191814 | H25: =YEAR(B25) -> 2027 | I25: =H25-2026 -> 1
A26: 11 | B26: =EOMONTH($C$10,10) -> 46721 | C26: =G25 -> 18191814 | D26: =IF(A26>$C$6,MIN(C26,$C$13),0) -> 0 | E26: =C26*$C$8*DAY(B26)/$C$11 -> 106118.91 | F26: =D26+E26 -> 106118.91 | G26: =C26-D26 -> 18191814 | H26: =YEAR(B26) -> 2027 | I26: =H26-2026 -> 1
A27: 12 | B27: =EOMONTH($C$10,11) -> 46752 | C27: =G26 -> 18191814 | D27: =IF(A27>$C$6,MIN(C27,$C$13),0) -> 0 | E27: =C27*$C$8*DAY(B27)/$C$11 -> 109656.21 | F27: =D27+E27 -> 109656.21 | G27: =C27-D27 -> 18191814 | H27: =YEAR(B27) -> 2027 | I27: =H27-2026 -> 1
A28: 13 | B28: =EOMONTH($C$10,12) -> 46783 | C28: =G27 -> 18191814 | D28: =IF(A28>$C$6,MIN(C28,$C$13),0) -> 252664.08 | E28: =C28*$C$8*DAY(B28)/$C$11 -> 109656.21 | F28: =D28+E28 -> 362320.29 | G28: =C28-D28 -> 17939150 | H28: =YEAR(B28) -> 2028 | I28: =H28-2026 -> 2
A29: 14 | B29: =EOMONTH($C$10,13) -> 46812 | C29: =G28 -> 17939150 | D29: =IF(A29>$C$6,MIN(C29,$C$13),0) -> 252664.08 | E29: =C29*$C$8*DAY(B29)/$C$11 -> 101156.87 | F29: =D29+E29 -> 353820.96 | G29: =C29-D29 -> 17686486 | H29: =YEAR(B29) -> 2028 | I29: =H29-2026 -> 2
A30: 15 | B30: =EOMONTH($C$10,14) -> 46843 | C30: =G29 -> 17686486 | D30: =IF(A30>$C$6,MIN(C30,$C$13),0) -> 252664.08 | E30: =C30*$C$8*DAY(B30)/$C$11 -> 106610.21 | F30: =D30+E30 -> 359274.29 | G30: =C30-D30 -> 17433822 | H30: =YEAR(B30) -> 2028 | I30: =H30-2026 -> 2
A31: 16 | B31: =EOMONTH($C$10,15) -> 46873 | C31: =G30 -> 17433822 | D31: =IF(A31>$C$6,MIN(C31,$C$13),0) -> 252664.08 | E31: =C31*$C$8*DAY(B31)/$C$11 -> 101697.29 | F31: =D31+E31 -> 354361.38 | G31: =C31-D31 -> 17181158 | H31: =YEAR(B31) -> 2028 | I31: =H31-2026 -> 2
A32: 17 | B32: =EOMONTH($C$10,16) -> 46904 | C32: =G31 -> 17181158 | D32: =IF(A32>$C$6,MIN(C32,$C$13),0) -> 252664.08 | E32: =C32*$C$8*DAY(B32)/$C$11 -> 103564.2 | F32: =D32+E32 -> 356228.28 | G32: =C32-D32 -> 16928494 | H32: =YEAR(B32) -> 2028 | I32: =H32-2026 -> 2
A33: 18 | B33: =EOMONTH($C$10,17) -> 46934 | C33: =G32 -> 16928494 | D33: =IF(A33>$C$6,MIN(C33,$C$13),0) -> 252664.08 | E33: =C33*$C$8*DAY(B33)/$C$11 -> 98749.546 | F33: =D33+E33 -> 351413.63 | G33: =C33-D33 -> 16675829 | H33: =YEAR(B33) -> 2028 | I33: =H33-2026 -> 2
A34: 19 | B34: =EOMONTH($C$10,18) -> 46965 | C34: =G33 -> 16675829 | D34: =IF(A34>$C$6,MIN(C34,$C$13),0) -> 252664.08 | E34: =C34*$C$8*DAY(B34)/$C$11 -> 100518.19 | F34: =D34+E34 -> 353182.28 | G34: =C34-D34 -> 16423165 | H34: =YEAR(B34) -> 2028 | I34: =H34-2026 -> 2
A35: 20 | B35: =EOMONTH($C$10,19) -> 46996 | C35: =G34 -> 16423165 | D35: =IF(A35>$C$6,MIN(C35,$C$13),0) -> 252664.08 | E35: =C35*$C$8*DAY(B35)/$C$11 -> 98995.191 | F35: =D35+E35 -> 351659.27 | G35: =C35-D35 -> 16170501 | H35: =YEAR(B35) -> 2028 | I35: =H35-2026 -> 2
A36: 21 | B36: =EOMONTH($C$10,20) -> 47026 | C36: =G35 -> 16170501 | D36: =IF(A36>$C$6,MIN(C36,$C$13),0) -> 252664.08 | E36: =C36*$C$8*DAY(B36)/$C$11 -> 94327.924 | F36: =D36+E36 -> 346992.01 | G36: =C36-D36 -> 15917837 | H36: =YEAR(B36) -> 2028 | I36: =H36-2026 -> 2
A37: 22 | B37: =EOMONTH($C$10,21) -> 47057 | C37: =G36 -> 15917837 | D37: =IF(A37>$C$6,MIN(C37,$C$13),0) -> 252664.08 | E37: =C37*$C$8*DAY(B37)/$C$11 -> 95949.185 | F37: =D37+E37 -> 348613.27 | G37: =C37-D37 -> 15665173 | H37: =YEAR(B37) -> 2028 | I37: =H37-2026 -> 2
A38: 23 | B38: =EOMONTH($C$10,22) -> 47087 | C38: =G37 -> 15665173 | D38: =IF(A38>$C$6,MIN(C38,$C$13),0) -> 252664.08 | E38: =C38*$C$8*DAY(B38)/$C$11 -> 91380.177 | F38: =D38+E38 -> 344044.26 | G38: =C38-D38 -> 15412509 | H38: =YEAR(B38) -> 2028 | I38: =H38-2026 -> 2
A39: 24 | B39: =EOMONTH($C$10,23) -> 47118 | C39: =G38 -> 15412509 | D39: =IF(A39>$C$6,MIN(C39,$C$13),0) -> 252664.08 | E39: =C39*$C$8*DAY(B39)/$C$11 -> 92903.18 | F39: =D39+E39 -> 345567.26 | G39: =C39-D39 -> 15159845 | H39: =YEAR(B39) -> 2028 | I39: =H39-2026 -> 2
A40: 25 | B40: =EOMONTH($C$10,24) -> 47149 | C40: =G39 -> 15159845 | D40: =IF(A40>$C$6,MIN(C40,$C$13),0) -> 252664.08 | E40: =C40*$C$8*DAY(B40)/$C$11 -> 91380.177 | F40: =D40+E40 -> 344044.26 | G40: =C40-D40 -> 14907181 | H40: =YEAR(B40) -> 2029 | I40: =H40-2026 -> 3
A41: 26 | B41: =EOMONTH($C$10,25) -> 47177 | C41: =G40 -> 14907181 | D41: =IF(A41>$C$6,MIN(C41,$C$13),0) -> 252664.08 | E41: =C41*$C$8*DAY(B41)/$C$11 -> 81161.318 | F41: =D41+E41 -> 333825.4 | G41: =C41-D41 -> 14654517 | H41: =YEAR(B41) -> 2029 | I41: =H41-2026 -> 3
A42: 27 | B42: =EOMONTH($C$10,26) -> 47208 | C42: =G41 -> 14654517 | D42: =IF(A42>$C$6,MIN(C42,$C$13),0) -> 252664.08 | E42: =C42*$C$8*DAY(B42)/$C$11 -> 88334.171 | F42: =D42+E42 -> 340998.25 | G42: =C42-D42 -> 14401853 | H42: =YEAR(B42) -> 2029 | I42: =H42-2026 -> 3
A43: 28 | B43: =EOMONTH($C$10,27) -> 47238 | C43: =G42 -> 14401853 | D43: =IF(A43>$C$6,MIN(C43,$C$13),0) -> 252664.08 | E43: =C43*$C$8*DAY(B43)/$C$11 -> 84010.808 | F43: =D43+E43 -> 336674.89 | G43: =C43-D43 -> 14149189 | H43: =YEAR(B43) -> 2029 | I43: =H43-2026 -> 3
A44: 29 | B44: =EOMONTH($C$10,28) -> 47269 | C44: =G43 -> 14149189 | D44: =IF(A44>$C$6,MIN(C44,$C$13),0) -> 252664.08 | E44: =C44*$C$8*DAY(B44)/$C$11 -> 85288.165 | F44: =D44+E44 -> 337952.25 | G44: =C44-D44 -> 13896525 | H44: =YEAR(B44) -> 2029 | I44: =H44-2026 -> 3
A45: 30 | B45: =EOMONTH($C$10,29) -> 47299 | C45: =G44 -> 13896525 | D45: =IF(A45>$C$6,MIN(C45,$C$13),0) -> 252664.08 | E45: =C45*$C$8*DAY(B45)/$C$11 -> 81063.06 | F45: =D45+E45 -> 333727.14 | G45: =C45-D45 -> 13643860 | H45: =YEAR(B45) -> 2029 | I45: =H45-2026 -> 3
A46: 31 | B46: =EOMONTH($C$10,30) -> 47330 | C46: =G45 -> 13643860 | D46: =IF(A46>$C$6,MIN(C46,$C$13),0) -> 252664.08 | E46: =C46*$C$8*DAY(B46)/$C$11 -> 82242.159 | F46: =D46+E46 -> 334906.24 | G46: =C46-D46 -> 13391196 | H46: =YEAR(B46) -> 2029 | I46: =H46-2026 -> 3
A47: 32 | B47: =EOMONTH($C$10,31) -> 47361 | C47: =G46 -> 13391196 | D47: =IF(A47>$C$6,MIN(C47,$C$13),0) -> 252664.08 | E47: =C47*$C$8*DAY(B47)/$C$11 -> 80719.156 | F47: =D47+E47 -> 333383.24 | G47: =C47-D47 -> 13138532 | H47: =YEAR(B47) -> 2029 | I47: =H47-2026 -> 3
A48: 33 | B48: =EOMONTH($C$10,32) -> 47391 | C48: =G47 -> 13138532 | D48: =IF(A48>$C$6,MIN(C48,$C$13),0) -> 252664.08 | E48: =C48*$C$8*DAY(B48)/$C$11 -> 76641.438 | F48: =D48+E48 -> 329305.52 | G48: =C48-D48 -> 12885868 | H48: =YEAR(B48) -> 2029 | I48: =H48-2026 -> 3
A49: 34 | B49: =EOMONTH($C$10,33) -> 47422 | C49: =G48 -> 12885868 | D49: =IF(A49>$C$6,MIN(C49,$C$13),0) -> 252664.08 | E49: =C49*$C$8*DAY(B49)/$C$11 -> 77673.15 | F49: =D49+E49 -> 330337.23 | G49: =C49-D49 -> 12633204 | H49: =YEAR(B49) -> 2029 | I49: =H49-2026 -> 3
A50: 35 | B50: =EOMONTH($C$10,34) -> 47452 | C50: =G49 -> 12633204 | D50: =IF(A50>$C$6,MIN(C50,$C$13),0) -> 252664.08 | E50: =C50*$C$8*DAY(B50)/$C$11 -> 73693.691 | F50: =D50+E50 -> 326357.77 | G50: =C50-D50 -> 12380540 | H50: =YEAR(B50) -> 2029 | I50: =H50-2026 -> 3
A51: 36 | B51: =EOMONTH($C$10,35) -> 47483 | C51: =G50 -> 12380540 | D51: =IF(A51>$C$6,MIN(C51,$C$13),0) -> 252664.08 | E51: =C51*$C$8*DAY(B51)/$C$11 -> 74627.144 | F51: =D51+E51 -> 327291.23 | G51: =C51-D51 -> 12127876 | H51: =YEAR(B51) -> 2029 | I51: =H51-2026 -> 3
A52: 37 | B52: =EOMONTH($C$10,36) -> 47514 | C52: =G51 -> 12127876 | D52: =IF(A52>$C$6,MIN(C52,$C$13),0) -> 252664.08 | E52: =C52*$C$8*DAY(B52)/$C$11 -> 73104.141 | F52: =D52+E52 -> 325768.22 | G52: =C52-D52 -> 11875212 | H52: =YEAR(B52) -> 2030 | I52: =H52-2026 -> 4
A53: 38 | B53: =EOMONTH($C$10,37) -> 47542 | C53: =G52 -> 11875212 | D53: =IF(A53>$C$6,MIN(C53,$C$13),0) -> 252664.08 | E53: =C53*$C$8*DAY(B53)/$C$11 -> 64653.931 | F53: =D53+E53 -> 317318.01 | G53: =C53-D53 -> 11622548 | H53: =YEAR(B53) -> 2030 | I53: =H53-2026 -> 4
A54: 39 | B54: =EOMONTH($C$10,38) -> 47573 | C54: =G53 -> 11622548 | D54: =IF(A54>$C$6,MIN(C54,$C$13),0) -> 252664.08 | E54: =C54*$C$8*DAY(B54)/$C$11 -> 70058.135 | F54: =D54+E54 -> 322722.22 | G54: =C54-D54 -> 11369884 | H54: =YEAR(B54) -> 2030 | I54: =H54-2026 -> 4
A55: 40 | B55: =EOMONTH($C$10,39) -> 47603 | C55: =G54 -> 11369884 | D55: =IF(A55>$C$6,MIN(C55,$C$13),0) -> 252664.08 | E55: =C55*$C$8*DAY(B55)/$C$11 -> 66324.322 | F55: =D55+E55 -> 318988.4 | G55: =C55-D55 -> 11117220 | H55: =YEAR(B55) -> 2030 | I55: =H55-2026 -> 4
A56: 41 | B56: =EOMONTH($C$10,40) -> 47634 | C56: =G55 -> 11117220 | D56: =IF(A56>$C$6,MIN(C56,$C$13),0) -> 252664.08 | E56: =C56*$C$8*DAY(B56)/$C$11 -> 67012.13 | F56: =D56+E56 -> 319676.21 | G56: =C56-D56 -> 10864556 | H56: =YEAR(B56) -> 2030 | I56: =H56-2026 -> 4
A57: 42 | B57: =EOMONTH($C$10,41) -> 47664 | C57: =G56 -> 10864556 | D57: =IF(A57>$C$6,MIN(C57,$C$13),0) -> 252664.08 | E57: =C57*$C$8*DAY(B57)/$C$11 -> 63376.574 | F57: =D57+E57 -> 316040.66 | G57: =C57-D57 -> 10611891 | H57: =YEAR(B57) -> 2030 | I57: =H57-2026 -> 4
A58: 43 | B58: =EOMONTH($C$10,42) -> 47695 | C58: =G57 -> 10611891 | D58: =IF(A58>$C$6,MIN(C58,$C$13),0) -> 252664.08 | E58: =C58*$C$8*DAY(B58)/$C$11 -> 63966.124 | F58: =D58+E58 -> 316630.21 | G58: =C58-D58 -> 10359227 | H58: =YEAR(B58) -> 2030 | I58: =H58-2026 -> 4
A59: 44 | B59: =EOMONTH($C$10,43) -> 47726 | C59: =G58 -> 10359227 | D59: =IF(A59>$C$6,MIN(C59,$C$13),0) -> 252664.08 | E59: =C59*$C$8*DAY(B59)/$C$11 -> 62443.121 | F59: =D59+E59 -> 315107.2 | G59: =C59-D59 -> 10106563 | H59: =YEAR(B59) -> 2030 | I59: =H59-2026 -> 4
A60: 45 | B60: =EOMONTH($C$10,44) -> 47756 | C60: =G59 -> 10106563 | D60: =IF(A60>$C$6,MIN(C60,$C$13),0) -> 252664.08 | E60: =C60*$C$8*DAY(B60)/$C$11 -> 58954.953 | F60: =D60+E60 -> 311619.04 | G60: =C60-D60 -> 9853899.2 | H60: =YEAR(B60) -> 2030 | I60: =H60-2026 -> 4
A61: 46 | B61: =EOMONTH($C$10,45) -> 47787 | C61: =G60 -> 9853899.2 | D61: =IF(A61>$C$6,MIN(C61,$C$13),0) -> 252664.08 | E61: =C61*$C$8*DAY(B61)/$C$11 -> 59397.115 | F61: =D61+E61 -> 312061.2 | G61: =C61-D61 -> 9601235.1 | H61: =YEAR(B61) -> 2030 | I61: =H61-2026 -> 4
A62: 47 | B62: =EOMONTH($C$10,46) -> 47817 | C62: =G61 -> 9601235.1 | D62: =IF(A62>$C$6,MIN(C62,$C$13),0) -> 252664.08 | E62: =C62*$C$8*DAY(B62)/$C$11 -> 56007.205 | F62: =D62+E62 -> 308671.29 | G62: =C62-D62 -> 9348571.1 | H62: =YEAR(B62) -> 2030 | I62: =H62-2026 -> 4
A63: 48 | B63: =EOMONTH($C$10,47) -> 47848 | C63: =G62 -> 9348571.1 | D63: =IF(A63>$C$6,MIN(C63,$C$13),0) -> 252664.08 | E63: =C63*$C$8*DAY(B63)/$C$11 -> 56351.109 | F63: =D63+E63 -> 309015.19 | G63: =C63-D63 -> 9095907 | H63: =YEAR(B63) -> 2030 | I63: =H63-2026 -> 4
A64: 49 | B64: =EOMONTH($C$10,48) -> 47879 | C64: =G63 -> 9095907 | D64: =IF(A64>$C$6,MIN(C64,$C$13),0) -> 252664.08 | E64: =C64*$C$8*DAY(B64)/$C$11 -> 54828.106 | F64: =D64+E64 -> 307492.19 | G64: =C64-D64 -> 8843242.9 | H64: =YEAR(B64) -> 2031 | I64: =H64-2026 -> 5
A65: 50 | B65: =EOMONTH($C$10,49) -> 47907 | C65: =G64 -> 8843242.9 | D65: =IF(A65>$C$6,MIN(C65,$C$13),0) -> 252664.08 | E65: =C65*$C$8*DAY(B65)/$C$11 -> 48146.545 | F65: =D65+E65 -> 300810.63 | G65: =C65-D65 -> 8590578.8 | H65: =YEAR(B65) -> 2031 | I65: =H65-2026 -> 5
A66: 51 | B66: =EOMONTH($C$10,50) -> 47938 | C66: =G65 -> 8590578.8 | D66: =IF(A66>$C$6,MIN(C66,$C$13),0) -> 252664.08 | E66: =C66*$C$8*DAY(B66)/$C$11 -> 51782.1 | F66: =D66+E66 -> 304446.18 | G66: =C66-D66 -> 8337914.7 | H66: =YEAR(B66) -> 2031 | I66: =H66-2026 -> 5
A67: 52 | B67: =EOMONTH($C$10,51) -> 47968 | C67: =G66 -> 8337914.7 | D67: =IF(A67>$C$6,MIN(C67,$C$13),0) -> 252664.08 | E67: =C67*$C$8*DAY(B67)/$C$11 -> 48637.836 | F67: =D67+E67 -> 301301.92 | G67: =C67-D67 -> 8085250.7 | H67: =YEAR(B67) -> 2031 | I67: =H67-2026 -> 5
A68: 53 | B68: =EOMONTH($C$10,52) -> 47999 | C68: =G67 -> 8085250.7 | D68: =IF(A68>$C$6,MIN(C68,$C$13),0) -> 252664.08 | E68: =C68*$C$8*DAY(B68)/$C$11 -> 48736.094 | F68: =D68+E68 -> 301400.18 | G68: =C68-D68 -> 7832586.6 | H68: =YEAR(B68) -> 2031 | I68: =H68-2026 -> 5
A69: 54 | B69: =EOMONTH($C$10,53) -> 48029 | C69: =G68 -> 7832586.6 | D69: =IF(A69>$C$6,MIN(C69,$C$13),0) -> 252664.08 | E69: =C69*$C$8*DAY(B69)/$C$11 -> 45690.088 | F69: =D69+E69 -> 298354.17 | G69: =C69-D69 -> 7579922.5 | H69: =YEAR(B69) -> 2031 | I69: =H69-2026 -> 5
A70: 55 | B70: =EOMONTH($C$10,54) -> 48060 | C70: =G69 -> 7579922.5 | D70: =IF(A70>$C$6,MIN(C70,$C$13),0) -> 252664.08 | E70: =C70*$C$8*DAY(B70)/$C$11 -> 45690.088 | F70: =D70+E70 -> 298354.17 | G70: =C70-D70 -> 7327258.4 | H70: =YEAR(B70) -> 2031 | I70: =H70-2026 -> 5
A71: 56 | B71: =EOMONTH($C$10,55) -> 48091 | C71: =G70 -> 7327258.4 | D71: =IF(A71>$C$6,MIN(C71,$C$13),0) -> 252664.08 | E71: =C71*$C$8*DAY(B71)/$C$11 -> 44167.085 | F71: =D71+E71 -> 296831.17 | G71: =C71-D71 -> 7074594.3 | H71: =YEAR(B71) -> 2031 | I71: =H71-2026 -> 5
A72: 57 | B72: =EOMONTH($C$10,56) -> 48121 | C72: =G71 -> 7074594.3 | D72: =IF(A72>$C$6,MIN(C72,$C$13),0) -> 252664.08 | E72: =C72*$C$8*DAY(B72)/$C$11 -> 41268.467 | F72: =D72+E72 -> 293932.55 | G72: =C72-D72 -> 6821930.2 | H72: =YEAR(B72) -> 2031 | I72: =H72-2026 -> 5
A73: 58 | B73: =EOMONTH($C$10,57) -> 48152 | C73: =G72 -> 6821930.2 | D73: =IF(A73>$C$6,MIN(C73,$C$13),0) -> 252664.08 | E73: =C73*$C$8*DAY(B73)/$C$11 -> 41121.079 | F73: =D73+E73 -> 293785.16 | G73: =C73-D73 -> 6569266.2 | H73: =YEAR(B73) -> 2031 | I73: =H73-2026 -> 5
A74: 59 | B74: =EOMONTH($C$10,58) -> 48182 | C74: =G73 -> 6569266.2 | D74: =IF(A74>$C$6,MIN(C74,$C$13),0) -> 252664.08 | E74: =C74*$C$8*DAY(B74)/$C$11 -> 38320.719 | F74: =D74+E74 -> 290984.8 | G74: =C74-D74 -> 6316602.1 | H74: =YEAR(B74) -> 2031 | I74: =H74-2026 -> 5
A75: 60 | B75: =EOMONTH($C$10,59) -> 48213 | C75: =G74 -> 6316602.1 | D75: =IF(A75>$C$6,MIN(C75,$C$13),0) -> 252664.08 | E75: =C75*$C$8*DAY(B75)/$C$11 -> 38075.074 | F75: =D75+E75 -> 290739.16 | G75: =C75-D75 -> 6063938 | H75: =YEAR(B75) -> 2031 | I75: =H75-2026 -> 5
A76: 61 | B76: =EOMONTH($C$10,60) -> 48244 | C76: =G75 -> 6063938 | D76: =IF(A76>$C$6,MIN(C76,$C$13),0) -> 252664.08 | E76: =C76*$C$8*DAY(B76)/$C$11 -> 36552.071 | F76: =D76+E76 -> 289216.15 | G76: =C76-D76 -> 5811273.9 | H76: =YEAR(B76) -> 2032 | I76: =H76-2026 -> 6
A77: 62 | B77: =EOMONTH($C$10,61) -> 48273 | C77: =G76 -> 5811273.9 | D77: =IF(A77>$C$6,MIN(C77,$C$13),0) -> 252664.08 | E77: =C77*$C$8*DAY(B77)/$C$11 -> 32769.128 | F77: =D77+E77 -> 285433.21 | G77: =C77-D77 -> 5558609.8 | H77: =YEAR(B77) -> 2032 | I77: =H77-2026 -> 6
A78: 63 | B78: =EOMONTH($C$10,62) -> 48304 | C78: =G77 -> 5558609.8 | D78: =IF(A78>$C$6,MIN(C78,$C$13),0) -> 252664.08 | E78: =C78*$C$8*DAY(B78)/$C$11 -> 33506.065 | F78: =D78+E78 -> 286170.15 | G78: =C78-D78 -> 5305945.7 | H78: =YEAR(B78) -> 2032 | I78: =H78-2026 -> 6
A79: 64 | B79: =EOMONTH($C$10,63) -> 48334 | C79: =G78 -> 5305945.7 | D79: =IF(A79>$C$6,MIN(C79,$C$13),0) -> 252664.08 | E79: =C79*$C$8*DAY(B79)/$C$11 -> 30951.35 | F79: =D79+E79 -> 283615.43 | G79: =C79-D79 -> 5053281.7 | H79: =YEAR(B79) -> 2032 | I79: =H79-2026 -> 6
A80: 65 | B80: =EOMONTH($C$10,64) -> 48365 | C80: =G79 -> 5053281.7 | D80: =IF(A80>$C$6,MIN(C80,$C$13),0) -> 252664.08 | E80: =C80*$C$8*DAY(B80)/$C$11 -> 30460.059 | F80: =D80+E80 -> 283124.14 | G80: =C80-D80 -> 4800617.6 | H80: =YEAR(B80) -> 2032 | I80: =H80-2026 -> 6
A81: 66 | B81: =EOMONTH($C$10,65) -> 48395 | C81: =G80 -> 4800617.6 | D81: =IF(A81>$C$6,MIN(C81,$C$13),0) -> 252664.08 | E81: =C81*$C$8*DAY(B81)/$C$11 -> 28003.603 | F81: =D81+E81 -> 280667.69 | G81: =C81-D81 -> 4547953.5 | H81: =YEAR(B81) -> 2032 | I81: =H81-2026 -> 6
A82: 67 | B82: =EOMONTH($C$10,66) -> 48426 | C82: =G81 -> 4547953.5 | D82: =IF(A82>$C$6,MIN(C82,$C$13),0) -> 252664.08 | E82: =C82*$C$8*DAY(B82)/$C$11 -> 27414.053 | F82: =D82+E82 -> 280078.14 | G82: =C82-D82 -> 4295289.4 | H82: =YEAR(B82) -> 2032 | I82: =H82-2026 -> 6
A83: 68 | B83: =EOMONTH($C$10,67) -> 48457 | C83: =G82 -> 4295289.4 | D83: =IF(A83>$C$6,MIN(C83,$C$13),0) -> 252664.08 | E83: =C83*$C$8*DAY(B83)/$C$11 -> 25891.05 | F83: =D83+E83 -> 278555.13 | G83: =C83-D83 -> 4042625.3 | H83: =YEAR(B83) -> 2032 | I83: =H83-2026 -> 6
A84: 69 | B84: =EOMONTH($C$10,68) -> 48487 | C84: =G83 -> 4042625.3 | D84: =IF(A84>$C$6,MIN(C84,$C$13),0) -> 252664.08 | E84: =C84*$C$8*DAY(B84)/$C$11 -> 23581.981 | F84: =D84+E84 -> 276246.06 | G84: =C84-D84 -> 3789961.2 | H84: =YEAR(B84) -> 2032 | I84: =H84-2026 -> 6
A85: 70 | B85: =EOMONTH($C$10,69) -> 48518 | C85: =G84 -> 3789961.2 | D85: =IF(A85>$C$6,MIN(C85,$C$13),0) -> 252664.08 | E85: =C85*$C$8*DAY(B85)/$C$11 -> 22845.044 | F85: =D85+E85 -> 275509.13 | G85: =C85-D85 -> 3537297.2 | H85: =YEAR(B85) -> 2032 | I85: =H85-2026 -> 6
A86: 71 | B86: =EOMONTH($C$10,70) -> 48548 | C86: =G85 -> 3537297.2 | D86: =IF(A86>$C$6,MIN(C86,$C$13),0) -> 252664.08 | E86: =C86*$C$8*DAY(B86)/$C$11 -> 20634.233 | F86: =D86+E86 -> 273298.32 | G86: =C86-D86 -> 3284633.1 | H86: =YEAR(B86) -> 2032 | I86: =H86-2026 -> 6
A87: 72 | B87: =EOMONTH($C$10,71) -> 48579 | C87: =G86 -> 3284633.1 | D87: =IF(A87>$C$6,MIN(C87,$C$13),0) -> 252664.08 | E87: =C87*$C$8*DAY(B87)/$C$11 -> 19799.038 | F87: =D87+E87 -> 272463.12 | G87: =C87-D87 -> 3031969 | H87: =YEAR(B87) -> 2032 | I87: =H87-2026 -> 6
A88: 73 | B88: =EOMONTH($C$10,72) -> 48610 | C88: =G87 -> 3031969 | D88: =IF(A88>$C$6,MIN(C88,$C$13),0) -> 252664.08 | E88: =C88*$C$8*DAY(B88)/$C$11 -> 18276.035 | F88: =D88+E88 -> 270940.12 | G88: =C88-D88 -> 2779304.9 | H88: =YEAR(B88) -> 2033 | I88: =H88-2026 -> 7
A89: 74 | B89: =EOMONTH($C$10,73) -> 48638 | C89: =G88 -> 2779304.9 | D89: =IF(A89>$C$6,MIN(C89,$C$13),0) -> 252664.08 | E89: =C89*$C$8*DAY(B89)/$C$11 -> 15131.771 | F89: =D89+E89 -> 267795.85 | G89: =C89-D89 -> 2526640.8 | H89: =YEAR(B89) -> 2033 | I89: =H89-2026 -> 7
A90: 75 | B90: =EOMONTH($C$10,74) -> 48669 | C90: =G89 -> 2526640.8 | D90: =IF(A90>$C$6,MIN(C90,$C$13),0) -> 252664.08 | E90: =C90*$C$8*DAY(B90)/$C$11 -> 15230.029 | F90: =D90+E90 -> 267894.11 | G90: =C90-D90 -> 2273976.7 | H90: =YEAR(B90) -> 2033 | I90: =H90-2026 -> 7
A91: 76 | B91: =EOMONTH($C$10,75) -> 48699 | C91: =G90 -> 2273976.7 | D91: =IF(A91>$C$6,MIN(C91,$C$13),0) -> 252664.08 | E91: =C91*$C$8*DAY(B91)/$C$11 -> 13264.864 | F91: =D91+E91 -> 265928.95 | G91: =C91-D91 -> 2021312.7 | H91: =YEAR(B91) -> 2033 | I91: =H91-2026 -> 7
A92: 77 | B92: =EOMONTH($C$10,76) -> 48730 | C92: =G91 -> 2021312.7 | D92: =IF(A92>$C$6,MIN(C92,$C$13),0) -> 252664.08 | E92: =C92*$C$8*DAY(B92)/$C$11 -> 12184.024 | F92: =D92+E92 -> 264848.11 | G92: =C92-D92 -> 1768648.6 | H92: =YEAR(B92) -> 2033 | I92: =H92-2026 -> 7
A93: 78 | B93: =EOMONTH($C$10,77) -> 48760 | C93: =G92 -> 1768648.6 | D93: =IF(A93>$C$6,MIN(C93,$C$13),0) -> 252664.08 | E93: =C93*$C$8*DAY(B93)/$C$11 -> 10317.117 | F93: =D93+E93 -> 262981.2 | G93: =C93-D93 -> 1515984.5 | H93: =YEAR(B93) -> 2033 | I93: =H93-2026 -> 7
A94: 79 | B94: =EOMONTH($C$10,78) -> 48791 | C94: =G93 -> 1515984.5 | D94: =IF(A94>$C$6,MIN(C94,$C$13),0) -> 252664.08 | E94: =C94*$C$8*DAY(B94)/$C$11 -> 9138.0177 | F94: =D94+E94 -> 261802.1 | G94: =C94-D94 -> 1263320.4 | H94: =YEAR(B94) -> 2033 | I94: =H94-2026 -> 7
A95: 80 | B95: =EOMONTH($C$10,79) -> 48822 | C95: =G94 -> 1263320.4 | D95: =IF(A95>$C$6,MIN(C95,$C$13),0) -> 252664.08 | E95: =C95*$C$8*DAY(B95)/$C$11 -> 7615.0147 | F95: =D95+E95 -> 260279.1 | G95: =C95-D95 -> 1010656.3 | H95: =YEAR(B95) -> 2033 | I95: =H95-2026 -> 7
A96: 81 | B96: =EOMONTH($C$10,80) -> 48852 | C96: =G95 -> 1010656.3 | D96: =IF(A96>$C$6,MIN(C96,$C$13),0) -> 252664.08 | E96: =C96*$C$8*DAY(B96)/$C$11 -> 5895.4953 | F96: =D96+E96 -> 258559.58 | G96: =C96-D96 -> 757992.25 | H96: =YEAR(B96) -> 2033 | I96: =H96-2026 -> 7
A97: 82 | B97: =EOMONTH($C$10,81) -> 48883 | C97: =G96 -> 757992.25 | D97: =IF(A97>$C$6,MIN(C97,$C$13),0) -> 252664.08 | E97: =C97*$C$8*DAY(B97)/$C$11 -> 4569.0088 | F97: =D97+E97 -> 257233.09 | G97: =C97-D97 -> 505328.17 | H97: =YEAR(B97) -> 2033 | I97: =H97-2026 -> 7
A98: 83 | B98: =EOMONTH($C$10,82) -> 48913 | C98: =G97 -> 505328.17 | D98: =IF(A98>$C$6,MIN(C98,$C$13),0) -> 252664.08 | E98: =C98*$C$8*DAY(B98)/$C$11 -> 2947.7476 | F98: =D98+E98 -> 255611.83 | G98: =C98-D98 -> 252664.08 | H98: =YEAR(B98) -> 2033 | I98: =H98-2026 -> 7
A99: 84 | B99: =EOMONTH($C$10,83) -> 48944 | C99: =G98 -> 252664.08 | D99: =IF(A99>$C$6,MIN(C99,$C$13),0) -> 252664.08 | E99: =C99*$C$8*DAY(B99)/$C$11 -> 1523.0029 | F99: =D99+E99 -> 254187.09 | G99: =C99-D99 -> 1.2747478e-08 | H99: =YEAR(B99) -> 2033 | I99: =H99-2026 -> 7
B100: ИТОГО | D100: =SUM(D16:D99) -> 18191814 | E100: =SUM(E16:E99) -> 5220068 | F100: =SUM(F16:F99) -> 23411882
B102: ГОДОВАЯ СВОДКА ПО КРЕДИТУ
B103: ПОКАЗАТЕЛИ | C103: 1 год (2027) | D103: 2 год (2028) | E103: 3 год (2029) | F103: 4 год (2030) | G103: 5 год (2031) | H103: 6 год (2032) | I103: 7 год (2033)
B104: Выдача кредита | C104: =$C$9 -> 18191814 | D104: 0 | E104: 0 | F104: 0 | G104: 0 | H104: 0 | I104: 0
B105: Погашение основного долга | C105: =SUMIF($I$16:$I$99,1,$D$16:$D$99) -> 0 | D105: =SUMIF($I$16:$I$99,2,$D$16:$D$99) -> 3031969 | E105: =SUMIF($I$16:$I$99,3,$D$16:$D$99) -> 3031969 | F105: =SUMIF($I$16:$I$99,4,$D$16:$D$99) -> 3031969 | G105: =SUMIF($I$16:$I$99,5,$D$16:$D$99) -> 3031969 | H105: =SUMIF($I$16:$I$99,6,$D$16:$D$99) -> 3031969 | I105: =SUMIF($I$16:$I$99,7,$D$16:$D$99) -> 3031969
...

Sheet ProfLoss
B2: ПРЕДПОЛАГАЕМЫЕ СЧЕТА ПРИБЫЛЕЙ И УБЫТКОВ (в экв. долл. США) | K2: Приложение 13
B4: ПОКАЗАТЕЛИ | C4: Ед. изм. | D4: 1 год (льготный / инвест.) | E4: 2 год | F4: 3 год | G4: 4 год | H4: 5 год | I4: 6 год | J4: 7 год
D5: 2027 | E5: 2028 | F5: 2029 | G5: 2030 | H5: 2031 | I5: 2032 | J5: 2033
B6: Выручка от реализации продукции (с НДС) | C6: USD | D6: =D7+D8 -> 9058233.4 | E6: =E7+E8 -> 36777950 | F6: =F7+F8 -> 48825712 | G6: =G7+G8 -> 58917295 | H6: =H7+H8 -> 60592704 | I6: =I7+I8 -> 61925327 | J6: =J7+J8 -> 63287696
B7: экспорт (в твёрдой валюте) | C7: USD | D7: =SalePlan!D10 -> 9058233.4 | E7: =SalePlan!E10 -> 36777950 | F7: =SalePlan!F10 -> 48825712 | G7: =SalePlan!G10 -> 58917295 | H7: =SalePlan!H10 -> 60592704 | I7: =SalePlan!I10 -> 61925327 | J7: =SalePlan!J10 -> 63287696
B8: внутренний рынок (с НДС) | C8: USD | D8: =SalePlan!D16+Taxes!D19 -> 0 | E8: =SalePlan!E16+Taxes!E19 -> 0 | F8: =SalePlan!F16+Taxes!F19 -> 0 | G8: =SalePlan!G16+Taxes!G19 -> 0 | H8: =SalePlan!H16+Taxes!H19 -> 0 | I8: =SalePlan!I16+Taxes!I19 -> 0 | J8: =SalePlan!J16+Taxes!J19 -> 0
B9: НДС, начисленный с реализации | C9: USD | D9: =Taxes!D19 -> 0 | E9: =Taxes!E19 -> 0 | F9: =Taxes!F19 -> 0 | G9: =Taxes!G19 -> 0 | H9: =Taxes!H19 -> 0 | I9: =Taxes!I19 -> 0 | J9: =Taxes!J19 -> 0
B10: Чистая выручка от реализации продукции | C10: USD | D10: =D6-D9 -> 9058233.4 | E10: =E6-E9 -> 36777950 | F10: =F6-F9 -> 48825712 | G10: =G6-G9 -> 58917295 | H10: =H6-H9 -> 60592704 | I10: =I6-I9 -> 61925327 | J10: =J6-J9 -> 63287696
B11: Себестоимость реализованной продукции | C11: USD | D11: =CostSold!D22 -> 3983085.3 | E11: =CostSold!E22 -> 22748393 | F11: =CostSold!F22 -> 28767726 | G11: =CostSold!G22 -> 33957554 | H11: =CostSold!H22 -> 35013223 | I11: =CostSold!I22 -> 35782806 | J11: =CostSold!J22 -> 36568133
B12: в твёрдой валюте | C12: USD | D12: =CostSold!D23 -> 154815.25 | E12: =CostSold!E23 -> 1123057.2 | F12: =CostSold!F23 -> 1434045.7 | G12: =CostSold!G23 -> 1689151.4 | H12: =CostSold!H23 -> 1717864.5 | I12: =CostSold!I23 -> 1731824.2 | J12: =CostSold!J23 -> 1746035.3
B13: в местной валюте | C13: USD | D13: =CostSold!D24 -> 3828270.1 | E13: =CostSold!E24 -> 21625336 | F13: =CostSold!F24 -> 27333680 | G13: =CostSold!G24 -> 32268403 | H13: =CostSold!H24 -> 33295359 | I13: =CostSold!I24 -> 34050982 | J13: =CostSold!J24 -> 34822098
B14: Валовая прибыль (убыток) | C14: USD | D14: =D10-D11 -> 5075148.1 | E14: =E10-E11 -> 14029557 | F14: =F10-F11 -> 20057986 | G14: =G10-G11 -> 24959740 | H14: =H10-H11 -> 25579481 | I14: =I10-I11 -> 26142521 | J14: =J10-J11 -> 26719563
B15: Расходы периода (административные и коммерческие) | C15: USD | D15: =CostSold!D31 -> 3408308.9 | E15: =CostSold!E31 -> 4496685.3 | F15: =CostSold!F31 -> 4875678.2 | G15: =CostSold!G31 -> 5197583.1 | H15: =CostSold!H31 -> 5304925.8 | I15: =CostSold!I31 -> 5412731.7 | J15: =CostSold!J31 -> 5522911.5
B16: Налоги и прочие операционные расходы | C16: USD | D16: =CostSold!D39 -> 1602669.4 | E16: =CostSold!E39 -> 1008756.5 | F16: =CostSold!F39 -> 1131203.6 | G16: =CostSold!G39 -> 1228090.4 | H16: =CostSold!H39 -> 1233680.2 | I16: =CostSold!I39 -> 1239587.9 | J16: =CostSold!J39 -> 1245858.3
B17: Прибыль (убыток) от основной деятельности (EBIT) | C17: USD | D17: =D14-D15-D16 -> 64169.808 | E17: =E14-E15-E16 -> 8524115.1 | F17: =F14-F15-F16 -> 14051104 | G17: =G14-G15-G16 -> 18534067 | H17: =H14-H15-H16 -> 19040875 | I17: =I14-I15-I16 -> 19490201 | J17: =J14-J15-J16 -> 19950793
B18: Финансовые расходы | C18: USD | D18: =D19 -> 0 | E18: =E19 -> 1195508.2 | F18: =F19 -> 976834.44 | G18: =G19 -> 761648.86 | H18: =H19 -> 546463.28 | I18: =I19 -> 332407.67 | J18: =J19 -> 116092.13
B19: Проценты за кредит | C19: USD | D19: =CostSold!D42 -> 0 | E19: =CostSold!E42 -> 1195508.2 | F19: =CostSold!F42 -> 976834.44 | G19: =CostSold!G42 -> 761648.86 | H19: =CostSold!H42 -> 546463.28 | I19: =CostSold!I42 -> 332407.67 | J19: =CostSold!J42 -> 116092.13
B20: Прибыль (убыток) до налогообложения | C20: USD | D20: =D17-D18 -> 64169.808 | E20: =E17-E18 -> 7328607 | F20: =F17-F18 -> 13074270 | G20: =G17-G18 -> 17772418 | H20: =H17-H18 -> 18494412 | I20: =I17-I18 -> 19157793 | J20: =J17-J18 -> 19834701
B21: Налог на прибыль (Приложение 9) | C21: USD | D21: =Taxes!D29 -> 9625.4712 | E21: =Taxes!E29 -> 1099291 | F21: =Taxes!F29 -> 1961140.5 | G21: =Taxes!G29 -> 2665862.7 | H21: =Taxes!H29 -> 2774161.7 | I21: =Taxes!I29 -> 2873669 | J21: =Taxes!J29 -> 2975205.2
B22: Чистая прибыль (убыток) | C22: USD | D22: =D20-D21 -> 54544.337 | E22: =E20-E21 -> 6229315.9 | F22: =F20-F21 -> 11113129 | G22: =G20-G21 -> 15106555 | H22: =H20-H21 -> 15720250 | I22: =I20-I21 -> 16284124 | J22: =J20-J21 -> 16859496
B24: Коэффициенты рентабельности и покрытия
B25: Валовая рентабельность | C25: % | D25: =IFERROR(D14/D10,0) -> 0.56028012 | E25: =IFERROR(E14/E10,0) -> 0.38146653 | F25: =IFERROR(F14/F10,0) -> 0.41080786 | G25: =IFERROR(G14/G10,0) -> 0.4236403 | H25: =IFERROR(H14/H10,0) -> 0.42215447 | I25: =IFERROR(I14/I10,0) -> 0.42216201 | J25: =IFERROR(J14/J10,0) -> 0.42219206
B26: Чистая рентабельность | C26: % | D26: =IFERROR(D22/D10,0) -> 0.0060215204 | E26: =IFERROR(E22/E10,0) -> 0.16937638 | F26: =IFERROR(F22/F10,0) -> 0.22760814 | G26: =IFERROR(G22/G10,0) -> 0.25640273 | H26: =IFERROR(H22/H10,0) -> 0.2594413 | I26: =IFERROR(I22/I10,0) -> 0.26296388 | J26: =IFERROR(J22/J10,0) -> 0.26639453
B27: EBITDA | C27: USD | D27: =D17+Depreciate!$G$18 -> 731448.94 | E27: =E17+Depreciate!$H$18 -> 11251688 | F27: =F17+Depreciate!$I$18 -> 16832637 | G27: =G17+Depreciate!$J$18 -> 21369559 | H27: =H17+Depreciate!$K$18 -> 21930327 | I27: =I17+Depreciate!$L$18 -> 22433613 | J27: =J17+Depreciate!$M$18 -> 22948165
B28: Маржа EBITDA | C28: % | D28: =IFERROR(D27/D10,0) -> 0.080749623 | E28: =IFERROR(E27/E10,0) -> 0.30593571 | F28: =IFERROR(F27/F10,0) -> 0.34474945 | G28: =IFERROR(G27/G10,0) -> 0.36270436 | H28: =IFERROR(H27/H10,0) -> 0.36193016 | I28: =IFERROR(I27/I10,0) -> 0.36226879 | J28: =IFERROR(J27/J10,0) -> 0.36260074
B29: EBIT / Проценты за кредит | C29: x | D29: =IF(D19>0,D17/D19,"-") -> - | E29: =IF(E19>0,E17/E19,"-") -> 7.1301186 | F29: =IF(F19>0,F17/F19,"-") -> 14.384325 | G29: =IF(G19>0,G17/G19,"-") -> 24.334136 | H29: =IF(H19>0,H17/H19,"-") -> 34.843832 | I29: =IF(I19>0,I17/I19,"-") -> 58.633427 | J29: =IF(J19>0,J17/J19,"-") -> 171.85311
B30: Задолженность по кредиту на конец года | C30: USD | D30: =LOANS!$C$108 -> 18191814 | E30: =LOANS!$D$108 -> 15159845 | F30: =LOANS!$E$108 -> 12127876 | G30: =LOANS!$F$108 -> 9095907 | H30: =LOANS!$G$108 -> 6063938 | I30: =LOANS!$H$108 -> 3031969 | J30: =LOANS!$I$108 -> 0
B31: Долг / EBITDA | C31: x | D31: =IFERROR(D30/D27,0) -> 24.870928 | E31: =IFERROR(E30/E27,0) -> 1.3473396 | F31: =IFERROR(F30/F27,0) -> 0.72049768 | G31: =IFERROR(G30/G27,0) -> 0.42564785 | H31: =IFERROR(H30/H27,0) -> 0.27650923 | I31: =IFERROR(I30/I27,0) -> 0.13515295 | J31: =IFERROR(J30/J27,0) -> 0
B33: 1-й год: проценты за кредит льготного периода оплачиваются за счёт собственных средств и капитализируются в стоимость основных средств (МСФО IAS 23, Приложения 1 и 4); в отчёт о прибылях и убытках не включаются.

Sheet WorkCap
B2: ПРЕДПОЛОЖЕНИЯ ПО РАБОЧЕМУ КАПИТАЛУ (в экв. долл. США) | K2: Приложение 14
B4: Показатели | C4: Дни покрытия
B5: Период поступления от продаж (дебиторская задолженность) | C5: 30
B6: Запасы сырья и материалов на складе | C6: 15
B7: Незавершенная продукция | C7: 10
B8: Запасы готовой продукции (минимальный запас) | C8: 15
B9: Период оплаты поставщикам (кредиторская задолженность) | C9: 0
B10: Задолженность по заработной плате | C10: 30
B11: Возмещение НДС (операционный) | C11: 90
B12: Возмещение НДС по капитальным вложениям | C12: 540
B14: ПОКАЗАТЕЛИ (на конец года) | C14: Начало | D14: 1 год | E14: 2 год | F14: 3 год | G14: 4 год | H14: 5 год | I14: 6 год | J14: 7 год
C15: 01.01.2026 | D15: 2027 | E15: 2028 | F15: 2029 | G15: 2030 | H15: 2031 | I15: 2032 | J15: 2033
B16: Дебиторская задолженность | C16: 0 | D16: 3511500.4 | E16: 3022845.2 | F16: 4013072.2 | G16: 4842517.4 | H16: 4980222.2 | I16: 5089752.9 | J16: 5201728.4
B17: Запасы (сырьё, материалы, НЗП, готовая продукция) | C17: 0 | D17: 1919043.6 | E17: 2118484.2 | F17: 2786912.4 | G17: 3324859.4 | H17: 3398006.3 | I17: 3472762.5 | J17: 3549163.2
B18: НДС к возмещению | C18: 0 | D18: 7100743.1 | E18: 684353.87 | F18: 880322.21 | G18: 1038353.7 | H18: 1060918.7 | I18: 1083907.7 | J18: 1107402.4
B19: Итого текущих активов | C19: 0 | D19: =SUM(D16:D18) -> 12531287 | E19: =SUM(E16:E18) -> 5825683.2 | F19: =SUM(F16:F18) -> 7680306.8 | G19: =SUM(G16:G18) -> 9205730.5 | H19: =SUM(H16:H18) -> 9439147.3 | I19: =SUM(I16:I18) -> 9646423.1 | J19: =SUM(J16:J18) -> 9858294.1
B20: Кредиторская задолженность | C20: 0 | D20: 0 | E20: 0 | F20: 0 | G20: 0 | H20: 0 | I20: 0 | J20: 0
B21: Задолженность по оплате труда и налогам с ФОТ | C21: 0 | D21: 146799.77 | E21: 154738.8 | F21: 158126.33 | G21: 161603.63 | H21: 165158.91 | I21: 168792.41 | J21: 172505.84
B22: Итого текущих обязательств | C22: 0 | D22: =D20+D21 -> 146799.77 | E22: =E20+E21 -> 154738.8 | F22: =F20+F21 -> 158126.33 | G22: =G20+G21 -> 161603.63 | H22: =H20+H21 -> 165158.91 | I22: =I20+I21 -> 168792.41 | J22: =J20+J21 -> 172505.84
B23: Чистый рабочий капитал | C23: 0 | D23: =D19-D22 -> 12384487 | E23: =E19-E22 -> 5670944.4 | F23: =F19-F22 -> 7522180.5 | G23: =G19-G22 -> 9044126.9 | H23: =H19-H22 -> 9273988.4 | I23: =I19-I22 -> 9477630.7 | J23: =J19-J22 -> 9685788.3
B25: Изменения в рабочем капитале (- рост / + снижение) | D25: =-(D23-C23) -> -12384487 | E25: =-(E23-D23) -> 6713542.8 | F25: =-(F23-E23) -> -1851236 | G25: =-(G23-F23) -> -1521946.5 | H25: =-(H23-G23) -> -229861.49 | I25: =-(I23-H23) -> -203642.26 | J25: =-(J23-I23) -> -208157.6
B26: Прочие изменения операционных статей (налоги к уплате и пр.) | D26: 0 | E26: 0 | F26: 0 | G26: -8.3819032e-09 | H26: -1.1175871e-08 | I26: -1.8626451e-09 | J26: -5.5879354e-09
B27: Изменение рабочего капитала для потока наличности (Приложение 15) | D27: =D25+D26 -> -12384487 | E27: =E25+E26 -> 6713542.8 | F27: =F25+F26 -> -1851236 | G27: =G25+G26 -> -1521946.5 | H27: =H25+H26 -> -229861.49 | I27: =I25+I26 -> -203642.26 | J27: =J25+J26 -> -208157.6
B29: 1-й год: изменение рассчитано от начала строительства (01.01.2026), т.е. включает 2026 г.

Sheet CashFlow
B2: ПОТОКИ НАЛИЧНОСТИ (в экв. долл. США) | K2: Приложение 15
B3: 1-й год (2027) - инвестиционный и льготный период; включает также освоение капвложений и расходы подготовительного периода 2026 г.
B4: ПОКАЗАТЕЛИ | C4: Ед. изм. | D4: 1 год (льготный / инвест.) | E4: 2 год | F4: 3 год | G4: 4 год | H4: 5 год | I4: 6 год | J4: 7 год
D5: 2027 | E5: 2028 | F5: 2029 | G5: 2030 | H5: 2031 | I5: 2032 | J5: 2033
B6: Выручка от реализации продукции (с НДС) | C6: USD | D6: =ProfLoss!D6 -> 9058233.4 | E6: =ProfLoss!E6 -> 36777950 | F6: =ProfLoss!F6 -> 48825712 | G6: =ProfLoss!G6 -> 58917295 | H6: =ProfLoss!H6 -> 60592704 | I6: =ProfLoss!I6 -> 61925327 | J6: =ProfLoss!J6 -> 63287696
B7: НДС, начисленный с реализации | C7: USD | D7: =-ProfLoss!D9 -> 0 | E7: =-ProfLoss!E9 -> 0 | F7: =-ProfLoss!F9 -> 0 | G7: =-ProfLoss!G9 -> 0 | H7: =-ProfLoss!H9 -> 0 | I7: =-ProfLoss!I9 -> 0 | J7: =-ProfLoss!J9 -> 0
B8: Чистая выручка от реализации продукции | C8: USD | D8: =D6+D7 -> 9058233.4 | E8: =E6+E7 -> 36777950 | F8: =F6+F7 -> 48825712 | G8: =G6+G7 -> 58917295 | H8: =H6+H7 -> 60592704 | I8: =I6+I7 -> 61925327 | J8: =J6+J7 -> 63287696
B9: Изменения в рабочем капитале (Приложение 14) | C9: USD | D9: =WorkCap!D27 -> -12384487 | E9: =WorkCap!E27 -> 6713542.8 | F9: =WorkCap!F27 -> -1851236 | G9: =WorkCap!G27 -> -1521946.5 | H9: =WorkCap!H27 -> -229861.49 | I9: =WorkCap!I27 -> -203642.26 | J9: =WorkCap!J27 -> -208157.6
B10: Наличность от продаж | C10: USD | D10: =D8+D9 -> -3326253.9 | E10: =E8+E9 -> 43491493 | F10: =F8+F9 -> 46974476 | G10: =G8+G9 -> 57395348 | H10: =H8+H9 -> 60362842 | I10: =I8+I9 -> 61721685 | J10: =J8+J9 -> 63079538
B11: Себестоимость реализованной продукции | C11: USD | D11: =-ProfLoss!D11 -> -3983085.3 | E11: =-ProfLoss!E11 -> -22748393 | F11: =-ProfLoss!F11 -> -28767726 | G11: =-ProfLoss!G11 -> -33957554 | H11: =-ProfLoss!H11 -> -35013223 | I11: =-ProfLoss!I11 -> -35782806 | J11: =-ProfLoss!J11 -> -36568133
B12: Валовые поступления наличности | C12: USD | D12: =D10+D11 -> -7309339.2 | E12: =E10+E11 -> 20743100 | F12: =F10+F11 -> 18206750 | G12: =G10+G11 -> 23437794 | H12: =H10+H11 -> 25349619 | I12: =I10+I11 -> 25938878 | J12: =J10+J11 -> 26511405
B13: Расходы периода | C13: USD | D13: =-ProfLoss!D15 -> -3408308.9 | E13: =-ProfLoss!E15 -> -4496685.3 | F13: =-ProfLoss!F15 -> -4875678.2 | G13: =-ProfLoss!G15 -> -5197583.1 | H13: =-ProfLoss!H15 -> -5304925.8 | I13: =-ProfLoss!I15 -> -5412731.7 | J13: =-ProfLoss!J15 -> -5522911.5
B14: Налоги и прочие операционные расходы | C14: USD | D14: =-ProfLoss!D16 -> -1602669.4 | E14: =-ProfLoss!E16 -> -1008756.5 | F14: =-ProfLoss!F16 -> -1131203.6 | G14: =-ProfLoss!G16 -> -1228090.4 | H14: =-ProfLoss!H16 -> -1233680.2 | I14: =-ProfLoss!I16 -> -1239587.9 | J14: =-ProfLoss!J16 -> -1245858.3
B15: Расходы подготовительного периода 2026 г. | C15: USD | D15: =-ProjCost!$E$17 -> -1194254.1 | E15: =0 -> 0 | F15: =0 -> 0 | G15: =0 -> 0 | H15: =0 -> 0 | I15: =0 -> 0 | J15: =0 -> 0
B16: Налог на прибыль | C16: USD | D16: =-ProfLoss!D21 -> -9625.4712 | E16: =-ProfLoss!E21 -> -1099291 | F16: =-ProfLoss!F21 -> -1961140.5 | G16: =-ProfLoss!G21 -> -2665862.7 | H16: =-ProfLoss!H21 -> -2774161.7 | I16: =-ProfLoss!I21 -> -2873669 | J16: =-ProfLoss!J21 -> -2975205.2
B17: Амортизация (неденежная статья, прибавляется) | C17: USD | D17: =Depreciate!$G$18 -> 667279.13 | E17: =Depreciate!$H$18 -> 2727573 | F17: =Depreciate!$I$18 -> 2781532.8 | G17: =Depreciate!$J$18 -> 2835492.6 | H17: =Depreciate!$K$18 -> 2889452.4 | I17: =Depreciate!$L$18 -> 2943412.2 | J17: =Depreciate!$M$18 -> 2997372
B18: Операционный поток наличности (A) | C18: USD | D18: =SUM(D12:D17) -> -12856918 | E18: =SUM(E12:E17) -> 16865940 | F18: =SUM(F12:F17) -> 13020261 | G18: =SUM(G12:G17) -> 17181750 | H18: =SUM(H12:H17) -> 18926304 | I18: =SUM(I12:I17) -> 19356302 | J18: =SUM(J12:J17) -> 19764802
B19: Собственный капитал (взнос заемщика) | C19: USD | D19: =FinPlan!$E$10 -> 50954665 | E19: =0 -> 0 | F19: =0 -> 0 | G19: =0 -> 0 | H19: =0 -> 0 | I19: =0 -> 0 | J19: =0 -> 0
B20: Привлеченный кредит банка | C20: USD | D20: =LOANS!$C$104 -> 18191814 | E20: =LOANS!$D$104 -> 0 | F20: =LOANS!$E$104 -> 0 | G20: =LOANS!$F$104 -> 0 | H20: =LOANS!$G$104 -> 0 | I20: =LOANS!$H$104 -> 0 | J20: =LOANS!$I$104 -> 0
B21: Инвестиции (капитальные вложения; 1-й год вкл. 2026 г.) | C21: USD | D21: -54094706 | E21: -539598.06 | F21: -539598.06 | G21: -539598.06 | H21: -539598.06 | I21: -539598.06 | J21: -539598.06
B22: Проценты за кредит (B) | C22: USD | D22: =-ProfLoss!D19 -> 0 | E22: =-ProfLoss!E19 -> -1195508.2 | F22: =-ProfLoss!F19 -> -976834.44 | G22: =-ProfLoss!G19 -> -761648.86 | H22: =-ProfLoss!H19 -> -546463.28 | I22: =-ProfLoss!I19 -> -332407.67 | J22: =-ProfLoss!J19 -> -116092.13
B23: Прочие финансовые издержки в инвестиционный период (проценты льготного периода) | C23: USD | D23: =-LOANS!$C$106 -> -1291113.5 | E23: =0 -> 0 | F23: =0 -> 0 | G23: =0 -> 0 | H23: =0 -> 0 | I23: =0 -> 0 | J23: =0 -> 0
B24: Чистые поступления наличности | C24: USD | D24: =D18+D19+D20+D21+D22+D23 -> 903741.6 | E24: =E18+E19+E20+E21+E22+E23 -> 15130834 | F24: =F18+F19+F20+F21+F22+F23 -> 11503828 | G24: =G18+G19+G20+G21+G22+G23 -> 15880503 | H24: =H18+H19+H20+H21+H22+H23 -> 17840243 | I24: =I18+I19+I20+I21+I22+I23 -> 18484296 | J24: =J18+J19+J20+J21+J22+J23 -> 19109112
B25: Выплата основного долга (C) | C25: USD | D25: =-LOANS!$C$105 -> 0 | E25: =-LOANS!$D$105 -> -3031969 | F25: =-LOANS!$E$105 -> -3031969 | G25: =-LOANS!$F$105 -> -3031969 | H25: =-LOANS!$G$105 -> -3031969 | I25: =-LOANS!$H$105 -> -3031969 | J25: =-LOANS!$I$105 -> -3031969
B26: Чистый поток наличности | C26: USD | D26: =D24+D25 -> 903741.6 | E26: =E24+E25 -> 12098865 | F26: =F24+F25 -> 8471859.2 | G26: =G24+G25 -> 12848534 | H26: =H24+H25 -> 14808274 | I26: =I24+I25 -> 15452327 | J26: =J24+J25 -> 16077143
B27: Кумулятивный поток наличности | C27: USD | D27: =D26 -> 903741.6 | E27: =D27+E26 -> 13002606 | F27: =E27+F26 -> 21474465 | G27: =F27+G26 -> 34323000 | H27: =G27+H26 -> 49131273 | I27: =H27+I26 -> 64583601 | J27: =I27+J26 -> 80660744
B29: Коэффициент обслуживания долга, DSCR [(A)/(B+C)] | C29: x | D29: ="-" -> - | E29: =IFERROR(E18/-(E22+E25),0) -> 3.9895993 | F29: =IFERROR(F18/-(F22+F25),0) -> 3.247917 | G29: =IFERROR(G18/-(G22+G25),0) -> 4.5291199 | H29: =IFERROR(H18/-(H22+H25),0) -> 5.2889932 | I29: =IFERROR(I18/-(I22+I25),0) -> 5.75331 | J29: =IFERROR(J18/-(J22+J25),0) -> 6.2784049
B30: DSCR с учётом поддерживающих капвложений [(A - инвестиции)/(B+C)] | C30: x | D30: ="-" -> - | E30: =IFERROR((E18+E21)/-(E22+E25),0) -> 3.8619586 | F30: =IFERROR((F18+F21)/-(F22+F25),0) -> 3.1133137 | G30: =IFERROR((G18+G21)/-(G22+G25),0) -> 4.3868816 | H30: =IFERROR((H18+H21)/-(H22+H25),0) -> 5.1382015 | I30: =IFERROR((I18+I21)/-(I22+I25),0) -> 5.5929243 | J30: =IFERROR((J18+J21)/-(J22+J25),0) -> 6.1069984
B31: Минимальный DSCR (2-7 годы) | D31: =MIN(E30:J30) -> 3.1133137
B32: Средний DSCR (2-7 годы) | D32: =AVERAGE(E30:J30) -> 4.7000463
B34: Проценты льготного периода (1-й год) уплачиваются за счёт собственных средств заемщика (включены в стоимость проекта, Приложение 1). Налог на прибыль - в размере начисленного (без учёта отсрочки уплаты).

Sheet BreakPoint
B2: ТОЧКА БЕЗУБЫТОЧНОСТИ (в экв. долл. США, 2030 г.) | D2: Приложение 16
B4: Общие продажи при проектной мощности | C4: =CostTotal!C26 -> 58917295
B5: в местной валюте | C5: =SalePlan!G16 -> 0
B6: в твердой валюте | C6: =SalePlan!G10 -> 58917295
B7: Фиксированная стоимость | C7: =CostTotal!F22 -> 9798442.1
B8: Переменная стоимость | C8: =CostTotal!G22 -> 30933666
B9: Маржинальный доход | C9: =C4-C8 -> 27983629
B10: Точка безубыточности (доля от выручки при проектной мощности) | C10: =IFERROR(C7/C9,0) -> 0.35014908
B11: Точка безубыточности, USD выручки | C11: =C10*C4 -> 20629837
B12: Точка безубыточности в натуральном выражении (основная продукция) | C12: =C10*ProdPlan!G17 -> 694.37014 | D12: t
B13: Запас финансовой прочности | C13: =1-C10 -> 0.64985092

Sheet NPV_IRR
B2: РАСЧЁТ NPV, IRR И СРОКА ОКУПАЕМОСТИ ПРОЕКТА (в экв. долл. США)
B3: Денежный поток проекта (до финансирования) = операционный поток (A) - инвестиции; горизонт - срок кредита (7 лет), без остаточной стоимости.
B4: ПОКАЗАТЕЛИ | C4: Ед. изм. | D4: 1 год (льготный / инвест.) | E4: 2 год | F4: 3 год | G4: 4 год | H4: 5 год | I4: 6 год | J4: 7 год
D5: 2027 | E5: 2028 | F5: 2029 | G5: 2030 | H5: 2031 | I5: 2032 | J5: 2033
B6: Период (лет) | D6: 1 | E6: 2 | F6: 3 | G6: 4 | H6: 5 | I6: 6 | J6: 7
B7: Операционный поток наличности (A) | C7: USD | D7: =CashFlow!D18 -> -12856918 | E7: =CashFlow!E18 -> 16865940 | F7: =CashFlow!F18 -> 13020261 | G7: =CashFlow!G18 -> 17181750 | H7: =CashFlow!H18 -> 18926304 | I7: =CashFlow!I18 -> 19356302 | J7: =CashFlow!J18 -> 19764802
B8: Инвестиции | C8: USD | D8: =CashFlow!D21 -> -54094706 | E8: =CashFlow!E21 -> -539598.06 | F8: =CashFlow!F21 -> -539598.06 | G8: =CashFlow!G21 -> -539598.06 | H8: =CashFlow!H21 -> -539598.06 | I8: =CashFlow!I21 -> -539598.06 | J8: =CashFlow!J21 -> -539598.06
B9: Поток наличности проекта (FCFF) | C9: USD | D9: =D7+D8 -> -66951623 | E9: =E7+E8 -> 16326342 | F9: =F7+F8 -> 12480663 | G9: =G7+G8 -> 16642152 | H9: =H7+H8 -> 18386706 | I9: =I7+I8 -> 18816704 | J9: =J7+J8 -> 19225204
B10: Ставка дисконта (WACC) | C10: % | D10: 0.11170815 | E10: 0.11170815 | F10: 0.11170815 | G10: 0.11170815 | H10: 0.11170815 | I10: 0.11170815 | J10: 0.11170815
B11: Коэффициент дисконтирования | D11: =1/(1+D10)^D6 -> 0.89951666 | E11: =1/(1+E10)^E6 -> 0.80913022 | F11: =1/(1+F10)^F6 -> 0.72782611 | G11: =1/(1+G10)^G6 -> 0.65469172 | H11: =1/(1+H10)^H6 -> 0.58890611 | I11: =1/(1+I10)^I6 -> 0.52973085 | J11: =1/(1+J10)^J6 -> 0.47650173
B12: Дисконтированный поток | C12: USD | D12: =D9*D11 -> -60224101 | E12: =E9*E11 -> 13210137 | F12: =F9*F11 -> 9083752.2 | G12: =G9*G11 -> 10895479 | H12: =H9*H11 -> 10828043 | I12: =I9*I11 -> 9967788.7 | J12: =J9*J11 -> 9160843.1
B13: Накопленный поток | C13: USD | D13: =D9 -> -66951623 | E13: =D13+E9 -> -50625282 | F13: =E13+F9 -> -38144619 | G13: =F13+G9 -> -21502467 | H13: =G13+H9 -> -3115760.9 | I13: =H13+I9 -> 15700943 | J13: =I13+J9 -> 34926147
B14: Накопленный дисконтированный поток (NPV нарастающим итогом) | C14: USD | D14: =D12 -> -60224101 | E14: =D14+E12 -> -47013964 | F14: =E14+F12 -> -37930212 | G14: =F14+G12 -> -27034733 | H14: =G14+H12 -> -16206689 | I14: =H14+I12 -> -6238900.7 | J14: =I14+J12 -> 2921942.4
B15: вспом.: окупаемость | D15: ="" | E15: =IF(AND(D13<0,E13>=0),D6-D13/E9,"") | F15: =IF(AND(E13<0,F13>=0),E6-E13/F9,"") | G15: =IF(AND(F13<0,G13>=0),F6-F13/G9,"") | H15: =IF(AND(G13<0,H13>=0),G6-G13/H9,"") | I15: =IF(AND(H13<0,I13>=0),H6-H13/I9,"") -> 5.1655848 | J15: =IF(AND(I13<0,J13>=0),I6-I13/J9,"")
B16: вспом.: дисконтированная окупаемость | D16: ="" | E16: =IF(AND(D14<0,E14>=0),D6-D14/E12,"") | F16: =IF(AND(E14<0,F14>=0),E6-E14/F12,"") | G16: =IF(AND(F14<0,G14>=0),F6-F14/G12,"") | H16: =IF(AND(G14<0,H14>=0),G6-G14/H12,"") | I16: =IF(AND(H14<0,I14>=0),H6-H14/I12,"") | J16: =IF(AND(I14<0,J14>=0),I6-I14/J12,"") -> 6.68104
B18: NPV (чистая приведённая стоимость), USD | D18: =SUM(D12:J12) -> 2921942.4
B19: IRR (внутренняя норма доходности) | D19: =IFERROR(IRR(D9:J9),"-") -> 0.12759398
B20: Индекс доходности (PI) | D20: =IFERROR(SUM(E12:J12)/-D12,0) -> 1.0485178
B21: Простой срок окупаемости, лет (от начала 1-го года) | D21: =IF(COUNT(E15:J15)>0,SUM(E15:J15),"> 7") -> 5.1655848
B22: Дисконтированный срок окупаемости, лет | D22: =IF(COUNT(E16:J16)>0,SUM(E16:J16),"> 7") -> 6.68104
