Workbook

Sheet Резюме
B2: БИЗНЕС-ПЛАН ИНВЕСТИЦИОННОГО ПРОЕКТА
B3: Строительство нового гидрометаллургического завода по переработке вольфрамового концентрата (1-я очередь)
B4: (Цех по переработке вольфрамового концентрата)
B6: 1. ОБЩИЕ СВЕДЕНИЯ
B7: Суть проекта | C7: Строительство нового гидрометаллургического завода по переработке вольфрамового концентрата (1-я очередь). Переработка 5 000 т вольфрамового концентрата в год; выпуск основной продукции - Триоксид вольфрама WO3 2 656.5 t/год при проектной мощности; реализация - экспорт.
B8: Заемщик | C8: АО «Узбекский комбинат технологических металлов» (АО «Ўзбекистон ТМК», UzTMK)
B9: Местоположение | C9: Самаркандская обл., Нурабадский р-н, 9,6 га
B10: Продукция | C10: Триоксид вольфрама WO3
B11: Производственная мощность | C11: Переработка 5 000 т вольфрамового концентрата в год; выпуск основной продукции - 2 656 t/год
B12: Рынок сбыта | C12: экспорт (100% выручки в USD)
B13: Сроки | C13: начало строительства - 01.10.2026; начало производства - 01.10.2027; выход на проектную мощность - 3-й год
B14: Стадия проработки | C14: ТЭО
B16: 2. ПАРАМЕТРЫ КРЕДИТА
B17: Кредитор | C17: Национальный банк внешнеэкономической деятельности Республики Узбекистан
B18: Сумма кредита, USD | C18: =ИНФОРМАЦИЯ!$C$26 -> 17024290
B19: Процентная ставка | C19: =ИНФОРМАЦИЯ!$C$27 -> 0.07
B20: Срок кредита | C20: 84 месяца (7 лет): льготный (инвестиционный) период - 12 месяцев (1-й год), погашение - 72 месяца (2-7 годы)
B21: Порядок погашения | C21: основной долг - ежемесячно равными долями; проценты - ежемесячно на остаток задолженности
B22: Проценты льготного периода | C22: =TEXT(LOANS!$C$106,"#,##0") & " USD - уплачиваются за счёт собственных средств заемщика (включены в стоимость проекта)" -> 1,208,252 USD - уплачиваются за счёт собственных средств заемщика (включены в стоимость проекта)
B23: Целевое назначение | C23: 30% авансовый платёж по EPC-контракту (E - проектирование, P - поставка оборудования, C - строительство)
B25: 3. СТОИМОСТЬ ПРОЕКТА И ИСТОЧНИКИ ФИНАНСИРОВАНИЯ
B26: Статья | C26: USD | D26: Доля
B27: Фиксированные активы | C27: =ProjCost!E5 -> 47761338 | D27: =IFERROR(C27/ProjCost!$E$16,0) -> 0.61136616
B28: Рабочий капитал | C28: =ProjCost!E10 -> 28280512 | D28: =IFERROR(C28/ProjCost!$E$16,0) -> 0.36200301
B29: Проценты льготного периода и расходы подготовительного периода | C29: =ProjCost!E11 -> 1910218.9 | D29: =IFERROR(C29/ProjCost!$E$16,0) -> 0.024451643
B30: Резерв | C30: =ProjCost!E14 -> 170242.9 | D30: =IFERROR(C30/ProjCost!$E$16,0) -> 0.0021791841
B31: ВСЕГО СТОИМОСТЬ ПРОЕКТА | C31: =ProjCost!E16 -> 78122312 | D31: =IFERROR(C31/ProjCost!$E$16,0) -> 1
B32: Собственные средства заемщика | C32: =FinPlan!$E$10 -> 61098022 | D32: =IFERROR(C32/ProjCost!$E$16,0) -> 0.78208159
B33: Кредит НБУ | C33: =FinPlan!$E$14 -> 17024290 | D33: =IFERROR(C33/ProjCost!$E$16,0) -> 0.21791841
B35: 4. ОСНОВНЫЕ ФИНАНСОВЫЕ ПОКАЗАТЕЛИ ПО ГОДАМ
B36: ПОКАЗАТЕЛИ | C36: Ед. изм. | D36: 1 год (льготный период) | E36: 2 год | F36: 3 год | G36: 4 год | H36: 5 год | I36: 6 год | J36: 7 год
B38: Выручка (без НДС) | C38: USD | D38: =ProfLoss!D10 -> 28331250 | E38: =ProfLoss!E10 -> 2.4740556e+08 | F38: =ProfLoss!F10 -> 3.079196e+08 | G38: =ProfLoss!G10 -> 3.186764e+08 | H38: =ProfLoss!H10 -> 325686900 | I38: =ProfLoss!I10 -> 3.3285148e+08 | J38: =ProfLoss!J10 -> 340175451
B39: EBITDA | C39: USD | D39: =ProfLoss!D27 -> 4067929.8 | E39: =ProfLoss!E27 -> 22679487 | F39: =ProfLoss!F27 -> 28130752 | G39: =ProfLoss!G27 -> 30221089 | H39: =ProfLoss!H27 -> 30902858 | I39: =ProfLoss!I27 -> 31599285 | J39: =ProfLoss!J27 -> 32312606
B40: Чистая прибыль | C40: USD | D40: =ProfLoss!D22 -> 2927686.4 | E40: =ProfLoss!E22 -> 16162513 | F40: =ProfLoss!F22 -> 20929536 | G40: =ProfLoss!G22 -> 22836995 | H40: =ProfLoss!H22 -> 23547172 | I40: =ProfLoss!I22 -> 24271186 | J40: =ProfLoss!J22 -> 25015911
B41: Операционный поток наличности (A) | C41: USD | D41: =CashFlow!D18 -> -25431200 | E41: =CashFlow!E18 -> 5266470.1 | F41: =CashFlow!F18 -> 14249199 | G41: =CashFlow!G18 -> 24697202 | H41: =CashFlow!H18 -> 25548304 | I41: =CashFlow!I18 -> 26090595 | J41: =CashFlow!J18 -> 26645386
B42: Обслуживание долга (проценты + основной долг) | C42: USD | D42: =LOANS!$C$107 -> 1208251.7 | E42: =LOANS!$D$107 -> 3956163.8 | F42: =LOANS!$E$107 -> 3751524.2 | G42: =LOANS!$F$107 -> 3550149 | H42: =LOANS!$G$107 -> 3348773.7 | I42: =LOANS!$H$107 -> 3148455.8 | J42: =LOANS!$I$107 -> 2946023.1
B43: Чистый поток наличности | C43: USD | D43: =CashFlow!D26 -> 3721522.2 | E43: =CashFlow!E26 -> 833883.94 | F43: =CashFlow!F26 -> 10021253 | G43: =CashFlow!G26 -> 20670631 | H43: =CashFlow!H26 -> 21723108 | I43: =CashFlow!I26 -> 22465717 | J43: =CashFlow!J26 -> 23222941
B44: Кумулятивный поток наличности | C44: USD | D44: =CashFlow!D27 -> 3721522.2 | E44: =CashFlow!E27 -> 4555406.1 | F44: =CashFlow!F27 -> 14576659 | G44: =CashFlow!G27 -> 35247290 | H44: =CashFlow!H27 -> 56970399 | I44: =CashFlow!I27 -> 79436115 | J44: =CashFlow!J27 -> 1.0265906e+08
B45: DSCR (с учётом поддерживающих капвложений) | C45: x | D45: =CashFlow!D30 -> - | E45: =CashFlow!E30 -> 1.2107809 | F45: =CashFlow!F30 -> 3.6712484 | G45: =CashFlow!G30 -> 6.8224687 | H45: =CashFlow!H30 -> 7.4868846 | I45: =CashFlow!I30 -> 8.1354714 | J45: =CashFlow!J30 -> 8.8828101
B46: Задолженность по кредиту на конец года | C46: USD | D46: =LOANS!$C$108 -> 17024290 | E46: =LOANS!$D$108 -> 14186908 | F46: =LOANS!$E$108 -> 11349526 | G46: =LOANS!$F$108 -> 8512144.8 | H46: =LOANS!$G$108 -> 5674763.2 | I46: =LOANS!$H$108 -> 2837381.6 | J46: =LOANS!$I$108 -> 0
B48: 5. ПОКАЗАТЕЛИ ЭФФЕКТИВНОСТИ И УСТОЙЧИВОСТИ
B49: NPV проекта за 7 лет, USD | C49: =NPV_IRR!D18 -> 4404865.2
B50: IRR проекта за 7 лет | C50: =NPV_IRR!D19 -> 0.13187811
B51: Индекс доходности (PI) | C51: =NPV_IRR!D20 -> 1.0669814
B52: Простой срок окупаемости, лет | C52: =NPV_IRR!D21 -> 5.2083632
B53: Дисконтированный срок окупаемости, лет | C53: =NPV_IRR!D22 -> 6.6439041
B54: Минимальный / средний DSCR (2-7 годы) | C54: =TEXT(CashFlow!D31,"0.00") & "x / " & TEXT(CashFlow!D32,"0.00") & "x" -> 1.21x / 6.03x
B55: Точка безубыточности при проектной мощности, % от выручки | C55: =BreakPoint!C10 -> 0.29841943
B57: 6. ВЫПОЛНЕНИЕ УСЛОВИЙ ФИНАНСИРОВАНИЯ
B58: Положительный чистый поток наличности в каждом из 1-7 годов | C58: =IF(MIN(CashFlow!D26:J26)>0,"Да","Нет") -> Да
B59: Чистая прибыль в каждом из 1-7 годов | C59: =IF(MIN(ProfLoss!D22:J22)>0,"Да","Нет") -> Да
B60: Погашение кредита в течение 6 лет после льготного периода | C60: =IF(ABS(LOANS!$I$108)<1,"Да","Нет") -> Да
B61: Проценты льготного периода покрыты собственными средствами | C61: =IF(ProjCost!E12>0,"Да","Нет") -> Да
B62: Дисконтированный срок окупаемости - в пределах срока кредита (7 лет) | C62: =IF(AND(ISNUMBER(NPV_IRR!D22),NPV_IRR!D22<=7),"Да","Нет") -> Да
B64: 7. ОСНОВНЫЕ ДОПУЩЕНИЯ
B65: - Производственные, затратные, налоговые и инвестиционные показатели приняты по ТЭО проекта; цены реализации - на консервативном уровне.
B66: - Кредитор - Национальный банк внешнеэкономической деятельности Республики Узбекистан. Сумма кредита определена по 30% авансу по EPC-контрактам (распределение 78 млн USD между тремя проектами - лист «ИНФОРМАЦИЯ»).
B67: - Кредит: 7% годовых, 84 месяца, льготный период 12 месяцев, погашение основного долга ежемесячно равными долями; база начисления процентов - 360 дней.
B68: - Все затраты сверх суммы кредита финансируются за счёт собственных средств заемщика.
B69: - Кредит выдаётся единовременно в начале 1-го года; проценты 1-го года капитализируются в стоимость основных средств.
B70: - Резерв на непредвиденные расходы - 1% суммы кредита.
B72: 8. ОСНОВНЫЕ РИСКИ И МЕРЫ ПО ИХ СНИЖЕНИЮ
B73: Ценовой риск | C73: ="Точка безубыточности при проектной мощности - " & TEXT(BreakPoint!C10,"0%") & " выручки; цены реализации в плане приняты консервативно. Меры: долгосрочные контракты на реализацию, мониторинг рыночных цен." -> Точка безубыточности при проектной мощности - 30% выручки; цены реализации в плане приняты консервативно. Меры: долгосрочные контракты на реализацию, мониторинг рыночных цен.
B74: Валютный риск | C74: ="Доля экспорта в выручке: " & TEXT(SalePlan!F8/SalePlan!F14,"0%") & "; цены продукции установлены в USD; кредит - в USD (естественное хеджирование валютной позиции)." -> Доля экспорта в выручке: 100%; цены продукции установлены в USD; кредит - в USD (естественное хеджирование валютной позиции).
B75: Риск освоения мощностей | C75: ="Освоение мощности: 1-й год - " & TEXT(ProdPlan!D11,"0%") & ", 2-й год - " & TEXT(ProdPlan!E11,"0%") & ", 3-й год - " & TEXT(ProdPlan!F11,"0%") & "; льготный период 12 мес. и запас DSCR (мин. " & TEXT(CashFlow!D31,"0.00") & "x) покрывают период выхода на мощность." -> Освоение мощности: 1-й год - 10%, 2-й год - 83%, 3-й год - 100%; льготный период 12 мес. и запас DSCR (мин. 1.21x) покрывают период выхода на мощность.
B76: Строительный риск | C76: ="Капитальные затраты приняты в фиксированных ценах (EPC-контракт: проектирование, поставка, строительство); превышение сметы финансируется за счёт собственных средств заемщика." -> Капитальные затраты приняты в фиксированных ценах (EPC-контракт: проектирование, поставка, строительство); превышение сметы финансируется за счёт собственных средств заемщика.
B77: Сырьевой риск | C77: ="Основное сырьё - Вольфрамовый концентрат 55%: " & TEXT(RawMat!F24/CostTotal!C22,"0%") & " затрат при проектной мощности (с учётом прочих материалов). Меры: долгосрочные договоры поставки." -> Основное сырьё - Вольфрамовый концентрат 55%: 93% затрат при проектной мощности (с учётом прочих материалов). Меры: долгосрочные договоры поставки.

Sheet ИНФОРМАЦИЯ
B2: ДАННЫЕ ПО ПРОЕКТУ
B4: ЗАЕМЩИК | C4: АО «Узбекский комбинат технологических металлов» (АО «Ўзбекистон ТМК», UzTMK)
B5: ИНН | C5: - (заполняется заемщиком)
B6: ДЕЯТЕЛЬНОСТЬ | C6: Добыча и переработка редких и тугоплавких металлов (вольфрам, молибден)
B7: НАИМЕНОВАНИЕ ПРОЕКТА | C7: Строительство нового гидрометаллургического завода по переработке вольфрамового концентрата (1-я очередь) (Цех по переработке вольфрамового концентрата)
B8: МЕСТО РЕАЛИЗАЦИИ | C8: Самаркандская обл., Нурабадский р-н, 9,6 га
B9: ПРОИЗВОДСТВЕННАЯ МОЩНОСТЬ | C9: Переработка 5 000 т вольфрамового концентрата в год
B10: ОСНОВНАЯ ПРОДУКЦИЯ | C10: Триоксид вольфрама WO3
B11: СТАДИЯ ПРОРАБОТКИ | C11: ТЭО (технико-экономическое обоснование)
B12: НАЧАЛО СТРОИТЕЛЬСТВА | C12: 01.10.2026
B13: НАЧАЛО ПРОИЗВОДСТВА | C13: 01.10.2027
B14: СРОК РЕАЛИЗАЦИИ (по данным заемщика) | C14: ноябрь 2027 г.
B16: УЧАСТНИКИ ПРОЕКТА
B17: Заемщик (инициатор проекта) | C17: АО «Узбекский комбинат технологических металлов» (АО «Ўзбекистон ТМК», UzTMK)
B18: Доля заемщика в проекте | C18: 100%
B19: Кредитор №1 | C19: Национальный банк внешнеэкономической деятельности Республики Узбекистан
B20: Генеральный подрядчик | C20: EPC-подрядчик (по EPC-контракту)
B22: ВАЛЮТА ПРОЕКТА | C22: Доллар США (экв.)
B23: 1 USD = (сум, средний курс 1-го года) | C23: 12231.234
B25: УСЛОВИЯ КРЕДИТА
B26: Сумма кредита, USD | C26: =O41 -> 17024290
B27: Процентная ставка, % годовых | C27: 0.07
B28: Срок кредита, месяцев | C28: 84
B29: Льготный период по основному долгу, месяцев | C29: 12
B30: Инвестиционный период, месяцев | C30: 12
B31: Дата выдачи кредита | C31: 46388
B32: База начисления процентов, дней в году (по форме банка) | C32: 360
B33: Погашение основного долга | C33: ежемесячно равными долями: 72 платежа, со 2-го по 7-й год
B34: Уплата процентов | C34: ежемесячно; в льготный период (1-й год) - за счёт собственных средств заемщика (включены в стоимость проекта)
B35: Целевое назначение | C35: 30% авансовый платёж по EPC-контракту (данные заемщика)
B36: Резерв (непредвиденные расходы) - % от суммы кредита (по форме банка) | C36: 0.01
B38: РАСПРЕДЕЛЕНИЕ КРЕДИТА 78 МЛН USD МЕЖДУ ПРОЕКТАМИ (по 30% авансу EPC-контрактов, файл заемщика от 14.10.2026)
B39: Проект | C39: Мощность | D39: Стоимость проекта, млн USD | E39: EPC: E (Engineering), млрд сум | F39: EPC: P (Procurement), млрд сум | G39: EPC: C (Construction), млрд сум | H39: EPC итого, млрд сум | I39: Курс EPC (тыс. сум/USD) | J39: EPC итого, экв. млн USD | K39: 30% аванс, млрд сум | L39: Курс аванса (тыс. сум/USD) | M39: 30% аванс, млн USD | N39: Доля в кредите | O39: Кредит, USD
B40: Освоение центральной части вольфрамового месторождения Сарикуль (1-я очередь) | C40: Переработка 600 тыс. т руды в год | D40: 158 | E40: 116.0323 | F40: 532.896 | G40: 1041.5674 | H40: =E40+F40+G40 -> 1690.4957 | I40: 12.2 | J40: =H40/I40 -> 138.56522 | K40: =H40*30% -> 507.1487 | L40: 11.838 | M40: =K40/L40 -> 42.840742 | N40: =M40/$M$43 -> 0.54851149 | O40: =N40*$O$44 -> 42783896
B41: Строительство нового гидрометаллургического завода по переработке вольфрамового концентрата (1-я очередь) | C41: Переработка 5 000 т вольфрамового концентрата в год | D41: 80 | E41: 25.272 | F41: 293.4 | G41: 353.99904 | H41: =E41+F41+G41 -> 672.67104 | I41: 12 | J41: =H41/I41 -> 56.05592 | K41: =H41*30% -> 201.80131 | L41: 11.838 | M41: =K41/L41 -> 17.046909 | N41: =M41/$M$43 -> 0.21826012 | O41: =N41*$O$44 -> 17024290
B42: Строительство нового гидрометаллургического завода по переработке промышленного продукта - молибденового огарка | C42: Переработка 5 000 т молибденового огарка (концентрата) в год | D42: 65 | E42: 25.35648 | F42: 251.13528 | G42: 442.311 | H42: =E42+F42+G42 -> 718.80276 | I42: 12 | J42: =H42/I42 -> 59.90023 | K42: =H42*30% -> 215.64083 | L42: 11.838 | M42: =K42/L42 -> 18.215985 | N42: =M42/$M$43 -> 0.23322838 | O42: =N42*$O$44 -> 18191814
B43: ИТОГО | D43: =SUM(D40:D42) -> 303 | E43: =SUM(E40:E42) -> 166.66078 | F43: =SUM(F40:F42) -> 1077.4313 | G43: =SUM(G40:G42) -> 1837.8774 | H43: =SUM(H40:H42) -> 3081.9695 | J43: =SUM(J40:J42) -> 254.52137 | K43: =SUM(K40:K42) -> 924.59084 | M43: =SUM(M40:M42) -> 78.103636 | N43: =SUM(N40:N42) -> 1 | O43: =SUM(O40:O42) -> 78000000
N44: Лимит кредита, USD | O44: 78000000
B46: Распределение кредита - пропорционально 30% авансу по EPC-контрактам, с приведением к лимиту 78,0 млн USD.

Sheet ProjCost
B2: ПЕРВОНАЧАЛЬНАЯ СТОИМОСТЬ ПРОЕКТА (в экв. долл. США) | F2: Приложение 1
B3: Инвестиционный период: с начала строительства до конца 1-го года (льготный период по кредиту).
B4: Наименование затрат | C4: МЕСТНАЯ ВАЛЮТА | D4: ТВЕРДАЯ ВАЛЮТА | E4: ВСЕГО | F4: СТРУКТУРА (%)
B5: ВСЕГО ФИКСИРОВАННЫЕ АКТИВЫ | C5: =SUM(C6:C9) -> 0 | D5: =SUM(D6:D9) -> 47761338 | E5: =SUM(E6:E9) -> 47761338 | F5: =IFERROR(E5/$E$16,0) -> 0.61136616
B6: Здания, сооружения и передаточные устройства | C6: 0 | D6: 28395000 | E6: =C6+D6 -> 28395000 | F6: =IFERROR(E6/$E$16,0) -> 0.36346851
B7: Машины и оборудование | C7: 0 | D7: 19089552 | E7: =C7+D7 -> 19089552 | F7: =IFERROR(E7/$E$16,0) -> 0.24435467
B8: Транспортные средства | C8: 0 | D8: 223214.29 | E8: =C8+D8 -> 223214.29 | F8: =IFERROR(E8/$E$16,0) -> 0.0028572412
B9: Мебель, оргтехника и офисное оборудование | C9: 0 | D9: 53571.429 | E9: =C9+D9 -> 53571.429 | F9: =IFERROR(E9/$E$16,0) -> 0.00068573788
B10: РАБОЧИЙ КАПИТАЛ | C10: =WorkCap!D23-D10 -> 17296073 | D10: =WorkCap!D16 -> 10984439 | E10: =C10+D10 -> 28280512 | F10: =IFERROR(E10/$E$16,0) -> 0.36200301
B11: ПРОЧИЕ ФИНАНСОВЫЕ ИЗДЕРЖКИ, ВКЛЮЧАЯ: | C11: =SUM(C12:C13) -> 701967.23 | D11: =SUM(D12:D13) -> 1208251.7 | E11: =SUM(E12:E13) -> 1910218.9 | F11: =IFERROR(E11/$E$16,0) -> 0.024451643
B12: Проценты по кредиту за льготный период (1-й год) - за счёт собственных средств | C12: 0 | D12: =LOANS!$C$106 -> 1208251.7 | E12: =C12+D12 -> 1208251.7 | F12: =IFERROR(E12/$E$16,0) -> 0.015466154
B13: Расходы подготовительного периода (административные и пусковые расходы) | C13: 701967.23 | D13: 0 | E13: =C13+D13 -> 701967.23 | F13: =IFERROR(E13/$E$16,0) -> 0.0089854898
B14: НЕПРЕДВИДЕННЫЕ РАСХОДЫ/РЕЗЕРВ (1% от суммы кредита) | C14: 0 | D14: =ИНФОРМАЦИЯ!$C$26*ИНФОРМАЦИЯ!$C$36 -> 170242.9 | E14: =C14+D14 -> 170242.9 | F14: =IFERROR(E14/$E$16,0) -> 0.0021791841
B16: ВСЕГО ПЕРВОНАЧАЛЬНАЯ СТОИМОСТЬ ПРОЕКТА | C16: =C5+C10+C11+C14 -> 17998040 | D16: =D5+D10+D11+D14 -> 60124271 | E16: =E5+E10+E11+E14 -> 78122312 | F16: =IFERROR(E16/$E$16,0) -> 1

Sheet FinPlan
B2: ФИНАНСОВЫЙ ПЛАН (в экв. долл. США) | G2: Приложение 2
B4: ПОКАЗАТЕЛИ | C4: МЕСТНАЯ ВАЛЮТА | D4: ТВЁРДАЯ ВАЛЮТА | E4: ВСЕГО | F4: СТРУКТУРА (%) | G4: ДОЛЯ В ФИНАНСИРОВАНИИ
B5: СОБСТВЕННЫЙ КАПИТАЛ
B6: АО «Узбекский комбинат технологических металлов» (АО «Ўзбекистон ТМК», UzTMK)
B7: Фиксированные активы | C7: ='Share of costs'!C6 -> 0 | D7: ='Share of costs'!D6 -> 30737048 | E7: =C7+D7 -> 30737048 | F7: =IFERROR(E7/$E$10,0) -> 0.50307763
B8: Рабочий капитал | C8: ='Share of costs'!C11 -> 17296073 | D8: ='Share of costs'!D11 -> 10984439 | E8: =C8+D8 -> 28280512 | F8: =IFERROR(E8/$E$10,0) -> 0.46287116
B9: Денежные средства (финансовые издержки льготного периода, расходы подготовительного периода, резерв) | C9: ='Share of costs'!C12+'Share of costs'!C15 -> 701967.23 | D9: ='Share of costs'!D12+'Share of costs'!D15 -> 1378494.6 | E9: =C9+D9 -> 2080461.8 | F9: =IFERROR(E9/$E$10,0) -> 0.034051214
B10: ВСЕГО | C10: =SUM(C7:C9) -> 17998040 | D10: =SUM(D7:D9) -> 43099982 | E10: =SUM(E7:E9) -> 61098022 | F10: =IFERROR(E10/$E$10,0) -> 1 | G10: =IFERROR(E10/$E$15,0) -> 0.78208159
B11: КРЕДИТЫ
B12: Национальный банк внешнеэкономической деятельности Республики Узбекистан (7% годовых, 84 мес., льготный период 12 мес.) | C12: =C13 -> 0 | D12: =D13 -> 17024290 | E12: =C12+D12 -> 17024290 | F12: =IFERROR(E12/$E$14,0) -> 1
B13: Фиксированные активы (30% аванс по EPC-контракту) | C13: ='Share of costs'!E6 -> 0 | D13: ='Share of costs'!F6 -> 17024290 | E13: =C13+D13 -> 17024290 | F13: =IFERROR(E13/$E$14,0) -> 1
B14: ВСЕГО | C14: =C12 -> 0 | D14: =D12 -> 17024290 | E14: =E12 -> 17024290 | F14: =IFERROR(E14/$E$14,0) -> 1 | G14: =IFERROR(E14/$E$15,0) -> 0.21791841
B15: ВСЕГО ФИНАНСИРОВАНИЯ | C15: =C14+C10 -> 17998040 | D15: =D14+D10 -> 60124271 | E15: =E14+E10 -> 78122312 | G15: =IFERROR(E15/$E$15,0) -> 1

Sheet Share of costs
B2: ПЕРВОНАЧАЛЬНАЯ СТОИМОСТЬ ПРОЕКТА ПО ИСТОЧНИКАМ ФИНАНСИРОВАНИЯ (в экв. долл. США) | H2: Приложение 3
B4: Наименование затрат | C4: Собственные средства заемщика | E4: Кредит НБУ | G4: Всего
C5: в местной валюте | D5: в твердой валюте | E5: в местной валюте | F5: в твердой валюте | G5: в местной валюте | H5: в твердой валюте
B6: ВСЕГО ФИКСИРОВАННЫЕ АКТИВЫ | C6: =SUM(C7:C10) -> 0 | D6: =SUM(D7:D10) -> 30737048 | E6: =SUM(E7:E10) -> 0 | F6: =SUM(F7:F10) -> 17024290 | G6: =SUM(G7:G10) -> 0 | H6: =SUM(H7:H10) -> 47761338
B7: Здания, сооружения и передаточные устройства | C7: =ProjCost!$C$6 -> 0 | D7: =ProjCost!$D$6-F7 -> 18796222 | E7: 0 | F7: =ИНФОРМАЦИЯ!$C$26*(1-ИНФОРМАЦИЯ!$F$41/ИНФОРМАЦИЯ!$H$41)*ProjCost!$E$6/(ProjCost!$E$6) -> 9598778.1 | G7: =C7+E7 -> 0 | H7: =D7+F7 -> 28395000
B8: Машины и оборудование | C8: =ProjCost!$C$7 -> 0 | D8: =ProjCost!$D$7-F8 -> 11770167 | E8: 0 | F8: =ИНФОРМАЦИЯ!$C$26*ИНФОРМАЦИЯ!$F$41/ИНФОРМАЦИЯ!$H$41*ProjCost!$E$7/(ProjCost!$E$7+ProjCost!$E$8+ProjCost!$E$9) -> 7319385.4 | G8: =C8+E8 -> 0 | H8: =D8+F8 -> 19089552
B9: Транспортные средства | C9: =ProjCost!$C$8 -> 0 | D9: =ProjCost!$D$8-F9 -> 137628.65 | E9: 0 | F9: =ИНФОРМАЦИЯ!$C$26*ИНФОРМАЦИЯ!$F$41/ИНФОРМАЦИЯ!$H$41*ProjCost!$E$8/(ProjCost!$E$7+ProjCost!$E$8+ProjCost!$E$9) -> 85585.632 | G9: =C9+E9 -> 0 | H9: =D9+F9 -> 223214.29
B10: Мебель, оргтехника и офисное оборудование | C10: =ProjCost!$C$9 -> 0 | D10: =ProjCost!$D$9-F10 -> 33030.877 | E10: 0 | F10: =ИНФОРМАЦИЯ!$C$26*ИНФОРМАЦИЯ!$F$41/ИНФОРМАЦИЯ!$H$41*ProjCost!$E$9/(ProjCost!$E$7+ProjCost!$E$8+ProjCost!$E$9) -> 20540.552 | G10: =C10+E10 -> 0 | H10: =D10+F10 -> 53571.429
B11: РАБОЧИЙ КАПИТАЛ | C11: =ProjCost!$C$10 -> 17296073 | D11: =ProjCost!$D$10 -> 10984439 | E11: 0 | F11: 0 | G11: =C11+E11 -> 17296073 | H11: =D11+F11 -> 10984439
B12: ПРОЧИЕ ФИНАНСОВЫЕ ИЗДЕРЖКИ | C12: =ProjCost!$C$11 -> 701967.23 | D12: =ProjCost!$D$11 -> 1208251.7 | E12: 0 | F12: 0 | G12: =C12+E12 -> 701967.23 | H12: =D12+F12 -> 1208251.7
B13: в т.ч. проценты по кредиту за льготный период | C13: =ProjCost!$C$12 -> 0 | D13: =ProjCost!$D$12 -> 1208251.7 | E13: 0 | F13: 0 | G13: =C13+E13 -> 0 | H13: =D13+F13 -> 1208251.7
B14: в т.ч. расходы подготовительного периода | C14: =ProjCost!$C$13 -> 701967.23 | D14: =ProjCost!$D$13 -> 0 | E14: 0 | F14: 0 | G14: =C14+E14 -> 701967.23 | H14: =D14+F14 -> 0
B15: НЕПРЕДВИДЕННЫЕ РАСХОДЫ/РЕЗЕРВ | C15: =ProjCost!$C$14 -> 0 | D15: =ProjCost!$D$14 -> 170242.9 | E15: 0 | F15: 0 | G15: =C15+E15 -> 0 | H15: =D15+F15 -> 170242.9
B17: ВСЕГО ПЕРВОНАЧАЛЬНАЯ СТОИМОСТЬ ПРОЕКТА | C17: =C6+C11+C12+C15 -> 17998040 | D17: =D6+D11+D12+D15 -> 43099982 | E17: =E6+E11+E12+E15 -> 0 | F17: =F6+F11+F12+F15 -> 17024290 | G17: =G6+G11+G12+G15 -> 17998040 | H17: =H6+H11+H12+H15 -> 60124271
B18: Итого по источнику | C18: =C17+D17 -> 61098022 | E18: =E17+F17 -> 17024290 | G18: =G17+H17 -> 78122312
B20: Кредит НБУ направляется на 30% авансовый платёж по EPC-контракту; распределение по группам активов - пропорционально составу EPC-контракта: P (поставка оборудования) - машины и оборудование, E+C (проектирование и строительство) - здания, сооружения и прочие объекты.

Sheet Depreciate
B2: АМОРТИЗАЦИЯ (в долл. США) | N2: Приложение 4
B3: Линейный метод. Проценты льготного периода капитализированы в стоимость основных средств (МСФО IAS 23).
B5: ОБЪЕКТЫ АМОРТИЗАЦИИ | C5: Группа основных средств | D5: Первоначальная стоимость | E5: Срок, лет | F5: Норма, % | G5: 1 год | H5: 2 год | I5: 3 год | J5: 4 год | K5: 5 год | L5: 6 год | M5: 7 год
B7: Разработка проектных документов (ТЭО и ЗВОС) | C7: Здания, сооружения и передаточные устройства | D7: 147321.43 | E7: 50 | F7: =1/E7 -> 0.02 | G7: 736.60714 | H7: 2946.4286 | I7: 2946.4286 | J7: 2946.4286 | K7: 2946.4286 | L7: 2946.4286 | M7: 2946.4286
B8: Разработка PFS проекта | C8: Здания, сооружения и передаточные устройства | D8: 321428.57 | E8: 50 | F8: =1/E8 -> 0.02 | G8: 1607.1429 | H8: 6428.5714 | I8: 6428.5714 | J8: 6428.5714 | K8: 6428.5714 | L8: 6428.5714 | M8: 6428.5714
B9: Проектно-инженерные работы | C9: Здания, сооружения и передаточные устройства | D9: 2232142.9 | E9: 50 | F9: =1/E9 -> 0.02 | G9: 11160.714 | H9: 44642.857 | I9: 44642.857 | J9: 44642.857 | K9: 44642.857 | L9: 44642.857 | M9: 44642.857
B10: Приобретение оборудования | C10: Машины и оборудование | D10: 18256161 | E10: 10 | F10: =1/E10 -> 0.1 | G10: 456404.02 | H10: 1825616.1 | I10: 1825616.1 | J10: 1825616.1 | K10: 1825616.1 | L10: 1825616.1 | M10: 1825616.1
B11: Строительство | C11: Здания, сооружения и передаточные устройства | D11: 22238750 | E11: 50 | F11: =1/E11 -> 0.02 | G11: 111193.75 | H11: 444775 | I11: 444775 | J11: 444775 | K11: 444775 | L11: 444775 | M11: 444775
B12: Земляные работы | C12: Здания, сооружения и передаточные устройства | D12: 178571.43 | E12: 50 | F12: =1/E12 -> 0.02 | G12: 892.85714 | H12: 3571.4286 | I12: 3571.4286 | J12: 3571.4286 | K12: 3571.4286 | L12: 3571.4286 | M12: 3571.4286
B13: Адаптация проектной документации | C13: Здания, сооружения и передаточные устройства | D13: 89285.714 | E13: 50 | F13: =1/E13 -> 0.02 | G13: 446.42857 | H13: 1785.7143 | I13: 1785.7143 | J13: 1785.7143 | K13: 1785.7143 | L13: 1785.7143 | M13: 1785.7143
B14: Строительство инфраструктуры (вода, газ, электроэнергия) | C14: Здания, сооружения и передаточные устройства | D14: 3125000 | E14: 50 | F14: =1/E14 -> 0.02 | G14: 15625 | H14: 62500 | I14: 62500 | J14: 62500 | K14: 62500 | L14: 62500 | M14: 62500
B15: Технологический транспорт | C15: Транспортные средства | D15: 223214.29 | E15: 10 | F15: =1/E15 -> 0.1 | G15: 5580.3571 | H15: 22321.429 | I15: 22321.429 | J15: 22321.429 | K15: 22321.429 | L15: 22321.429 | M15: 22321.429
B16: Солнечные панели | C16: Машины и оборудование | D16: 714285.71 | E16: 20 | F16: =1/E16 -> 0.05 | G16: 8928.5714 | H16: 35714.286 | I16: 35714.286 | J16: 35714.286 | K16: 35714.286 | L16: 35714.286 | M16: 35714.286
B17: Камеры наблюдения и вертикальные стойки | C17: Мебель, оргтехника и офисное оборудование | D17: 53571.429 | E17: 5 | F17: =1/E17 -> 0.2 | G17: 2678.5714 | H17: 10714.286 | I17: 10714.286 | J17: 10714.286 | K17: 10714.286 | L17: 8035.7143 | M17: 0
B18: Дополнительные расходы | C18: Здания, сооружения и передаточные устройства | D18: 62500 | E18: 50 | F18: =1/E18 -> 0.02 | G18: 312.5 | H18: 1250 | I18: 1250 | J18: 1250 | K18: 1250 | L18: 1250 | M18: 1250
B19: Поддерживающие капвложения (% от первоначальной стоимости ОС) | C19: Машины и оборудование | D19: 2977639.5 | E19: 10 | F19: =1/E19 -> 0.1 | G19: 1985.093 | H19: 59552.79 | I19: 107195.02 | J19: 154837.25 | K19: 202479.49 | L19: 250121.72 | M19: 297763.95
B20: Капитализированные проценты по кредиту за льготный период (1-й год) | C20: Затраты по займам (МСФО IAS 23) | D20: =LOANS!$C$106 -> 1208251.7 | E20: 50 | F20: =1/E20 -> 0.02 | G20: =D20/E20*3/12 -> 6041.2584 | H20: =D20/E20 -> 24165.033 | I20: =D20/E20 -> 24165.033 | J20: =D20/E20 -> 24165.033 | K20: =D20/E20 -> 24165.033 | L20: =D20/E20 -> 24165.033 | M20: =D20/E20 -> 24165.033
B21: ВСЕГО | C21: Х | D21: =SUM(D7:D20) -> 51828123 | G21: =SUM(G7:G20) -> 623592.87 | H21: =SUM(H7:H20) -> 2545983.9 | I21: =SUM(I7:I20) -> 2593626.1 | J21: =SUM(J7:J20) -> 2641268.4 | K21: =SUM(K7:K20) -> 2688910.6 | L21: =SUM(L7:L20) -> 2733874.3 | M21: =SUM(M7:M20) -> 2773480.8
B22: в т.ч. в себестоимости продукции | G22: =G21-G23 -> 620914.3 | H22: =H21-H23 -> 2535269.6 | I22: =I21-I23 -> 2582911.8 | J22: =J21-J23 -> 2630554.1 | K22: =K21-K23 -> 2678196.3 | L22: =L21-L23 -> 2725838.5 | M22: =M21-M23 -> 2773480.8
B23: в т.ч. в административных расходах | G23: 2678.5714 | H23: 10714.286 | I23: 10714.286 | J23: 10714.286 | K23: 10714.286 | L23: 8035.7143 | M23: 0
B25: Капитальные вложения (освоение; 1-й год вкл. подготовительный период) | G25: 47761338 | H25: 476422.32 | I25: 476422.32 | J25: 476422.32 | K25: 476422.32 | L25: 476422.32 | M25: 476422.32
B26: Накопленная амортизация | G26: =SUM($G$21:G21) -> 623592.87 | H26: =SUM($G$21:H21) -> 3169576.8 | I26: =SUM($G$21:I21) -> 5763202.9 | J26: =SUM($G$21:J21) -> 8404471.3 | K26: =SUM($G$21:K21) -> 11093382 | L26: =SUM($G$21:L21) -> 13827256 | M26: =SUM($G$21:M21) -> 16600737
B27: Остаточная стоимость основных средств (на конец года) | G27: =G25+$D$20-G21 -> 48345997 | H27: =G27+H25-H21 -> 46276435 | I27: =H27+I25-I21 -> 44159231 | J27: =I27+J25-J21 -> 41994385 | K27: =J27+K25-K21 -> 39781897 | L27: =K27+L25-L21 -> 37524445 | M27: =L27+M25-M21 -> 35227386

Sheet ProdPlan
B2: ПРОИЗВОДСТВЕННЫЙ ПЛАН | K2: Приложение 5
B4: Н А И М Е Н О В А Н И Е | C4: Ед. изм. | D4: Мощность в год | E4: Рынок сбыта | F4: Цена за единицу, USD (при проектной мощности) | G4: Выручка при полной мощности: экспорт | H4: Выручка при полной мощности: внутр. рынок
B5: Триоксид вольфрама WO3 | C5: t | D5: 2656.5 | E5: экспорт | F5: =F20 -> 117379 | G5: =D5*F5 -> 3.1181731e+08 | H5: 0
B6: Всего | G6: =SUM(G5:G5) -> 3.1181731e+08 | H6: =SUM(H5:H5) -> 0
B8: ПОКАЗАТЕЛИ | C8: Ед. изм. | D8: 1 год (льготный период) | E8: 2 год | F8: 3 год | G8: 4 год | H8: 5 год | I8: 6 год | J8: 7 год
B10: ОСВОЕНИЕ МОЩНОСТЕЙ
B11: Триоксид вольфрама WO3 | C11: % | D11: 0.10163749 | E11: 0.82971014 | F11: 1 | G11: 1 | H11: 1 | I11: 1 | J11: 1
B12: КОЛИЧЕСТВО ПРОИЗВОДСТВА
B13: Триоксид вольфрама WO3 | C13: t | D13: =$D$5*D11 -> 270 | E13: =$D$5*E11 -> 2204.125 | F13: =$D$5*F11 -> 2656.5 | G13: =$D$5*G11 -> 2656.5 | H13: =$D$5*H11 -> 2656.5 | I13: =$D$5*I11 -> 2656.5 | J13: =$D$5*J11 -> 2656.5
B14: КОЛИЧЕСТВО ДЛЯ РЕАЛИЗАЦИИ
B15: Триоксид вольфрама WO3 - экспорт | C15: t | D15: 250 | E15: 2154.125 | F15: 2623.2937 | G15: 2656.5 | H15: 2656.5 | I15: 2656.5 | J15: 2656.5
B16: Триоксид вольфрама WO3 - внутренний рынок | C16: t | D16: 0 | E16: 0 | F16: 0 | G16: 0 | H16: 0 | I16: 0 | J16: 0
B17: КОЛИЧЕСТВО ЗАПАСА ГОТОВОЙ ПРОДУКЦИИ НА КОНЕЦ ГОДА
B18: Триоксид вольфрама WO3 | C18: t | D18: =0+D13-D15-D16 -> 20 | E18: =D18+E13-E15-E16 -> 70 | F18: =E18+F13-F15-F16 -> 103.20625 | G18: =F18+G13-G15-G16 -> 103.20625 | H18: =G18+H13-H15-H16 -> 103.20625 | I18: =H18+I13-I15-I16 -> 103.20625 | J18: =I18+J13-J15-J16 -> 103.20625
B19: ЦЕНА РЕАЛИЗАЦИИ
B20: Триоксид вольфрама WO3 | C20: USD/t | D20: 113325 | E20: 114852 | F20: 117379 | G20: 119961 | H20: 122600 | I20: 125297 | J20: 128054

Sheet SalePlan
B2: ПЛАН ПРОДАЖ (в экв. долл. США, без НДС) | K2: Приложение 6
B4: ПОКАЗАТЕЛИ | C4: Ед. изм. | D4: 1 год (льготный период) | E4: 2 год | F4: 3 год | G4: 4 год | H4: 5 год | I4: 6 год | J4: 7 год
B6: ЭКСПОРТ
B7: Триоксид вольфрама WO3 | C7: USD | D7: =ProdPlan!D15*ProdPlan!D20 -> 28331250 | E7: =ProdPlan!E15*ProdPlan!E20 -> 2.4740556e+08 | F7: =ProdPlan!F15*ProdPlan!F20 -> 3.079196e+08 | G7: =ProdPlan!G15*ProdPlan!G20 -> 3.186764e+08 | H7: =ProdPlan!H15*ProdPlan!H20 -> 325686900 | I7: =ProdPlan!I15*ProdPlan!I20 -> 3.3285148e+08 | J7: =ProdPlan!J15*ProdPlan!J20 -> 340175451
B8: Всего | C8: USD | D8: =SUM(D7:D7) -> 28331250 | E8: =SUM(E7:E7) -> 2.4740556e+08 | F8: =SUM(F7:F7) -> 3.079196e+08 | G8: =SUM(G7:G7) -> 3.186764e+08 | H8: =SUM(H7:H7) -> 325686900 | I8: =SUM(I7:I7) -> 3.3285148e+08 | J8: =SUM(J7:J7) -> 340175451
B10: ВНУТРЕННИЕ ПРОДАЖИ
B11: Триоксид вольфрама WO3 | C11: USD | D11: =ProdPlan!D16*ProdPlan!D20 -> 0 | E11: =ProdPlan!E16*ProdPlan!E20 -> 0 | F11: =ProdPlan!F16*ProdPlan!F20 -> 0 | G11: =ProdPlan!G16*ProdPlan!G20 -> 0 | H11: =ProdPlan!H16*ProdPlan!H20 -> 0 | I11: =ProdPlan!I16*ProdPlan!I20 -> 0 | J11: =ProdPlan!J16*ProdPlan!J20 -> 0
B12: Всего | C12: USD | D12: =SUM(D11:D11) -> 0 | E12: =SUM(E11:E11) -> 0 | F12: =SUM(F11:F11) -> 0 | G12: =SUM(G11:G11) -> 0 | H12: =SUM(H11:H11) -> 0 | I12: =SUM(I11:I11) -> 0 | J12: =SUM(J11:J11) -> 0
B14: ВСЕГО ПРОДАЖ | C14: USD | D14: =D8+D12 -> 28331250 | E14: =E8+E12 -> 2.4740556e+08 | F14: =F8+F12 -> 3.079196e+08 | G14: =G8+G12 -> 3.186764e+08 | H14: =H8+H12 -> 325686900 | I14: =I8+I12 -> 3.3285148e+08 | J14: =J8+J12 -> 340175451
B15: Доля экспорта в выручке | C15: % | D15: =IFERROR(D8/D14,0) -> 1 | E15: =IFERROR(E8/E14,0) -> 1 | F15: =IFERROR(F8/F14,0) -> 1 | G15: =IFERROR(G8/G14,0) -> 1 | H15: =IFERROR(H8/H14,0) -> 1 | I15: =IFERROR(I8/I14,0) -> 1 | J15: =IFERROR(J8/J14,0) -> 1

Sheet RawMat
B2: СТОИМОСТЬ СЫРЬЯ И МАТЕРИАЛОВ ПРИ ПРОЕКТНОЙ МОЩНОСТИ (в экв. долл. США) | G2: Приложение 7
B3: Расчёт на 3-й год (освоение мощности 100%); цены в номинальном выражении; без НДС.
B5: НАИМЕНОВАНИЕ | C5: Ед. изм. | D5: Цена за единицу, USD | E5: Годовая потребность | F5: Годовая стоимость, USD | G5: ДОЛЯ (%) | H5: Примечание
B6: СЫРЬЁ, МАТЕРИАЛЫ И ПЕРЕМЕННЫЕ ЗАТРАТЫ С ЦЕНОЙ В ТВЁРДОЙ ВАЛЮТЕ (USD)
B7: Вольфрамовый концентрат 55% | C7: t | D7: =IFERROR(F7/E7,0) -> 51900.129 | E7: 5000 | F7: 2.5950064e+08 | G7: =IFERROR(F7/$F$24,0) -> 0.97811923 | H7: Сырьё
B8: ВСЕГО В ТВЁРДОЙ ВАЛЮТЕ | F8: =SUM(F7:F7) -> 2.5950064e+08 | G8: =IFERROR(F8/$F$24,0) -> 0.97811923
B10: СЫРЬЁ, МАТЕРИАЛЫ И ПЕРЕМЕННЫЕ ЗАТРАТЫ С ЦЕНОЙ В НАЦИОНАЛЬНОЙ ВАЛЮТЕ (UZS)
B11: Аммиачная вода 25% (на 100%) | C11: t | D11: =IFERROR(F11/E11,0) -> 211.5735 | E11: 449.61 | F11: 95125.559 | G11: =IFERROR(F11/$F$24,0) -> 0.00035855071 | H11: Вспомогательные материалы
B12: Соляная кислота 30% | C12: t | D12: =IFERROR(F12/E12,0) -> 65.644455 | E12: 9800 | F12: 643315.66 | G12: =IFERROR(F12/$F$24,0) -> 0.0024248087 | H12: Вспомогательные материалы
B13: Гидроксид натрия | C13: t | D13: =IFERROR(F13/E13,0) -> 998.8347 | E13: 2000 | F13: 1997669.4 | G13: =IFERROR(F13/$F$24,0) -> 0.0075296879 | H13: Вспомогательные материалы
B14: Карбонат натрия | C14: t | D14: =IFERROR(F14/E14,0) -> 493.61485 | E14: 3769.4 | F14: 1860631.8 | G14: =IFERROR(F14/$F$24,0) -> 0.0070131609 | H14: Вспомогательные материалы
B15: Гидроксид алюминия | C15: t | D15: =IFERROR(F15/E15,0) -> 947.52208 | E15: 163.5 | F15: 154919.86 | G15: =IFERROR(F15/$F$24,0) -> 0.00058392955 | H15: Вспомогательные материалы
B16: Хлорид аммония | C16: t | D16: =IFERROR(F16/E16,0) -> 451.48273 | E16: 2098.19 | F16: 947296.54 | G16: =IFERROR(F16/$F$24,0) -> 0.0035705845 | H16: Вспомогательные материалы
B17: Ионообменная смола | C17: t | D17: =IFERROR(F17/E17,0) -> 381.58791 | E17: 5.99 | F17: 2285.7116 | G17: =IFERROR(F17/$F$24,0) -> 8.615387e-06 | H17: Вспомогательные материалы
B18: Сульфид меди | C18: t | D18: =IFERROR(F18/E18,0) -> 213.46254 | E18: 6.79 | F18: 1449.4107 | G18: =IFERROR(F18/$F$24,0) -> 5.4631713e-06 | H18: Вспомогательные материалы
B19: Сульфид аммония | C19: t | D19: =IFERROR(F19/E19,0) -> 965.30407 | E19: 19.33 | F19: 18659.328 | G19: =IFERROR(F19/$F$24,0) -> 7.0331414e-05 | H19: Вспомогательные материалы
B20: Фильтроткань | C20: m2 | D20: =IFERROR(F20/E20,0) -> 14.64013 | E20: 4000 | F20: 58560.521 | G20: =IFERROR(F20/$F$24,0) -> 0.00022072844 | H20: Вспомогательные материалы
B21: Мешки 25 кг | C21: pcs | D21: =IFERROR(F21/E21,0) -> 0.23697446 | E21: 106260 | F21: 25180.906 | G21: =IFERROR(F21/$F$24,0) -> 9.4912784e-05 | H21: Вспомогательные материалы
B22: ВСЕГО В НАЦИОНАЛЬНОЙ ВАЛЮТЕ | F22: =SUM(F11:F21) -> 5805094.7 | G22: =IFERROR(F22/$F$24,0) -> 0.021880773
B24: ИТОГО СЫРЬЁ, МАТЕРИАЛЫ И ПРОЧИЕ ПЕРЕМЕННЫЕ ЗАТРАТЫ | F24: =F8+F22 -> 2.6530574e+08 | G24: =IFERROR(F24/$F$24,0) -> 1
B26: ПРОЧИЕ ПРОИЗВОДСТВЕННЫЕ РАСХОДЫ (постоянные)
B27: Статьи затрат | F27: Годовая стоимость, USD | H27: Состав затрат
B28: Ремонт и техническое обслуживание | F28: 945456.72 | H28: Ремонт СМР (0,5%); Ремонт оборудования (4%)
B29: Прочие производственные расходы (охрана труда, накладные и др.) | F29: 617586.5 | H29: Охрана труда; Прочие накладные СМР (0,5%); Прочие накладные оборудование (2%)
B30: Налог за пользование недрами (НДПИ) | F30: =CostSold!F19 -> 0
B31: Итого: | F31: =SUM(F28:F30) -> 1563043.2

Sheet Labour
B2: ЭНЕРГОРЕСУРСЫ И ОПЛАТА ТРУДА ПРИ ПРОЕКТНОЙ МОЩНОСТИ (в экв. долл. США) | G2: Приложение 8
B3: Расчёт на 3-й год.
B5: СТАТЬИ ЗАТРАТ | C5: Ед. изм. | D5: Годовая потребность | E5: Цена за единицу, USD | F5: Годовая стоимость, USD
B6: Электроэнергия - переменная часть 80% | C6: MWh | D6: 8388.832 | E6: =IFERROR(F6/D6,0) -> 112.58732 | F6: 944476.15
B7: Техническая вода - переменная часть 80% | C7: m3 | D7: 172529.28 | E7: =IFERROR(F7/D7,0) -> 0.63283144 | F7: 109181.95
B8: Природный газ - переменная часть 80% | C8: m3 | D8: 4675367.2 | E8: =IFERROR(F8/D8,0) -> 0.18890491 | F8: 883199.81
B9: Сброс сточных вод | C9: m3 | D9: 18463.472 | E9: =IFERROR(F9/D9,0) -> 0.48029244 | F9: 8867.866
B10: Электроэнергия - постоянная часть | F10: 236119.04
B11: Природный газ / топливо - постоянная часть | F11: 220799.95
B12: Вода - постоянная часть | F12: 27295.488
B13: ВСЕГО ЭНЕРГОРЕСУРСЫ | F13: =SUM(F6:F12) -> 2429940.3
B15: РАСЧЕТ ЗАРАБОТНОЙ ПЛАТЫ | F15: Ставка социального налога | G15: 0.12
B16: ПОКАЗАТЕЛИ | C16: Количество, чел. | D16: Среднемесячная з/плата на 1 чел., сум | E16: Среднемесячная з/плата на 1 чел., USD | F16: Годовой фонд з/платы, USD | G16: Отчисления (соц. налог), USD
B17: ПРОИЗВОДСТВЕННЫЙ ПЕРСОНАЛ
B18: Цех выщелачивания - начальник | C18: 1 | D18: 17835000 | E18: =IFERROR(F18/C18/12,0) -> 1609.0076 | F18: 19308.091 | G18: =F18*$G$15 -> 2316.9709
B19: Цех выщелачивания - операторы | C19: 16 | D19: 15457000 | E19: =IFERROR(F19/C19/12,0) -> 1394.4732 | F19: 267738.86 | G19: =F19*$G$15 -> 32128.663
B20: Цех ионного обмена - начальник | C20: 1 | D20: 17835000 | E20: =IFERROR(F20/C20/12,0) -> 1609.0076 | F20: 19308.091 | G20: =F20*$G$15 -> 2316.9709
B21: Операторы тонкой фильтрации | C21: 4 | D21: 15457000 | E21: =IFERROR(F21/C21/12,0) -> 1394.4732 | F21: 66934.714 | G21: =F21*$G$15 -> 8032.1657
B22: Операторы ионного обмена | C22: 8 | D22: 15457000 | E22: =IFERROR(F22/C22/12,0) -> 1394.4732 | F22: 133869.43 | G22: =F22*$G$15 -> 16064.331
B23: Операторы участка очистки | C23: 4 | D23: 15457000 | E23: =IFERROR(F23/C23/12,0) -> 1394.4732 | F23: 66934.714 | G23: =F23*$G$15 -> 8032.1657
B24: Цех APT и WO3 - руководитель | C24: 1 | D24: 17835000 | E24: =IFERROR(F24/C24/12,0) -> 1609.0076 | F24: 19308.091 | G24: =F24*$G$15 -> 2316.9709
B25: Выпаривание-кристаллизация | C25: 4 | D25: 15457000 | E25: =IFERROR(F25/C25/12,0) -> 1394.4732 | F25: 66934.714 | G25: =F25*$G$15 -> 8032.1657
B26: Фильтр-прессование и дробление | C26: 4 | D26: 15457000 | E26: =IFERROR(F26/C26/12,0) -> 1394.4732 | F26: 66934.714 | G26: =F26*$G$15 -> 8032.1657
B27: Пирометаллургия и очистка газов | C27: 8 | D27: 15457000 | E27: =IFERROR(F27/C27/12,0) -> 1394.4732 | F27: 133869.43 | G27: =F27*$G$15 -> 16064.331
B28: Очистка стоков - бригадир | C28: 1 | D28: 9512000 | E28: =IFERROR(F28/C28/12,0) -> 858.13736 | F28: 10297.648 | G28: =F28*$G$15 -> 1235.7178
B29: Очистка стоков - рабочие | C29: 8 | D29: 11592750 | E29: =IFERROR(F29/C29/12,0) -> 1045.8549 | F29: 100402.07 | G29: =F29*$G$15 -> 12048.249
... B37: Охрана | C37: 6 | D37: 8917500 | E37: =IFERROR(F37/C37/12,0) -> 804.50378 | F37: 57924.272 | G37: =F37*$G$15 -> 6950.9126
B38: ВСЕГО | C38: =SUM(C18:C37) -> 114 | F38: =SUM(F18:F37) -> 1524052 | G38: =SUM(G18:G37) -> 182886.23
B39: ИТОГО (фонд оплаты труда + социальный налог) | F39: =F38+G38 -> 1706938.2
B41: АДМИНИСТРАЦИЯ
B42: Генеральный директор | C42: 1 | D42: 35670000 | E42: =IFERROR(F42/C42/12,0) -> 3218.0151 | F42: 38616.181 | G42: =F42*$G$15 -> 4633.9418
B43: Заместитель ген. директора | C43: 1 | D43: 23780000 | E43: =IFERROR(F43/C43/12,0) -> 2145.3434 | F43: 25744.121 | G43: =F43*$G$15 -> 3089.2945
B44: Офисные служащие | C44: 2 | D44: 8323000 | E44: =IFERROR(F44/C44/12,0) -> 750.87019 | F44: 18020.885 | G44: =F44*$G$15 -> 2162.5062
B45: Руководитель финансового отдела | C45: 1 | D45: 14268000 | E45: =IFERROR(F45/C45/12,0) -> 1287.206 | F45: 15446.473 | G45: =F45*$G$15 -> 1853.5767
B46: Бухгалтер | C46: 1 | D46: 11890000 | E46: =IFERROR(F46/C46/12,0) -> 1072.6717 | F46: 12872.06 | G46: =F46*$G$15 -> 1544.6473
B47: Кассир | C47: 1 | D47: 8323000 | E47: =IFERROR(F47/C47/12,0) -> 750.87019 | F47: 9010.4423 | G47: =F47*$G$15 -> 1081.2531
B48: Руководитель отдела снабжения и сбыта | C48: 1 | D48: 14268000 | E48: =IFERROR(F48/C48/12,0) -> 1287.206 | F48: 15446.473 | G48: =F48*$G$15 -> 1853.5767
B49: Специалист по закупкам | C49: 1 | D49: 9512000 | E49: =IFERROR(F49/C49/12,0) -> 858.13736 | F49: 10297.648 | G49: =F49*$G$15 -> 1235.7178
B50: Специалист по сбыту | C50: 1 | D50: 9512000 | E50: =IFERROR(F50/C50/12,0) -> 858.13736 | F50: 10297.648 | G50: =F50*$G$15 -> 1235.7178
B51: Руководитель отдела кадров | C51: 1 | D51: 14268000 | E51: =IFERROR(F51/C51/12,0) -> 1287.206 | F51: 15446.473 | G51: =F51*$G$15 -> 1853.5767
B52: Специалист по кадрам | C52: 1 | D52: 9512000 | E52: =IFERROR(F52/C52/12,0) -> 858.13736 | F52: 10297.648 | G52: =F52*$G$15 -> 1235.7178
B53: Специалист по обучению | C53: 1 | D53: 9512000 | E53: =IFERROR(F53/C53/12,0) -> 858.13736 | F53: 10297.648 | G53: =F53*$G$15 -> 1235.7178
... B59: Прочий обслуживающий персонал | C59: 2 | D59: 7134000 | E59: =IFERROR(F59/C59/12,0) -> 643.60302 | F59: 15446.473 | G59: =F59*$G$15 -> 1853.5767
B60: ВСЕГО | C60: =SUM(C42:C59) -> 26 | F60: =SUM(F42:F59) -> 326950.33 | G60: =SUM(G42:G59) -> 39234.04
B61: ИТОГО (фонд оплаты труда + социальный налог) | F61: =F60+G60 -> 366184.37
B63: ОБЩАЯ СУММА | C63: =C38+C60 -> 140 | F63: =F39+F61 -> 2073122.6
B64: Заработная плата установлена в сумах и пересчитана в USD с учётом индексации и курса.

Sheet Taxes
B2: НАЛОГИ И СБОРЫ (в экв. долл. США) | K2: Приложение 9
B4: ПОКАЗАТЕЛИ | C4: Ставка | D4: 1 год (льготный период) | E4: 2 год | F4: 3 год | G4: 4 год | H4: 5 год | I4: 6 год | J4: 7 год
B6: Налоги и сборы, включаемые в расходы | D6: =SUM(D7:D11) -> 187328.59 | E6: =SUM(E7:E11) -> 632638.68 | F6: =SUM(F7:F11) -> 628878.65 | G6: =SUM(G7:G11) -> 625244.72 | H6: =SUM(H7:H11) -> 621720.33 | I6: =SUM(I7:I11) -> 618305.8 | J6: =SUM(J7:J11) -> 615003.57
B7: Налог на имущество | C7: 1.50% | D7: =CostSold!D35 -> 106126.31 | E7: =CostSold!E35 -> 415276.88 | F7: =CostSold!F35 -> 406758.38 | G7: =CostSold!G35 -> 398239.88 | H7: =CostSold!H35 -> 389721.38 | I7: =CostSold!I35 -> 381202.88 | J7: =CostSold!J35 -> 372684.38
B8: Земельный налог | D8: =CostSold!D36 -> 0 | E8: =CostSold!E36 -> 0 | F8: =CostSold!F36 -> 0 | G8: =CostSold!G36 -> 0 | H8: =CostSold!H36 -> 0 | I8: =CostSold!I36 -> 0 | J8: =CostSold!J36 -> 0
B9: Специальный рентный налог | D9: =CostSold!D37 -> 0 | E9: =CostSold!E37 -> 0 | F9: =CostSold!F37 -> 0 | G9: =CostSold!G37 -> 0 | H9: =CostSold!H37 -> 0 | I9: =CostSold!I37 -> 0 | J9: =CostSold!J37 -> 0
B10: Налог за пользование недрами (НДПИ) - в себестоимости | D10: =CostSold!D19 -> 0 | E10: =CostSold!E19 -> 0 | F10: =CostSold!F19 -> 0 | G10: =CostSold!G19 -> 0 | H10: =CostSold!H19 -> 0 | I10: =CostSold!I19 -> 0 | J10: =CostSold!J19 -> 0
B11: Социальный налог (производственный и административный персонал) | C11: 12% | D11: 81202.279 | E11: 217361.81 | F11: 222120.27 | G11: 227004.84 | H11: 231998.95 | I11: 237102.93 | J11: 242319.19
B13: Прочие налоги | D13: =D14+D15 -> 516650.54 | E13: =E14+E15 -> 2852208.2 | F13: =F14+F15 -> 3693447.6 | G13: =G14+G15 -> 4030058 | H13: =H14+H15 -> 4155383.3 | I13: =I14+I15 -> 4283150.4 | J13: =J14+J15 -> 4414572.5
B14: Налог на прибыль (Приложение 13) | D14: =ProfLoss!D21 -> 516650.54 | E14: =ProfLoss!E21 -> 2852208.2 | F14: =ProfLoss!F21 -> 3693447.6 | G14: =ProfLoss!G21 -> 4030058 | H14: =ProfLoss!H21 -> 4155383.3 | I14: =ProfLoss!I21 -> 4283150.4 | J14: =ProfLoss!J21 -> 4414572.5
B15: НДС к уплате в бюджет (при превышении входящего НДС - к возмещению, см. ниже) | C15: 12% | D15: =MAX(0,D22) -> 0 | E15: =MAX(0,E22) -> 0 | F15: =MAX(0,F22) -> 0 | G15: =MAX(0,G22) -> 0 | H15: =MAX(0,H22) -> 0 | I15: =MAX(0,I22) -> 0 | J15: =MAX(0,J22) -> 0
B16: ВСЕГО НАЛОГОВ И ОТЧИСЛЕНИЙ | D16: =D6+D13 -> 703979.13 | E16: =E6+E13 -> 3484846.8 | F16: =F6+F13 -> 4322326.2 | G16: =G6+G13 -> 4655302.7 | H16: =H6+H13 -> 4777103.6 | I16: =I6+I13 -> 4901456.2 | J16: =J6+J13 -> 5029576.1
B18: Расчет НДС
B19: НДС исходящий (реализация на внутреннем рынке; экспорт - 0%) | D19: 0 | E19: 0 | F19: 0 | G19: 0 | H19: 0 | I19: 0 | J19: 0
B20: НДС входящий - по операционным затратам | D20: 3507350.7 | E20: 26814175 | F20: 32950208 | G20: 33677557 | H20: 34418463 | I20: 35175669 | J20: 35949534
B21: НДС входящий - по капитальным вложениям (1-й год вкл. подготовительный период) | D21: 5731360.5 | E21: 57170.679 | F21: 57170.679 | G21: 57170.679 | H21: 57170.679 | I21: 57170.679 | J21: 57170.679
B22: НДС к уплате (+) / к возмещению из бюджета (-) | D22: =D19-D20-D21 -> -9238711.2 | E22: =E19-E20-E21 -> -26871346 | F22: =F19-F20-F21 -> -33007379 | G22: =G19-G20-G21 -> -33734727 | H22: =H19-H20-H21 -> -34475634 | I22: =I19-I20-I21 -> -35232840 | J22: =J19-J20-J21 -> -36006705
B24: Расчет налога на прибыль
B25: Прибыль (убыток) до налогообложения (Приложение 13) | D25: =ProfLoss!D20 -> 3444336.9 | E25: =ProfLoss!E20 -> 19014721 | F25: =ProfLoss!F20 -> 24622984 | G25: =ProfLoss!G20 -> 26867053 | H25: =ProfLoss!H20 -> 27702555 | I25: =ProfLoss!I20 -> 28554336 | J25: =ProfLoss!J20 -> 29430483
B26: Налоговые корректировки | D26: 0 | E26: 0 | F26: 0 | G26: 0 | H26: 0 | I26: 0 | J26: 0
B27: Налогооблагаемая прибыль | D27: =D25+D26 -> 3444336.9 | E27: =E25+E26 -> 19014721 | F27: =F25+F26 -> 24622984 | G27: =G25+G26 -> 26867053 | H27: =H25+H26 -> 27702555 | I27: =I25+I26 -> 28554336 | J27: =J25+J26 -> 29430483
B28: Ставка налога на прибыль | C28: % | D28: 0.15 | E28: 0.15 | F28: 0.15 | G28: 0.15 | H28: 0.15 | I28: 0.15 | J28: 0.15
B29: Налог на прибыль | D29: =D27*D28 -> 516650.54 | E29: =E27*E28 -> 2852208.2 | F29: =F27*F28 -> 3693447.6 | G29: =G27*G28 -> 4030058 | H29: =H27*H28 -> 4155383.3 | I29: =I27*I28 -> 4283150.4 | J29: =J27*J28 -> 4414572.5

Sheet CostTotal
B2: СТОИМОСТЬ ПРОДУКЦИИ ПРИ ПРОЕКТНОЙ МОЩНОСТИ (в экв. долл. США) | H2: Приложение 10
B3: Расчёт на 3-й год; разделение на постоянные и переменные затраты.
B5: Статьи издержек | C5: Всего стоимость | D5: Доля постоянных затрат (%) | E5: Доля переменных затрат (%) | F5: Фиксированная стоимость | G5: Переменная стоимость
B6: Сырьё, материалы и прочие переменные затраты | C6: =C7+C8 -> 2.6530574e+08 | D6: =IFERROR(F6/C6,0) -> 0 | E6: =IFERROR(G6/C6,0) -> 1 | F6: =F7+F8 -> 0 | G6: =G7+G8 -> 2.6530574e+08
B7: с ценой в твёрдой валюте (USD) | C7: =F7+G7 -> 2.5950064e+08 | D7: =IFERROR(F7/C7,0) -> 0 | E7: =IFERROR(G7/C7,0) -> 1 | F7: 0 | G7: =RawMat!F8 -> 2.5950064e+08
B8: с ценой в национальной валюте | C8: =F8+G8 -> 5805094.7 | D8: =IFERROR(F8/C8,0) -> 0 | E8: =IFERROR(G8/C8,0) -> 1 | F8: 0 | G8: =RawMat!F22 -> 5805094.7
B9: Энергоресурсы (электроэнергия, газ, вода) | C9: =F9+G9 -> 2429940.3 | D9: =IFERROR(F9/C9,0) -> 0.19927012 | E9: =IFERROR(G9/C9,0) -> 0.80072988 | F9: =SUM(Labour!F10:F12) -> 484214.48 | G9: =SUM(Labour!F6:F9) -> 1945725.8
B10: Зарплата производственного персонала (с соц. налогом) | C10: =F10+G10 -> 1706938.2 | D10: =IFERROR(F10/C10,0) -> 1 | E10: =IFERROR(G10/C10,0) -> 0 | F10: =Labour!F39 -> 1706938.2 | G10: 0
B11: Зарплата административного персонала (с соц. налогом) | C11: =F11+G11 -> 366184.37 | D11: =IFERROR(F11/C11,0) -> 1 | E11: =IFERROR(G11/C11,0) -> 0 | F11: =Labour!F61 -> 366184.37 | G11: 0
B12: Ремонт и техническое обслуживание (постоянная часть) | C12: =F12+G12 -> 945456.72 | D12: =IFERROR(F12/C12,0) -> 1 | E12: =IFERROR(G12/C12,0) -> 0 | F12: =RawMat!F28 -> 945456.72 | G12: 0
B13: Прочие производственные расходы (постоянная часть) | C13: =F13+G13 -> 617586.5 | D13: =IFERROR(F13/C13,0) -> 1 | E13: =IFERROR(G13/C13,0) -> 0 | F13: =RawMat!F29 -> 617586.5 | G13: 0
B14: Налог за пользование недрами (НДПИ) | C14: =F14+G14 -> 0 | D14: =IFERROR(F14/C14,0) -> 0 | E14: =IFERROR(G14/C14,0) -> 0 | F14: 0 | G14: =RawMat!F30 -> 0
B15: Административные расходы (без персонала и амортизации) | C15: =F15+G15 -> 3712123.4 | D15: =IFERROR(F15/C15,0) -> 0.69006913 | E15: =IFERROR(G15/C15,0) -> 0.30993087 | F15: 2561621.8 | G15: 1150501.6
B16: Коммерческие расходы | C16: =F16+G16 -> 1539598 | D16: =IFERROR(F16/C16,0) -> 0 | E16: =IFERROR(G16/C16,0) -> 1 | F16: 0 | G16: =CostSold!F31 -> 1539598
B17: Налог на имущество и земельный налог | C17: =F17+G17 -> 406758.38 | D17: =IFERROR(F17/C17,0) -> 1 | E17: =IFERROR(G17/C17,0) -> 0 | F17: =CostSold!F35+CostSold!F36 -> 406758.38 | G17: 0
B18: Специальный рентный налог | C18: =F18+G18 -> 0 | D18: =IFERROR(F18/C18,0) -> 0 | E18: =IFERROR(G18/C18,0) -> 0 | F18: 0 | G18: =CostSold!F37 -> 0
B19: Резерв на непредвиденные операционные расходы | C19: =F19+G19 -> 5532471.3 | D19: =IFERROR(F19/C19,0) -> 0 | E19: =IFERROR(G19/C19,0) -> 1 | F19: 0 | G19: =CostSold!F38 -> 5532471.3
B20: Прочие операционные расходы / (доходы) | C20: =F20+G20 -> 0 | D20: =IFERROR(F20/C20,0) -> 0 | E20: =IFERROR(G20/C20,0) -> 0 | F20: =CostSold!F39 -> 0 | G20: 0
B21: Амортизация (Приложение 4) | C21: =F21+G21 -> 2593626.1 | D21: =IFERROR(F21/C21,0) -> 1 | E21: =IFERROR(G21/C21,0) -> 0 | F21: =Depreciate!I21 -> 2593626.1 | G21: 0
B22: ИТОГО | C22: =SUM(C6:C21)-C6 -> 2.8515642e+08 | D22: =IFERROR(F22/C22,0) -> 0.03395465 | E22: =IFERROR(G22/C22,0) -> 0.96604535 | F22: =SUM(F6:F21)-F6 -> 9682386.6 | G22: =SUM(G6:G21)-G6 -> 2.7547403e+08
B23: в т.ч. в местной валюте | C23: =C22-C24 -> 24201325
B24: в т.ч. в твёрдой валюте (производственные затраты в USD) | C24: 2.609551e+08
B26: Выручка при проектной мощности | C26: =SalePlan!F14 -> 3.079196e+08
B27: Затраты на 1 USD выручки | C27: =IFERROR(C22/C26,0) -> 0.92607428
B28: Полная себестоимость единицы основной продукции, USD/t | C28: =IFERROR(C22/ProdPlan!F13,0) -> 107342.9

Sheet CostSold
B2: ГОДОВАЯ СТОИМОСТЬ ПРОДАННОЙ ПРОДУКЦИИ (в экв. долл. США) | K2: Приложение 11
B4: ПОКАЗАТЕЛИ | C4: Ед. изм. | D4: 1 год (льготный период) | E4: 2 год | F4: 3 год | G4: 4 год | H4: 5 год | I4: 6 год | J4: 7 год
B6: Освоение мощностей (основная продукция) | C6: % | D6: =ProdPlan!D11 -> 0.10163749 | E6: =ProdPlan!E11 -> 0.82971014 | F6: =ProdPlan!F11 -> 1 | G6: =ProdPlan!G11 -> 1 | H6: =ProdPlan!H11 -> 1 | I6: =ProdPlan!I11 -> 1 | J6: =ProdPlan!J11 -> 1
B8: ПРОИЗВОДСТВЕННАЯ СЕБЕСТОИМОСТЬ ПО ЭЛЕМЕНТАМ
B9: Сырьё | C9: USD | D9: 25462057 | E9: 2.1067546e+08 | F9: 2.5950064e+08 | G9: 2.6520966e+08 | H9: 2.7104427e+08 | I9: 2.7700724e+08 | J9: 2.831014e+08
B10: Вспомогательные материалы | C10: USD | D10: 569592.63 | E10: 4712863 | F10: 5805094.7 | G10: 5932806.8 | H10: 6063328.5 | I10: 6196721.8 | J10: 6333049.6
B11: Электроэнергия | C11: USD | D11: 149650.33 | E11: 997808.69 | F11: 1180595.2 | G11: 1206568.3 | H11: 1233112.8 | I11: 1260241.3 | J11: 1287966.6
B12: Природный газ / топливо | C12: USD | D12: 139941.22 | E12: 933072.2 | F12: 1103999.8 | G12: 1128287.8 | H12: 1153110.1 | I12: 1178478.5 | J12: 1204405
B13: Вода | C13: USD | D13: 18169.769 | E13: 122546.59 | F13: 145345.31 | G13: 148542.9 | H13: 151810.85 | I13: 155150.69 | J13: 158564
B14: Заработная плата | C14: USD | D14: 361689.03 | E14: 1491402.3 | F14: 1524052 | G14: 1557566.9 | H14: 1591833.3 | I14: 1626853.7 | J14: 1662644.4
B15: Социальный налог | C15: USD | D15: 43402.684 | E15: 178968.28 | F15: 182886.23 | G15: 186908.02 | H15: 191020 | I15: 195222.44 | J15: 199517.33
B16: Амортизация (Приложение 4) | C16: USD | D16: =Depreciate!$G$22 -> 620914.3 | E16: =Depreciate!$H$22 -> 2535269.6 | F16: =Depreciate!$I$22 -> 2582911.8 | G16: =Depreciate!$J$22 -> 2630554.1 | H16: =Depreciate!$K$22 -> 2678196.3 | I16: =Depreciate!$L$22 -> 2725838.5 | J16: =Depreciate!$M$22 -> 2773480.8
B17: Ремонт и техобслуживание | C17: USD | D17: 92767.682 | E17: 767568.53 | F17: 945456.72 | G17: 966256.77 | H17: 987514.42 | I17: 1009239.7 | J17: 1031443
B18: Прочие производственные расходы (без НДПИ) | C18: USD | D18: 60597.24 | E18: 501387.26 | F18: 617586.5 | G18: 631173.4 | H18: 645059.22 | I18: 659250.52 | J18: 673754.03
B19: Налог за пользование недрами (НДПИ) | C19: USD | D19: 0 | E19: 0 | F19: 0 | G19: 0 | H19: 0 | I19: 0 | J19: 0
B20: Себестоимость произведенной продукции | C20: USD | D20: =SUM(D9:D19) -> 27518782 | E20: =SUM(E9:E19) -> 2.2291634e+08 | F20: =SUM(F9:F19) -> 2.7358857e+08 | G20: =SUM(G9:G19) -> 2.7959832e+08 | H20: =SUM(H9:H19) -> 2.8573925e+08 | I20: =SUM(I9:I19) -> 2.9201424e+08 | J20: =SUM(J9:J19) -> 2.9842623e+08
B21: Изменение остатков готовой продукции (- прирост запаса) | C21: USD | D21: -6425081.9 | E21: -5650593.3 | F21: -2773949.9 | G21: -326690.88 | H21: -333878.95 | I21: -341224.29 | J21: -348731.22
B22: Себестоимость реализованной продукции | C22: USD | D22: =D20+D21 -> 21093700 | E22: =E20+E21 -> 2.1726575e+08 | F22: =F20+F21 -> 2.7081462e+08 | G22: =G20+G21 -> 2.7927163e+08 | H22: =H20+H21 -> 2.8540538e+08 | I22: =I20+I21 -> 2.9167302e+08 | J22: =J20+J21 -> 2.980775e+08
B23: Доля затрат в твёрдой валюте (USD) в денежной себестоимости | C23: % | D23: 0.95211461 | E23: 0.96143498 | F23: 0.96291383 | G23: 0.96279906 | H23: 0.9626867 | I23: 0.96257677 | J23: 0.9624692
B24: в т.ч. затраты в твёрдой валюте (USD) | C24: USD | D24: =D22*D23 -> 20083620 | E24: =E22*E23 -> 2.0888689e+08 | F24: =F22*F23 -> 2.6077114e+08 | G24: =G22*G23 -> 2.6888246e+08 | H24: =H22*H23 -> 2.7475596e+08 | I24: =I22*I23 -> 2.8075767e+08 | J24: =J22*J23 -> 2.8689041e+08
B25: в т.ч. затраты в национальной валюте | C25: USD | D25: =D22-D24 -> 1010080 | E25: =E22-E24 -> 8378858 | F25: =F22-F24 -> 10043478 | G25: =G22-G24 -> 10389168 | H25: =H22-H24 -> 10649416 | I25: =I22-I24 -> 10915347 | J25: =J22-J24 -> 11187087
B27: РАСХОДЫ ПЕРИОДА
B28: Зарплата административного персонала (с соц. налогом) | C28: USD | D28: 352796.23 | E28: 358339.63 | F28: 366184.37 | G28: 374237.01 | H28: 382470.22 | I28: 390884.57 | J28: 399484.03
B29: Амортизация административных активов | C29: USD | D29: =Depreciate!$G$23 -> 2678.5714 | E29: =Depreciate!$H$23 -> 10714.286 | F29: =Depreciate!$I$23 -> 10714.286 | G29: =Depreciate!$J$23 -> 10714.286 | H29: =Depreciate!$K$23 -> 10714.286 | I29: =Depreciate!$L$23 -> 8035.7143 | J29: =Depreciate!$M$23 -> 0
B30: Прочие административные расходы (аренда, налог за воду, прочие) | C30: USD | D30: 2590303.2 | E30: 3475906.7 | F30: 3712123.4 | G30: 3793788.6 | H30: 3877251.9 | I30: 3962551.4 | J30: 4049727.6
B31: Коммерческие расходы (расходы по реализации) | C31: USD | D31: 141656.25 | E31: 1237027.8 | F31: 1539598 | G31: 1593382 | H31: 1628434.5 | I31: 1664257.4 | J31: 1700877.3
B32: Итого расходы периода | C32: USD | D32: =SUM(D28:D31) -> 3087434.2 | E32: =SUM(E28:E31) -> 5081988.4 | F32: =SUM(F28:F31) -> 5628620.1 | G32: =SUM(G28:G31) -> 5772121.8 | H32: =SUM(H28:H31) -> 5898870.9 | I32: =SUM(I28:I31) -> 6025729.1 | J32: =SUM(J28:J31) -> 6150088.9
B34: НАЛОГИ И ПРОЧИЕ ОПЕРАЦИОННЫЕ РАСХОДЫ
B35: Налог на имущество | C35: USD | D35: 106126.31 | E35: 415276.88 | F35: 406758.38 | G35: 398239.88 | H35: 389721.38 | I35: 381202.88 | J35: 372684.38
B36: Земельный налог | C36: USD | D36: 0 | E36: 0 | F36: 0 | G36: 0 | H36: 0 | I36: 0 | J36: 0
B37: Специальный рентный налог | C37: USD | D37: 0 | E37: 0 | F37: 0 | G37: 0 | H37: 0 | I37: 0 | J37: 0
B38: Резерв на непредвиденные операционные расходы | C38: USD | D38: 599652.47 | E38: 4509046.9 | F38: 5532471.3 | G38: 5654583.5 | H38: 5778984.3 | I38: 5906121.9 | J38: 6036056.7
B39: Прочие операционные расходы / (доходы) | C39: USD | D39: 0 | E39: 0 | F39: 0 | G39: 0 | H39: 0 | I39: 0 | J39: 0
B40: Итого налоги и прочие операционные расходы | C40: USD | D40: =SUM(D35:D39) -> 705778.78 | E40: =SUM(E35:E39) -> 4924323.8 | F40: =SUM(F35:F39) -> 5939229.7 | G40: =SUM(G35:G39) -> 6052823.4 | H40: =SUM(H35:H39) -> 6168705.7 | I40: =SUM(I35:I39) -> 6287324.8 | J40: =SUM(J35:J39) -> 6408741.1
B42: ФИНАНСОВЫЕ ИЗДЕРЖКИ
B43: Проценты за кредит (1-й год - капитализированы, оплачены за счёт собственных средств) | C43: USD | D43: 0 | E43: =LOANS!$D$106 -> 1118782.2 | F43: =LOANS!$E$106 -> 914142.62 | G43: =LOANS!$F$106 -> 712767.34 | H43: =LOANS!$G$106 -> 511392.06 | I43: =LOANS!$H$106 -> 311074.23 | J43: =LOANS!$I$106 -> 108641.5
B45: ПОЛНАЯ СТОИМОСТЬ ПРОДАННОЙ ПРОДУКЦИИ | C45: USD | D45: =D22+D32+D40+D43 -> 24886913 | E45: =E22+E32+E40+E43 -> 2.2839084e+08 | F45: =F22+F32+F40+F43 -> 2.8329661e+08 | G45: =G22+G32+G40+G43 -> 2.9180934e+08 | H45: =H22+H32+H40+H43 -> 2.9798434e+08 | I45: =I22+I32+I40+I43 -> 3.0429714e+08 | J45: =J22+J32+J40+J43 -> 3.1074497e+08
B46: Полная себестоимость единицы основной продукции | C46: USD/t | D46: =IFERROR(D45/(ProdPlan!D15+ProdPlan!D16),0) -> 99547.652 | E46: =IFERROR(E45/(ProdPlan!E15+ProdPlan!E16),0) -> 106024.88 | F46: =IFERROR(F45/(ProdPlan!F15+ProdPlan!F16),0) -> 107992.71 | G46: =IFERROR(G45/(ProdPlan!G15+ProdPlan!G16),0) -> 109847.3 | H46: =IFERROR(H45/(ProdPlan!H15+ProdPlan!H16),0) -> 112171.78 | I46: =IFERROR(I45/(ProdPlan!I15+ProdPlan!I16),0) -> 114548.14 | J46: =IFERROR(J45/(ProdPlan!J15+ProdPlan!J16),0) -> 116975.33

Sheet LOANS
B2: СХЕМА ВЫПЛАТЫ КРЕДИТА (в долл. США) | H2: Приложение 12
B5: Срок кредита | C5: =ИНФОРМАЦИЯ!$C$28 -> 84 | D5: месяцев
B6: Льготный период | C6: =ИНФОРМАЦИЯ!$C$29 -> 12 | D6: месяцев
B7: Инвестиционный период | C7: =ИНФОРМАЦИЯ!$C$30 -> 12 | D7: месяцев
B8: Процентная ставка | C8: =ИНФОРМАЦИЯ!$C$27 -> 0.07 | D8: годовых
B9: Сумма кредита | C9: =ИНФОРМАЦИЯ!$C$26 -> 17024290 | D9: USD
B10: Дата выдачи | C10: =ИНФОРМАЦИЯ!$C$31 -> 46388
B11: База начисления процентов | C11: =ИНФОРМАЦИЯ!$C$32 -> 360 | D11: дней
B12: Количество платежей по основному долгу | C12: =C5-C6 -> 72 | D12: платежей
B13: Ежемесячный платёж по основному долгу | C13: =C9/C12 -> 236448.47 | D13: USD
A15: № | B15: Дата платежа | C15: Остаток на начало | D15: Погашение основного долга | E15: Проценты | F15: Всего выплат | G15: Остаток на конец | H15: № года
A16: 1 | B16: =EOMONTH($C$10,0) -> 46418 | C16: =$C$9 -> 17024290 | D16: =IF(A16>$C$6,MIN(C16,$C$13),0) -> 0 | E16: =C16*$C$8*DAY(B16)/$C$11 -> 102618.64 | F16: =D16+E16 -> 102618.64 | G16: =C16-D16 -> 17024290 | H16: =YEAR(B16)-YEAR($C$10)+1 -> 1
A17: 2 | B17: =EOMONTH($C$10,1) -> 46446 | C17: =G16 -> 17024290 | D17: =IF(A17>$C$6,MIN(C17,$C$13),0) -> 0 | E17: =C17*$C$8*DAY(B17)/$C$11 -> 92687.799 | F17: =D17+E17 -> 92687.799 | G17: =C17-D17 -> 17024290 | H17: =YEAR(B17)-YEAR($C$10)+1 -> 1
A18: 3 | B18: =EOMONTH($C$10,2) -> 46477 | C18: =G17 -> 17024290 | D18: =IF(A18>$C$6,MIN(C18,$C$13),0) -> 0 | E18: =C18*$C$8*DAY(B18)/$C$11 -> 102618.64 | F18: =D18+E18 -> 102618.64 | G18: =C18-D18 -> 17024290 | H18: =YEAR(B18)-YEAR($C$10)+1 -> 1
A19: 4 | B19: =EOMONTH($C$10,3) -> 46507 | C19: =G18 -> 17024290 | D19: =IF(A19>$C$6,MIN(C19,$C$13),0) -> 0 | E19: =C19*$C$8*DAY(B19)/$C$11 -> 99308.357 | F19: =D19+E19 -> 99308.357 | G19: =C19-D19 -> 17024290 | H19: =YEAR(B19)-YEAR($C$10)+1 -> 1
A20: 5 | B20: =EOMONTH($C$10,4) -> 46538 | C20: =G19 -> 17024290 | D20: =IF(A20>$C$6,MIN(C20,$C$13),0) -> 0 | E20: =C20*$C$8*DAY(B20)/$C$11 -> 102618.64 | F20: =D20+E20 -> 102618.64 | G20: =C20-D20 -> 17024290 | H20: =YEAR(B20)-YEAR($C$10)+1 -> 1
A21: 6 | B21: =EOMONTH($C$10,5) -> 46568 | C21: =G20 -> 17024290 | D21: =IF(A21>$C$6,MIN(C21,$C$13),0) -> 0 | E21: =C21*$C$8*DAY(B21)/$C$11 -> 99308.357 | F21: =D21+E21 -> 99308.357 | G21: =C21-D21 -> 17024290 | H21: =YEAR(B21)-YEAR($C$10)+1 -> 1
A22: 7 | B22: =EOMONTH($C$10,6) -> 46599 | C22: =G21 -> 17024290 | D22: =IF(A22>$C$6,MIN(C22,$C$13),0) -> 0 | E22: =C22*$C$8*DAY(B22)/$C$11 -> 102618.64 | F22: =D22+E22 -> 102618.64 | G22: =C22-D22 -> 17024290 | H22: =YEAR(B22)-YEAR($C$10)+1 -> 1
A23: 8 | B23: =EOMONTH($C$10,7) -> 46630 | C23: =G22 -> 17024290 | D23: =IF(A23>$C$6,MIN(C23,$C$13),0) -> 0 | E23: =C23*$C$8*DAY(B23)/$C$11 -> 102618.64 | F23: =D23+E23 -> 102618.64 | G23: =C23-D23 -> 17024290 | H23: =YEAR(B23)-YEAR($C$10)+1 -> 1
A24: 9 | B24: =EOMONTH($C$10,8) -> 46660 | C24: =G23 -> 17024290 | D24: =IF(A24>$C$6,MIN(C24,$C$13),0) -> 0 | E24: =C24*$C$8*DAY(B24)/$C$11 -> 99308.357 | F24: =D24+E24 -> 99308.357 | G24: =C24-D24 -> 17024290 | H24: =YEAR(B24)-YEAR($C$10)+1 -> 1
A25: 10 | B25: =EOMONTH($C$10,9) -> 46691 | C25: =G24 -> 17024290 | D25: =IF(A25>$C$6,MIN(C25,$C$13),0) -> 0 | E25: =C25*$C$8*DAY(B25)/$C$11 -> 102618.64 | F25: =D25+E25 -> 102618.64 | G25: =C25-D25 -> 17024290 | H25: =YEAR(B25)-YEAR($C$10)+1 -> 1
A26: 11 | B26: =EOMONTH($C$10,10) -> 46721 | C26: =G25 -> 17024290 | D26: =IF(A26>$C$6,MIN(C26,$C$13),0) -> 0 | E26: =C26*$C$8*DAY(B26)/$C$11 -> 99308.357 | F26: =D26+E26 -> 99308.357 | G26: =C26-D26 -> 17024290 | H26: =YEAR(B26)-YEAR($C$10)+1 -> 1
A27: 12 | B27: =EOMONTH($C$10,11) -> 46752 | C27: =G26 -> 17024290 | D27: =IF(A27>$C$6,MIN(C27,$C$13),0) -> 0 | E27: =C27*$C$8*DAY(B27)/$C$11 -> 102618.64 | F27: =D27+E27 -> 102618.64 | G27: =C27-D27 -> 17024290 | H27: =YEAR(B27)-YEAR($C$10)+1 -> 1
A28: 13 | B28: =EOMONTH($C$10,12) -> 46783 | C28: =G27 -> 17024290 | D28: =IF(A28>$C$6,MIN(C28,$C$13),0) -> 236448.47 | E28: =C28*$C$8*DAY(B28)/$C$11 -> 102618.64 | F28: =D28+E28 -> 339067.1 | G28: =C28-D28 -> 16787841 | H28: =YEAR(B28)-YEAR($C$10)+1 -> 2
A29: 14 | B29: =EOMONTH($C$10,13) -> 46812 | C29: =G28 -> 16787841 | D29: =IF(A29>$C$6,MIN(C29,$C$13),0) -> 236448.47 | E29: =C29*$C$8*DAY(B29)/$C$11 -> 94664.771 | F29: =D29+E29 -> 331113.24 | G29: =C29-D29 -> 16551393 | H29: =YEAR(B29)-YEAR($C$10)+1 -> 2
A30: 15 | B30: =EOMONTH($C$10,14) -> 46843 | C30: =G29 -> 16551393 | D30: =IF(A30>$C$6,MIN(C30,$C$13),0) -> 236448.47 | E30: =C30*$C$8*DAY(B30)/$C$11 -> 99768.117 | F30: =D30+E30 -> 336216.59 | G30: =C30-D30 -> 16314944 | H30: =YEAR(B30)-YEAR($C$10)+1 -> 2
A31: 16 | B31: =EOMONTH($C$10,15) -> 46873 | C31: =G30 -> 16314944 | D31: =IF(A31>$C$6,MIN(C31,$C$13),0) -> 236448.47 | E31: =C31*$C$8*DAY(B31)/$C$11 -> 95170.508 | F31: =D31+E31 -> 331618.98 | G31: =C31-D31 -> 16078496 | H31: =YEAR(B31)-YEAR($C$10)+1 -> 2
A32: 17 | B32: =EOMONTH($C$10,16) -> 46904 | C32: =G31 -> 16078496 | D32: =IF(A32>$C$6,MIN(C32,$C$13),0) -> 236448.47 | E32: =C32*$C$8*DAY(B32)/$C$11 -> 96917.6 | F32: =D32+E32 -> 333366.07 | G32: =C32-D32 -> 15842047 | H32: =YEAR(B32)-YEAR($C$10)+1 -> 2
A33: 18 | B33: =EOMONTH($C$10,17) -> 46934 | C33: =G32 -> 15842047 | D33: =IF(A33>$C$6,MIN(C33,$C$13),0) -> 236448.47 | E33: =C33*$C$8*DAY(B33)/$C$11 -> 92411.943 | F33: =D33+E33 -> 328860.41 | G33: =C33-D33 -> 15605599 | H33: =YEAR(B33)-YEAR($C$10)+1 -> 2
A34: 19 | B34: =EOMONTH($C$10,18) -> 46965 | C34: =G33 -> 15605599 | D34: =IF(A34>$C$6,MIN(C34,$C$13),0) -> 236448.47 | E34: =C34*$C$8*DAY(B34)/$C$11 -> 94067.082 | F34: =D34+E34 -> 330515.55 | G34: =C34-D34 -> 15369150 | H34: =YEAR(B34)-YEAR($C$10)+1 -> 2
A35: 20 | B35: =EOMONTH($C$10,19) -> 46996 | C35: =G34 -> 15369150 | D35: =IF(A35>$C$6,MIN(C35,$C$13),0) -> 236448.47 | E35: =C35*$C$8*DAY(B35)/$C$11 -> 92641.823 | F35: =D35+E35 -> 329090.29 | G35: =C35-D35 -> 15132702 | H35: =YEAR(B35)-YEAR($C$10)+1 -> 2
A36: 21 | B36: =EOMONTH($C$10,20) -> 47026 | C36: =G35 -> 15132702 | D36: =IF(A36>$C$6,MIN(C36,$C$13),0) -> 236448.47 | E36: =C36*$C$8*DAY(B36)/$C$11 -> 88274.095 | F36: =D36+E36 -> 324722.56 | G36: =C36-D36 -> 14896253 | H36: =YEAR(B36)-YEAR($C$10)+1 -> 2
A37: 22 | B37: =EOMONTH($C$10,21) -> 47057 | C37: =G36 -> 14896253 | D37: =IF(A37>$C$6,MIN(C37,$C$13),0) -> 236448.47 | E37: =C37*$C$8*DAY(B37)/$C$11 -> 89791.306 | F37: =D37+E37 -> 326239.77 | G37: =C37-D37 -> 14659805 | H37: =YEAR(B37)-YEAR($C$10)+1 -> 2
A38: 23 | B38: =EOMONTH($C$10,22) -> 47087 | C38: =G37 -> 14659805 | D38: =IF(A38>$C$6,MIN(C38,$C$13),0) -> 236448.47 | E38: =C38*$C$8*DAY(B38)/$C$11 -> 85515.529 | F38: =D38+E38 -> 321964 | G38: =C38-D38 -> 14423357 | H38: =YEAR(B38)-YEAR($C$10)+1 -> 2
A39: 24 | B39: =EOMONTH($C$10,23) -> 47118 | C39: =G38 -> 14423357 | D39: =IF(A39>$C$6,MIN(C39,$C$13),0) -> 236448.47 | E39: =C39*$C$8*DAY(B39)/$C$11 -> 86940.788 | F39: =D39+E39 -> 323389.26 | G39: =C39-D39 -> 14186908 | H39: =YEAR(B39)-YEAR($C$10)+1 -> 2
A40: 25 | B40: =EOMONTH($C$10,24) -> 47149 | C40: =G39 -> 14186908 | D40: =IF(A40>$C$6,MIN(C40,$C$13),0) -> 236448.47 | E40: =C40*$C$8*DAY(B40)/$C$11 -> 85515.529 | F40: =D40+E40 -> 321964 | G40: =C40-D40 -> 13950460 | H40: =YEAR(B40)-YEAR($C$10)+1 -> 3
A41: 26 | B41: =EOMONTH($C$10,25) -> 47177 | C41: =G40 -> 13950460 | D41: =IF(A41>$C$6,MIN(C41,$C$13),0) -> 236448.47 | E41: =C41*$C$8*DAY(B41)/$C$11 -> 75952.502 | F41: =D41+E41 -> 312400.97 | G41: =C41-D41 -> 13714011 | H41: =YEAR(B41)-YEAR($C$10)+1 -> 3
A42: 27 | B42: =EOMONTH($C$10,26) -> 47208 | C42: =G41 -> 13714011 | D42: =IF(A42>$C$6,MIN(C42,$C$13),0) -> 236448.47 | E42: =C42*$C$8*DAY(B42)/$C$11 -> 82665.012 | F42: =D42+E42 -> 319113.48 | G42: =C42-D42 -> 13477563 | H42: =YEAR(B42)-YEAR($C$10)+1 -> 3
A43: 28 | B43: =EOMONTH($C$10,27) -> 47238 | C43: =G42 -> 13477563 | D43: =IF(A43>$C$6,MIN(C43,$C$13),0) -> 236448.47 | E43: =C43*$C$8*DAY(B43)/$C$11 -> 78619.116 | F43: =D43+E43 -> 315067.58 | G43: =C43-D43 -> 13241114 | H43: =YEAR(B43)-YEAR($C$10)+1 -> 3
A44: 29 | B44: =EOMONTH($C$10,28) -> 47269 | C44: =G43 -> 13241114 | D44: =IF(A44>$C$6,MIN(C44,$C$13),0) -> 236448.47 | E44: =C44*$C$8*DAY(B44)/$C$11 -> 79814.494 | F44: =D44+E44 -> 316262.96 | G44: =C44-D44 -> 13004666 | H44: =YEAR(B44)-YEAR($C$10)+1 -> 3
A45: 30 | B45: =EOMONTH($C$10,29) -> 47299 | C45: =G44 -> 13004666 | D45: =IF(A45>$C$6,MIN(C45,$C$13),0) -> 236448.47 | E45: =C45*$C$8*DAY(B45)/$C$11 -> 75860.55 | F45: =D45+E45 -> 312309.02 | G45: =C45-D45 -> 12768217 | H45: =YEAR(B45)-YEAR($C$10)+1 -> 3
A46: 31 | B46: =EOMONTH($C$10,30) -> 47330 | C46: =G45 -> 12768217 | D46: =IF(A46>$C$6,MIN(C46,$C$13),0) -> 236448.47 | E46: =C46*$C$8*DAY(B46)/$C$11 -> 76963.976 | F46: =D46+E46 -> 313412.44 | G46: =C46-D46 -> 12531769 | H46: =YEAR(B46)-YEAR($C$10)+1 -> 3
A47: 32 | B47: =EOMONTH($C$10,31) -> 47361 | C47: =G46 -> 12531769 | D47: =IF(A47>$C$6,MIN(C47,$C$13),0) -> 236448.47 | E47: =C47*$C$8*DAY(B47)/$C$11 -> 75538.718 | F47: =D47+E47 -> 311987.19 | G47: =C47-D47 -> 12295320 | H47: =YEAR(B47)-YEAR($C$10)+1 -> 3
A48: 33 | B48: =EOMONTH($C$10,32) -> 47391 | C48: =G47 -> 12295320 | D48: =IF(A48>$C$6,MIN(C48,$C$13),0) -> 236448.47 | E48: =C48*$C$8*DAY(B48)/$C$11 -> 71722.702 | F48: =D48+E48 -> 308171.17 | G48: =C48-D48 -> 12058872 | H48: =YEAR(B48)-YEAR($C$10)+1 -> 3
A49: 34 | B49: =EOMONTH($C$10,33) -> 47422 | C49: =G48 -> 12058872 | D49: =IF(A49>$C$6,MIN(C49,$C$13),0) -> 236448.47 | E49: =C49*$C$8*DAY(B49)/$C$11 -> 72688.2 | F49: =D49+E49 -> 309136.67 | G49: =C49-D49 -> 11822423 | H49: =YEAR(B49)-YEAR($C$10)+1 -> 3
A50: 35 | B50: =EOMONTH($C$10,34) -> 47452 | C50: =G49 -> 11822423 | D50: =IF(A50>$C$6,MIN(C50,$C$13),0) -> 236448.47 | E50: =C50*$C$8*DAY(B50)/$C$11 -> 68964.136 | F50: =D50+E50 -> 305412.6 | G50: =C50-D50 -> 11585975 | H50: =YEAR(B50)-YEAR($C$10)+1 -> 3
A51: 36 | B51: =EOMONTH($C$10,35) -> 47483 | C51: =G50 -> 11585975 | D51: =IF(A51>$C$6,MIN(C51,$C$13),0) -> 236448.47 | E51: =C51*$C$8*DAY(B51)/$C$11 -> 69837.682 | F51: =D51+E51 -> 306286.15 | G51: =C51-D51 -> 11349526 | H51: =YEAR(B51)-YEAR($C$10)+1 -> 3
A52: 37 | B52: =EOMONTH($C$10,36) -> 47514 | C52: =G51 -> 11349526 | D52: =IF(A52>$C$6,MIN(C52,$C$13),0) -> 236448.47 | E52: =C52*$C$8*DAY(B52)/$C$11 -> 68412.423 | F52: =D52+E52 -> 304860.89 | G52: =C52-D52 -> 11113078 | H52: =YEAR(B52)-YEAR($C$10)+1 -> 4
A53: 38 | B53: =EOMONTH($C$10,37) -> 47542 | C53: =G52 -> 11113078 | D53: =IF(A53>$C$6,MIN(C53,$C$13),0) -> 236448.47 | E53: =C53*$C$8*DAY(B53)/$C$11 -> 60504.536 | F53: =D53+E53 -> 296953 | G53: =C53-D53 -> 10876630 | H53: =YEAR(B53)-YEAR($C$10)+1 -> 4
A54: 39 | B54: =EOMONTH($C$10,38) -> 47573 | C54: =G53 -> 10876630 | D54: =IF(A54>$C$6,MIN(C54,$C$13),0) -> 236448.47 | E54: =C54*$C$8*DAY(B54)/$C$11 -> 65561.906 | F54: =D54+E54 -> 302010.37 | G54: =C54-D54 -> 10640181 | H54: =YEAR(B54)-YEAR($C$10)+1 -> 4
A55: 40 | B55: =EOMONTH($C$10,39) -> 47603 | C55: =G54 -> 10640181 | D55: =IF(A55>$C$6,MIN(C55,$C$13),0) -> 236448.47 | E55: =C55*$C$8*DAY(B55)/$C$11 -> 62067.723 | F55: =D55+E55 -> 298516.19 | G55: =C55-D55 -> 10403733 | H55: =YEAR(B55)-YEAR($C$10)+1 -> 4
A56: 41 | B56: =EOMONTH($C$10,40) -> 47634 | C56: =G55 -> 10403733 | D56: =IF(A56>$C$6,MIN(C56,$C$13),0) -> 236448.47 | E56: =C56*$C$8*DAY(B56)/$C$11 -> 62711.388 | F56: =D56+E56 -> 299159.86 | G56: =C56-D56 -> 10167284 | H56: =YEAR(B56)-YEAR($C$10)+1 -> 4
A57: 42 | B57: =EOMONTH($C$10,41) -> 47664 | C57: =G56 -> 10167284 | D57: =IF(A57>$C$6,MIN(C57,$C$13),0) -> 236448.47 | E57: =C57*$C$8*DAY(B57)/$C$11 -> 59309.157 | F57: =D57+E57 -> 295757.63 | G57: =C57-D57 -> 9930835.7 | H57: =YEAR(B57)-YEAR($C$10)+1 -> 4
A58: 43 | B58: =EOMONTH($C$10,42) -> 47695 | C58: =G57 -> 9930835.7 | D58: =IF(A58>$C$6,MIN(C58,$C$13),0) -> 236448.47 | E58: =C58*$C$8*DAY(B58)/$C$11 -> 59860.87 | F58: =D58+E58 -> 296309.34 | G58: =C58-D58 -> 9694387.2 | H58: =YEAR(B58)-YEAR($C$10)+1 -> 4
A59: 44 | B59: =EOMONTH($C$10,43) -> 47726 | C59: =G58 -> 9694387.2 | D59: =IF(A59>$C$6,MIN(C59,$C$13),0) -> 236448.47 | E59: =C59*$C$8*DAY(B59)/$C$11 -> 58435.612 | F59: =D59+E59 -> 294884.08 | G59: =C59-D59 -> 9457938.7 | H59: =YEAR(B59)-YEAR($C$10)+1 -> 4
A60: 45 | B60: =EOMONTH($C$10,44) -> 47756 | C60: =G59 -> 9457938.7 | D60: =IF(A60>$C$6,MIN(C60,$C$13),0) -> 236448.47 | E60: =C60*$C$8*DAY(B60)/$C$11 -> 55171.309 | F60: =D60+E60 -> 291619.78 | G60: =C60-D60 -> 9221490.3 | H60: =YEAR(B60)-YEAR($C$10)+1 -> 4
A61: 46 | B61: =EOMONTH($C$10,45) -> 47787 | C61: =G60 -> 9221490.3 | D61: =IF(A61>$C$6,MIN(C61,$C$13),0) -> 236448.47 | E61: =C61*$C$8*DAY(B61)/$C$11 -> 55585.094 | F61: =D61+E61 -> 292033.56 | G61: =C61-D61 -> 8985041.8 | H61: =YEAR(B61)-YEAR($C$10)+1 -> 4
A62: 47 | B62: =EOMONTH($C$10,46) -> 47817 | C62: =G61 -> 8985041.8 | D62: =IF(A62>$C$6,MIN(C62,$C$13),0) -> 236448.47 | E62: =C62*$C$8*DAY(B62)/$C$11 -> 52412.744 | F62: =D62+E62 -> 288861.21 | G62: =C62-D62 -> 8748593.3 | H62: =YEAR(B62)-YEAR($C$10)+1 -> 4
A63: 48 | B63: =EOMONTH($C$10,47) -> 47848 | C63: =G62 -> 8748593.3 | D63: =IF(A63>$C$6,MIN(C63,$C$13),0) -> 236448.47 | E63: =C63*$C$8*DAY(B63)/$C$11 -> 52734.576 | F63: =D63+E63 -> 289183.04 | G63: =C63-D63 -> 8512144.8 | H63: =YEAR(B63)-YEAR($C$10)+1 -> 4
A64: 49 | B64: =EOMONTH($C$10,48) -> 47879 | C64: =G63 -> 8512144.8 | D64: =IF(A64>$C$6,MIN(C64,$C$13),0) -> 236448.47 | E64: =C64*$C$8*DAY(B64)/$C$11 -> 51309.318 | F64: =D64+E64 -> 287757.79 | G64: =C64-D64 -> 8275696.4 | H64: =YEAR(B64)-YEAR($C$10)+1 -> 5
A65: 50 | B65: =EOMONTH($C$10,49) -> 47907 | C65: =G64 -> 8275696.4 | D65: =IF(A65>$C$6,MIN(C65,$C$13),0) -> 236448.47 | E65: =C65*$C$8*DAY(B65)/$C$11 -> 45056.569 | F65: =D65+E65 -> 281505.04 | G65: =C65-D65 -> 8039247.9 | H65: =YEAR(B65)-YEAR($C$10)+1 -> 5
A66: 51 | B66: =EOMONTH($C$10,50) -> 47938 | C66: =G65 -> 8039247.9 | D66: =IF(A66>$C$6,MIN(C66,$C$13),0) -> 236448.47 | E66: =C66*$C$8*DAY(B66)/$C$11 -> 48458.8 | F66: =D66+E66 -> 284907.27 | G66: =C66-D66 -> 7802799.4 | H66: =YEAR(B66)-YEAR($C$10)+1 -> 5
A67: 52 | B67: =EOMONTH($C$10,51) -> 47968 | C67: =G66 -> 7802799.4 | D67: =IF(A67>$C$6,MIN(C67,$C$13),0) -> 236448.47 | E67: =C67*$C$8*DAY(B67)/$C$11 -> 45516.33 | F67: =D67+E67 -> 281964.8 | G67: =C67-D67 -> 7566351 | H67: =YEAR(B67)-YEAR($C$10)+1 -> 5
A68: 53 | B68: =EOMONTH($C$10,52) -> 47999 | C68: =G67 -> 7566351 | D68: =IF(A68>$C$6,MIN(C68,$C$13),0) -> 236448.47 | E68: =C68*$C$8*DAY(B68)/$C$11 -> 45608.282 | F68: =D68+E68 -> 282056.75 | G68: =C68-D68 -> 7329902.5 | H68: =YEAR(B68)-YEAR($C$10)+1 -> 5
A69: 54 | B69: =EOMONTH($C$10,53) -> 48029 | C69: =G68 -> 7329902.5 | D69: =IF(A69>$C$6,MIN(C69,$C$13),0) -> 236448.47 | E69: =C69*$C$8*DAY(B69)/$C$11 -> 42757.765 | F69: =D69+E69 -> 279206.23 | G69: =C69-D69 -> 7093454 | H69: =YEAR(B69)-YEAR($C$10)+1 -> 5
A70: 55 | B70: =EOMONTH($C$10,54) -> 48060 | C70: =G69 -> 7093454 | D70: =IF(A70>$C$6,MIN(C70,$C$13),0) -> 236448.47 | E70: =C70*$C$8*DAY(B70)/$C$11 -> 42757.765 | F70: =D70+E70 -> 279206.23 | G70: =C70-D70 -> 6857005.6 | H70: =YEAR(B70)-YEAR($C$10)+1 -> 5
A71: 56 | B71: =EOMONTH($C$10,55) -> 48091 | C71: =G70 -> 6857005.6 | D71: =IF(A71>$C$6,MIN(C71,$C$13),0) -> 236448.47 | E71: =C71*$C$8*DAY(B71)/$C$11 -> 41332.506 | F71: =D71+E71 -> 277780.97 | G71: =C71-D71 -> 6620557.1 | H71: =YEAR(B71)-YEAR($C$10)+1 -> 5
A72: 57 | B72: =EOMONTH($C$10,56) -> 48121 | C72: =G71 -> 6620557.1 | D72: =IF(A72>$C$6,MIN(C72,$C$13),0) -> 236448.47 | E72: =C72*$C$8*DAY(B72)/$C$11 -> 38619.916 | F72: =D72+E72 -> 275068.38 | G72: =C72-D72 -> 6384108.6 | H72: =YEAR(B72)-YEAR($C$10)+1 -> 5
A73: 58 | B73: =EOMONTH($C$10,57) -> 48152 | C73: =G72 -> 6384108.6 | D73: =IF(A73>$C$6,MIN(C73,$C$13),0) -> 236448.47 | E73: =C73*$C$8*DAY(B73)/$C$11 -> 38481.988 | F73: =D73+E73 -> 274930.46 | G73: =C73-D73 -> 6147660.2 | H73: =YEAR(B73)-YEAR($C$10)+1 -> 5
A74: 59 | B74: =EOMONTH($C$10,58) -> 48182 | C74: =G73 -> 6147660.2 | D74: =IF(A74>$C$6,MIN(C74,$C$13),0) -> 236448.47 | E74: =C74*$C$8*DAY(B74)/$C$11 -> 35861.351 | F74: =D74+E74 -> 272309.82 | G74: =C74-D74 -> 5911211.7 | H74: =YEAR(B74)-YEAR($C$10)+1 -> 5
A75: 60 | B75: =EOMONTH($C$10,59) -> 48213 | C75: =G74 -> 5911211.7 | D75: =IF(A75>$C$6,MIN(C75,$C$13),0) -> 236448.47 | E75: =C75*$C$8*DAY(B75)/$C$11 -> 35631.471 | F75: =D75+E75 -> 272079.94 | G75: =C75-D75 -> 5674763.2 | H75: =YEAR(B75)-YEAR($C$10)+1 -> 5
A76: 61 | B76: =EOMONTH($C$10,60) -> 48244 | C76: =G75 -> 5674763.2 | D76: =IF(A76>$C$6,MIN(C76,$C$13),0) -> 236448.47 | E76: =C76*$C$8*DAY(B76)/$C$11 -> 34206.212 | F76: =D76+E76 -> 270654.68 | G76: =C76-D76 -> 5438314.8 | H76: =YEAR(B76)-YEAR($C$10)+1 -> 6
A77: 62 | B77: =EOMONTH($C$10,61) -> 48273 | C77: =G76 -> 5438314.8 | D77: =IF(A77>$C$6,MIN(C77,$C$13),0) -> 236448.47 | E77: =C77*$C$8*DAY(B77)/$C$11 -> 30666.053 | F77: =D77+E77 -> 267114.52 | G77: =C77-D77 -> 5201866.3 | H77: =YEAR(B77)-YEAR($C$10)+1 -> 6
A78: 63 | B78: =EOMONTH($C$10,62) -> 48304 | C78: =G77 -> 5201866.3 | D78: =IF(A78>$C$6,MIN(C78,$C$13),0) -> 236448.47 | E78: =C78*$C$8*DAY(B78)/$C$11 -> 31355.694 | F78: =D78+E78 -> 267804.16 | G78: =C78-D78 -> 4965417.8 | H78: =YEAR(B78)-YEAR($C$10)+1 -> 6
A79: 64 | B79: =EOMONTH($C$10,63) -> 48334 | C79: =G78 -> 4965417.8 | D79: =IF(A79>$C$6,MIN(C79,$C$13),0) -> 236448.47 | E79: =C79*$C$8*DAY(B79)/$C$11 -> 28964.937 | F79: =D79+E79 -> 265413.41 | G79: =C79-D79 -> 4728969.4 | H79: =YEAR(B79)-YEAR($C$10)+1 -> 6
A80: 65 | B80: =EOMONTH($C$10,64) -> 48365 | C80: =G79 -> 4728969.4 | D80: =IF(A80>$C$6,MIN(C80,$C$13),0) -> 236448.47 | E80: =C80*$C$8*DAY(B80)/$C$11 -> 28505.176 | F80: =D80+E80 -> 264953.64 | G80: =C80-D80 -> 4492520.9 | H80: =YEAR(B80)-YEAR($C$10)+1 -> 6
A81: 66 | B81: =EOMONTH($C$10,65) -> 48395 | C81: =G80 -> 4492520.9 | D81: =IF(A81>$C$6,MIN(C81,$C$13),0) -> 236448.47 | E81: =C81*$C$8*DAY(B81)/$C$11 -> 26206.372 | F81: =D81+E81 -> 262654.84 | G81: =C81-D81 -> 4256072.4 | H81: =YEAR(B81)-YEAR($C$10)+1 -> 6
A82: 67 | B82: =EOMONTH($C$10,66) -> 48426 | C82: =G81 -> 4256072.4 | D82: =IF(A82>$C$6,MIN(C82,$C$13),0) -> 236448.47 | E82: =C82*$C$8*DAY(B82)/$C$11 -> 25654.659 | F82: =D82+E82 -> 262103.13 | G82: =C82-D82 -> 4019624 | H82: =YEAR(B82)-YEAR($C$10)+1 -> 6
A83: 68 | B83: =EOMONTH($C$10,67) -> 48457 | C83: =G82 -> 4019624 | D83: =IF(A83>$C$6,MIN(C83,$C$13),0) -> 236448.47 | E83: =C83*$C$8*DAY(B83)/$C$11 -> 24229.4 | F83: =D83+E83 -> 260677.87 | G83: =C83-D83 -> 3783175.5 | H83: =YEAR(B83)-YEAR($C$10)+1 -> 6
A84: 69 | B84: =EOMONTH($C$10,68) -> 48487 | C84: =G83 -> 3783175.5 | D84: =IF(A84>$C$6,MIN(C84,$C$13),0) -> 236448.47 | E84: =C84*$C$8*DAY(B84)/$C$11 -> 22068.524 | F84: =D84+E84 -> 258516.99 | G84: =C84-D84 -> 3546727 | H84: =YEAR(B84)-YEAR($C$10)+1 -> 6
A85: 70 | B85: =EOMONTH($C$10,69) -> 48518 | C85: =G84 -> 3546727 | D85: =IF(A85>$C$6,MIN(C85,$C$13),0) -> 236448.47 | E85: =C85*$C$8*DAY(B85)/$C$11 -> 21378.882 | F85: =D85+E85 -> 257827.35 | G85: =C85-D85 -> 3310278.6 | H85: =YEAR(B85)-YEAR($C$10)+1 -> 6
A86: 71 | B86: =EOMONTH($C$10,70) -> 48548 | C86: =G85 -> 3310278.6 | D86: =IF(A86>$C$6,MIN(C86,$C$13),0) -> 236448.47 | E86: =C86*$C$8*DAY(B86)/$C$11 -> 19309.958 | F86: =D86+E86 -> 255758.43 | G86: =C86-D86 -> 3073830.1 | H86: =YEAR(B86)-YEAR($C$10)+1 -> 6
A87: 72 | B87: =EOMONTH($C$10,71) -> 48579 | C87: =G86 -> 3073830.1 | D87: =IF(A87>$C$6,MIN(C87,$C$13),0) -> 236448.47 | E87: =C87*$C$8*DAY(B87)/$C$11 -> 18528.365 | F87: =D87+E87 -> 254976.83 | G87: =C87-D87 -> 2837381.6 | H87: =YEAR(B87)-YEAR($C$10)+1 -> 6
A88: 73 | B88: =EOMONTH($C$10,72) -> 48610 | C88: =G87 -> 2837381.6 | D88: =IF(A88>$C$6,MIN(C88,$C$13),0) -> 236448.47 | E88: =C88*$C$8*DAY(B88)/$C$11 -> 17103.106 | F88: =D88+E88 -> 253551.57 | G88: =C88-D88 -> 2600933.1 | H88: =YEAR(B88)-YEAR($C$10)+1 -> 7
A89: 74 | B89: =EOMONTH($C$10,73) -> 48638 | C89: =G88 -> 2600933.1 | D89: =IF(A89>$C$6,MIN(C89,$C$13),0) -> 236448.47 | E89: =C89*$C$8*DAY(B89)/$C$11 -> 14160.636 | F89: =D89+E89 -> 250609.1 | G89: =C89-D89 -> 2364484.7 | H89: =YEAR(B89)-YEAR($C$10)+1 -> 7
A90: 75 | B90: =EOMONTH($C$10,74) -> 48669 | C90: =G89 -> 2364484.7 | D90: =IF(A90>$C$6,MIN(C90,$C$13),0) -> 236448.47 | E90: =C90*$C$8*DAY(B90)/$C$11 -> 14252.588 | F90: =D90+E90 -> 250701.06 | G90: =C90-D90 -> 2128036.2 | H90: =YEAR(B90)-YEAR($C$10)+1 -> 7
A91: 76 | B91: =EOMONTH($C$10,75) -> 48699 | C91: =G90 -> 2128036.2 | D91: =IF(A91>$C$6,MIN(C91,$C$13),0) -> 236448.47 | E91: =C91*$C$8*DAY(B91)/$C$11 -> 12413.545 | F91: =D91+E91 -> 248862.01 | G91: =C91-D91 -> 1891587.7 | H91: =YEAR(B91)-YEAR($C$10)+1 -> 7
A92: 77 | B92: =EOMONTH($C$10,76) -> 48730 | C92: =G91 -> 1891587.7 | D92: =IF(A92>$C$6,MIN(C92,$C$13),0) -> 236448.47 | E92: =C92*$C$8*DAY(B92)/$C$11 -> 11402.071 | F92: =D92+E92 -> 247850.54 | G92: =C92-D92 -> 1655139.3 | H92: =YEAR(B92)-YEAR($C$10)+1 -> 7
A93: 78 | B93: =EOMONTH($C$10,77) -> 48760 | C93: =G92 -> 1655139.3 | D93: =IF(A93>$C$6,MIN(C93,$C$13),0) -> 236448.47 | E93: =C93*$C$8*DAY(B93)/$C$11 -> 9654.9791 | F93: =D93+E93 -> 246103.45 | G93: =C93-D93 -> 1418690.8 | H93: =YEAR(B93)-YEAR($C$10)+1 -> 7
A94: 79 | B94: =EOMONTH($C$10,78) -> 48791 | C94: =G93 -> 1418690.8 | D94: =IF(A94>$C$6,MIN(C94,$C$13),0) -> 236448.47 | E94: =C94*$C$8*DAY(B94)/$C$11 -> 8551.5529 | F94: =D94+E94 -> 245000.02 | G94: =C94-D94 -> 1182242.3 | H94: =YEAR(B94)-YEAR($C$10)+1 -> 7
A95: 80 | B95: =EOMONTH($C$10,79) -> 48822 | C95: =G94 -> 1182242.3 | D95: =IF(A95>$C$6,MIN(C95,$C$13),0) -> 236448.47 | E95: =C95*$C$8*DAY(B95)/$C$11 -> 7126.2941 | F95: =D95+E95 -> 243574.76 | G95: =C95-D95 -> 945793.87 | H95: =YEAR(B95)-YEAR($C$10)+1 -> 7
A96: 81 | B96: =EOMONTH($C$10,80) -> 48852 | C96: =G95 -> 945793.87 | D96: =IF(A96>$C$6,MIN(C96,$C$13),0) -> 236448.47 | E96: =C96*$C$8*DAY(B96)/$C$11 -> 5517.1309 | F96: =D96+E96 -> 241965.6 | G96: =C96-D96 -> 709345.4 | H96: =YEAR(B96)-YEAR($C$10)+1 -> 7
A97: 82 | B97: =EOMONTH($C$10,81) -> 48883 | C97: =G96 -> 709345.4 | D97: =IF(A97>$C$6,MIN(C97,$C$13),0) -> 236448.47 | E97: =C97*$C$8*DAY(B97)/$C$11 -> 4275.7765 | F97: =D97+E97 -> 240724.24 | G97: =C97-D97 -> 472896.94 | H97: =YEAR(B97)-YEAR($C$10)+1 -> 7
A98: 83 | B98: =EOMONTH($C$10,82) -> 48913 | C98: =G97 -> 472896.94 | D98: =IF(A98>$C$6,MIN(C98,$C$13),0) -> 236448.47 | E98: =C98*$C$8*DAY(B98)/$C$11 -> 2758.5655 | F98: =D98+E98 -> 239207.03 | G98: =C98-D98 -> 236448.47 | H98: =YEAR(B98)-YEAR($C$10)+1 -> 7
A99: 84 | B99: =EOMONTH($C$10,83) -> 48944 | C99: =G98 -> 236448.47 | D99: =IF(A99>$C$6,MIN(C99,$C$13),0) -> 236448.47 | E99: =C99*$C$8*DAY(B99)/$C$11 -> 1425.2588 | F99: =D99+E99 -> 237873.73 | G99: =C99-D99 -> 0 | H99: =YEAR(B99)-YEAR($C$10)+1 -> 7
B100: ИТОГО | D100: =SUM(D16:D99) -> 17024290 | E100: =SUM(E16:E99) -> 4885051.6 | F100: =SUM(F16:F99) -> 21909341
B102: ГОДОВАЯ СВОДКА ПО КРЕДИТУ
B103: ПОКАЗАТЕЛИ | C103: 1 год | D103: 2 год | E103: 3 год | F103: 4 год | G103: 5 год | H103: 6 год | I103: 7 год
B104: Выдача кредита | C104: =$C$9 -> 17024290 | D104: 0 | E104: 0 | F104: 0 | G104: 0 | H104: 0 | I104: 0
B105: Погашение основного долга | C105: =SUMIF($H$16:$H$99,1,$D$16:$D$99) -> 0 | D105: =SUMIF($H$16:$H$99,2,$D$16:$D$99) -> 2837381.6 | E105: =SUMIF($H$16:$H$99,3,$D$16:$D$99) -> 2837381.6 | F105: =SUMIF($H$16:$H$99,4,$D$16:$D$99) -> 2837381.6 | G105: =SUMIF($H$16:$H$99,5,$D$16:$D$99) -> 2837381.6 | H105: =SUMIF($H$16:$H$99,6,$D$16:$D$99) -> 2837381.6 | I105: =SUMIF($H$16:$H$99,7,$D$16:$D$99) -> 2837381.6
...

Sheet ProfLoss
B2: ПРЕДПОЛАГАЕМЫЕ СЧЕТА ПРИБЫЛЕЙ И УБЫТКОВ (в экв. долл. США) | K2: Приложение 13
B4: ПОКАЗАТЕЛИ | C4: Ед. изм. | D4: 1 год (льготный период) | E4: 2 год | F4: 3 год | G4: 4 год | H4: 5 год | I4: 6 год | J4: 7 год
B6: Выручка от реализации продукции (с НДС) | C6: USD | D6: =D7+D8 -> 28331250 | E6: =E7+E8 -> 2.4740556e+08 | F6: =F7+F8 -> 3.079196e+08 | G6: =G7+G8 -> 3.186764e+08 | H6: =H7+H8 -> 325686900 | I6: =I7+I8 -> 3.3285148e+08 | J6: =J7+J8 -> 340175451
B7: экспорт (в твёрдой валюте) | C7: USD | D7: =SalePlan!D8 -> 28331250 | E7: =SalePlan!E8 -> 2.4740556e+08 | F7: =SalePlan!F8 -> 3.079196e+08 | G7: =SalePlan!G8 -> 3.186764e+08 | H7: =SalePlan!H8 -> 325686900 | I7: =SalePlan!I8 -> 3.3285148e+08 | J7: =SalePlan!J8 -> 340175451
B8: внутренний рынок (с НДС) | C8: USD | D8: =SalePlan!D12+Taxes!D19 -> 0 | E8: =SalePlan!E12+Taxes!E19 -> 0 | F8: =SalePlan!F12+Taxes!F19 -> 0 | G8: =SalePlan!G12+Taxes!G19 -> 0 | H8: =SalePlan!H12+Taxes!H19 -> 0 | I8: =SalePlan!I12+Taxes!I19 -> 0 | J8: =SalePlan!J12+Taxes!J19 -> 0
B9: НДС, начисленный с реализации | C9: USD | D9: =Taxes!D19 -> 0 | E9: =Taxes!E19 -> 0 | F9: =Taxes!F19 -> 0 | G9: =Taxes!G19 -> 0 | H9: =Taxes!H19 -> 0 | I9: =Taxes!I19 -> 0 | J9: =Taxes!J19 -> 0
B10: Чистая выручка от реализации продукции | C10: USD | D10: =D6-D9 -> 28331250 | E10: =E6-E9 -> 2.4740556e+08 | F10: =F6-F9 -> 3.079196e+08 | G10: =G6-G9 -> 3.186764e+08 | H10: =H6-H9 -> 325686900 | I10: =I6-I9 -> 3.3285148e+08 | J10: =J6-J9 -> 340175451
B11: Себестоимость реализованной продукции | C11: USD | D11: =CostSold!D22 -> 21093700 | E11: =CostSold!E22 -> 2.1726575e+08 | F11: =CostSold!F22 -> 2.7081462e+08 | G11: =CostSold!G22 -> 2.7927163e+08 | H11: =CostSold!H22 -> 2.8540538e+08 | I11: =CostSold!I22 -> 2.9167302e+08 | J11: =CostSold!J22 -> 2.980775e+08
B12: в твёрдой валюте | C12: USD | D12: =CostSold!D24 -> 20083620 | E12: =CostSold!E24 -> 2.0888689e+08 | F12: =CostSold!F24 -> 2.6077114e+08 | G12: =CostSold!G24 -> 2.6888246e+08 | H12: =CostSold!H24 -> 2.7475596e+08 | I12: =CostSold!I24 -> 2.8075767e+08 | J12: =CostSold!J24 -> 2.8689041e+08
B13: в местной валюте | C13: USD | D13: =CostSold!D25 -> 1010080 | E13: =CostSold!E25 -> 8378858 | F13: =CostSold!F25 -> 10043478 | G13: =CostSold!G25 -> 10389168 | H13: =CostSold!H25 -> 10649416 | I13: =CostSold!I25 -> 10915347 | J13: =CostSold!J25 -> 11187087
B14: Валовая прибыль (убыток) | C14: USD | D14: =D10-D11 -> 7237550 | E14: =E10-E11 -> 30139815 | F14: =F10-F11 -> 37104976 | G14: =G10-G11 -> 39404766 | H14: =H10-H11 -> 40281524 | I14: =I10-I11 -> 41178464 | J14: =J10-J11 -> 42097955
B15: Расходы периода (административные и коммерческие) | C15: USD | D15: =CostSold!D32 -> 3087434.2 | E15: =CostSold!E32 -> 5081988.4 | F15: =CostSold!F32 -> 5628620.1 | G15: =CostSold!G32 -> 5772121.8 | H15: =CostSold!H32 -> 5898870.9 | I15: =CostSold!I32 -> 6025729.1 | J15: =CostSold!J32 -> 6150088.9
B16: Налоги и прочие операционные расходы | C16: USD | D16: =CostSold!D40 -> 705778.78 | E16: =CostSold!E40 -> 4924323.8 | F16: =CostSold!F40 -> 5939229.7 | G16: =CostSold!G40 -> 6052823.4 | H16: =CostSold!H40 -> 6168705.7 | I16: =CostSold!I40 -> 6287324.8 | J16: =CostSold!J40 -> 6408741.1
B17: Прибыль (убыток) от основной деятельности (EBIT) | C17: USD | D17: =D14-D15-D16 -> 3444336.9 | E17: =E14-E15-E16 -> 20133503 | F17: =F14-F15-F16 -> 25537126 | G17: =G14-G15-G16 -> 27579820 | H17: =H14-H15-H16 -> 28213948 | I17: =I14-I15-I16 -> 28865411 | J17: =J14-J15-J16 -> 29539125
B18: Финансовые расходы | C18: USD | D18: =D19 -> 0 | E18: =E19 -> 1118782.2 | F18: =F19 -> 914142.62 | G18: =G19 -> 712767.34 | H18: =H19 -> 511392.06 | I18: =I19 -> 311074.23 | J18: =J19 -> 108641.5
B19: Проценты за кредит | C19: USD | D19: =CostSold!D43 -> 0 | E19: =CostSold!E43 -> 1118782.2 | F19: =CostSold!F43 -> 914142.62 | G19: =CostSold!G43 -> 712767.34 | H19: =CostSold!H43 -> 511392.06 | I19: =CostSold!I43 -> 311074.23 | J19: =CostSold!J43 -> 108641.5
B20: Прибыль (убыток) до налогообложения | C20: USD | D20: =D17-D18 -> 3444336.9 | E20: =E17-E18 -> 19014721 | F20: =F17-F18 -> 24622984 | G20: =G17-G18 -> 26867053 | H20: =H17-H18 -> 27702555 | I20: =I17-I18 -> 28554336 | J20: =J17-J18 -> 29430483
B21: Налог на прибыль (Приложение 9) | C21: USD | D21: =Taxes!D29 -> 516650.54 | E21: =Taxes!E29 -> 2852208.2 | F21: =Taxes!F29 -> 3693447.6 | G21: =Taxes!G29 -> 4030058 | H21: =Taxes!H29 -> 4155383.3 | I21: =Taxes!I29 -> 4283150.4 | J21: =Taxes!J29 -> 4414572.5
B22: Чистая прибыль (убыток) | C22: USD | D22: =D20-D21 -> 2927686.4 | E22: =E20-E21 -> 16162513 | F22: =F20-F21 -> 20929536 | G22: =G20-G21 -> 22836995 | H22: =H20-H21 -> 23547172 | I22: =I20-I21 -> 24271186 | J22: =J20-J21 -> 25015911
B24: Коэффициенты рентабельности и покрытия
B25: Валовая рентабельность | C25: % | D25: =IFERROR(D14/D10,0) -> 0.25546172 | E25: =IFERROR(E14/E10,0) -> 0.12182351 | F25: =IFERROR(F14/F10,0) -> 0.12050216 | G25: =IFERROR(G14/G10,0) -> 0.12365135 | H25: =IFERROR(H14/H10,0) -> 0.12368174 | I25: =IFERROR(I14/I10,0) -> 0.12371423 | J25: =IFERROR(J14/J10,0) -> 0.12375365
B26: Чистая рентабельность | C26: % | D26: =IFERROR(D22/D10,0) -> 0.10333771 | E26: =IFERROR(E22/E10,0) -> 0.065328009 | F26: =IFERROR(F22/F10,0) -> 0.067970783 | G26: =IFERROR(G22/G10,0) -> 0.071662023 | H26: =IFERROR(H22/H10,0) -> 0.072300028 | I26: =IFERROR(I22/I10,0) -> 0.072918966 | J26: =IFERROR(J22/J10,0) -> 0.07353826
B27: EBITDA | C27: USD | D27: =D17+Depreciate!$G$21 -> 4067929.8 | E27: =E17+Depreciate!$H$21 -> 22679487 | F27: =F17+Depreciate!$I$21 -> 28130752 | G27: =G17+Depreciate!$J$21 -> 30221089 | H27: =H17+Depreciate!$K$21 -> 30902858 | I27: =I17+Depreciate!$L$21 -> 31599285 | J27: =J17+Depreciate!$M$21 -> 32312606
B28: Маржа EBITDA | C28: % | D28: =IFERROR(D27/D10,0) -> 0.14358455 | E28: =IFERROR(E27/E10,0) -> 0.091669269 | F28: =IFERROR(F27/F10,0) -> 0.091357461 | G28: =IFERROR(G27/G10,0) -> 0.094833157 | H28: =IFERROR(H27/H10,0) -> 0.094885174 | I28: =IFERROR(I27/I10,0) -> 0.094935089 | J28: =IFERROR(J27/J10,0) -> 0.094988058
B29: EBIT / Проценты за кредит | C29: x | D29: =IF(D19>0,D17/D19,"-") -> - | E29: =IF(E19>0,E17/E19,"-") -> 17.99591 | F29: =IF(F19>0,F17/F19,"-") -> 27.935604 | G29: =IF(G19>0,G17/G19,"-") -> 38.694001 | H29: =IF(H19>0,H17/H19,"-") -> 55.170875 | I29: =IF(I19>0,I17/I19,"-") -> 92.792676 | J29: =IF(J19>0,J17/J19,"-") -> 271.8954
B30: Задолженность по кредиту на конец года | C30: USD | D30: =LOANS!$C$108 -> 17024290 | E30: =LOANS!$D$108 -> 14186908 | F30: =LOANS!$E$108 -> 11349526 | G30: =LOANS!$F$108 -> 8512144.8 | H30: =LOANS!$G$108 -> 5674763.2 | I30: =LOANS!$H$108 -> 2837381.6 | J30: =LOANS!$I$108 -> 0
B31: Долг / EBITDA | C31: x | D31: =IFERROR(D30/D27,0) -> 4.1850008 | E31: =IFERROR(E30/E27,0) -> 0.62553919 | F31: =IFERROR(F30/F27,0) -> 0.4034562 | G31: =IFERROR(G30/G27,0) -> 0.28166241 | H31: =IFERROR(H30/H27,0) -> 0.18363231 | I31: =IFERROR(I30/I27,0) -> 0.08979259 | J31: =IFERROR(J30/J27,0) -> 0
B33: 1-й год: проценты за кредит льготного периода оплачиваются за счёт собственных средств и капитализируются в стоимость основных средств (МСФО IAS 23, Приложения 1 и 4); в отчёт о прибылях и убытках не включаются.

Sheet WorkCap
B2: ПРЕДПОЛОЖЕНИЯ ПО РАБОЧЕМУ КАПИТАЛУ (в экв. долл. США) | K2: Приложение 14
B4: Показатели | C4: Дни покрытия
B5: Период поступления от продаж (дебиторская задолженность) | C5: 30
B6: Запасы сырья и материалов на складе | C6: 15
B7: Незавершенная продукция | C7: 5
B8: Запасы готовой продукции (минимальный запас) | C8: 15
B9: Период оплаты поставщикам (кредиторская задолженность) | C9: 8
B10: Задолженность по заработной плате | C10: 30
B11: Возмещение НДС (операционный) | C11: 90
B12: Возмещение НДС по капитальным вложениям | C12: 540
B14: ПОКАЗАТЕЛИ (на конец года) | C14: На начало строительства | D14: 1 год (льготный период) | E14: 2 год | F14: 3 год | G14: 4 год | H14: 5 год | I14: 6 год | J14: 7 год
B16: Дебиторская задолженность | C16: 0 | D16: 10984439 | E16: 20334704 | F16: 25308460 | G16: 26192581 | H16: 26768786 | I16: 27357656 | J16: 27959626
B17: Запасы (сырьё, материалы, НЗП, готовая продукция) | C17: 0 | D17: 11098087 | E17: 20927250 | F17: 25752601 | G17: 26319157 | H17: 26898178 | I17: 27489938 | J17: 28094717
B18: НДС к возмещению | C18: 0 | D18: 8955924.5 | E18: 6625811.4 | F18: 8138805.8 | G18: 8318152 | H18: 8500841.2 | I18: 8687549.5 | J18: 8878365.5
B19: Итого текущих активов | C19: 0 | D19: =SUM(D16:D18) -> 31038450 | E19: =SUM(E16:E18) -> 47887765 | F19: =SUM(F16:F18) -> 59199867 | G19: =SUM(G16:G18) -> 60829889 | H19: =SUM(H16:H18) -> 62167806 | I19: =SUM(I16:I18) -> 63535144 | J19: =SUM(J16:J18) -> 64932709
B20: Кредиторская задолженность | C20: 0 | D20: 2616698.8 | E20: 4897566.3 | F20: 6018302.9 | G20: 6151151.9 | H20: 6286477.2 | I20: 6424779.7 | J20: 6566124.9
B21: Задолженность по оплате труда и налогам с ФОТ | C21: 0 | D21: 141239.62 | E21: 148877.95 | F21: 152137.17 | G21: 155482.77 | H21: 158903.39 | I21: 162399.27 | J21: 165972.05
B22: Итого текущих обязательств | C22: 0 | D22: =D20+D21 -> 2757938.4 | E22: =E20+E21 -> 5046444.2 | F22: =F20+F21 -> 6170440.1 | G22: =G20+G21 -> 6306634.7 | H22: =H20+H21 -> 6445380.6 | I22: =I20+I21 -> 6587179 | J22: =J20+J21 -> 6732097
B23: Чистый рабочий капитал | C23: 0 | D23: =D19-D22 -> 28280512 | E23: =E19-E22 -> 42841321 | F23: =F19-F22 -> 53029426 | G23: =G19-G22 -> 54523255 | H23: =H19-H22 -> 55722425 | I23: =I19-I22 -> 56947965 | J23: =J19-J22 -> 58200612
B25: Изменения в рабочем капитале (- рост / + снижение) | D25: =-(D23-C23) -> -28280512 | E25: =-(E23-D23) -> -14560809 | F25: =-(F23-E23) -> -10188105 | G25: =-(G23-F23) -> -1493828.4 | H25: =-(H23-G23) -> -1199170.5 | I25: =-(I23-H23) -> -1225539.6 | J25: =-(J23-I23) -> -1252646.8
B26: Прочие изменения операционных статей (налоги к уплате и пр.) | D26: 0 | E26: 0 | F26: 0 | G26: 0 | H26: 0 | I26: 0 | J26: 0
B27: Изменение рабочего капитала для потока наличности (Приложение 15) | D27: =D25+D26 -> -28280512 | E27: =E25+E26 -> -14560809 | F27: =F25+F26 -> -10188105 | G27: =G25+G26 -> -1493828.4 | H27: =H25+H26 -> -1199170.5 | I27: =I25+I26 -> -1225539.6 | J27: =J25+J26 -> -1252646.8
B29: 1-й год: изменение рассчитано от начала строительства, т.е. включает подготовительный период.

Sheet CashFlow
B2: ПОТОКИ НАЛИЧНОСТИ (в экв. долл. США) | K2: Приложение 15
B3: 1-й год - инвестиционный и льготный период; включает также освоение капвложений и расходы подготовительного периода.
B4: ПОКАЗАТЕЛИ | C4: Ед. изм. | D4: 1 год (льготный период) | E4: 2 год | F4: 3 год | G4: 4 год | H4: 5 год | I4: 6 год | J4: 7 год
B6: Выручка от реализации продукции (с НДС) | C6: USD | D6: =ProfLoss!D6 -> 28331250 | E6: =ProfLoss!E6 -> 2.4740556e+08 | F6: =ProfLoss!F6 -> 3.079196e+08 | G6: =ProfLoss!G6 -> 3.186764e+08 | H6: =ProfLoss!H6 -> 325686900 | I6: =ProfLoss!I6 -> 3.3285148e+08 | J6: =ProfLoss!J6 -> 340175451
B7: НДС, начисленный с реализации | C7: USD | D7: =-ProfLoss!D9 -> 0 | E7: =-ProfLoss!E9 -> 0 | F7: =-ProfLoss!F9 -> 0 | G7: =-ProfLoss!G9 -> 0 | H7: =-ProfLoss!H9 -> 0 | I7: =-ProfLoss!I9 -> 0 | J7: =-ProfLoss!J9 -> 0
B8: Чистая выручка от реализации продукции | C8: USD | D8: =D6+D7 -> 28331250 | E8: =E6+E7 -> 2.4740556e+08 | F8: =F6+F7 -> 3.079196e+08 | G8: =G6+G7 -> 3.186764e+08 | H8: =H6+H7 -> 325686900 | I8: =I6+I7 -> 3.3285148e+08 | J8: =J6+J7 -> 340175451
B9: Изменения в рабочем капитале (Приложение 14) | C9: USD | D9: =WorkCap!D27 -> -28280512 | E9: =WorkCap!E27 -> -14560809 | F9: =WorkCap!F27 -> -10188105 | G9: =WorkCap!G27 -> -1493828.4 | H9: =WorkCap!H27 -> -1199170.5 | I9: =WorkCap!I27 -> -1225539.6 | J9: =WorkCap!J27 -> -1252646.8
B10: Наличность от продаж | C10: USD | D10: =D8+D9 -> 50737.911 | E10: =E8+E9 -> 2.3284476e+08 | F10: =F8+F9 -> 2.9773149e+08 | G10: =G8+G9 -> 3.1718257e+08 | H10: =H8+H9 -> 3.2448773e+08 | I10: =I8+I9 -> 3.3162594e+08 | J10: =J8+J9 -> 3.389228e+08
B11: Себестоимость реализованной продукции | C11: USD | D11: =-ProfLoss!D11 -> -21093700 | E11: =-ProfLoss!E11 -> -2.1726575e+08 | F11: =-ProfLoss!F11 -> -2.7081462e+08 | G11: =-ProfLoss!G11 -> -2.7927163e+08 | H11: =-ProfLoss!H11 -> -2.8540538e+08 | I11: =-ProfLoss!I11 -> -2.9167302e+08 | J11: =-ProfLoss!J11 -> -2.980775e+08
B12: Валовые поступления наличности | C12: USD | D12: =D10+D11 -> -21042962 | E12: =E10+E11 -> 15579007 | F12: =F10+F11 -> 26916871 | G12: =G10+G11 -> 37910937 | H12: =H10+H11 -> 39082354 | I12: =I10+I11 -> 39952925 | J12: =J10+J11 -> 40845308
B13: Расходы периода | C13: USD | D13: =-ProfLoss!D15 -> -3087434.2 | E13: =-ProfLoss!E15 -> -5081988.4 | F13: =-ProfLoss!F15 -> -5628620.1 | G13: =-ProfLoss!G15 -> -5772121.8 | H13: =-ProfLoss!H15 -> -5898870.9 | I13: =-ProfLoss!I15 -> -6025729.1 | J13: =-ProfLoss!J15 -> -6150088.9
B14: Налоги и прочие операционные расходы | C14: USD | D14: =-ProfLoss!D16 -> -705778.78 | E14: =-ProfLoss!E16 -> -4924323.8 | F14: =-ProfLoss!F16 -> -5939229.7 | G14: =-ProfLoss!G16 -> -6052823.4 | H14: =-ProfLoss!H16 -> -6168705.7 | I14: =-ProfLoss!I16 -> -6287324.8 | J14: =-ProfLoss!J16 -> -6408741.1
B15: Расходы подготовительного периода | C15: USD | D15: =-ProjCost!$E$13 -> -701967.23 | E15: 0 | F15: 0 | G15: 0 | H15: 0 | I15: 0 | J15: 0
B16: Налог на прибыль | C16: USD | D16: =-ProfLoss!D21 -> -516650.54 | E16: =-ProfLoss!E21 -> -2852208.2 | F16: =-ProfLoss!F21 -> -3693447.6 | G16: =-ProfLoss!G21 -> -4030058 | H16: =-ProfLoss!H21 -> -4155383.3 | I16: =-ProfLoss!I21 -> -4283150.4 | J16: =-ProfLoss!J21 -> -4414572.5
B17: Амортизация (неденежная статья, прибавляется) | C17: USD | D17: =Depreciate!$G$21 -> 623592.87 | E17: =Depreciate!$H$21 -> 2545983.9 | F17: =Depreciate!$I$21 -> 2593626.1 | G17: =Depreciate!$J$21 -> 2641268.4 | H17: =Depreciate!$K$21 -> 2688910.6 | I17: =Depreciate!$L$21 -> 2733874.3 | J17: =Depreciate!$M$21 -> 2773480.8
B18: Операционный поток наличности (A) | C18: USD | D18: =SUM(D12:D17) -> -25431200 | E18: =SUM(E12:E17) -> 5266470.1 | F18: =SUM(F12:F17) -> 14249199 | G18: =SUM(G12:G17) -> 24697202 | H18: =SUM(H12:H17) -> 25548304 | I18: =SUM(I12:I17) -> 26090595 | J18: =SUM(J12:J17) -> 26645386
B19: Собственный капитал (взнос заемщика) | C19: USD | D19: =FinPlan!$E$10 -> 61098022 | E19: 0 | F19: 0 | G19: 0 | H19: 0 | I19: 0 | J19: 0
B20: Привлеченный кредит НБУ | C20: USD | D20: =LOANS!$C$104 -> 17024290 | E20: =LOANS!$D$104 -> 0 | F20: =LOANS!$E$104 -> 0 | G20: =LOANS!$F$104 -> 0 | H20: =LOANS!$G$104 -> 0 | I20: =LOANS!$H$104 -> 0 | J20: =LOANS!$I$104 -> 0
B21: Инвестиции (капитальные вложения, Приложение 4) | C21: USD | D21: =-Depreciate!$G$25 -> -47761338 | E21: =-Depreciate!$H$25 -> -476422.32 | F21: =-Depreciate!$I$25 -> -476422.32 | G21: =-Depreciate!$J$25 -> -476422.32 | H21: =-Depreciate!$K$25 -> -476422.32 | I21: =-Depreciate!$L$25 -> -476422.32 | J21: =-Depreciate!$M$25 -> -476422.32
B22: Проценты за кредит (B) | C22: USD | D22: =-ProfLoss!D19 -> 0 | E22: =-ProfLoss!E19 -> -1118782.2 | F22: =-ProfLoss!F19 -> -914142.62 | G22: =-ProfLoss!G19 -> -712767.34 | H22: =-ProfLoss!H19 -> -511392.06 | I22: =-ProfLoss!I19 -> -311074.23 | J22: =-ProfLoss!J19 -> -108641.5
B23: Прочие финансовые издержки в инвестиционный период (проценты льготного периода) | C23: USD | D23: =-LOANS!$C$106 -> -1208251.7 | E23: 0 | F23: 0 | G23: 0 | H23: 0 | I23: 0 | J23: 0
B24: Чистые поступления наличности | C24: USD | D24: =D18+D19+D20+D21+D22+D23 -> 3721522.2 | E24: =E18+E19+E20+E21+E22+E23 -> 3671265.6 | F24: =F18+F19+F20+F21+F22+F23 -> 12858635 | G24: =G18+G19+G20+G21+G22+G23 -> 23508013 | H24: =H18+H19+H20+H21+H22+H23 -> 24560490 | I24: =I18+I19+I20+I21+I22+I23 -> 25303098 | J24: =J18+J19+J20+J21+J22+J23 -> 26060322
B25: Выплата основного долга (C) | C25: USD | D25: =-LOANS!$C$105 -> 0 | E25: =-LOANS!$D$105 -> -2837381.6 | F25: =-LOANS!$E$105 -> -2837381.6 | G25: =-LOANS!$F$105 -> -2837381.6 | H25: =-LOANS!$G$105 -> -2837381.6 | I25: =-LOANS!$H$105 -> -2837381.6 | J25: =-LOANS!$I$105 -> -2837381.6
B26: Чистый поток наличности | C26: USD | D26: =D24+D25 -> 3721522.2 | E26: =E24+E25 -> 833883.94 | F26: =F24+F25 -> 10021253 | G26: =G24+G25 -> 20670631 | H26: =H24+H25 -> 21723108 | I26: =I24+I25 -> 22465717 | J26: =J24+J25 -> 23222941
B27: Кумулятивный поток наличности | C27: USD | D27: =D26 -> 3721522.2 | E27: =D27+E26 -> 4555406.1 | F27: =E27+F26 -> 14576659 | G27: =F27+G26 -> 35247290 | H27: =G27+H26 -> 56970399 | I27: =H27+I26 -> 79436115 | J27: =I27+J26 -> 1.0265906e+08
B29: Коэффициент обслуживания долга, DSCR [(A)/(B+C)] | C29: x | D29: ="-" -> - | E29: =IFERROR(E18/-(E22+E25),0) -> 1.3312063 | F29: =IFERROR(F18/-(F22+F25),0) -> 3.7982427 | G29: =IFERROR(G18/-(G22+G25),0) -> 6.9566665 | H29: =IFERROR(H18/-(H22+H25),0) -> 7.6291523 | I29: =IFERROR(I18/-(I22+I25),0) -> 8.2867907 | J29: =IFERROR(J18/-(J22+J25),0) -> 9.0445272
B30: DSCR с учётом поддерживающих капвложений [(A - инвестиции)/(B+C)] | C30: x | D30: ="-" -> - | E30: =IFERROR((E18+E21)/-(E22+E25),0) -> 1.2107809 | F30: =IFERROR((F18+F21)/-(F22+F25),0) -> 3.6712484 | G30: =IFERROR((G18+G21)/-(G22+G25),0) -> 6.8224687 | H30: =IFERROR((H18+H21)/-(H22+H25),0) -> 7.4868846 | I30: =IFERROR((I18+I21)/-(I22+I25),0) -> 8.1354714 | J30: =IFERROR((J18+J21)/-(J22+J25),0) -> 8.8828101
B31: Минимальный DSCR (2-7 годы) | D31: =MIN(E30:J30) -> 1.2107809
B32: Средний DSCR (2-7 годы) | D32: =AVERAGE(E30:J30) -> 6.034944
B34: Проценты льготного периода (1-й год) уплачиваются за счёт собственных средств заемщика (включены в стоимость проекта, Приложение 1). Налог на прибыль - в размере начисленного (без учёта отсрочки уплаты).

Sheet BreakPoint
B2: ТОЧКА БЕЗУБЫТОЧНОСТИ (в экв. долл. США) | D2: Приложение 16
B3: Расчёт на 3-й год (проектная мощность).
B4: Общие продажи при проектной мощности | C4: =CostTotal!C26 -> 3.079196e+08
B5: в местной валюте | C5: =SalePlan!F12 -> 0
B6: в твердой валюте | C6: =SalePlan!F8 -> 3.079196e+08
B7: Фиксированная стоимость | C7: =CostTotal!F22 -> 9682386.6
B8: Переменная стоимость | C8: =CostTotal!G22 -> 2.7547403e+08
B9: Маржинальный доход | C9: =C4-C8 -> 32445563
B10: Точка безубыточности (доля от выручки при проектной мощности) | C10: =IFERROR(C7/C9,0) -> 0.29841943
B11: Точка безубыточности, USD выручки | C11: =C10*C4 -> 91889192
B12: Точка безубыточности в натуральном выражении (основная продукция) | C12: =C10*ProdPlan!F13 -> 792.75123 | D12: t
B13: Запас финансовой прочности | C13: =1-C10 -> 0.70158057

Sheet NPV_IRR
B2: РАСЧЁТ NPV, IRR И СРОКА ОКУПАЕМОСТИ ПРОЕКТА (в экв. долл. США)
B3: Денежный поток проекта (до финансирования) = операционный поток (A) - инвестиции; горизонт - срок кредита (7 лет), без остаточной стоимости.
B4: ПОКАЗАТЕЛИ | C4: Ед. изм. | D4: 1 год (льготный период) | E4: 2 год | F4: 3 год | G4: 4 год | H4: 5 год | I4: 6 год | J4: 7 год
B6: Период (лет) | D6: 1 | E6: 2 | F6: 3 | G6: 4 | H6: 5 | I6: 6 | J6: 7
B7: Операционный поток наличности (A) | C7: USD | D7: =CashFlow!D18 -> -25431200 | E7: =CashFlow!E18 -> 5266470.1 | F7: =CashFlow!F18 -> 14249199 | G7: =CashFlow!G18 -> 24697202 | H7: =CashFlow!H18 -> 25548304 | I7: =CashFlow!I18 -> 26090595 | J7: =CashFlow!J18 -> 26645386
B8: Инвестиции | C8: USD | D8: =CashFlow!D21 -> -47761338 | E8: =CashFlow!E21 -> -476422.32 | F8: =CashFlow!F21 -> -476422.32 | G8: =CashFlow!G21 -> -476422.32 | H8: =CashFlow!H21 -> -476422.32 | I8: =CashFlow!I21 -> -476422.32 | J8: =CashFlow!J21 -> -476422.32
B9: Поток наличности проекта (FCFF) | C9: USD | D9: =D7+D8 -> -73192538 | E9: =E7+E8 -> 4790047.8 | F9: =F7+F8 -> 13772777 | G9: =G7+G8 -> 24220780 | H9: =H7+H8 -> 25071882 | I9: =I7+I8 -> 25614172 | J9: =J7+J8 -> 26168964
B10: Ставка дисконта (WACC) | C10: % | D10: 0.11298341 | E10: =D10 -> 0.11298341 | F10: =D10 -> 0.11298341 | G10: =D10 -> 0.11298341 | H10: =D10 -> 0.11298341 | I10: =D10 -> 0.11298341 | J10: =D10 -> 0.11298341
B11: Коэффициент дисконтирования | D11: =1/(1+D10)^D6 -> 0.89848599 | E11: =1/(1+E10)^E6 -> 0.80727708 | F11: =1/(1+F10)^F6 -> 0.72532715 | G11: =1/(1+G10)^G6 -> 0.65169628 | H11: =1/(1+H10)^H6 -> 0.58553998 | I11: =1/(1+I10)^I6 -> 0.52609947 | J11: =1/(1+J10)^J6 -> 0.472693
B12: Дисконтированный поток | C12: USD | D12: =D9*D11 -> -65762470 | E12: =E9*E11 -> 3866895.8 | F12: =F9*F11 -> 9989769.2 | G12: =G9*G11 -> 15784592 | H12: =H9*H11 -> 14680589 | I12: =I9*I11 -> 13475602 | J12: =J9*J11 -> 12369886
B13: Накопленный поток | C13: USD | D13: =D9 -> -73192538 | E13: =D13+E9 -> -68402490 | F13: =E13+F9 -> -54629713 | G13: =F13+G9 -> -30408933 | H13: =G13+H9 -> -5337050.7 | I13: =H13+I9 -> 20277122 | J13: =I13+J9 -> 46446086
B14: Накопленный дисконтированный поток (NPV нарастающим итогом) | C14: USD | D14: =D12 -> -65762470 | E14: =D14+E12 -> -61895574 | F14: =E14+F12 -> -51905805 | G14: =F14+G12 -> -36121213 | H14: =G14+H12 -> -21440623 | I14: =H14+I12 -> -7965021 | J14: =I14+J12 -> 4404865.2
B15: вспом.: окупаемость | D15: ="" | E15: =IF(AND(D13<0,E13>=0),D6-D13/E9,"") | F15: =IF(AND(E13<0,F13>=0),E6-E13/F9,"") | G15: =IF(AND(F13<0,G13>=0),F6-F13/G9,"") | H15: =IF(AND(G13<0,H13>=0),G6-G13/H9,"") | I15: =IF(AND(H13<0,I13>=0),H6-H13/I9,"") -> 5.2083632 | J15: =IF(AND(I13<0,J13>=0),I6-I13/J9,"")
B16: вспом.: дисконтированная окупаемость | D16: ="" | E16: =IF(AND(D14<0,E14>=0),D6-D14/E12,"") | F16: =IF(AND(E14<0,F14>=0),E6-E14/F12,"") | G16: =IF(AND(F14<0,G14>=0),F6-F14/G12,"") | H16: =IF(AND(G14<0,H14>=0),G6-G14/H12,"") | I16: =IF(AND(H14<0,I14>=0),H6-H14/I12,"") | J16: =IF(AND(I14<0,J14>=0),I6-I14/J12,"") -> 6.6439041
B18: NPV (чистая приведённая стоимость), USD | D18: =SUM(D12:J12) -> 4404865.2
B19: IRR (внутренняя норма доходности) | D19: =IFERROR(IRR(D9:J9),"-") -> 0.13187811
B20: Индекс доходности (PI) | D20: =IFERROR(SUM(E12:J12)/-D12,0) -> 1.0669814
B21: Простой срок окупаемости, лет (от начала 1-го года) | D21: =IF(COUNT(E15:J15)>0,SUM(E15:J15),"> 7") -> 5.2083632
B22: Дисконтированный срок окупаемости, лет | D22: =IF(COUNT(E16:J16)>0,SUM(E16:J16),"> 7") -> 6.6439041
